Workbook

Sheet Q2 2026 Summary
C2: Multifamily Market Summary — Q2 2026 | P2: Hold Period (Yrs) | R2: Value Add Rev | S2: Expense Growth | AB2: Going-In Cap Rate | AD2: Basis Growth | AK2: Lev Yield
C3: Effective RPSF | Rent Roll PSF | Effective Rent Ratio (Eff. RPSF ÷ Rent Roll PSF) | P3: 5 | R3: 0.051 | S3: 0.025 | AB3: 0.05 | AD3: 0.08 | AK3: 0.05
B4: # | C4: Market | D4: Rent Roll PSF | E4: Asking RPSF | F4: Gross Rent Ratio | G4: Unit Starts as % of Inv | H4: Gross Embedded RR Mark to Market | I4: Effective RPSF | J4: Eff. Rent Ratio | K4: Effective Embedded RR Mark to Market | L4: 10-year Historical Avg Rent Growth (GSA) | M4: 10-year Historical Avg Rent Growth (RP) | N4: 10-year Avg Hist. Rent Growth (GSA & RP) | O4: PF Yrs Negative | P4: PF Organic Revenue Growth | Q4: PF Organic Rev CAGR | R4: PF Total Revenue Growth | S4: Expense Growth | T4: Initial NOI | U4: Initial Revenue | V4: Initial Expenses | W4: Terminal Revenue | X4: Terminal Expenses | Y4: Terminal NOI | Z4: Total PF NOI Growth | AA4: PF NOI CAGR | AB4: Going-In Cap Rate | AC4: Initial Basis | AD4: Residual Basis | AE4: Going in NOI | AF4: Residual NOI | AG4: Residual YOC | AH4: Cap Rate Growth | AI4: Rounded | AJ4: LIRR From Appreciation | AK4: LIRR from Yield | AL4: PF LIRR
B5: 1 | C5: Wichita, KS | D5: =SUMIFS(Realpage!$I:$I,Realpage!$A:$A,$C5,Realpage!$F:$F,"Rent Roll (Rev/OSF)") -> 2.1056087 | E5: =SUMIFS(Realpage!$I:$I,Realpage!$A:$A,$C5,Realpage!$F:$F,"Asking RPSF") -> 2.338 | F5: =E5/D5 -> 1.1103678 | G5: {=SUMPRODUCT(('RP - Unit Starts'!$C$2:$C$101=$C5)*('RP - Unit Starts'!$F$2:$F$101="Unit Starts")*'RP - Unit Starts'!$I$2:$L$101)/SUMIFS('RP - Unit Starts'!$L:$L,'RP - Unit Starts'!$C:$C,$C5,'RP - Unit Starts'!$F:$F,"Existing Units")} -> 0.0038874164 | H5: =F5-1 -> 0.11036776 | I5: =SUMIFS(Realpage!$I:$I,Realpage!$A:$A,$C5,Realpage!$F:$F,"Effective RPSF") -> 2.331 | J5: =I5/D5 -> 1.1070433 | K5: =J5-1 -> 0.1070433 | M5: =AVERAGEIF('Realpage - His. Rent Change'!$A$2:$A$577,'Q2 2026 Summary'!C5,'Realpage - His. Rent Change'!$I$2:$AV$577) -> 0.0451 | N5: =AVERAGE(L5:M5) -> 0.0451 | O5: =MAX(0,-(K5/M5)) -> 0 | P5: =($P$3*M5)+K5 -> 0.3325433 | Q5: =(1+P5)^(1/$P$3)-1 -> 0.059098289 | R5: =$R$3+P5 -> 0.3835433 | S5: =$S$3*$P$3 -> 0.125 | T5: =SUMIFS(Realpage!$I:$I,Realpage!$A:$A,$C5,Realpage!$F:$F,"NOI % of Revenue") -> 1.1619755 | U5: 1 | V5: =U5-T5 -> -0.1619755 | W5: =U5*(1+R5) -> 1.3835433 | X5: =V5*(1+S5) -> -0.18222243 | Y5: =W5-X5 -> 1.5657657 | Z5: =Y5/T5-1 -> 0.34750323 | AA5: =(Y5/T5)^(1/$P$3)-1 -> 0.061465695 | AB5: =$AB$3 -> 0.05 | AC5: =AB5/$AB$3 -> 1 | AD5: =AC5*(1+$AD$3) -> 1.08 | AE5: =AC5*AB5 -> 0.05 | AF5: =AE5*(1+Z5) -> 0.067375162 | AG5: =AF5/AD5 -> 0.062384409 | AH5: =AG5-AB5 -> 0.012384409 | AI5: =ROUND(AH5,4) -> 0.0124 | AJ5: {=INDEX('Cap Rate to IRR Map'!$F$3:$F$623,MATCH(ROUND(AI5,4),ROUND('Cap Rate to IRR Map'!$E$3:$E$623,4),0))} -> 0.111 | AK5: =$AK$3 -> 0.05 | AL5: 0.2075 | AO5: Any outsized VA opportuntiies to enhance growth
B6: 2 | C6: Salt Lake City/Ogden/Brigham City, UT-ID | D6: =SUMIFS(Realpage!$I:$I,Realpage!$A:$A,$C6,Realpage!$F:$F,"Rent Roll (Rev/OSF)") -> 3.1832356 | E6: =SUMIFS(Realpage!$I:$I,Realpage!$A:$A,$C6,Realpage!$F:$F,"Asking RPSF") -> 3.455 | F6: =E6/D6 -> 1.0853736 | G6: {=SUMPRODUCT(('RP - Unit Starts'!$C$2:$C$101=$C6)*('RP - Unit Starts'!$F$2:$F$101="Unit Starts")*'RP - Unit Starts'!$I$2:$L$101)/SUMIFS('RP - Unit Starts'!$L:$L,'RP - Unit Starts'!$C:$C,$C6,'RP - Unit Starts'!$F:$F,"Existing Units")} -> 0.011486296 | H6: =F6-1 -> 0.085373647 | I6: =SUMIFS(Realpage!$I:$I,Realpage!$A:$A,$C6,Realpage!$F:$F,"Effective RPSF") -> 3.351 | J6: =I6/D6 -> 1.0527025 | K6: =J6-1 -> 0.052702487 | L6: 0.0423 | M6: =AVERAGEIF('Realpage - His. Rent Change'!$A$2:$A$577,'Q2 2026 Summary'!C12,'Realpage - His. Rent Change'!$I$2:$AV$577) -> 0.038 | N6: =AVERAGE(L6:M6) -> 0.04015 | O6: =MAX(0,-(K6/M6)) -> 0 | P6: =($P$3*M6)+K6 -> 0.24270249 | Q6: =(1+P6)^(1/$P$3)-1 -> 0.044415801 | R6: =$R$3+P6 -> 0.29370249 | S6: =$S$3*$P$3 -> 0.125 | T6: =SUMIFS(Realpage!$I:$I,Realpage!$A:$A,$C6,Realpage!$F:$F,"NOI % of Revenue") -> 1.2728915 | U6: 1 | V6: =U6-T6 -> -0.27289146 | W6: =U6*(1+R6) -> 1.2937025 | X6: =V6*(1+S6) -> -0.30700289 | Y6: =W6-X6 -> 1.6007054 | Z6: =Y6/T6-1 -> 0.25753486 | AA6: =(Y6/T6)^(1/$P$3)-1 -> 0.046897123 | AB6: =$AB$3 -> 0.05 | AC6: =AB6/$AB$3 -> 1 | AD6: =AC6*(1+$AD$3) -> 1.08 | AE6: =AC6*AB6 -> 0.05 | AF6: =AE6*(1+Z6) -> 0.062876743 | AG6: =AF6/AD6 -> 0.058219206 | AH6: =AG6-AB6 -> 0.0082192063 | AI6: =ROUND(AH6,4) -> 0.0082 | AJ6: {=INDEX('Cap Rate to IRR Map'!$F$3:$F$623,MATCH(ROUND(AI6,4),ROUND('Cap Rate to IRR Map'!$E$3:$E$623,4),0))} -> 0.076333 | AK6: =$AK$3 -> 0.05 | AL6: 0.15 | AO6: Washington DC
B7: =B6+1 -> 3 | C7: Reno, NV | D7: =SUMIFS(Realpage!$I:$I,Realpage!$A:$A,$C7,Realpage!$F:$F,"Rent Roll (Rev/OSF)") -> 3.6695941 | E7: =SUMIFS(Realpage!$I:$I,Realpage!$A:$A,$C7,Realpage!$F:$F,"Asking RPSF") -> 3.965 | F7: =E7/D7 -> 1.080501 | G7: {=SUMPRODUCT(('RP - Unit Starts'!$C$2:$C$101=$C7)*('RP - Unit Starts'!$F$2:$F$101="Unit Starts")*'RP - Unit Starts'!$I$2:$L$101)/SUMIFS('RP - Unit Starts'!$L:$L,'RP - Unit Starts'!$C:$C,$C7,'RP - Unit Starts'!$F:$F,"Existing Units")} -> 0.023921244 | H7: =F7-1 -> 0.08050096 | I7: =SUMIFS(Realpage!$I:$I,Realpage!$A:$A,$C7,Realpage!$F:$F,"Effective RPSF") -> 3.929 | J7: =I7/D7 -> 1.0706906 | K7: =J7-1 -> 0.070690611 | M7: =AVERAGEIF('Realpage - His. Rent Change'!$A$2:$A$577,'Q2 2026 Summary'!C9,'Realpage - His. Rent Change'!$I$2:$AV$577) -> 0.0467 | N7: =AVERAGE(L7:M7) -> 0.0467 | O7: =MAX(0,-(K7/M7)) -> 0 | P7: =($P$3*M7)+K7 -> 0.30419061 | Q7: =(1+P7)^(1/$P$3)-1 -> 0.05455252 | R7: =$R$3+P7 -> 0.35519061 | S7: =$S$3*$P$3 -> 0.125 | T7: =SUMIFS(Realpage!$I:$I,Realpage!$A:$A,$C7,Realpage!$F:$F,"NOI % of Revenue") -> 1.19992 | U7: 1 | V7: =U7-T7 -> -0.19992 | W7: =U7*(1+R7) -> 1.3551906 | X7: =V7*(1+S7) -> -0.22491 | Y7: =W7-X7 -> 1.5801006 | Z7: =Y7/T7-1 -> 0.3168383 | AA7: =(Y7/T7)^(1/$P$3)-1 -> 0.056589985 | AB7: =$AB$3 -> 0.05 | AC7: =AB7/$AB$3 -> 1 | AD7: =AC7*(1+$AD$3) -> 1.08 | AE7: =AC7*AB7 -> 0.05 | AF7: =AE7*(1+Z7) -> 0.065841915 | AG7: =AF7/AD7 -> 0.060964736 | AH7: =AG7-AB7 -> 0.010964736 | AI7: =ROUND(AH7,4) -> 0.011 | AJ7: {=INDEX('Cap Rate to IRR Map'!$F$3:$F$623,MATCH(ROUND(AI7,4),ROUND('Cap Rate to IRR Map'!$E$3:$E$623,4),0))} -> 0.1 | AK7: =$AK$3 -> 0.05 | AL7: 0.1965
B8: =B7+1 -> 4 | C8: Columbus, OH | D8: =SUMIFS(Realpage!$I:$I,Realpage!$A:$A,$C8,Realpage!$F:$F,"Rent Roll (Rev/OSF)") -> 2.8266178 | E8: =SUMIFS(Realpage!$I:$I,Realpage!$A:$A,$C8,Realpage!$F:$F,"Asking RPSF") -> 2.999 | F8: =E8/D8 -> 1.0609853 | G8: {=SUMPRODUCT(('RP - Unit Starts'!$C$2:$C$101=$C8)*('RP - Unit Starts'!$F$2:$F$101="Unit Starts")*'RP - Unit Starts'!$I$2:$L$101)/SUMIFS('RP - Unit Starts'!$L:$L,'RP - Unit Starts'!$C:$C,$C8,'RP - Unit Starts'!$F:$F,"Existing Units")} -> 0.018135846 | H8: =F8-1 -> 0.060985307 | I8: =SUMIFS(Realpage!$I:$I,Realpage!$A:$A,$C8,Realpage!$F:$F,"Effective RPSF") -> 2.964 | J8: =I8/D8 -> 1.048603 | K8: =J8-1 -> 0.048603017 | L8: 0.044 | M8: =AVERAGEIF('Realpage - His. Rent Change'!$A$2:$A$577,'Q2 2026 Summary'!C6,'Realpage - His. Rent Change'!$I$2:$AV$577) -> 0.0759 | N8: =AVERAGE(L8:M8) -> 0.05995 | O8: =MAX(0,-(K8/M8)) -> 0 | P8: =($P$3*M8)+K8 -> 0.42810302 | Q8: =(1+P8)^(1/$P$3)-1 -> 0.073870488 | R8: =$R$3+P8 -> 0.47910302 | S8: =$S$3*$P$3 -> 0.125 | T8: =SUMIFS(Realpage!$I:$I,Realpage!$A:$A,$C8,Realpage!$F:$F,"NOI % of Revenue") -> 1.1013939 | U8: 1 | V8: =U8-T8 -> -0.10139388 | W8: =U8*(1+R8) -> 1.479103 | X8: =V8*(1+S8) -> -0.11406811 | Y8: =W8-X8 -> 1.5931711 | Z8: =Y8/T8-1 -> 0.44650444 | AA8: =(Y8/T8)^(1/$P$3)-1 -> 0.076623745 | AB8: =$AB$3 -> 0.05 | AC8: =AB8/$AB$3 -> 1 | AD8: =AC8*(1+$AD$3) -> 1.08 | AE8: =AC8*AB8 -> 0.05 | AF8: =AE8*(1+Z8) -> 0.072325222 | AG8: =AF8/AD8 -> 0.066967798 | AH8: =AG8-AB8 -> 0.016967798 | AI8: =ROUND(AH8,4) -> 0.017 | AJ8: {=INDEX('Cap Rate to IRR Map'!$F$3:$F$623,MATCH(ROUND(AI8,4),ROUND('Cap Rate to IRR Map'!$E$3:$E$623,4),0))} -> 0.146 | AK8: =$AK$3 -> 0.05 | AL8: 0.181
B9: =B8+1 -> 5 | C9: Savannah, GA | D9: =SUMIFS(Realpage!$I:$I,Realpage!$A:$A,$C9,Realpage!$F:$F,"Rent Roll (Rev/OSF)") -> 3.0129341 | E9: =SUMIFS(Realpage!$I:$I,Realpage!$A:$A,$C9,Realpage!$F:$F,"Asking RPSF") -> 3.196 | F9: =E9/D9 -> 1.06076 | G9: {=SUMPRODUCT(('RP - Unit Starts'!$C$2:$C$101=$C9)*('RP - Unit Starts'!$F$2:$F$101="Unit Starts")*'RP - Unit Starts'!$I$2:$L$101)/SUMIFS('RP - Unit Starts'!$L:$L,'RP - Unit Starts'!$C:$C,$C9,'RP - Unit Starts'!$F:$F,"Existing Units")} -> 0.018218772 | H9: =F9-1 -> 0.06076 | I9: =SUMIFS(Realpage!$I:$I,Realpage!$A:$A,$C9,Realpage!$F:$F,"Effective RPSF") -> 3.086 | J9: =I9/D9 -> 1.0242507 | K9: =J9-1 -> 0.024250738 | M9: =AVERAGEIF('Realpage - His. Rent Change'!$A$2:$A$577,'Q2 2026 Summary'!C13,'Realpage - His. Rent Change'!$I$2:$AV$577) -> 0.0663 | N9: =AVERAGE(L9:M9) -> 0.0663 | O9: =MAX(0,-(K9/M9)) -> 0 | P9: =($P$3*M9)+K9 -> 0.35575074 | Q9: =(1+P9)^(1/$P$3)-1 -> 0.062761884 | R9: =$R$3+P9 -> 0.40675074 | S9: =$S$3*$P$3 -> 0.125 | T9: =SUMIFS(Realpage!$I:$I,Realpage!$A:$A,$C9,Realpage!$F:$F,"NOI % of Revenue") -> 1.0744997 | U9: 1 | V9: =U9-T9 -> -0.074499718 | W9: =U9*(1+R9) -> 1.4067507 | X9: =V9*(1+S9) -> -0.083812183 | Y9: =W9-X9 -> 1.4905629 | Z9: =Y9/T9-1 -> 0.38721574 | AA9: =(Y9/T9)^(1/$P$3)-1 -> 0.067649747 | AB9: =$AB$3 -> 0.05 | AC9: =AB9/$AB$3 -> 1 | AD9: =AC9*(1+$AD$3) -> 1.08 | AE9: =AC9*AB9 -> 0.05 | AF9: =AE9*(1+Z9) -> 0.069360787 | AG9: =AF9/AD9 -> 0.064222951 | AH9: =AG9-AB9 -> 0.014222951 | AI9: =ROUND(AH9,4) -> 0.0142 | AJ9: {=INDEX('Cap Rate to IRR Map'!$F$3:$F$623,MATCH(ROUND(AI9,4),ROUND('Cap Rate to IRR Map'!$E$3:$E$623,4),0))} -> 0.125333 | AK9: =$AK$3 -> 0.05 | AL9: 0.105 | AN9: IF these markets have visibility to positive short term rent growth, and if longer term demand expectations are similar to previous 10 years
B10: =B9+1 -> 6 | C10: Miami-Miami Beach-Kendall, FL | D10: =SUMIFS(Realpage!$I:$I,Realpage!$A:$A,$C10,Realpage!$F:$F,"Rent Roll (Rev/OSF)") -> 5.6228267 | E10: =SUMIFS(Realpage!$I:$I,Realpage!$A:$A,$C10,Realpage!$F:$F,"Asking RPSF") -> 5.963 | F10: =E10/D10 -> 1.0604986 | G10: {=SUMPRODUCT(('RP - Unit Starts'!$C$2:$C$101=$C10)*('RP - Unit Starts'!$F$2:$F$101="Unit Starts")*'RP - Unit Starts'!$I$2:$L$101)/SUMIFS('RP - Unit Starts'!$L:$L,'RP - Unit Starts'!$C:$C,$C10,'RP - Unit Starts'!$F:$F,"Existing Units")} -> 0.024001428 | H10: =F10-1 -> 0.06049863 | I10: =SUMIFS(Realpage!$I:$I,Realpage!$A:$A,$C10,Realpage!$F:$F,"Effective RPSF") -> 5.857 | J10: =I10/D10 -> 1.0416469 | K10: =J10-1 -> 0.041646902 | M10: =AVERAGEIF('Realpage - His. Rent Change'!$A$2:$A$577,'Q2 2026 Summary'!C7,'Realpage - His. Rent Change'!$I$2:$AV$577) -> 0.1035 | N10: =AVERAGE(L10:M10) -> 0.1035 | O10: =MAX(0,-(K10/M10)) -> 0 | P10: =($P$3*M10)+K10 -> 0.5591469 | Q10: =(1+P10)^(1/$P$3)-1 -> 0.092892403 | R10: =$R$3+P10 -> 0.6101469 | S10: =$S$3*$P$3 -> 0.125 | T10: =SUMIFS(Realpage!$I:$I,Realpage!$A:$A,$C10,Realpage!$F:$F,"NOI % of Revenue") -> 1.1842603 | U10: 1 | V10: =U10-T10 -> -0.18426034 | W10: =U10*(1+R10) -> 1.6101469 | X10: =V10*(1+S10) -> -0.20729288 | Y10: =W10-X10 -> 1.8174398 | Z10: =Y10/T10-1 -> 0.53466238 | AA10: =(Y10/T10)^(1/$P$3)-1 -> 0.089438124 | AB10: =$AB$3 -> 0.05 | AC10: =AB10/$AB$3 -> 1 | AD10: =AC10*(1+$AD$3) -> 1.08 | AE10: =AC10*AB10 -> 0.05 | AF10: =AE10*(1+Z10) -> 0.076733119 | AG10: =AF10/AD10 -> 0.071049184 | AH10: =AG10-AB10 -> 0.021049184 | AI10: =ROUND(AH10,4) -> 0.021 | AJ10: {=INDEX('Cap Rate to IRR Map'!$F$3:$F$623,MATCH(ROUND(AI10,4),ROUND('Cap Rate to IRR Map'!$E$3:$E$623,4),0))} -> 0.173 | AK10: =$AK$3 -> 0.05 | AL10: 0.133667 | AO10: Dallas
B11: =B10+1 -> 7 | C11: Huntsville, AL | D11: =SUMIFS(Realpage!$I:$I,Realpage!$A:$A,$C11,Realpage!$F:$F,"Rent Roll (Rev/OSF)") -> 2.311599 | E11: =SUMIFS(Realpage!$I:$I,Realpage!$A:$A,$C11,Realpage!$F:$F,"Asking RPSF") -> 2.44 | F11: =E11/D11 -> 1.0555464 | G11: {=SUMPRODUCT(('RP - Unit Starts'!$C$2:$C$101=$C11)*('RP - Unit Starts'!$F$2:$F$101="Unit Starts")*'RP - Unit Starts'!$I$2:$L$101)/SUMIFS('RP - Unit Starts'!$L:$L,'RP - Unit Starts'!$C:$C,$C11,'RP - Unit Starts'!$F:$F,"Existing Units")} -> 0.028401115 | H11: =F11-1 -> 0.055546384 | I11: =SUMIFS(Realpage!$I:$I,Realpage!$A:$A,$C11,Realpage!$F:$F,"Effective RPSF") -> 2.336 | J11: =I11/D11 -> 1.0105559 | K11: =J11-1 -> 0.010555882 | M11: =AVERAGEIF('Realpage - His. Rent Change'!$A$2:$A$577,'Q2 2026 Summary'!C21,'Realpage - His. Rent Change'!$I$2:$AV$577) -> 0.0339 | N11: =AVERAGE(L11:M11) -> 0.0339 | O11: =MAX(0,-(K11/M11)) -> 0 | P11: =($P$3*M11)+K11 -> 0.18005588 | Q11: =(1+P11)^(1/$P$3)-1 -> 0.033666675 | R11: =$R$3+P11 -> 0.23105588 | S11: =$S$3*$P$3 -> 0.125 | T11: =SUMIFS(Realpage!$I:$I,Realpage!$A:$A,$C11,Realpage!$F:$F,"NOI % of Revenue") -> 1.062209 | U11: 1 | V11: =U11-T11 -> -0.062208979 | W11: =U11*(1+R11) -> 1.2310559 | X11: =V11*(1+S11) -> -0.069985102 | Y11: =W11-X11 -> 1.301041 | Z11: =Y11/T11-1 -> 0.22484465 | AA11: =(Y11/T11)^(1/$P$3)-1 -> 0.041396711 | AB11: =$AB$3 -> 0.05 | AC11: =AB11/$AB$3 -> 1 | AD11: =AC11*(1+$AD$3) -> 1.08 | AE11: =AC11*AB11 -> 0.05 | AF11: =AE11*(1+Z11) -> 0.061242232 | AG11: =AF11/AD11 -> 0.056705771 | AH11: =AG11-AB11 -> 0.0067057708 | AI11: =ROUND(AH11,4) -> 0.0067 | AJ11: {=INDEX('Cap Rate to IRR Map'!$F$3:$F$623,MATCH(ROUND(AI11,4),ROUND('Cap Rate to IRR Map'!$E$3:$E$623,4),0))} -> 0.063 | AK11: =$AK$3 -> 0.05 | AL11: 0.176 | AN11: No cap rate compression/expansion (5% going in and exit)
B12: =B11+1 -> 8 | C12: Richmond, VA | D12: =SUMIFS(Realpage!$I:$I,Realpage!$A:$A,$C12,Realpage!$F:$F,"Rent Roll (Rev/OSF)") -> 3.4093003 | E12: =SUMIFS(Realpage!$I:$I,Realpage!$A:$A,$C12,Realpage!$F:$F,"Asking RPSF") -> 3.589 | F12: =E12/D12 -> 1.0527087 | G12: {=SUMPRODUCT(('RP - Unit Starts'!$C$2:$C$101=$C12)*('RP - Unit Starts'!$F$2:$F$101="Unit Starts")*'RP - Unit Starts'!$I$2:$L$101)/SUMIFS('RP - Unit Starts'!$L:$L,'RP - Unit Starts'!$C:$C,$C12,'RP - Unit Starts'!$F:$F,"Existing Units")} -> 0.013758423 | H12: =F12-1 -> 0.052708661 | I12: =SUMIFS(Realpage!$I:$I,Realpage!$A:$A,$C12,Realpage!$F:$F,"Effective RPSF") -> 3.55 | J12: =I12/D12 -> 1.0412694 | K12: =J12-1 -> 0.041269364 | L12: 0.0451 | M12: =AVERAGEIF('Realpage - His. Rent Change'!$A$2:$A$577,'Q2 2026 Summary'!C10,'Realpage - His. Rent Change'!$I$2:$AV$577) -> 0.0591 | N12: =AVERAGE(L12:M12) -> 0.0521 | O12: =MAX(0,-(K12/M12)) -> 0 | P12: =($P$3*M12)+K12 -> 0.33676936 | Q12: =(1+P12)^(1/$P$3)-1 -> 0.059769208 | R12: =$R$3+P12 -> 0.38776936 | S12: =$S$3*$P$3 -> 0.125 | T12: =SUMIFS(Realpage!$I:$I,Realpage!$A:$A,$C12,Realpage!$F:$F,"NOI % of Revenue") -> 1.069903 | U12: 1 | V12: =U12-T12 -> -0.069903024 | W12: =U12*(1+R12) -> 1.3877694 | X12: =V12*(1+S12) -> -0.078640902 | Y12: =W12-X12 -> 1.4664103 | Z12: =Y12/T12-1 -> 0.3706011 | AA12: =(Y12/T12)^(1/$P$3)-1 -> 0.065079965 | AB12: =$AB$3 -> 0.05 | AC12: =AB12/$AB$3 -> 1 | AD12: =AC12*(1+$AD$3) -> 1.08 | AE12: =AC12*AB12 -> 0.05 | AF12: =AE12*(1+Z12) -> 0.068530055 | AG12: =AF12/AD12 -> 0.063453755 | AH12: =AG12-AB12 -> 0.013453755 | AI12: =ROUND(AH12,4) -> 0.0135 | AJ12: {=INDEX('Cap Rate to IRR Map'!$F$3:$F$623,MATCH(ROUND(AI12,4),ROUND('Cap Rate to IRR Map'!$E$3:$E$623,4),0))} -> 0.119667 | AK12: =$AK$3 -> 0.05 | AL12: 0.145 | AO12: WPB / Fort Lauderdale
B13: =B12+1 -> 9 | C13: Boise City, ID | D13: =SUMIFS(Realpage!$I:$I,Realpage!$A:$A,$C13,Realpage!$F:$F,"Rent Roll (Rev/OSF)") -> 1.7530692 | E13: =SUMIFS(Realpage!$I:$I,Realpage!$A:$A,$C13,Realpage!$F:$F,"Asking RPSF") -> 1.838 | F13: =E13/D13 -> 1.0484469 | G13: {=SUMPRODUCT(('RP - Unit Starts'!$C$2:$C$101=$C13)*('RP - Unit Starts'!$F$2:$F$101="Unit Starts")*'RP - Unit Starts'!$I$2:$L$101)/SUMIFS('RP - Unit Starts'!$L:$L,'RP - Unit Starts'!$C:$C,$C13,'RP - Unit Starts'!$F:$F,"Existing Units")} -> 0.011981268 | H13: =F13-1 -> 0.048446926 | I13: =SUMIFS(Realpage!$I:$I,Realpage!$A:$A,$C13,Realpage!$F:$F,"Effective RPSF") -> 1.824 | J13: =I13/D13 -> 1.0404609 | K13: =J13-1 -> 0.040460932 | M13: =AVERAGEIF('Realpage - His. Rent Change'!$A$2:$A$577,'Q2 2026 Summary'!C31,'Realpage - His. Rent Change'!$I$2:$AV$577) -> 0.0898 | N13: =AVERAGE(L13:M13) -> 0.0898 | O13: =MAX(0,-(K13/M13)) -> 0 | P13: =($P$3*M13)+K13 -> 0.48946093 | Q13: =(1+P13)^(1/$P$3)-1 -> 0.082943561 | R13: =$R$3+P13 -> 0.54046093 | S13: =$S$3*$P$3 -> 0.125 | T13: =SUMIFS(Realpage!$I:$I,Realpage!$A:$A,$C13,Realpage!$F:$F,"NOI % of Revenue") -> 0.66685537 | U13: 1 | V13: =U13-T13 -> 0.33314463 | W13: =U13*(1+R13) -> 1.5404609 | X13: =V13*(1+S13) -> 0.37478771 | Y13: =W13-X13 -> 1.1656732 | Z13: =Y13/T13-1 -> 0.74801505 | AA13: =(Y13/T13)^(1/$P$3)-1 -> 0.11817308 | AB13: =$AB$3 -> 0.05 | AC13: =AB13/$AB$3 -> 1 | AD13: =AC13*(1+$AD$3) -> 1.08 | AE13: =AC13*AB13 -> 0.05 | AF13: =AE13*(1+Z13) -> 0.087400752 | AG13: =AF13/AD13 -> 0.080926623 | AH13: =AG13-AB13 -> 0.030926623 | AI13: =ROUND(AH13,4) -> 0.0309 | AJ13: {=INDEX('Cap Rate to IRR Map'!$F$3:$F$623,MATCH(ROUND(AI13,4),ROUND('Cap Rate to IRR Map'!$E$3:$E$623,4),0))} -> 0.24000292 | AK13: =$AK$3 -> 0.05 | AL13: 0.169667 | AN13: THEN these markets should be actionable for us on a market pricing/market debt basis:
B14: =B13+1 -> 10 | C14: Wilmington, NC | D14: =SUMIFS(Realpage!$I:$I,Realpage!$A:$A,$C14,Realpage!$F:$F,"Rent Roll (Rev/OSF)") -> 3.01842 | E14: =SUMIFS(Realpage!$I:$I,Realpage!$A:$A,$C14,Realpage!$F:$F,"Asking RPSF") -> 3.154 | F14: =E14/D14 -> 1.0449175 | G14: {=SUMPRODUCT(('RP - Unit Starts'!$C$2:$C$101=$C14)*('RP - Unit Starts'!$F$2:$F$101="Unit Starts")*'RP - Unit Starts'!$I$2:$L$101)/SUMIFS('RP - Unit Starts'!$L:$L,'RP - Unit Starts'!$C:$C,$C14,'RP - Unit Starts'!$F:$F,"Existing Units")} -> 0.018594007 | H14: =F14-1 -> 0.044917537 | I14: =SUMIFS(Realpage!$I:$I,Realpage!$A:$A,$C14,Realpage!$F:$F,"Effective RPSF") -> 3.077 | J14: =I14/D14 -> 1.0194075 | K14: =J14-1 -> 0.019407502 | M14: =AVERAGEIF('Realpage - His. Rent Change'!$A$2:$A$577,'Q2 2026 Summary'!C18,'Realpage - His. Rent Change'!$I$2:$AV$577) -> 0.0396 | N14: =AVERAGE(L14:M14) -> 0.0396 | O14: =MAX(0,-(K14/M14)) -> 0 | P14: =($P$3*M14)+K14 -> 0.2174075 | Q14: =(1+P14)^(1/$P$3)-1 -> 0.040128975 | R14: =$R$3+P14 -> 0.2684075 | S14: =$S$3*$P$3 -> 0.125 | T14: =SUMIFS(Realpage!$I:$I,Realpage!$A:$A,$C14,Realpage!$F:$F,"NOI % of Revenue") -> 1.2239072 | U14: 1 | V14: =U14-T14 -> -0.22390722 | W14: =U14*(1+R14) -> 1.2684075 | X14: =V14*(1+S14) -> -0.25189563 | Y14: =W14-X14 -> 1.5203031 | Z14: =Y14/T14-1 -> 0.24217187 | AA14: =(Y14/T14)^(1/$P$3)-1 -> 0.044326596 | AB14: =$AB$3 -> 0.05 | AC14: =AB14/$AB$3 -> 1 | AD14: =AC14*(1+$AD$3) -> 1.08 | AE14: =AC14*AB14 -> 0.05 | AF14: =AE14*(1+Z14) -> 0.062108594 | AG14: =AF14/AD14 -> 0.057507957 | AH14: =AG14-AB14 -> 0.0075079571 | AI14: =ROUND(AH14,4) -> 0.0075 | AJ14: {=INDEX('Cap Rate to IRR Map'!$F$3:$F$623,MATCH(ROUND(AI14,4),ROUND('Cap Rate to IRR Map'!$E$3:$E$623,4),0))} -> 0.07 | AK14: =$AK$3 -> 0.05 | AL14: 0.174
B15: =B14+1 -> 11 | C15: Omaha, NE-IA | D15: =SUMIFS(Realpage!$I:$I,Realpage!$A:$A,$C15,Realpage!$F:$F,"Rent Roll (Rev/OSF)") -> 2.7537036 | E15: =SUMIFS(Realpage!$I:$I,Realpage!$A:$A,$C15,Realpage!$F:$F,"Asking RPSF") -> 2.877 | F15: =E15/D15 -> 1.0447748 | G15: {=SUMPRODUCT(('RP - Unit Starts'!$C$2:$C$101=$C15)*('RP - Unit Starts'!$F$2:$F$101="Unit Starts")*'RP - Unit Starts'!$I$2:$L$101)/SUMIFS('RP - Unit Starts'!$L:$L,'RP - Unit Starts'!$C:$C,$C15,'RP - Unit Starts'!$F:$F,"Existing Units")} -> 0.03111465 | H15: =F15-1 -> 0.044774754 | I15: =SUMIFS(Realpage!$I:$I,Realpage!$A:$A,$C15,Realpage!$F:$F,"Effective RPSF") -> 2.847 | J15: =I15/D15 -> 1.0338803 | K15: =J15-1 -> 0.033880335 | M15: =AVERAGEIF('Realpage - His. Rent Change'!$A$2:$A$577,'Q2 2026 Summary'!C11,'Realpage - His. Rent Change'!$I$2:$AV$577) -> 0.0346 | N15: =AVERAGE(L15:M15) -> 0.0346 | O15: =MAX(0,-(K15/M15)) -> 0 | P15: =($P$3*M15)+K15 -> 0.20688034 | Q15: =(1+P15)^(1/$P$3)-1 -> 0.03832388 | R15: =$R$3+P15 -> 0.25788034 | S15: =$S$3*$P$3 -> 0.125 | T15: =SUMIFS(Realpage!$I:$I,Realpage!$A:$A,$C15,Realpage!$F:$F,"NOI % of Revenue") -> 1.166822 | U15: 1 | V15: =U15-T15 -> -0.166822 | W15: =U15*(1+R15) -> 1.2578803 | X15: =V15*(1+S15) -> -0.18767475 | Y15: =W15-X15 -> 1.4455551 | Z15: =Y15/T15-1 -> 0.23888227 | AA15: =(Y15/T15)^(1/$P$3)-1 -> 0.043772877 | AB15: =$AB$3 -> 0.05 | AC15: =AB15/$AB$3 -> 1 | AD15: =AC15*(1+$AD$3) -> 1.08 | AE15: =AC15*AB15 -> 0.05 | AF15: =AE15*(1+Z15) -> 0.061944113 | AG15: =AF15/AD15 -> 0.057355661 | AH15: =AG15-AB15 -> 0.0073556605 | AI15: =ROUND(AH15,4) -> 0.0074 | AJ15: {=INDEX('Cap Rate to IRR Map'!$F$3:$F$623,MATCH(ROUND(AI15,4),ROUND('Cap Rate to IRR Map'!$E$3:$E$623,4),0))} -> 0.069 | AK15: =$AK$3 -> 0.05 | AL15: 0.187 | AO15: Nashville
B16: =B15+1 -> 12 | C16: Virginia Beach-Chesapeake-Norfolk, VA-NC | D16: =SUMIFS(Realpage!$I:$I,Realpage!$A:$A,$C16,Realpage!$F:$F,"Rent Roll (Rev/OSF)") -> 3.320201 | E16: =SUMIFS(Realpage!$I:$I,Realpage!$A:$A,$C16,Realpage!$F:$F,"Asking RPSF") -> 3.468 | F16: =E16/D16 -> 1.0445151 | G16: {=SUMPRODUCT(('RP - Unit Starts'!$C$2:$C$101=$C16)*('RP - Unit Starts'!$F$2:$F$101="Unit Starts")*'RP - Unit Starts'!$I$2:$L$101)/SUMIFS('RP - Unit Starts'!$L:$L,'RP - Unit Starts'!$C:$C,$C16,'RP - Unit Starts'!$F:$F,"Existing Units")} -> 0.0039863635 | H16: =F16-1 -> 0.044515078 | I16: =SUMIFS(Realpage!$I:$I,Realpage!$A:$A,$C16,Realpage!$F:$F,"Effective RPSF") -> 3.456 | J16: =I16/D16 -> 1.0409008 | K16: =J16-1 -> 0.040900838 | M16: =AVERAGEIF('Realpage - His. Rent Change'!$A$2:$A$577,'Q2 2026 Summary'!C8,'Realpage - His. Rent Change'!$I$2:$AV$577) -> 0.0513 | N16: =AVERAGE(L16:M16) -> 0.0513 | O16: =MAX(0,-(K16/M16)) -> 0 | P16: =($P$3*M16)+K16 -> 0.29740084 | Q16: =(1+P16)^(1/$P$3)-1 -> 0.053452201 | R16: =$R$3+P16 -> 0.34840084 | S16: =$S$3*$P$3 -> 0.125 | T16: =SUMIFS(Realpage!$I:$I,Realpage!$A:$A,$C16,Realpage!$F:$F,"NOI % of Revenue") -> 1.184724 | U16: 1 | V16: =U16-T16 -> -0.18472398 | W16: =U16*(1+R16) -> 1.3484008 | X16: =V16*(1+S16) -> -0.20781448 | Y16: =W16-X16 -> 1.5562153 | Z16: =Y16/T16-1 -> 0.31356784 | AA16: =(Y16/T16)^(1/$P$3)-1 -> 0.056064639 | AB16: =$AB$3 -> 0.05 | AC16: =AB16/$AB$3 -> 1 | AD16: =AC16*(1+$AD$3) -> 1.08 | AE16: =AC16*AB16 -> 0.05 | AF16: =AE16*(1+Z16) -> 0.065678392 | AG16: =AF16/AD16 -> 0.060813326 | AH16: =AG16-AB16 -> 0.010813326 | AI16: =ROUND(AH16,4) -> 0.0108 | AJ16: {=INDEX('Cap Rate to IRR Map'!$F$3:$F$623,MATCH(ROUND(AI16,4),ROUND('Cap Rate to IRR Map'!$E$3:$E$623,4),0))} -> 0.098 | AK16: =$AK$3 -> 0.05 | AL16: 0.123
B17: =B16+1 -> 13 | C17: Nashville-Davidson--Murfreesboro--Franklin, TN | D17: =SUMIFS(Realpage!$I:$I,Realpage!$A:$A,$C17,Realpage!$F:$F,"Rent Roll (Rev/OSF)") -> 3.3563372 | E17: =SUMIFS(Realpage!$I:$I,Realpage!$A:$A,$C17,Realpage!$F:$F,"Asking RPSF") -> 3.501 | F17: =E17/D17 -> 1.0431014 | G17: {=SUMPRODUCT(('RP - Unit Starts'!$C$2:$C$101=$C17)*('RP - Unit Starts'!$F$2:$F$101="Unit Starts")*'RP - Unit Starts'!$I$2:$L$101)/SUMIFS('RP - Unit Starts'!$L:$L,'RP - Unit Starts'!$C:$C,$C17,'RP - Unit Starts'!$F:$F,"Existing Units")} -> 0.028013395 | H17: =F17-1 -> 0.043101392 | I17: =SUMIFS(Realpage!$I:$I,Realpage!$A:$A,$C17,Realpage!$F:$F,"Effective RPSF") -> 3.368 | J17: =I17/D17 -> 1.0034749 | K17: =J17-1 -> 0.0034748612 | L17: 0.0365 | M17: =AVERAGEIF('Realpage - His. Rent Change'!$A$2:$A$577,'Q2 2026 Summary'!C19,'Realpage - His. Rent Change'!$I$2:$AV$577) -> 0.0535 | N17: =AVERAGE(L17:M17) -> 0.045 | O17: =MAX(0,-(K17/M17)) -> 0 | P17: =($P$3*M17)+K17 -> 0.27097486 | Q17: =(1+P17)^(1/$P$3)-1 -> 0.049125377 | R17: =$R$3+P17 -> 0.32197486 | S17: =$S$3*$P$3 -> 0.125 | T17: =SUMIFS(Realpage!$I:$I,Realpage!$A:$A,$C17,Realpage!$F:$F,"NOI % of Revenue") -> 1.1659141 | U17: 1 | V17: =U17-T17 -> -0.16591406 | W17: =U17*(1+R17) -> 1.3219749 | X17: =V17*(1+S17) -> -0.18665332 | Y17: =W17-X17 -> 1.5086282 | Z17: =Y17/T17-1 -> 0.29394458 | AA17: =(Y17/T17)^(1/$P$3)-1 -> 0.052890325 | AB17: =$AB$3 -> 0.05 | AC17: =AB17/$AB$3 -> 1 | AD17: =AC17*(1+$AD$3) -> 1.08 | AE17: =AC17*AB17 -> 0.05 | AF17: =AE17*(1+Z17) -> 0.064697229 | AG17: =AF17/AD17 -> 0.059904842 | AH17: =AG17-AB17 -> 0.0099048416 | AI17: =ROUND(AH17,4) -> 0.0099 | AJ17: {=INDEX('Cap Rate to IRR Map'!$F$3:$F$623,MATCH(ROUND(AI17,4),ROUND('Cap Rate to IRR Map'!$E$3:$E$623,4),0))} -> 0.09075 | AK17: =$AK$3 -> 0.05 | AL17: 0.086
B18: =B17+1 -> 14 | C18: Minneapolis-St. Paul-Bloomington, MN-WI | D18: =SUMIFS(Realpage!$I:$I,Realpage!$A:$A,$C18,Realpage!$F:$F,"Rent Roll (Rev/OSF)") -> 3.6840669 | E18: =SUMIFS(Realpage!$I:$I,Realpage!$A:$A,$C18,Realpage!$F:$F,"Asking RPSF") -> 3.794 | F18: =E18/D18 -> 1.0298401 | G18: {=SUMPRODUCT(('RP - Unit Starts'!$C$2:$C$101=$C18)*('RP - Unit Starts'!$F$2:$F$101="Unit Starts")*'RP - Unit Starts'!$I$2:$L$101)/SUMIFS('RP - Unit Starts'!$L:$L,'RP - Unit Starts'!$C:$C,$C18,'RP - Unit Starts'!$F:$F,"Existing Units")} -> 0.0093966239 | H18: =F18-1 -> 0.029840137 | I18: =SUMIFS(Realpage!$I:$I,Realpage!$A:$A,$C18,Realpage!$F:$F,"Effective RPSF") -> 3.736 | J18: =I18/D18 -> 1.0140967 | K18: =J18-1 -> 0.014096666 | L18: 0.0264 | M18: =AVERAGEIF('Realpage - His. Rent Change'!$A$2:$A$577,'Q2 2026 Summary'!C14,'Realpage - His. Rent Change'!$I$2:$AV$577) -> 0.0714 | N18: =AVERAGE(L18:M18) -> 0.0489 | O18: =MAX(0,-(K18/M18)) -> 0 | P18: =($P$3*M18)+K18 -> 0.37109667 | Q18: =(1+P18)^(1/$P$3)-1 -> 0.065156973 | R18: =$R$3+P18 -> 0.42209667 | S18: =$S$3*$P$3 -> 0.125 | T18: =SUMIFS(Realpage!$I:$I,Realpage!$A:$A,$C18,Realpage!$F:$F,"NOI % of Revenue") -> 1.0798477 | U18: 1 | V18: =U18-T18 -> -0.079847711 | W18: =U18*(1+R18) -> 1.4220967 | X18: =V18*(1+S18) -> -0.089828674 | Y18: =W18-X18 -> 1.5119253 | Z18: =Y18/T18-1 -> 0.4001283 | AA18: =(Y18/T18)^(1/$P$3)-1 -> 0.06962998 | AB18: =$AB$3 -> 0.05 | AC18: =AB18/$AB$3 -> 1 | AD18: =AC18*(1+$AD$3) -> 1.08 | AE18: =AC18*AB18 -> 0.05 | AF18: =AE18*(1+Z18) -> 0.070006415 | AG18: =AF18/AD18 -> 0.064820755 | AH18: =AG18-AB18 -> 0.014820755 | AI18: =ROUND(AH18,4) -> 0.0148 | AJ18: {=INDEX('Cap Rate to IRR Map'!$F$3:$F$623,MATCH(ROUND(AI18,4),ROUND('Cap Rate to IRR Map'!$E$3:$E$623,4),0))} -> 0.129667 | AK18: =$AK$3 -> 0.05 | AL18: 0.164667
B19: =B18+1 -> 15 | C19: Kansas City, MO-KS | D19: =SUMIFS(Realpage!$I:$I,Realpage!$A:$A,$C19,Realpage!$F:$F,"Rent Roll (Rev/OSF)") -> 2.9700488 | E19: =SUMIFS(Realpage!$I:$I,Realpage!$A:$A,$C19,Realpage!$F:$F,"Asking RPSF") -> 3.042 | F19: =E19/D19 -> 1.0242256 | G19: {=SUMPRODUCT(('RP - Unit Starts'!$C$2:$C$101=$C19)*('RP - Unit Starts'!$F$2:$F$101="Unit Starts")*'RP - Unit Starts'!$I$2:$L$101)/SUMIFS('RP - Unit Starts'!$L:$L,'RP - Unit Starts'!$C:$C,$C19,'RP - Unit Starts'!$F:$F,"Existing Units")} -> 0.025479466 | H19: =F19-1 -> 0.02422561 | I19: =SUMIFS(Realpage!$I:$I,Realpage!$A:$A,$C19,Realpage!$F:$F,"Effective RPSF") -> 3.017 | J19: =I19/D19 -> 1.0158082 | K19: =J19-1 -> 0.01580824 | L19: 0.0367 | M19: =AVERAGEIF('Realpage - His. Rent Change'!$A$2:$A$577,'Q2 2026 Summary'!C16,'Realpage - His. Rent Change'!$I$2:$AV$577) -> 0.0275 | N19: =AVERAGE(L19:M19) -> 0.0321 | O19: =MAX(0,-(K19/M19)) -> 0 | P19: =($P$3*M19)+K19 -> 0.15330824 | Q19: =(1+P19)^(1/$P$3)-1 -> 0.028937698 | R19: =$R$3+P19 -> 0.20430824 | S19: =$S$3*$P$3 -> 0.125 | T19: =SUMIFS(Realpage!$I:$I,Realpage!$A:$A,$C19,Realpage!$F:$F,"NOI % of Revenue") -> 1.104193 | U19: 1 | V19: =U19-T19 -> -0.104193 | W19: =U19*(1+R19) -> 1.2043082 | X19: =V19*(1+S19) -> -0.11721712 | Y19: =W19-X19 -> 1.3215254 | Z19: =Y19/T19-1 -> 0.19682462 | AA19: =(Y19/T19)^(1/$P$3)-1 -> 0.036587823 | AB19: =$AB$3 -> 0.05 | AC19: =AB19/$AB$3 -> 1 | AD19: =AC19*(1+$AD$3) -> 1.08 | AE19: =AC19*AB19 -> 0.05 | AF19: =AE19*(1+Z19) -> 0.059841231 | AG19: =AF19/AD19 -> 0.055408547 | AH19: =AG19-AB19 -> 0.0054085471 | AI19: =ROUND(AH19,4) -> 0.0054 | AJ19: {=INDEX('Cap Rate to IRR Map'!$F$3:$F$623,MATCH(ROUND(AI19,4),ROUND('Cap Rate to IRR Map'!$E$3:$E$623,4),0))} -> 0.051 | AK19: =$AK$3 -> 0.05 | AL19: 0.181
B20: =B19+1 -> 16 | C20: Birmingham, AL | D20: =SUMIFS(Realpage!$I:$I,Realpage!$A:$A,$C20,Realpage!$F:$F,"Rent Roll (Rev/OSF)") -> 1.272755 | E20: =SUMIFS(Realpage!$I:$I,Realpage!$A:$A,$C20,Realpage!$F:$F,"Asking RPSF") -> 1.303 | F20: =E20/D20 -> 1.0237634 | G20: {=SUMPRODUCT(('RP - Unit Starts'!$C$2:$C$101=$C20)*('RP - Unit Starts'!$F$2:$F$101="Unit Starts")*'RP - Unit Starts'!$I$2:$L$101)/SUMIFS('RP - Unit Starts'!$L:$L,'RP - Unit Starts'!$C:$C,$C20,'RP - Unit Starts'!$F:$F,"Existing Units")} -> 0.001636324 | H20: =F20-1 -> 0.023763405 | I20: =SUMIFS(Realpage!$I:$I,Realpage!$A:$A,$C20,Realpage!$F:$F,"Effective RPSF") -> 1.273 | J20: =I20/D20 -> 1.0001925 | K20: =J20-1 -> 0.00019248987 | M20: =AVERAGEIF('Realpage - His. Rent Change'!$A$2:$A$577,'Q2 2026 Summary'!C23,'Realpage - His. Rent Change'!$I$2:$AV$577) -> 0.0693 | N20: =AVERAGE(L20:M20) -> 0.0693 | O20: =MAX(0,-(K20/M20)) -> 0 | P20: =($P$3*M20)+K20 -> 0.34669249 | Q20: =(1+P20)^(1/$P$3)-1 -> 0.061337936 | R20: =$R$3+P20 -> 0.39769249 | S20: =$S$3*$P$3 -> 0.125 | T20: =SUMIFS(Realpage!$I:$I,Realpage!$A:$A,$C20,Realpage!$F:$F,"NOI % of Revenue") -> 0.51096299 | U20: 1 | V20: =U20-T20 -> 0.48903701 | W20: =U20*(1+R20) -> 1.3976925 | X20: =V20*(1+S20) -> 0.55016664 | Y20: =W20-X20 -> 0.84752585 | Z20: =Y20/T20-1 -> 0.65868345 | AA20: =(Y20/T20)^(1/$P$3)-1 -> 0.10650327 | AB20: =$AB$3 -> 0.05 | AC20: =AB20/$AB$3 -> 1 | AD20: =AC20*(1+$AD$3) -> 1.08 | AE20: =AC20*AB20 -> 0.05 | AF20: =AE20*(1+Z20) -> 0.082934172 | AG20: =AF20/AD20 -> 0.0767909 | AH20: =AG20-AB20 -> 0.0267909 | AI20: =ROUND(AH20,4) -> 0.0268 | AJ20: {=INDEX('Cap Rate to IRR Map'!$F$3:$F$623,MATCH(ROUND(AI20,4),ROUND('Cap Rate to IRR Map'!$E$3:$E$623,4),0))} -> 0.209 | AK20: =$AK$3 -> 0.05 | AL20: 0.187 | AO20: Raleigh
B21: =B20+1 -> 17 | C21: Louisville/Jefferson County, KY-IN | D21: =SUMIFS(Realpage!$I:$I,Realpage!$A:$A,$C21,Realpage!$F:$F,"Rent Roll (Rev/OSF)") -> 2.639315 | E21: =SUMIFS(Realpage!$I:$I,Realpage!$A:$A,$C21,Realpage!$F:$F,"Asking RPSF") -> 2.7 | F21: =E21/D21 -> 1.0229927 | G21: {=SUMPRODUCT(('RP - Unit Starts'!$C$2:$C$101=$C21)*('RP - Unit Starts'!$F$2:$F$101="Unit Starts")*'RP - Unit Starts'!$I$2:$L$101)/SUMIFS('RP - Unit Starts'!$L:$L,'RP - Unit Starts'!$C:$C,$C21,'RP - Unit Starts'!$F:$F,"Existing Units")} -> 0.021078337 | H21: =F21-1 -> 0.022992725 | I21: =SUMIFS(Realpage!$I:$I,Realpage!$A:$A,$C21,Realpage!$F:$F,"Effective RPSF") -> 2.655 | J21: =I21/D21 -> 1.0059428 | K21: =J21-1 -> 0.0059428458 | M21: =AVERAGEIF('Realpage - His. Rent Change'!$A$2:$A$577,'Q2 2026 Summary'!C20,'Realpage - His. Rent Change'!$I$2:$AV$577) -> 0.0419 | N21: =AVERAGE(L21:M21) -> 0.0419 | O21: =MAX(0,-(K21/M21)) -> 0 | P21: =($P$3*M21)+K21 -> 0.21544285 | Q21: =(1+P21)^(1/$P$3)-1 -> 0.039793045 | R21: =$R$3+P21 -> 0.26644285 | S21: =$S$3*$P$3 -> 0.125 | T21: =SUMIFS(Realpage!$I:$I,Realpage!$A:$A,$C21,Realpage!$F:$F,"NOI % of Revenue") -> 1.0370489 | U21: 1 | V21: =U21-T21 -> -0.037048852 | W21: =U21*(1+R21) -> 1.2664428 | X21: =V21*(1+S21) -> -0.041679958 | Y21: =W21-X21 -> 1.3081228 | Z21: =Y21/T21-1 -> 0.26138976 | AA21: =(Y21/T21)^(1/$P$3)-1 -> 0.047538179 | AB21: =$AB$3 -> 0.05 | AC21: =AB21/$AB$3 -> 1 | AD21: =AC21*(1+$AD$3) -> 1.08 | AE21: =AC21*AB21 -> 0.05 | AF21: =AE21*(1+Z21) -> 0.063069488 | AG21: =AF21/AD21 -> 0.058397674 | AH21: =AG21-AB21 -> 0.0083976742 | AI21: =ROUND(AH21,4) -> 0.0084 | AJ21: {=INDEX('Cap Rate to IRR Map'!$F$3:$F$623,MATCH(ROUND(AI21,4),ROUND('Cap Rate to IRR Map'!$E$3:$E$623,4),0))} -> 0.078 | AK21: =$AK$3 -> 0.05 | AL21: 0.171 | AN21: These other markets are fringe returns from a market pricing/debt, perspective
B22: =B21+1 -> 18 | C22: Cincinnati, OH-KY-IN | D22: =SUMIFS(Realpage!$I:$I,Realpage!$A:$A,$C22,Realpage!$F:$F,"Rent Roll (Rev/OSF)") -> 3.1663271 | E22: =SUMIFS(Realpage!$I:$I,Realpage!$A:$A,$C22,Realpage!$F:$F,"Asking RPSF") -> 3.238 | F22: =E22/D22 -> 1.022636 | G22: {=SUMPRODUCT(('RP - Unit Starts'!$C$2:$C$101=$C22)*('RP - Unit Starts'!$F$2:$F$101="Unit Starts")*'RP - Unit Starts'!$I$2:$L$101)/SUMIFS('RP - Unit Starts'!$L:$L,'RP - Unit Starts'!$C:$C,$C22,'RP - Unit Starts'!$F:$F,"Existing Units")} -> 0.014331659 | H22: =F22-1 -> 0.02263597 | I22: =SUMIFS(Realpage!$I:$I,Realpage!$A:$A,$C22,Realpage!$F:$F,"Effective RPSF") -> 3.218 | J22: =I22/D22 -> 1.0163195 | K22: =J22-1 -> 0.016319504 | M22: =AVERAGEIF('Realpage - His. Rent Change'!$A$2:$A$577,'Q2 2026 Summary'!C17,'Realpage - His. Rent Change'!$I$2:$AV$577) -> 0.0893 | N22: =AVERAGE(L22:M22) -> 0.0893 | O22: =MAX(0,-(K22/M22)) -> 0 | P22: =($P$3*M22)+K22 -> 0.4628195 | Q22: =(1+P22)^(1/$P$3)-1 -> 0.079041501 | R22: =$R$3+P22 -> 0.5138195 | S22: =$S$3*$P$3 -> 0.125 | T22: =SUMIFS(Realpage!$I:$I,Realpage!$A:$A,$C22,Realpage!$F:$F,"NOI % of Revenue") -> 1.013682 | U22: 1 | V22: =U22-T22 -> -0.013682018 | W22: =U22*(1+R22) -> 1.5138195 | X22: =V22*(1+S22) -> -0.01539227 | Y22: =W22-X22 -> 1.5292118 | Z22: =Y22/T22-1 -> 0.50857147 | AA22: =(Y22/T22)^(1/$P$3)-1 -> 0.08570835 | AB22: =$AB$3 -> 0.05 | AC22: =AB22/$AB$3 -> 1 | AD22: =AC22*(1+$AD$3) -> 1.08 | AE22: =AC22*AB22 -> 0.05 | AF22: =AE22*(1+Z22) -> 0.075428574 | AG22: =AF22/AD22 -> 0.069841272 | AH22: =AG22-AB22 -> 0.019841272 | AI22: =ROUND(AH22,4) -> 0.0198 | AJ22: {=INDEX('Cap Rate to IRR Map'!$F$3:$F$623,MATCH(ROUND(AI22,4),ROUND('Cap Rate to IRR Map'!$E$3:$E$623,4),0))} -> 0.165 | AK22: =$AK$3 -> 0.05 | AL22: 0.14225 | AO22: SLC
B23: =B22+1 -> 19 | C23: West Palm Beach-Boca Raton-Delray Beach, FL | D23: =SUMIFS(Realpage!$I:$I,Realpage!$A:$A,$C23,Realpage!$F:$F,"Rent Roll (Rev/OSF)") -> 4.8360194 | E23: =SUMIFS(Realpage!$I:$I,Realpage!$A:$A,$C23,Realpage!$F:$F,"Asking RPSF") -> 4.912 | F23: =E23/D23 -> 1.0157114 | G23: {=SUMPRODUCT(('RP - Unit Starts'!$C$2:$C$101=$C23)*('RP - Unit Starts'!$F$2:$F$101="Unit Starts")*'RP - Unit Starts'!$I$2:$L$101)/SUMIFS('RP - Unit Starts'!$L:$L,'RP - Unit Starts'!$C:$C,$C23,'RP - Unit Starts'!$F:$F,"Existing Units")} -> 0.022218027 | H23: =F23-1 -> 0.015711401 | I23: =SUMIFS(Realpage!$I:$I,Realpage!$A:$A,$C23,Realpage!$F:$F,"Effective RPSF") -> 4.884 | J23: =I23/D23 -> 1.0099215 | K23: =J23-1 -> 0.0099215155 | L23: 0.0503 | M23: =AVERAGEIF('Realpage - His. Rent Change'!$A$2:$A$577,'Q2 2026 Summary'!C15,'Realpage - His. Rent Change'!$I$2:$AV$577) -> 0.0329 | N23: =AVERAGE(L23:M23) -> 0.0416 | O23: =MAX(0,-(K23/M23)) -> 0 | P23: =($P$3*M23)+K23 -> 0.17442152 | Q23: =(1+P23)^(1/$P$3)-1 -> 0.032677702 | R23: =$R$3+P23 -> 0.22542152 | S23: =$S$3*$P$3 -> 0.125 | T23: =SUMIFS(Realpage!$I:$I,Realpage!$A:$A,$C23,Realpage!$F:$F,"NOI % of Revenue") -> 1.1956526 | U23: 1 | V23: =U23-T23 -> -0.1956526 | W23: =U23*(1+R23) -> 1.2254215 | X23: =V23*(1+S23) -> -0.22010918 | Y23: =W23-X23 -> 1.4455307 | Z23: =Y23/T23-1 -> 0.20898887 | AA23: =(Y23/T23)^(1/$P$3)-1 -> 0.038686437 | AB23: =$AB$3 -> 0.05 | AC23: =AB23/$AB$3 -> 1 | AD23: =AC23*(1+$AD$3) -> 1.08 | AE23: =AC23*AB23 -> 0.05 | AF23: =AE23*(1+Z23) -> 0.060449444 | AG23: =AF23/AD23 -> 0.055971707 | AH23: =AG23-AB23 -> 0.0059717071 | AI23: =ROUND(AH23,4) -> 0.006 | AJ23: {=INDEX('Cap Rate to IRR Map'!$F$3:$F$623,MATCH(ROUND(AI23,4),ROUND('Cap Rate to IRR Map'!$E$3:$E$623,4),0))} -> 0.056 | AK23: =$AK$3 -> 0.05 | AL23: 0.15 | AN23: Therefore they need incremental return support, pursue the following:
B24: =B23+1 -> 20 | C24: Charleston-North Charleston, SC | D24: =SUMIFS(Realpage!$I:$I,Realpage!$A:$A,$C24,Realpage!$F:$F,"Rent Roll (Rev/OSF)") -> 3.6438246 | E24: =SUMIFS(Realpage!$I:$I,Realpage!$A:$A,$C24,Realpage!$F:$F,"Asking RPSF") -> 3.692 | F24: =E24/D24 -> 1.0132211 | G24: {=SUMPRODUCT(('RP - Unit Starts'!$C$2:$C$101=$C24)*('RP - Unit Starts'!$F$2:$F$101="Unit Starts")*'RP - Unit Starts'!$I$2:$L$101)/SUMIFS('RP - Unit Starts'!$L:$L,'RP - Unit Starts'!$C:$C,$C24,'RP - Unit Starts'!$F:$F,"Existing Units")} -> 0.029310723 | H24: =F24-1 -> 0.013221118 | I24: =SUMIFS(Realpage!$I:$I,Realpage!$A:$A,$C24,Realpage!$F:$F,"Effective RPSF") -> 3.624 | J24: =I24/D24 -> 0.99455941 | K24: =J24-1 -> -0.0054405928 | M24: =AVERAGEIF('Realpage - His. Rent Change'!$A$2:$A$577,'Q2 2026 Summary'!C28,'Realpage - His. Rent Change'!$I$2:$AV$577) -> 0.0468 | N24: =AVERAGE(L24:M24) -> 0.0468 | O24: =MAX(0,-(K24/M24)) -> 0.11625198 | P24: =($P$3*M24)+K24 -> 0.22855941 | Q24: =(1+P24)^(1/$P$3)-1 -> 0.042027624 | R24: =$R$3+P24 -> 0.27955941 | S24: =$S$3*$P$3 -> 0.125 | T24: =SUMIFS(Realpage!$I:$I,Realpage!$A:$A,$C24,Realpage!$F:$F,"NOI % of Revenue") -> 1.0900598 | U24: 1 | V24: =U24-T24 -> -0.090059789 | W24: =U24*(1+R24) -> 1.2795594 | X24: =V24*(1+S24) -> -0.10131726 | Y24: =W24-X24 -> 1.3808767 | Z24: =Y24/T24-1 -> 0.26678984 | AA24: =(Y24/T24)^(1/$P$3)-1 -> 0.048433561 | AB24: =$AB$3 -> 0.05 | AC24: =AB24/$AB$3 -> 1 | AD24: =AC24*(1+$AD$3) -> 1.08 | AE24: =AC24*AB24 -> 0.05 | AF24: =AE24*(1+Z24) -> 0.063339492 | AG24: =AF24/AD24 -> 0.058647678 | AH24: =AG24-AB24 -> 0.008647678 | AI24: =ROUND(AH24,4) -> 0.0086 | AJ24: {=INDEX('Cap Rate to IRR Map'!$F$3:$F$623,MATCH(ROUND(AI24,4),ROUND('Cap Rate to IRR Map'!$E$3:$E$623,4),0))} -> 0.08 | AK24: =$AK$3 -> 0.05 | AL24: 0.103667
B25: =B24+1 -> 21 | C25: Columbia, SC | D25: =SUMIFS(Realpage!$I:$I,Realpage!$A:$A,$C25,Realpage!$F:$F,"Rent Roll (Rev/OSF)") -> 2.6995689 | E25: =SUMIFS(Realpage!$I:$I,Realpage!$A:$A,$C25,Realpage!$F:$F,"Asking RPSF") -> 2.734 | F25: =E25/D25 -> 1.0127543 | G25: {=SUMPRODUCT(('RP - Unit Starts'!$C$2:$C$101=$C25)*('RP - Unit Starts'!$F$2:$F$101="Unit Starts")*'RP - Unit Starts'!$I$2:$L$101)/SUMIFS('RP - Unit Starts'!$L:$L,'RP - Unit Starts'!$C:$C,$C25,'RP - Unit Starts'!$F:$F,"Existing Units")} -> 0.016225482 | H25: =F25-1 -> 0.012754304 | I25: =SUMIFS(Realpage!$I:$I,Realpage!$A:$A,$C25,Realpage!$F:$F,"Effective RPSF") -> 2.708 | J25: =I25/D25 -> 1.0031231 | K25: =J25-1 -> 0.0031231367 | M25: =AVERAGEIF('Realpage - His. Rent Change'!$A$2:$A$577,'Q2 2026 Summary'!C22,'Realpage - His. Rent Change'!$I$2:$AV$577) -> 0.0357 | N25: =AVERAGE(L25:M25) -> 0.0357 | O25: =MAX(0,-(K25/M25)) -> 0 | P25: =($P$3*M25)+K25 -> 0.18162314 | Q25: =(1+P25)^(1/$P$3)-1 -> 0.033941095 | R25: =$R$3+P25 -> 0.23262314 | S25: =$S$3*$P$3 -> 0.125 | T25: =SUMIFS(Realpage!$I:$I,Realpage!$A:$A,$C25,Realpage!$F:$F,"NOI % of Revenue") -> 1.1093339 | U25: 1 | V25: =U25-T25 -> -0.10933389 | W25: =U25*(1+R25) -> 1.2326231 | X25: =V25*(1+S25) -> -0.12300062 | Y25: =W25-X25 -> 1.3556238 | Z25: =Y25/T25-1 -> 0.222016 | AA25: =(Y25/T25)^(1/$P$3)-1 -> 0.040915267 | AB25: =$AB$3 -> 0.05 | AC25: =AB25/$AB$3 -> 1 | AD25: =AC25*(1+$AD$3) -> 1.08 | AE25: =AC25*AB25 -> 0.05 | AF25: =AE25*(1+Z25) -> 0.0611008 | AG25: =AF25/AD25 -> 0.056574815 | AH25: =AG25-AB25 -> 0.0065748148 | AI25: =ROUND(AH25,4) -> 0.0066 | AJ25: {=INDEX('Cap Rate to IRR Map'!$F$3:$F$623,MATCH(ROUND(AI25,4),ROUND('Cap Rate to IRR Map'!$E$3:$E$623,4),0))} -> 0.062 | AK25: =$AK$3 -> 0.05 | AL25: 0.2015 | AO25: Submarkets with outsized growth above mkt avg
B26: =B25+1 -> 22 | C26: Tucson, AZ | D26: =SUMIFS(Realpage!$I:$I,Realpage!$A:$A,$C26,Realpage!$F:$F,"Rent Roll (Rev/OSF)") -> 2.9490836 | E26: =SUMIFS(Realpage!$I:$I,Realpage!$A:$A,$C26,Realpage!$F:$F,"Asking RPSF") -> 2.986 | F26: =E26/D26 -> 1.0125179 | G26: {=SUMPRODUCT(('RP - Unit Starts'!$C$2:$C$101=$C26)*('RP - Unit Starts'!$F$2:$F$101="Unit Starts")*'RP - Unit Starts'!$I$2:$L$101)/SUMIFS('RP - Unit Starts'!$L:$L,'RP - Unit Starts'!$C:$C,$C26,'RP - Unit Starts'!$F:$F,"Existing Units")} -> 0.0050482755 | H26: =F26-1 -> 0.012517928 | I26: =SUMIFS(Realpage!$I:$I,Realpage!$A:$A,$C26,Realpage!$F:$F,"Effective RPSF") -> 2.92 | J26: =I26/D26 -> 0.99013809 | K26: =J26-1 -> -0.0098619052 | M26: =AVERAGEIF('Realpage - His. Rent Change'!$A$2:$A$577,'Q2 2026 Summary'!C32,'Realpage - His. Rent Change'!$I$2:$AV$577) -> 0.0782 | N26: =AVERAGE(L26:M26) -> 0.0782 | O26: =MAX(0,-(K26/M26)) -> 0.12611132 | P26: =($P$3*M26)+K26 -> 0.38113809 | Q26: =(1+P26)^(1/$P$3)-1 -> 0.06671259 | R26: =$R$3+P26 -> 0.43213809 | S26: =$S$3*$P$3 -> 0.125 | T26: =SUMIFS(Realpage!$I:$I,Realpage!$A:$A,$C26,Realpage!$F:$F,"NOI % of Revenue") -> 1.2121145 | U26: 1 | V26: =U26-T26 -> -0.21211451 | W26: =U26*(1+R26) -> 1.4321381 | X26: =V26*(1+S26) -> -0.23862882 | Y26: =W26-X26 -> 1.6707669 | Z26: =Y26/T26-1 -> 0.37839033 | AA26: =(Y26/T26)^(1/$P$3)-1 -> 0.066287808 | AB26: =$AB$3 -> 0.05 | AC26: =AB26/$AB$3 -> 1 | AD26: =AC26*(1+$AD$3) -> 1.08 | AE26: =AC26*AB26 -> 0.05 | AF26: =AE26*(1+Z26) -> 0.068919516 | AG26: =AF26/AD26 -> 0.063814367 | AH26: =AG26-AB26 -> 0.013814367 | AI26: =ROUND(AH26,4) -> 0.0138 | AJ26: {=INDEX('Cap Rate to IRR Map'!$F$3:$F$623,MATCH(ROUND(AI26,4),ROUND('Cap Rate to IRR Map'!$E$3:$E$623,4),0))} -> 0.122 | AK26: =$AK$3 -> 0.05 | AL26: 0.109
B27: =B26+1 -> 23 | C27: Des Moines-West Des Moines, IA | D27: =SUMIFS(Realpage!$I:$I,Realpage!$A:$A,$C27,Realpage!$F:$F,"Rent Roll (Rev/OSF)") -> 2.5974637 | E27: =SUMIFS(Realpage!$I:$I,Realpage!$A:$A,$C27,Realpage!$F:$F,"Asking RPSF") -> 2.627 | F27: =E27/D27 -> 1.0113712 | G27: {=SUMPRODUCT(('RP - Unit Starts'!$C$2:$C$101=$C27)*('RP - Unit Starts'!$F$2:$F$101="Unit Starts")*'RP - Unit Starts'!$I$2:$L$101)/SUMIFS('RP - Unit Starts'!$L:$L,'RP - Unit Starts'!$C:$C,$C27,'RP - Unit Starts'!$F:$F,"Existing Units")} -> 0.011765675 | H27: =F27-1 -> 0.011371189 | I27: =SUMIFS(Realpage!$I:$I,Realpage!$A:$A,$C27,Realpage!$F:$F,"Effective RPSF") -> 2.571 | J27: =I27/D27 -> 0.9898117 | K27: =J27-1 -> -0.010188304 | M27: =AVERAGEIF('Realpage - His. Rent Change'!$A$2:$A$577,'Q2 2026 Summary'!C30,'Realpage - His. Rent Change'!$I$2:$AV$577) -> 0.0686 | N27: =AVERAGE(L27:M27) -> 0.0686 | O27: =MAX(0,-(K27/M27)) -> 0.14851755 | P27: =($P$3*M27)+K27 -> 0.3328117 | Q27: =(1+P27)^(1/$P$3)-1 -> 0.059140948 | R27: =$R$3+P27 -> 0.3838117 | S27: =$S$3*$P$3 -> 0.125 | T27: =SUMIFS(Realpage!$I:$I,Realpage!$A:$A,$C27,Realpage!$F:$F,"NOI % of Revenue") -> 1.0647583 | U27: 1 | V27: =U27-T27 -> -0.064758277 | W27: =U27*(1+R27) -> 1.3838117 | X27: =V27*(1+S27) -> -0.072853061 | Y27: =W27-X27 -> 1.4566648 | Z27: =Y27/T27-1 -> 0.36807085 | AA27: =(Y27/T27)^(1/$P$3)-1 -> 0.064686427 | AB27: =$AB$3 -> 0.05 | AC27: =AB27/$AB$3 -> 1 | AD27: =AC27*(1+$AD$3) -> 1.08 | AE27: =AC27*AB27 -> 0.05 | AF27: =AE27*(1+Z27) -> 0.068403542 | AG27: =AF27/AD27 -> 0.063336613 | AH27: =AG27-AB27 -> 0.013336613 | AI27: =ROUND(AH27,4) -> 0.0133 | AJ27: {=INDEX('Cap Rate to IRR Map'!$F$3:$F$623,MATCH(ROUND(AI27,4),ROUND('Cap Rate to IRR Map'!$E$3:$E$623,4),0))} -> 0.11825 | AK27: =$AK$3 -> 0.05 | AL27: 0.169667 | AO27: Atlanta
B28: =B27+1 -> 24 | C28: Greensboro-High Point/Winston-Salem/Burlington, NC | D28: =SUMIFS(Realpage!$I:$I,Realpage!$A:$A,$C28,Realpage!$F:$F,"Rent Roll (Rev/OSF)") -> 2.6386152 | E28: =SUMIFS(Realpage!$I:$I,Realpage!$A:$A,$C28,Realpage!$F:$F,"Asking RPSF") -> 2.661 | F28: =E28/D28 -> 1.0084835 | G28: {=SUMPRODUCT(('RP - Unit Starts'!$C$2:$C$101=$C28)*('RP - Unit Starts'!$F$2:$F$101="Unit Starts")*'RP - Unit Starts'!$I$2:$L$101)/SUMIFS('RP - Unit Starts'!$L:$L,'RP - Unit Starts'!$C:$C,$C28,'RP - Unit Starts'!$F:$F,"Existing Units")} -> 0.015879717 | H28: =F28-1 -> 0.0084835233 | I28: =SUMIFS(Realpage!$I:$I,Realpage!$A:$A,$C28,Realpage!$F:$F,"Effective RPSF") -> 2.63 | J28: =I28/D28 -> 0.99673494 | K28: =J28-1 -> -0.0032650634 | M28: =AVERAGEIF('Realpage - His. Rent Change'!$A$2:$A$577,'Q2 2026 Summary'!C25,'Realpage - His. Rent Change'!$I$2:$AV$577) -> 0.0465 | N28: =AVERAGE(L28:M28) -> 0.0465 | O28: =MAX(0,-(K28/M28)) -> 0.070216418 | P28: =($P$3*M28)+K28 -> 0.22923494 | Q28: =(1+P28)^(1/$P$3)-1 -> 0.042142192 | R28: =$R$3+P28 -> 0.28023494 | S28: =$S$3*$P$3 -> 0.125 | T28: =SUMIFS(Realpage!$I:$I,Realpage!$A:$A,$C28,Realpage!$F:$F,"NOI % of Revenue") -> 1.0800774 | U28: 1 | V28: =U28-T28 -> -0.080077403 | W28: =U28*(1+R28) -> 1.2802349 | X28: =V28*(1+S28) -> -0.090087079 | Y28: =W28-X28 -> 1.370322 | Z28: =Y28/T28-1 -> 0.26872575 | AA28: =(Y28/T28)^(1/$P$3)-1 -> 0.048753809 | AB28: =$AB$3 -> 0.05 | AC28: =AB28/$AB$3 -> 1 | AD28: =AC28*(1+$AD$3) -> 1.08 | AE28: =AC28*AB28 -> 0.05 | AF28: =AE28*(1+Z28) -> 0.063436288 | AG28: =AF28/AD28 -> 0.058737303 | AH28: =AG28-AB28 -> 0.0087373033 | AI28: =ROUND(AH28,4) -> 0.0087 | AJ28: {=INDEX('Cap Rate to IRR Map'!$F$3:$F$623,MATCH(ROUND(AI28,4),ROUND('Cap Rate to IRR Map'!$E$3:$E$623,4),0))} -> 0.081 | AK28: =$AK$3 -> 0.05 | AL28: 0.164667
B29: =B28+1 -> 25 | C29: St. Louis, MO-IL | D29: =SUMIFS(Realpage!$I:$I,Realpage!$A:$A,$C29,Realpage!$F:$F,"Rent Roll (Rev/OSF)") -> 3.0998673 | E29: =SUMIFS(Realpage!$I:$I,Realpage!$A:$A,$C29,Realpage!$F:$F,"Asking RPSF") -> 3.118 | F29: =E29/D29 -> 1.0058495 | G29: {=SUMPRODUCT(('RP - Unit Starts'!$C$2:$C$101=$C29)*('RP - Unit Starts'!$F$2:$F$101="Unit Starts")*'RP - Unit Starts'!$I$2:$L$101)/SUMIFS('RP - Unit Starts'!$L:$L,'RP - Unit Starts'!$C:$C,$C29,'RP - Unit Starts'!$F:$F,"Existing Units")} -> 0.011046634 | H29: =F29-1 -> 0.0058495057 | I29: =SUMIFS(Realpage!$I:$I,Realpage!$A:$A,$C29,Realpage!$F:$F,"Effective RPSF") -> 3.091 | J29: =I29/D29 -> 0.99713946 | K29: =J29-1 -> -0.0028605445 | M29: =AVERAGEIF('Realpage - His. Rent Change'!$A$2:$A$577,'Q2 2026 Summary'!C24,'Realpage - His. Rent Change'!$I$2:$AV$577) -> 0.0618 | N29: =AVERAGE(L29:M29) -> 0.0618 | O29: =MAX(0,-(K29/M29)) -> 0.046287128 | P29: =($P$3*M29)+K29 -> 0.30613946 | Q29: =(1+P29)^(1/$P$3)-1 -> 0.054867494 | R29: =$R$3+P29 -> 0.35713946 | S29: =$S$3*$P$3 -> 0.125 | T29: =SUMIFS(Realpage!$I:$I,Realpage!$A:$A,$C29,Realpage!$F:$F,"NOI % of Revenue") -> 1.119636 | U29: 1 | V29: =U29-T29 -> -0.11963596 | W29: =U29*(1+R29) -> 1.3571395 | X29: =V29*(1+S29) -> -0.13459045 | Y29: =W29-X29 -> 1.4917299 | Z29: =Y29/T29-1 -> 0.33233476 | AA29: =(Y29/T29)^(1/$P$3)-1 -> 0.059065137 | AB29: =$AB$3 -> 0.05 | AC29: =AB29/$AB$3 -> 1 | AD29: =AC29*(1+$AD$3) -> 1.08 | AE29: =AC29*AB29 -> 0.05 | AF29: =AE29*(1+Z29) -> 0.066616738 | AG29: =AF29/AD29 -> 0.061682165 | AH29: =AG29-AB29 -> 0.011682165 | AI29: =ROUND(AH29,4) -> 0.0117 | AJ29: {=INDEX('Cap Rate to IRR Map'!$F$3:$F$623,MATCH(ROUND(AI29,4),ROUND('Cap Rate to IRR Map'!$E$3:$E$623,4),0))} -> 0.106 | AK29: =$AK$3 -> 0.05 | AL29: 0.171 | AN29: These markets should be monitored but materially de-prioritized until or unless there is an extraordinary opportunity that offsets the organic headwinds, or a submarket/location that is wildy different than market avg
B30: =B29+1 -> 26 | C30: Fort Lauderdale-Pompano Beach-Sunrise, FL | D30: =SUMIFS(Realpage!$I:$I,Realpage!$A:$A,$C30,Realpage!$F:$F,"Rent Roll (Rev/OSF)") -> 4.8866681 | E30: =SUMIFS(Realpage!$I:$I,Realpage!$A:$A,$C30,Realpage!$F:$F,"Asking RPSF") -> 4.901 | F30: =E30/D30 -> 1.0029329 | G30: {=SUMPRODUCT(('RP - Unit Starts'!$C$2:$C$101=$C30)*('RP - Unit Starts'!$F$2:$F$101="Unit Starts")*'RP - Unit Starts'!$I$2:$L$101)/SUMIFS('RP - Unit Starts'!$L:$L,'RP - Unit Starts'!$C:$C,$C30,'RP - Unit Starts'!$F:$F,"Existing Units")} -> 0.0097416072 | H30: =F30-1 -> 0.0029328568 | I30: =SUMIFS(Realpage!$I:$I,Realpage!$A:$A,$C30,Realpage!$F:$F,"Effective RPSF") -> 4.838 | J30: =I30/D30 -> 0.99004064 | K30: =J30-1 -> -0.0099593632 | L30: 0.0444 | M30: =AVERAGEIF('Realpage - His. Rent Change'!$A$2:$A$577,'Q2 2026 Summary'!C26,'Realpage - His. Rent Change'!$I$2:$AV$577) -> 0.0658 | N30: =AVERAGE(L30:M30) -> 0.0551 | O30: =MAX(0,-(K30/M30)) -> 0.1513581 | P30: =($P$3*M30)+K30 -> 0.31904064 | Q30: =(1+P30)^(1/$P$3)-1 -> 0.056943166 | R30: =$R$3+P30 -> 0.37004064 | S30: =$S$3*$P$3 -> 0.125 | T30: =SUMIFS(Realpage!$I:$I,Realpage!$A:$A,$C30,Realpage!$F:$F,"NOI % of Revenue") -> 1.1143069 | U30: 1 | V30: =U30-T30 -> -0.11430694 | W30: =U30*(1+R30) -> 1.3700406 | X30: =V30*(1+S30) -> -0.12859531 | Y30: =W30-X30 -> 1.4986359 | Z30: =Y30/T30-1 -> 0.34490407 | AA30: =(Y30/T30)^(1/$P$3)-1 -> 0.061055893 | AB30: =$AB$3 -> 0.05 | AC30: =AB30/$AB$3 -> 1 | AD30: =AC30*(1+$AD$3) -> 1.08 | AE30: =AC30*AB30 -> 0.05 | AF30: =AE30*(1+Z30) -> 0.067245204 | AG30: =AF30/AD30 -> 0.062264078 | AH30: =AG30-AB30 -> 0.012264078 | AI30: =ROUND(AH30,4) -> 0.0123 | AJ30: {=INDEX('Cap Rate to IRR Map'!$F$3:$F$623,MATCH(ROUND(AI30,4),ROUND('Cap Rate to IRR Map'!$E$3:$E$623,4),0))} -> 0.110333 | AK30: =$AK$3 -> 0.05 | AL30: 0.126333 | AN30: 65% Leverage, 5 years, 3 years IO, leverage neutral (5% fixed rate)
B31: =B30+1 -> 27 | C31: Cape Coral-Fort Myers, FL | D31: =SUMIFS(Realpage!$I:$I,Realpage!$A:$A,$C31,Realpage!$F:$F,"Rent Roll (Rev/OSF)") -> 3.338843 | E31: =SUMIFS(Realpage!$I:$I,Realpage!$A:$A,$C31,Realpage!$F:$F,"Asking RPSF") -> 3.348 | F31: =E31/D31 -> 1.0027426 | G31: {=SUMPRODUCT(('RP - Unit Starts'!$C$2:$C$101=$C31)*('RP - Unit Starts'!$F$2:$F$101="Unit Starts")*'RP - Unit Starts'!$I$2:$L$101)/SUMIFS('RP - Unit Starts'!$L:$L,'RP - Unit Starts'!$C:$C,$C31,'RP - Unit Starts'!$F:$F,"Existing Units")} -> 0.016965989 | H31: =F31-1 -> 0.0027425565 | I31: =SUMIFS(Realpage!$I:$I,Realpage!$A:$A,$C31,Realpage!$F:$F,"Effective RPSF") -> 3.145 | J31: =I31/D31 -> 0.94194305 | K31: =J31-1 -> -0.058056947 | M31: =AVERAGEIF('Realpage - His. Rent Change'!$A$2:$A$577,'Q2 2026 Summary'!C50,'Realpage - His. Rent Change'!$I$2:$AV$577) -> 0.0741 | N31: =AVERAGE(L31:M31) -> 0.0741 | O31: =MAX(0,-(K31/M31)) -> 0.78349457 | P31: =($P$3*M31)+K31 -> 0.31244305 | Q31: =(1+P31)^(1/$P$3)-1 -> 0.05588372 | R31: =$R$3+P31 -> 0.36344305 | S31: =$S$3*$P$3 -> 0.125 | T31: =SUMIFS(Realpage!$I:$I,Realpage!$A:$A,$C31,Realpage!$F:$F,"NOI % of Revenue") -> 1.0244956 | U31: 1 | V31: =U31-T31 -> -0.02449564 | W31: =U31*(1+R31) -> 1.3634431 | X31: =V31*(1+S31) -> -0.027557595 | Y31: =W31-X31 -> 1.3910006 | Z31: =Y31/T31-1 -> 0.35774189 | AA31: =(Y31/T31)^(1/$P$3)-1 -> 0.06307387 | AB31: =$AB$3 -> 0.05 | AC31: =AB31/$AB$3 -> 1 | AD31: =AC31*(1+$AD$3) -> 1.08 | AE31: =AC31*AB31 -> 0.05 | AF31: =AE31*(1+Z31) -> 0.067887095 | AG31: =AF31/AD31 -> 0.062858421 | AH31: =AG31-AB31 -> 0.012858421 | AI31: =ROUND(AH31,4) -> 0.0129 | AJ31: {=INDEX('Cap Rate to IRR Map'!$F$3:$F$623,MATCH(ROUND(AI31,4),ROUND('Cap Rate to IRR Map'!$E$3:$E$623,4),0))} -> 0.115333 | AK31: =$AK$3 -> 0.05 | AL31: 0.1915 | AO31: Houston
B32: =B31+1 -> 28 | C32: Colorado Springs, CO | D32: =SUMIFS(Realpage!$I:$I,Realpage!$A:$A,$C32,Realpage!$F:$F,"Rent Roll (Rev/OSF)") -> 3.4269127 | E32: =SUMIFS(Realpage!$I:$I,Realpage!$A:$A,$C32,Realpage!$F:$F,"Asking RPSF") -> 3.436 | F32: =E32/D32 -> 1.0026518 | G32: {=SUMPRODUCT(('RP - Unit Starts'!$C$2:$C$101=$C32)*('RP - Unit Starts'!$F$2:$F$101="Unit Starts")*'RP - Unit Starts'!$I$2:$L$101)/SUMIFS('RP - Unit Starts'!$L:$L,'RP - Unit Starts'!$C:$C,$C32,'RP - Unit Starts'!$F:$F,"Existing Units")} -> 0.0067899973 | H32: =F32-1 -> 0.0026517534 | I32: =SUMIFS(Realpage!$I:$I,Realpage!$A:$A,$C32,Realpage!$F:$F,"Effective RPSF") -> 3.333 | J32: =I32/D32 -> 0.97259555 | K32: =J32-1 -> -0.027404455 | M32: =AVERAGEIF('Realpage - His. Rent Change'!$A$2:$A$577,'Q2 2026 Summary'!C36,'Realpage - His. Rent Change'!$I$2:$AV$577) -> 0.0706 | N32: =AVERAGE(L32:M32) -> 0.0706 | O32: =MAX(0,-(K32/M32)) -> 0.38816508 | P32: =($P$3*M32)+K32 -> 0.32559555 | Q32: =(1+P32)^(1/$P$3)-1 -> 0.05799157 | R32: =$R$3+P32 -> 0.37659555 | S32: =$S$3*$P$3 -> 0.125 | T32: =SUMIFS(Realpage!$I:$I,Realpage!$A:$A,$C32,Realpage!$F:$F,"NOI % of Revenue") -> 1.2797618 | U32: 1 | V32: =U32-T32 -> -0.27976184 | W32: =U32*(1+R32) -> 1.3765955 | X32: =V32*(1+S32) -> -0.31473207 | Y32: =W32-X32 -> 1.6913276 | Z32: =Y32/T32-1 -> 0.3215956 | AA32: =(Y32/T32)^(1/$P$3)-1 -> 0.057352306 | AB32: =$AB$3 -> 0.05 | AC32: =AB32/$AB$3 -> 1 | AD32: =AC32*(1+$AD$3) -> 1.08 | AE32: =AC32*AB32 -> 0.05 | AF32: =AE32*(1+Z32) -> 0.06607978 | AG32: =AF32/AD32 -> 0.061184981 | AH32: =AG32-AB32 -> 0.011184981 | AI32: =ROUND(AH32,4) -> 0.0112 | AJ32: {=INDEX('Cap Rate to IRR Map'!$F$3:$F$623,MATCH(ROUND(AI32,4),ROUND('Cap Rate to IRR Map'!$E$3:$E$623,4),0))} -> 0.101667 | AK32: =$AK$3 -> 0.05 | AL32: 0.093
B33: =B32+1 -> 29 | C33: Albuquerque, NM | D33: =SUMIFS(Realpage!$I:$I,Realpage!$A:$A,$C33,Realpage!$F:$F,"Rent Roll (Rev/OSF)") -> 1.628002 | E33: =SUMIFS(Realpage!$I:$I,Realpage!$A:$A,$C33,Realpage!$F:$F,"Asking RPSF") -> 1.628 | F33: =E33/D33 -> 0.99999877 | G33: {=SUMPRODUCT(('RP - Unit Starts'!$C$2:$C$101=$C33)*('RP - Unit Starts'!$F$2:$F$101="Unit Starts")*'RP - Unit Starts'!$I$2:$L$101)/SUMIFS('RP - Unit Starts'!$L:$L,'RP - Unit Starts'!$C:$C,$C33,'RP - Unit Starts'!$F:$F,"Existing Units")} -> 0.0046547843 | H33: =F33-1 -> -1.2264529e-06 | I33: =SUMIFS(Realpage!$I:$I,Realpage!$A:$A,$C33,Realpage!$F:$F,"Effective RPSF") -> 1.612 | J33: =I33/D33 -> 0.99017078 | K33: =J33-1 -> -0.0098292242 | M33: =AVERAGEIF('Realpage - His. Rent Change'!$A$2:$A$577,'Q2 2026 Summary'!C27,'Realpage - His. Rent Change'!$I$2:$AV$577) -> 0.0261 | N33: =AVERAGE(L33:M33) -> 0.0261 | O33: =MAX(0,-(K33/M33)) -> 0.37659863 | P33: =($P$3*M33)+K33 -> 0.12067078 | Q33: =(1+P33)^(1/$P$3)-1 -> 0.023047055 | R33: =$R$3+P33 -> 0.17167078 | S33: =$S$3*$P$3 -> 0.125 | T33: =SUMIFS(Realpage!$I:$I,Realpage!$A:$A,$C33,Realpage!$F:$F,"NOI % of Revenue") -> 0.61413872 | U33: 1 | V33: =U33-T33 -> 0.38586128 | W33: =U33*(1+R33) -> 1.1716708 | X33: =V33*(1+S33) -> 0.43409394 | Y33: =W33-X33 -> 0.73757684 | Z33: =Y33/T33-1 -> 0.20099387 | AA33: =(Y33/T33)^(1/$P$3)-1 -> 0.037309028 | AB33: =$AB$3 -> 0.05 | AC33: =AB33/$AB$3 -> 1 | AD33: =AC33*(1+$AD$3) -> 1.08 | AE33: =AC33*AB33 -> 0.05 | AF33: =AE33*(1+Z33) -> 0.060049693 | AG33: =AF33/AD33 -> 0.055601568 | AH33: =AG33-AB33 -> 0.0056015679 | AI33: =ROUND(AH33,4) -> 0.0056 | AJ33: {=INDEX('Cap Rate to IRR Map'!$F$3:$F$623,MATCH(ROUND(AI33,4),ROUND('Cap Rate to IRR Map'!$E$3:$E$623,4),0))} -> 0.053 | AK33: =$AK$3 -> 0.05 | AL33: 0.32432749 | AN33: VA: 50% of units, 10k avg cost with a 20% ROC
B34: =B33+1 -> 30 | C34: Austin-Round Rock-San Marcos, TX | D34: =SUMIFS(Realpage!$I:$I,Realpage!$A:$A,$C34,Realpage!$F:$F,"Rent Roll (Rev/OSF)") -> 1.6921104 | E34: =SUMIFS(Realpage!$I:$I,Realpage!$A:$A,$C34,Realpage!$F:$F,"Asking RPSF") -> 1.691 | F34: =E34/D34 -> 0.9993438 | G34: {=SUMPRODUCT(('RP - Unit Starts'!$C$2:$C$101=$C34)*('RP - Unit Starts'!$F$2:$F$101="Unit Starts")*'RP - Unit Starts'!$I$2:$L$101)/SUMIFS('RP - Unit Starts'!$L:$L,'RP - Unit Starts'!$C:$C,$C34,'RP - Unit Starts'!$F:$F,"Existing Units")} -> 0.015673893 | H34: =F34-1 -> -0.00065620205 | I34: =SUMIFS(Realpage!$I:$I,Realpage!$A:$A,$C34,Realpage!$F:$F,"Effective RPSF") -> 1.595 | J34: =I34/D34 -> 0.94260991 | K34: =J34-1 -> -0.05739009 | L34: 0.0198 | M34: =AVERAGEIF('Realpage - His. Rent Change'!$A$2:$A$577,'Q2 2026 Summary'!C53,'Realpage - His. Rent Change'!$I$2:$AV$577) -> 0.016 | N34: =AVERAGE(L34:M34) -> 0.0179 | O34: =MAX(0,-(K34/M34)) -> 3.5868806 | P34: =($P$3*M34)+K34 -> 0.02260991 | Q34: =(1+P34)^(1/$P$3)-1 -> 0.0044816315 | R34: =$R$3+P34 -> 0.07360991 | S34: =$S$3*$P$3 -> 0.125 | T34: =SUMIFS(Realpage!$I:$I,Realpage!$A:$A,$C34,Realpage!$F:$F,"NOI % of Revenue") -> 0.45675923 | U34: 1 | V34: =U34-T34 -> 0.54324077 | W34: =U34*(1+R34) -> 1.0736099 | X34: =V34*(1+S34) -> 0.61114586 | Y34: =W34-X34 -> 0.46246405 | Z34: =Y34/T34-1 -> 0.012489762 | AA34: =(Y34/T34)^(1/$P$3)-1 -> 0.0024855656 | AB34: =$AB$3 -> 0.05 | AC34: =AB34/$AB$3 -> 1 | AD34: =AC34*(1+$AD$3) -> 1.08 | AE34: =AC34*AB34 -> 0.05 | AF34: =AE34*(1+Z34) -> 0.050624488 | AG34: =AF34/AD34 -> 0.046874526 | AH34: =AG34-AB34 -> -0.003125474 | AI34: =ROUND(AH34,4) -> -0.0031 | AJ34: {=INDEX('Cap Rate to IRR Map'!$F$3:$F$623,MATCH(ROUND(AI34,4),ROUND('Cap Rate to IRR Map'!$E$3:$E$623,4),0))} -> -0.045 | AK34: =$AK$3 -> 0.05 | AL34: 0.268 | AN34: 10-year historical rent growth continues for next 5 years
B35: =B34+1 -> 31 | C35: Jacksonville, FL | D35: =SUMIFS(Realpage!$I:$I,Realpage!$A:$A,$C35,Realpage!$F:$F,"Rent Roll (Rev/OSF)") -> 2.9831686 | E35: =SUMIFS(Realpage!$I:$I,Realpage!$A:$A,$C35,Realpage!$F:$F,"Asking RPSF") -> 2.979 | F35: =E35/D35 -> 0.99860263 | G35: {=SUMPRODUCT(('RP - Unit Starts'!$C$2:$C$101=$C35)*('RP - Unit Starts'!$F$2:$F$101="Unit Starts")*'RP - Unit Starts'!$I$2:$L$101)/SUMIFS('RP - Unit Starts'!$L:$L,'RP - Unit Starts'!$C:$C,$C35,'RP - Unit Starts'!$F:$F,"Existing Units")} -> 0.010989511 | H35: =F35-1 -> -0.0013973677 | I35: =SUMIFS(Realpage!$I:$I,Realpage!$A:$A,$C35,Realpage!$F:$F,"Effective RPSF") -> 2.904 | J35: =I35/D35 -> 0.97346158 | K35: =J35-1 -> -0.026538421 | L35: 0.0435 | M35: =AVERAGEIF('Realpage - His. Rent Change'!$A$2:$A$577,'Q2 2026 Summary'!C38,'Realpage - His. Rent Change'!$I$2:$AV$577) -> 0.0695 | N35: =AVERAGE(L35:M35) -> 0.0565 | O35: =MAX(0,-(K35/M35)) -> 0.38184778 | P35: =($P$3*M35)+K35 -> 0.32096158 | Q35: =(1+P35)^(1/$P$3)-1 -> 0.057250836 | R35: =$R$3+P35 -> 0.37196158 | S35: =$S$3*$P$3 -> 0.125 | T35: =SUMIFS(Realpage!$I:$I,Realpage!$A:$A,$C35,Realpage!$F:$F,"NOI % of Revenue") -> 1.0428326 | U35: 1 | V35: =U35-T35 -> -0.042832612 | W35: =U35*(1+R35) -> 1.3719616 | X35: =V35*(1+S35) -> -0.048186689 | Y35: =W35-X35 -> 1.4201483 | Z35: =Y35/T35-1 -> 0.36181804 | AA35: =(Y35/T35)^(1/$P$3)-1 -> 0.063711408 | AB35: =$AB$3 -> 0.05 | AC35: =AB35/$AB$3 -> 1 | AD35: =AC35*(1+$AD$3) -> 1.08 | AE35: =AC35*AB35 -> 0.05 | AF35: =AE35*(1+Z35) -> 0.068090902 | AG35: =AF35/AD35 -> 0.063047132 | AH35: =AG35-AB35 -> 0.013047132 | AI35: =ROUND(AH35,4) -> 0.013 | AJ35: {=INDEX('Cap Rate to IRR Map'!$F$3:$F$623,MATCH(ROUND(AI35,4),ROUND('Cap Rate to IRR Map'!$E$3:$E$623,4),0))} -> 0.116 | AK35: =$AK$3 -> 0.05 | AL35: 0.152333
B36: =B35+1 -> 32 | C36: Palm Bay-Melbourne-Titusville, FL | D36: =SUMIFS(Realpage!$I:$I,Realpage!$A:$A,$C36,Realpage!$F:$F,"Rent Roll (Rev/OSF)") -> 3.3272076 | E36: =SUMIFS(Realpage!$I:$I,Realpage!$A:$A,$C36,Realpage!$F:$F,"Asking RPSF") -> 3.318 | F36: =E36/D36 -> 0.99723263 | G36: {=SUMPRODUCT(('RP - Unit Starts'!$C$2:$C$101=$C36)*('RP - Unit Starts'!$F$2:$F$101="Unit Starts")*'RP - Unit Starts'!$I$2:$L$101)/SUMIFS('RP - Unit Starts'!$L:$L,'RP - Unit Starts'!$C:$C,$C36,'RP - Unit Starts'!$F:$F,"Existing Units")} -> 0 | H36: =F36-1 -> -0.0027673696 | I36: =SUMIFS(Realpage!$I:$I,Realpage!$A:$A,$C36,Realpage!$F:$F,"Effective RPSF") -> 3.239 | J36: =I36/D36 -> 0.973489 | K36: =J36-1 -> -0.026511004 | M36: =AVERAGEIF('Realpage - His. Rent Change'!$A$2:$A$577,'Q2 2026 Summary'!C29,'Realpage - His. Rent Change'!$I$2:$AV$577) -> 0.0461 | N36: =AVERAGE(L36:M36) -> 0.0461 | O36: =MAX(0,-(K36/M36)) -> 0.575076 | P36: =($P$3*M36)+K36 -> 0.203989 | Q36: =(1+P36)^(1/$P$3)-1 -> 0.037825897 | R36: =$R$3+P36 -> 0.254989 | S36: =$S$3*$P$3 -> 0.125 | T36: =SUMIFS(Realpage!$I:$I,Realpage!$A:$A,$C36,Realpage!$F:$F,"NOI % of Revenue") -> 1.0697444 | U36: 1 | V36: =U36-T36 -> -0.069744449 | W36: =U36*(1+R36) -> 1.254989 | X36: =V36*(1+S36) -> -0.078462505 | Y36: =W36-X36 -> 1.3334515 | Z36: =Y36/T36-1 -> 0.24651406 | AA36: =(Y36/T36)^(1/$P$3)-1 -> 0.045055696 | AB36: =$AB$3 -> 0.05 | AC36: =AB36/$AB$3 -> 1 | AD36: =AC36*(1+$AD$3) -> 1.08 | AE36: =AC36*AB36 -> 0.05 | AF36: =AE36*(1+Z36) -> 0.062325703 | AG36: =AF36/AD36 -> 0.057708984 | AH36: =AG36-AB36 -> 0.0077089845 | AI36: =ROUND(AH36,4) -> 0.0077 | AJ36: {=INDEX('Cap Rate to IRR Map'!$F$3:$F$623,MATCH(ROUND(AI36,4),ROUND('Cap Rate to IRR Map'!$E$3:$E$623,4),0))} -> 0.072 | AK36: =$AK$3 -> 0.05 | AL36: 0.145 | AO36: Accretive loan assumptions that enhacne returns
B37: =B36+1 -> 33 | C37: Orlando-Kissimmee-Sanford, FL | D37: =SUMIFS(Realpage!$I:$I,Realpage!$A:$A,$C37,Realpage!$F:$F,"Rent Roll (Rev/OSF)") -> 3.6265711 | E37: =SUMIFS(Realpage!$I:$I,Realpage!$A:$A,$C37,Realpage!$F:$F,"Asking RPSF") -> 3.615 | F37: =E37/D37 -> 0.99680936 | G37: {=SUMPRODUCT(('RP - Unit Starts'!$C$2:$C$101=$C37)*('RP - Unit Starts'!$F$2:$F$101="Unit Starts")*'RP - Unit Starts'!$I$2:$L$101)/SUMIFS('RP - Unit Starts'!$L:$L,'RP - Unit Starts'!$C:$C,$C37,'RP - Unit Starts'!$F:$F,"Existing Units")} -> 0.019573331 | H37: =F37-1 -> -0.0031906449 | I37: =SUMIFS(Realpage!$I:$I,Realpage!$A:$A,$C37,Realpage!$F:$F,"Effective RPSF") -> 3.532 | J37: =I37/D37 -> 0.97392272 | K37: =J37-1 -> -0.026077277 | L37: 0.047 | M37: =AVERAGEIF('Realpage - His. Rent Change'!$A$2:$A$577,'Q2 2026 Summary'!C37,'Realpage - His. Rent Change'!$I$2:$AV$577) -> 0.0773 | N37: =AVERAGE(L37:M37) -> 0.06215 | O37: =MAX(0,-(K37/M37)) -> 0.33735158 | P37: =($P$3*M37)+K37 -> 0.36042272 | Q37: =(1+P37)^(1/$P$3)-1 -> 0.063493342 | R37: =$R$3+P37 -> 0.41142272 | S37: =$S$3*$P$3 -> 0.125 | T37: =SUMIFS(Realpage!$I:$I,Realpage!$A:$A,$C37,Realpage!$F:$F,"NOI % of Revenue") -> 1.1173672 | U37: 1 | V37: =U37-T37 -> -0.11736723 | W37: =U37*(1+R37) -> 1.4114227 | X37: =V37*(1+S37) -> -0.13203814 | Y37: =W37-X37 -> 1.5434609 | Z37: =Y37/T37-1 -> 0.38133714 | AA37: =(Y37/T37)^(1/$P$3)-1 -> 0.066743334 | AB37: =$AB$3 -> 0.05 | AC37: =AB37/$AB$3 -> 1 | AD37: =AC37*(1+$AD$3) -> 1.08 | AE37: =AC37*AB37 -> 0.05 | AF37: =AE37*(1+Z37) -> 0.069066857 | AG37: =AF37/AD37 -> 0.063950794 | AH37: =AG37-AB37 -> 0.013950794 | AI37: =ROUND(AH37,4) -> 0.014 | AJ37: {=INDEX('Cap Rate to IRR Map'!$F$3:$F$623,MATCH(ROUND(AI37,4),ROUND('Cap Rate to IRR Map'!$E$3:$E$623,4),0))} -> 0.124 | AK37: =$AK$3 -> 0.05 | AL37: 0.094 | AO37: Orlando
B38: =B37+1 -> 34 | C38: Las Vegas-Henderson-North Las Vegas, NV | D38: =SUMIFS(Realpage!$I:$I,Realpage!$A:$A,$C38,Realpage!$F:$F,"Rent Roll (Rev/OSF)") -> 3.1855552 | E38: =SUMIFS(Realpage!$I:$I,Realpage!$A:$A,$C38,Realpage!$F:$F,"Asking RPSF") -> 3.168 | F38: =E38/D38 -> 0.99448912 | G38: {=SUMPRODUCT(('RP - Unit Starts'!$C$2:$C$101=$C38)*('RP - Unit Starts'!$F$2:$F$101="Unit Starts")*'RP - Unit Starts'!$I$2:$L$101)/SUMIFS('RP - Unit Starts'!$L:$L,'RP - Unit Starts'!$C:$C,$C38,'RP - Unit Starts'!$F:$F,"Existing Units")} -> 0.0063787321 | H38: =F38-1 -> -0.0055108815 | I38: =SUMIFS(Realpage!$I:$I,Realpage!$A:$A,$C38,Realpage!$F:$F,"Effective RPSF") -> 3.074 | J38: =I38/D38 -> 0.96498092 | K38: =J38-1 -> -0.035019081 | L38: 0.0492 | M38: =AVERAGEIF('Realpage - His. Rent Change'!$A$2:$A$577,'Q2 2026 Summary'!C39,'Realpage - His. Rent Change'!$I$2:$AV$577) -> 0.0785 | N38: =AVERAGE(L38:M38) -> 0.06385 | O38: =MAX(0,-(K38/M38)) -> 0.44610295 | P38: =($P$3*M38)+K38 -> 0.35748092 | Q38: =(1+P38)^(1/$P$3)-1 -> 0.063033 | R38: =$R$3+P38 -> 0.40848092 | S38: =$S$3*$P$3 -> 0.125 | T38: =SUMIFS(Realpage!$I:$I,Realpage!$A:$A,$C38,Realpage!$F:$F,"NOI % of Revenue") -> 1.2623847 | U38: 1 | V38: =U38-T38 -> -0.26238471 | W38: =U38*(1+R38) -> 1.4084809 | X38: =V38*(1+S38) -> -0.2951828 | Y38: =W38-X38 -> 1.7036637 | Z38: =Y38/T38-1 -> 0.34955985 | AA38: =(Y38/T38)^(1/$P$3)-1 -> 0.061789508 | AB38: =$AB$3 -> 0.05 | AC38: =AB38/$AB$3 -> 1 | AD38: =AC38*(1+$AD$3) -> 1.08 | AE38: =AC38*AB38 -> 0.05 | AF38: =AE38*(1+Z38) -> 0.067477992 | AG38: =AF38/AD38 -> 0.062479623 | AH38: =AG38-AB38 -> 0.012479623 | AI38: =ROUND(AH38,4) -> 0.0125 | AJ38: {=INDEX('Cap Rate to IRR Map'!$F$3:$F$623,MATCH(ROUND(AI38,4),ROUND('Cap Rate to IRR Map'!$E$3:$E$623,4),0))} -> 0.112 | AK38: =$AK$3 -> 0.05 | AL38: 0.112 | AN38: Market level analysis that does not give visibility to submarket level nuances
B39: =B38+1 -> 35 | C39: Phoenix-Mesa-Chandler, AZ | D39: =SUMIFS(Realpage!$I:$I,Realpage!$A:$A,$C39,Realpage!$F:$F,"Rent Roll (Rev/OSF)") -> 3.495915 | E39: =SUMIFS(Realpage!$I:$I,Realpage!$A:$A,$C39,Realpage!$F:$F,"Asking RPSF") -> 3.472 | F39: =E39/D39 -> 0.99315917 | G39: {=SUMPRODUCT(('RP - Unit Starts'!$C$2:$C$101=$C39)*('RP - Unit Starts'!$F$2:$F$101="Unit Starts")*'RP - Unit Starts'!$I$2:$L$101)/SUMIFS('RP - Unit Starts'!$L:$L,'RP - Unit Starts'!$C:$C,$C39,'RP - Unit Starts'!$F:$F,"Existing Units")} -> 0.029425989 | H39: =F39-1 -> -0.006840828 | I39: =SUMIFS(Realpage!$I:$I,Realpage!$A:$A,$C39,Realpage!$F:$F,"Effective RPSF") -> 3.342 | J39: =I39/D39 -> 0.95597291 | K39: =J39-1 -> -0.044027087 | L39: 0.0507 | M39: =AVERAGEIF('Realpage - His. Rent Change'!$A$2:$A$577,'Q2 2026 Summary'!C46,'Realpage - His. Rent Change'!$I$2:$AV$577) -> 0.033 | N39: =AVERAGE(L39:M39) -> 0.04185 | O39: =MAX(0,-(K39/M39)) -> 1.3341542 | P39: =($P$3*M39)+K39 -> 0.12097291 | Q39: =(1+P39)^(1/$P$3)-1 -> 0.023102212 | R39: =$R$3+P39 -> 0.17197291 | S39: =$S$3*$P$3 -> 0.125 | T39: =SUMIFS(Realpage!$I:$I,Realpage!$A:$A,$C39,Realpage!$F:$F,"NOI % of Revenue") -> 1.2677488 | U39: 1 | V39: =U39-T39 -> -0.26774878 | W39: =U39*(1+R39) -> 1.1719729 | X39: =V39*(1+S39) -> -0.30121738 | Y39: =W39-X39 -> 1.4731903 | Z39: =Y39/T39-1 -> 0.16205222 | AA39: =(Y39/T39)^(1/$P$3)-1 -> 0.030493198 | AB39: =$AB$3 -> 0.05 | AC39: =AB39/$AB$3 -> 1 | AD39: =AC39*(1+$AD$3) -> 1.08 | AE39: =AC39*AB39 -> 0.05 | AF39: =AE39*(1+Z39) -> 0.058102611 | AG39: =AF39/AD39 -> 0.053798714 | AH39: =AG39-AB39 -> 0.0037987141 | AI39: =ROUND(AH39,4) -> 0.0038 | AJ39: {=INDEX('Cap Rate to IRR Map'!$F$3:$F$623,MATCH(ROUND(AI39,4),ROUND('Cap Rate to IRR Map'!$E$3:$E$623,4),0))} -> 0.035 | AK39: =$AK$3 -> 0.05 | AL39: 0.013 | AO39: Any tactical special situations that enhance returns
B40: =B39+1 -> 36 | C40: Washington-Arlington-Alexandria, DC-VA-MD-WV | D40: =SUMIFS(Realpage!$I:$I,Realpage!$A:$A,$C40,Realpage!$F:$F,"Rent Roll (Rev/OSF)") -> 5.1815224 | E40: =SUMIFS(Realpage!$I:$I,Realpage!$A:$A,$C40,Realpage!$F:$F,"Asking RPSF") -> 5.127 | F40: =E40/D40 -> 0.98947754 | G40: {=SUMPRODUCT(('RP - Unit Starts'!$C$2:$C$101=$C40)*('RP - Unit Starts'!$F$2:$F$101="Unit Starts")*'RP - Unit Starts'!$I$2:$L$101)/SUMIFS('RP - Unit Starts'!$L:$L,'RP - Unit Starts'!$C:$C,$C40,'RP - Unit Starts'!$F:$F,"Existing Units")} -> 0.01047627 | H40: =F40-1 -> -0.010522464 | I40: =SUMIFS(Realpage!$I:$I,Realpage!$A:$A,$C40,Realpage!$F:$F,"Effective RPSF") -> 5.041 | J40: =I40/D40 -> 0.9728801 | K40: =J40-1 -> -0.027119903 | L40: 0.0275 | M40: =AVERAGEIF('Realpage - His. Rent Change'!$A$2:$A$577,'Q2 2026 Summary'!C34,'Realpage - His. Rent Change'!$I$2:$AV$577) -> 0.0767 | N40: =AVERAGE(L40:M40) -> 0.0521 | O40: =MAX(0,-(K40/M40)) -> 0.35358414 | P40: =($P$3*M40)+K40 -> 0.3563801 | Q40: =(1+P40)^(1/$P$3)-1 -> 0.062860535 | R40: =$R$3+P40 -> 0.4073801 | S40: =$S$3*$P$3 -> 0.125 | T40: =SUMIFS(Realpage!$I:$I,Realpage!$A:$A,$C40,Realpage!$F:$F,"NOI % of Revenue") -> 1.1588666 | U40: 1 | V40: =U40-T40 -> -0.15886658 | W40: =U40*(1+R40) -> 1.4073801 | X40: =V40*(1+S40) -> -0.1787249 | Y40: =W40-X40 -> 1.586105 | Z40: =Y40/T40-1 -> 0.3686692 | AA40: =(Y40/T40)^(1/$P$3)-1 -> 0.064779544 | AB40: =$AB$3 -> 0.05 | AC40: =AB40/$AB$3 -> 1 | AD40: =AC40*(1+$AD$3) -> 1.08 | AE40: =AC40*AB40 -> 0.05 | AF40: =AE40*(1+Z40) -> 0.06843346 | AG40: =AF40/AD40 -> 0.063364315 | AH40: =AG40-AB40 -> 0.013364315 | AI40: =ROUND(AH40,4) -> 0.0134 | AJ40: {=INDEX('Cap Rate to IRR Map'!$F$3:$F$623,MATCH(ROUND(AI40,4),ROUND('Cap Rate to IRR Map'!$E$3:$E$623,4),0))} -> 0.119 | AK40: =$AK$3 -> 0.05 | AL40: 0.127
B41: =B40+1 -> 37 | C41: Raleigh/Durham, NC | D41: =SUMIFS(Realpage!$I:$I,Realpage!$A:$A,$C41,Realpage!$F:$F,"Rent Roll (Rev/OSF)") -> 3.1486624 | E41: =SUMIFS(Realpage!$I:$I,Realpage!$A:$A,$C41,Realpage!$F:$F,"Asking RPSF") -> 3.111 | F41: =E41/D41 -> 0.9880386 | G41: {=SUMPRODUCT(('RP - Unit Starts'!$C$2:$C$101=$C41)*('RP - Unit Starts'!$F$2:$F$101="Unit Starts")*'RP - Unit Starts'!$I$2:$L$101)/SUMIFS('RP - Unit Starts'!$L:$L,'RP - Unit Starts'!$C:$C,$C41,'RP - Unit Starts'!$F:$F,"Existing Units")} -> 0.046989443 | H41: =F41-1 -> -0.011961403 | I41: =SUMIFS(Realpage!$I:$I,Realpage!$A:$A,$C41,Realpage!$F:$F,"Effective RPSF") -> 3.023 | J41: =I41/D41 -> 0.96009022 | K41: =J41-1 -> -0.039909779 | L41: 0.0373 | M41: =AVERAGEIF('Realpage - His. Rent Change'!$A$2:$A$577,'Q2 2026 Summary'!C44,'Realpage - His. Rent Change'!$I$2:$AV$577) -> 0.0451 | N41: =AVERAGE(L41:M41) -> 0.0412 | O41: =MAX(0,-(K41/M41)) -> 0.8849175 | P41: =($P$3*M41)+K41 -> 0.18559022 | Q41: =(1+P41)^(1/$P$3)-1 -> 0.034634418 | R41: =$R$3+P41 -> 0.23659022 | S41: =$S$3*$P$3 -> 0.125 | T41: =SUMIFS(Realpage!$I:$I,Realpage!$A:$A,$C41,Realpage!$F:$F,"NOI % of Revenue") -> 1.1552491 | U41: 1 | V41: =U41-T41 -> -0.15524907 | W41: =U41*(1+R41) -> 1.2365902 | X41: =V41*(1+S41) -> -0.17465521 | Y41: =W41-X41 -> 1.4112454 | Z41: =Y41/T41-1 -> 0.22159408 | AA41: =(Y41/T41)^(1/$P$3)-1 -> 0.040843379 | AB41: =$AB$3 -> 0.05 | AC41: =AB41/$AB$3 -> 1 | AD41: =AC41*(1+$AD$3) -> 1.08 | AE41: =AC41*AB41 -> 0.05 | AF41: =AE41*(1+Z41) -> 0.061079704 | AG41: =AF41/AD41 -> 0.056555281 | AH41: =AG41-AB41 -> 0.0065552815 | AI41: =ROUND(AH41,4) -> 0.0066 | AJ41: {=INDEX('Cap Rate to IRR Map'!$F$3:$F$623,MATCH(ROUND(AI41,4),ROUND('Cap Rate to IRR Map'!$E$3:$E$623,4),0))} -> 0.062 | AK41: =$AK$3 -> 0.05 | AL41: 0.073
B42: =B41+1 -> 38 | C42: Atlanta-Sandy Springs-Roswell, GA | D42: =SUMIFS(Realpage!$I:$I,Realpage!$A:$A,$C42,Realpage!$F:$F,"Rent Roll (Rev/OSF)") -> 1.6321102 | E42: =SUMIFS(Realpage!$I:$I,Realpage!$A:$A,$C42,Realpage!$F:$F,"Asking RPSF") -> 1.607 | F42: =E42/D42 -> 0.98461488 | G42: {=SUMPRODUCT(('RP - Unit Starts'!$C$2:$C$101=$C42)*('RP - Unit Starts'!$F$2:$F$101="Unit Starts")*'RP - Unit Starts'!$I$2:$L$101)/SUMIFS('RP - Unit Starts'!$L:$L,'RP - Unit Starts'!$C:$C,$C42,'RP - Unit Starts'!$F:$F,"Existing Units")} -> 0.014393886 | H42: =F42-1 -> -0.015385121 | I42: =SUMIFS(Realpage!$I:$I,Realpage!$A:$A,$C42,Realpage!$F:$F,"Effective RPSF") -> 1.562 | J42: =I42/D42 -> 0.95704321 | K42: =J42-1 -> -0.042956789 | L42: 0.0394 | M42: =AVERAGEIF('Realpage - His. Rent Change'!$A$2:$A$577,'Q2 2026 Summary'!C43,'Realpage - His. Rent Change'!$I$2:$AV$577) -> 0.0616 | N42: =AVERAGE(L42:M42) -> 0.0505 | O42: =MAX(0,-(K42/M42)) -> 0.69735047 | P42: =($P$3*M42)+K42 -> 0.26504321 | Q42: =(1+P42)^(1/$P$3)-1 -> 0.048144288 | R42: =$R$3+P42 -> 0.31604321 | S42: =$S$3*$P$3 -> 0.125 | T42: =SUMIFS(Realpage!$I:$I,Realpage!$A:$A,$C42,Realpage!$F:$F,"NOI % of Revenue") -> 0.51648927 | U42: 1 | V42: =U42-T42 -> 0.48351073 | W42: =U42*(1+R42) -> 1.3160432 | X42: =V42*(1+S42) -> 0.54394957 | Y42: =W42-X42 -> 0.77209364 | Z42: =Y42/T42-1 -> 0.49488805 | AA42: =(Y42/T42)^(1/$P$3)-1 -> 0.083731593 | AB42: =$AB$3 -> 0.05 | AC42: =AB42/$AB$3 -> 1 | AD42: =AC42*(1+$AD$3) -> 1.08 | AE42: =AC42*AB42 -> 0.05 | AF42: =AE42*(1+Z42) -> 0.074744403 | AG42: =AF42/AD42 -> 0.06920778 | AH42: =AG42-AB42 -> 0.01920778 | AI42: =ROUND(AH42,4) -> 0.0192 | AJ42: {=INDEX('Cap Rate to IRR Map'!$F$3:$F$623,MATCH(ROUND(AI42,4),ROUND('Cap Rate to IRR Map'!$E$3:$E$623,4),0))} -> 0.16075 | AK42: =$AK$3 -> 0.05 | AL42: 0.2415
B43: =B42+1 -> 39 | C43: Denver-Aurora-Centennial, CO | D43: =SUMIFS(Realpage!$I:$I,Realpage!$A:$A,$C43,Realpage!$F:$F,"Rent Roll (Rev/OSF)") -> 4.2098846 | E43: =SUMIFS(Realpage!$I:$I,Realpage!$A:$A,$C43,Realpage!$F:$F,"Asking RPSF") -> 4.14 | F43: =E43/D43 -> 0.98339987 | G43: {=SUMPRODUCT(('RP - Unit Starts'!$C$2:$C$101=$C43)*('RP - Unit Starts'!$F$2:$F$101="Unit Starts")*'RP - Unit Starts'!$I$2:$L$101)/SUMIFS('RP - Unit Starts'!$L:$L,'RP - Unit Starts'!$C:$C,$C43,'RP - Unit Starts'!$F:$F,"Existing Units")} -> 0.019471733 | H43: =F43-1 -> -0.016600128 | I43: =SUMIFS(Realpage!$I:$I,Realpage!$A:$A,$C43,Realpage!$F:$F,"Effective RPSF") -> 3.929 | J43: =I43/D43 -> 0.93327973 | K43: =J43-1 -> -0.066720267 | L43: 0.0299 | M43: =AVERAGEIF('Realpage - His. Rent Change'!$A$2:$A$577,'Q2 2026 Summary'!C51,'Realpage - His. Rent Change'!$I$2:$AV$577) -> 0.0835 | N43: =AVERAGE(L43:M43) -> 0.0567 | O43: =MAX(0,-(K43/M43)) -> 0.79904511 | P43: =($P$3*M43)+K43 -> 0.35077973 | Q43: =(1+P43)^(1/$P$3)-1 -> 0.061981392 | R43: =$R$3+P43 -> 0.40177973 | S43: =$S$3*$P$3 -> 0.125 | T43: =SUMIFS(Realpage!$I:$I,Realpage!$A:$A,$C43,Realpage!$F:$F,"NOI % of Revenue") -> 1.212112 | U43: 1 | V43: =U43-T43 -> -0.21211196 | W43: =U43*(1+R43) -> 1.4017797 | X43: =V43*(1+S43) -> -0.23862596 | Y43: =W43-X43 -> 1.6404057 | Z43: =Y43/T43-1 -> 0.35334502 | AA43: =(Y43/T43)^(1/$P$3)-1 -> 0.062384452 | AB43: =$AB$3 -> 0.05 | AC43: =AB43/$AB$3 -> 1 | AD43: =AC43*(1+$AD$3) -> 1.08 | AE43: =AC43*AB43 -> 0.05 | AF43: =AE43*(1+Z43) -> 0.067667251 | AG43: =AF43/AD43 -> 0.062654862 | AH43: =AG43-AB43 -> 0.012654862 | AI43: =ROUND(AH43,4) -> 0.0127 | AJ43: {=INDEX('Cap Rate to IRR Map'!$F$3:$F$623,MATCH(ROUND(AI43,4),ROUND('Cap Rate to IRR Map'!$E$3:$E$623,4),0))} -> 0.114 | AK43: =$AK$3 -> 0.05 | AL43: 0.164 | AO43: Tampa
B44: =B43+1 -> 40 | C44: Knoxville, TN | D44: =SUMIFS(Realpage!$I:$I,Realpage!$A:$A,$C44,Realpage!$F:$F,"Rent Roll (Rev/OSF)") -> 3.1503675 | E44: =SUMIFS(Realpage!$I:$I,Realpage!$A:$A,$C44,Realpage!$F:$F,"Asking RPSF") -> 3.096 | F44: =E44/D44 -> 0.98274248 | G44: {=SUMPRODUCT(('RP - Unit Starts'!$C$2:$C$101=$C44)*('RP - Unit Starts'!$F$2:$F$101="Unit Starts")*'RP - Unit Starts'!$I$2:$L$101)/SUMIFS('RP - Unit Starts'!$L:$L,'RP - Unit Starts'!$C:$C,$C44,'RP - Unit Starts'!$F:$F,"Existing Units")} -> 0 | H44: =F44-1 -> -0.01725752 | I44: =SUMIFS(Realpage!$I:$I,Realpage!$A:$A,$C44,Realpage!$F:$F,"Effective RPSF") -> 3.053 | J44: =I44/D44 -> 0.96909328 | K44: =J44-1 -> -0.030906721 | M44: =AVERAGEIF('Realpage - His. Rent Change'!$A$2:$A$577,'Q2 2026 Summary'!C35,'Realpage - His. Rent Change'!$I$2:$AV$577) -> 0.0635 | N44: =AVERAGE(L44:M44) -> 0.0635 | O44: =MAX(0,-(K44/M44)) -> 0.48672002 | P44: =($P$3*M44)+K44 -> 0.28659328 | Q44: =(1+P44)^(1/$P$3)-1 -> 0.051691238 | R44: =$R$3+P44 -> 0.33759328 | S44: =$S$3*$P$3 -> 0.125 | T44: =SUMIFS(Realpage!$I:$I,Realpage!$A:$A,$C44,Realpage!$F:$F,"NOI % of Revenue") -> 1.2481543 | U44: 1 | V44: =U44-T44 -> -0.24815427 | W44: =U44*(1+R44) -> 1.3375933 | X44: =V44*(1+S44) -> -0.27917356 | Y44: =W44-X44 -> 1.6167668 | Z44: =Y44/T44-1 -> 0.29532612 | AA44: =(Y44/T44)^(1/$P$3)-1 -> 0.053115063 | AB44: =$AB$3 -> 0.05 | AC44: =AB44/$AB$3 -> 1 | AD44: =AC44*(1+$AD$3) -> 1.08 | AE44: =AC44*AB44 -> 0.05 | AF44: =AE44*(1+Z44) -> 0.064766306 | AG44: =AF44/AD44 -> 0.059968802 | AH44: =AG44-AB44 -> 0.009968802 | AI44: =ROUND(AH44,4) -> 0.01 | AJ44: {=INDEX('Cap Rate to IRR Map'!$F$3:$F$623,MATCH(ROUND(AI44,4),ROUND('Cap Rate to IRR Map'!$E$3:$E$623,4),0))} -> 0.0915 | AK44: =$AK$3 -> 0.05 | AL44: 0.091 | AO44: Charlotte
B45: =B44+1 -> 41 | C45: Fort Worth-Arlington-Grapevine/Granbury, TX | D45: =SUMIFS(Realpage!$I:$I,Realpage!$A:$A,$C45,Realpage!$F:$F,"Rent Roll (Rev/OSF)") -> 3.2572527 | E45: =SUMIFS(Realpage!$I:$I,Realpage!$A:$A,$C45,Realpage!$F:$F,"Asking RPSF") -> 3.197 | F45: =E45/D45 -> 0.98150199 | G45: {=SUMPRODUCT(('RP - Unit Starts'!$C$2:$C$101=$C45)*('RP - Unit Starts'!$F$2:$F$101="Unit Starts")*'RP - Unit Starts'!$I$2:$L$101)/SUMIFS('RP - Unit Starts'!$L:$L,'RP - Unit Starts'!$C:$C,$C45,'RP - Unit Starts'!$F:$F,"Existing Units")} -> 0.021879053 | H45: =F45-1 -> -0.018498006 | I45: =SUMIFS(Realpage!$I:$I,Realpage!$A:$A,$C45,Realpage!$F:$F,"Effective RPSF") -> 3.12 | J45: =I45/D45 -> 0.95786244 | K45: =J45-1 -> -0.04213756 | M45: =AVERAGEIF('Realpage - His. Rent Change'!$A$2:$A$577,'Q2 2026 Summary'!C42,'Realpage - His. Rent Change'!$I$2:$AV$577) -> 0.0721 | N45: =AVERAGE(L45:M45) -> 0.0721 | O45: =MAX(0,-(K45/M45)) -> 0.58443218 | P45: =($P$3*M45)+K45 -> 0.31836244 | Q45: =(1+P45)^(1/$P$3)-1 -> 0.056834456 | R45: =$R$3+P45 -> 0.36936244 | S45: =$S$3*$P$3 -> 0.125 | T45: =SUMIFS(Realpage!$I:$I,Realpage!$A:$A,$C45,Realpage!$F:$F,"NOI % of Revenue") -> 1.0011724 | U45: 1 | V45: =U45-T45 -> -0.0011724249 | W45: =U45*(1+R45) -> 1.3693624 | X45: =V45*(1+S45) -> -0.001318978 | Y45: =W45-X45 -> 1.3706814 | Z45: =Y45/T45-1 -> 0.36907628 | AA45: =(Y45/T45)^(1/$P$3)-1 -> 0.064842875 | AB45: =$AB$3 -> 0.05 | AC45: =AB45/$AB$3 -> 1 | AD45: =AC45*(1+$AD$3) -> 1.08 | AE45: =AC45*AB45 -> 0.05 | AF45: =AE45*(1+Z45) -> 0.068453814 | AG45: =AF45/AD45 -> 0.063383161 | AH45: =AG45-AB45 -> 0.013383161 | AI45: =ROUND(AH45,4) -> 0.0134 | AJ45: {=INDEX('Cap Rate to IRR Map'!$F$3:$F$623,MATCH(ROUND(AI45,4),ROUND('Cap Rate to IRR Map'!$E$3:$E$623,4),0))} -> 0.119 | AK45: =$AK$3 -> 0.05 | AL45: 0.166 | AO45: I.e. no further deterioration or elevated bounce back considered
B46: =B45+1 -> 42 | C46: Indianapolis-Carmel-Greenwood/Greencastle, IN | D46: =SUMIFS(Realpage!$I:$I,Realpage!$A:$A,$C46,Realpage!$F:$F,"Rent Roll (Rev/OSF)") -> 2.9395599 | E46: =SUMIFS(Realpage!$I:$I,Realpage!$A:$A,$C46,Realpage!$F:$F,"Asking RPSF") -> 2.879 | F46: =E46/D46 -> 0.97939832 | G46: {=SUMPRODUCT(('RP - Unit Starts'!$C$2:$C$101=$C46)*('RP - Unit Starts'!$F$2:$F$101="Unit Starts")*'RP - Unit Starts'!$I$2:$L$101)/SUMIFS('RP - Unit Starts'!$L:$L,'RP - Unit Starts'!$C:$C,$C46,'RP - Unit Starts'!$F:$F,"Existing Units")} -> 0.016665342 | H46: =F46-1 -> -0.020601678 | I46: =SUMIFS(Realpage!$I:$I,Realpage!$A:$A,$C46,Realpage!$F:$F,"Effective RPSF") -> 2.851 | J46: =I46/D46 -> 0.96987309 | K46: =J46-1 -> -0.030126913 | L46: 0.0459 | M46: =AVERAGEIF('Realpage - His. Rent Change'!$A$2:$A$577,'Q2 2026 Summary'!C41,'Realpage - His. Rent Change'!$I$2:$AV$577) -> 0.0656 | N46: =AVERAGE(L46:M46) -> 0.05575 | O46: =MAX(0,-(K46/M46)) -> 0.45925173 | P46: =($P$3*M46)+K46 -> 0.29787309 | Q46: =(1+P46)^(1/$P$3)-1 -> 0.05352888 | R46: =$R$3+P46 -> 0.34887309 | S46: =$S$3*$P$3 -> 0.125 | T46: =SUMIFS(Realpage!$I:$I,Realpage!$A:$A,$C46,Realpage!$F:$F,"NOI % of Revenue") -> 1.0869248 | U46: 1 | V46: =U46-T46 -> -0.086924763 | W46: =U46*(1+R46) -> 1.3488731 | X46: =V46*(1+S46) -> -0.097790358 | Y46: =W46-X46 -> 1.4466634 | Z46: =Y46/T46-1 -> 0.33096926 | AA46: =(Y46/T46)^(1/$P$3)-1 -> 0.058847962 | AB46: =$AB$3 -> 0.05 | AC46: =AB46/$AB$3 -> 1 | AD46: =AC46*(1+$AD$3) -> 1.08 | AE46: =AC46*AB46 -> 0.05 | AF46: =AE46*(1+Z46) -> 0.066548463 | AG46: =AF46/AD46 -> 0.061618947 | AH46: =AG46-AB46 -> 0.011618947 | AI46: =ROUND(AH46,4) -> 0.0116 | AJ46: {=INDEX('Cap Rate to IRR Map'!$F$3:$F$623,MATCH(ROUND(AI46,4),ROUND('Cap Rate to IRR Map'!$E$3:$E$623,4),0))} -> 0.105 | AK46: =$AK$3 -> 0.05 | AL46: 0.172 | AN46: 2.5% annual expense growth
B47: =B46+1 -> 43 | C47: Houston-Pasadena-The Woodlands, TX | D47: =SUMIFS(Realpage!$I:$I,Realpage!$A:$A,$C47,Realpage!$F:$F,"Rent Roll (Rev/OSF)") -> 3.1375055 | E47: =SUMIFS(Realpage!$I:$I,Realpage!$A:$A,$C47,Realpage!$F:$F,"Asking RPSF") -> 3.061 | F47: =E47/D47 -> 0.97561581 | G47: {=SUMPRODUCT(('RP - Unit Starts'!$C$2:$C$101=$C47)*('RP - Unit Starts'!$F$2:$F$101="Unit Starts")*'RP - Unit Starts'!$I$2:$L$101)/SUMIFS('RP - Unit Starts'!$L:$L,'RP - Unit Starts'!$C:$C,$C47,'RP - Unit Starts'!$F:$F,"Existing Units")} -> 0.016723492 | H47: =F47-1 -> -0.024384188 | I47: =SUMIFS(Realpage!$I:$I,Realpage!$A:$A,$C47,Realpage!$F:$F,"Effective RPSF") -> 2.985 | J47: =I47/D47 -> 0.95139275 | K47: =J47-1 -> -0.048607253 | L47: 0.0186 | M47: =AVERAGEIF('Realpage - His. Rent Change'!$A$2:$A$577,'Q2 2026 Summary'!C45,'Realpage - His. Rent Change'!$I$2:$AV$577) -> 0.0731 | N47: =AVERAGE(L47:M47) -> 0.04585 | O47: =MAX(0,-(K47/M47)) -> 0.6649419 | P47: =($P$3*M47)+K47 -> 0.31689275 | Q47: =(1+P47)^(1/$P$3)-1 -> 0.056598722 | R47: =$R$3+P47 -> 0.36789275 | S47: =$S$3*$P$3 -> 0.125 | T47: =SUMIFS(Realpage!$I:$I,Realpage!$A:$A,$C47,Realpage!$F:$F,"NOI % of Revenue") -> 0.99891272 | U47: 1 | V47: =U47-T47 -> 0.0010872784 | W47: =U47*(1+R47) -> 1.3678927 | X47: =V47*(1+S47) -> 0.0012231882 | Y47: =W47-X47 -> 1.3666696 | Z47: =Y47/T47-1 -> 0.36815713 | AA47: =(Y47/T47)^(1/$P$3)-1 -> 0.064699856 | AB47: =$AB$3 -> 0.05 | AC47: =AB47/$AB$3 -> 1 | AD47: =AC47*(1+$AD$3) -> 1.08 | AE47: =AC47*AB47 -> 0.05 | AF47: =AE47*(1+Z47) -> 0.068407856 | AG47: =AF47/AD47 -> 0.063340608 | AH47: =AG47-AB47 -> 0.013340608 | AI47: =ROUND(AH47,4) -> 0.0133 | AJ47: {=INDEX('Cap Rate to IRR Map'!$F$3:$F$623,MATCH(ROUND(AI47,4),ROUND('Cap Rate to IRR Map'!$E$3:$E$623,4),0))} -> 0.11825 | AK47: =$AK$3 -> 0.05 | AL47: 0.099
B48: =B47+1 -> 44 | C48: Charlotte-Concord-Gastonia, NC-SC | D48: =SUMIFS(Realpage!$I:$I,Realpage!$A:$A,$C48,Realpage!$F:$F,"Rent Roll (Rev/OSF)") -> 3.3420672 | E48: =SUMIFS(Realpage!$I:$I,Realpage!$A:$A,$C48,Realpage!$F:$F,"Asking RPSF") -> 3.258 | F48: =E48/D48 -> 0.97484574 | G48: {=SUMPRODUCT(('RP - Unit Starts'!$C$2:$C$101=$C48)*('RP - Unit Starts'!$F$2:$F$101="Unit Starts")*'RP - Unit Starts'!$I$2:$L$101)/SUMIFS('RP - Unit Starts'!$L:$L,'RP - Unit Starts'!$C:$C,$C48,'RP - Unit Starts'!$F:$F,"Existing Units")} -> 0.019942911 | H48: =F48-1 -> -0.025154263 | I48: =SUMIFS(Realpage!$I:$I,Realpage!$A:$A,$C48,Realpage!$F:$F,"Effective RPSF") -> 3.15 | J48: =I48/D48 -> 0.94253041 | K48: =J48-1 -> -0.057469592 | L48: 0.0361 | M48: =AVERAGEIF('Realpage - His. Rent Change'!$A$2:$A$577,'Q2 2026 Summary'!C49,'Realpage - His. Rent Change'!$I$2:$AV$577) -> -0.0015 | N48: =AVERAGE(L48:M48) -> 0.0173 | O48: =MAX(0,-(K48/M48)) -> 0 | P48: =($P$3*M48)+K48 -> -0.064969592 | Q48: =(1+P48)^(1/$P$3)-1 -> -0.013345395 | R48: =$R$3+P48 -> -0.013969592 | S48: =$S$3*$P$3 -> 0.125 | T48: =SUMIFS(Realpage!$I:$I,Realpage!$A:$A,$C48,Realpage!$F:$F,"NOI % of Revenue") -> 1.1603773 | U48: 1 | V48: =U48-T48 -> -0.16037731 | W48: =U48*(1+R48) -> 0.98603041 | X48: =V48*(1+S48) -> -0.18042447 | Y48: =W48-X48 -> 1.1664549 | Z48: =Y48/T48-1 -> 0.0052375828 | AA48: =(Y48/T48)^(1/$P$3)-1 -> 0.0010453288 | AB48: =$AB$3 -> 0.05 | AC48: =AB48/$AB$3 -> 1 | AD48: =AC48*(1+$AD$3) -> 1.08 | AE48: =AC48*AB48 -> 0.05 | AF48: =AE48*(1+Z48) -> 0.050261879 | AG48: =AF48/AD48 -> 0.046538777 | AH48: =AG48-AB48 -> -0.003461223 | AI48: =ROUND(AH48,4) -> -0.0035 | AJ48: {=INDEX('Cap Rate to IRR Map'!$F$3:$F$623,MATCH(ROUND(AI48,4),ROUND('Cap Rate to IRR Map'!$E$3:$E$623,4),0))} -> -0.05 | AK48: =$AK$3 -> 0.05 | AL48: 0.108
B49: =B48+1 -> 45 | C49: Oklahoma City, OK | D49: =SUMIFS(Realpage!$I:$I,Realpage!$A:$A,$C49,Realpage!$F:$F,"Rent Roll (Rev/OSF)") -> 2.5480474 | E49: =SUMIFS(Realpage!$I:$I,Realpage!$A:$A,$C49,Realpage!$F:$F,"Asking RPSF") -> 2.479 | F49: =E49/D49 -> 0.97290184 | G49: {=SUMPRODUCT(('RP - Unit Starts'!$C$2:$C$101=$C49)*('RP - Unit Starts'!$F$2:$F$101="Unit Starts")*'RP - Unit Starts'!$I$2:$L$101)/SUMIFS('RP - Unit Starts'!$L:$L,'RP - Unit Starts'!$C:$C,$C49,'RP - Unit Starts'!$F:$F,"Existing Units")} -> 0 | H49: =F49-1 -> -0.027098155 | I49: =SUMIFS(Realpage!$I:$I,Realpage!$A:$A,$C49,Realpage!$F:$F,"Effective RPSF") -> 2.455 | J49: =I49/D49 -> 0.96348287 | K49: =J49-1 -> -0.036517132 | M49: =AVERAGEIF('Realpage - His. Rent Change'!$A$2:$A$577,'Q2 2026 Summary'!C40,'Realpage - His. Rent Change'!$I$2:$AV$577) -> 0.0343 | N49: =AVERAGE(L49:M49) -> 0.0343 | O49: =MAX(0,-(K49/M49)) -> 1.0646394 | P49: =($P$3*M49)+K49 -> 0.13498287 | Q49: =(1+P49)^(1/$P$3)-1 -> 0.025646875 | R49: =$R$3+P49 -> 0.18598287 | S49: =$S$3*$P$3 -> 0.125 | T49: =SUMIFS(Realpage!$I:$I,Realpage!$A:$A,$C49,Realpage!$F:$F,"NOI % of Revenue") -> 0.98095281 | U49: 1 | V49: =U49-T49 -> 0.019047193 | W49: =U49*(1+R49) -> 1.1859829 | X49: =V49*(1+S49) -> 0.021428092 | Y49: =W49-X49 -> 1.1645548 | Z49: =Y49/T49-1 -> 0.18716697 | AA49: =(Y49/T49)^(1/$P$3)-1 -> 0.034909471 | AB49: =$AB$3 -> 0.05 | AC49: =AB49/$AB$3 -> 1 | AD49: =AC49*(1+$AD$3) -> 1.08 | AE49: =AC49*AB49 -> 0.05 | AF49: =AE49*(1+Z49) -> 0.059358349 | AG49: =AF49/AD49 -> 0.054961434 | AH49: =AG49-AB49 -> 0.004961434 | AI49: =ROUND(AH49,4) -> 0.005 | AJ49: {=INDEX('Cap Rate to IRR Map'!$F$3:$F$623,MATCH(ROUND(AI49,4),ROUND('Cap Rate to IRR Map'!$E$3:$E$623,4),0))} -> 0.047 | AK49: =$AK$3 -> 0.05 | AL49: 0.097
B50: =B49+1 -> 46 | C50: Dallas-Plano-Irving, TX | D50: =SUMIFS(Realpage!$I:$I,Realpage!$A:$A,$C50,Realpage!$F:$F,"Rent Roll (Rev/OSF)") -> 3.6002067 | E50: =SUMIFS(Realpage!$I:$I,Realpage!$A:$A,$C50,Realpage!$F:$F,"Asking RPSF") -> 3.482 | F50: =E50/D50 -> 0.9671667 | G50: {=SUMPRODUCT(('RP - Unit Starts'!$C$2:$C$101=$C50)*('RP - Unit Starts'!$F$2:$F$101="Unit Starts")*'RP - Unit Starts'!$I$2:$L$101)/SUMIFS('RP - Unit Starts'!$L:$L,'RP - Unit Starts'!$C:$C,$C50,'RP - Unit Starts'!$F:$F,"Existing Units")} -> 0.02449441 | H50: =F50-1 -> -0.032833297 | I50: =SUMIFS(Realpage!$I:$I,Realpage!$A:$A,$C50,Realpage!$F:$F,"Effective RPSF") -> 3.387 | J50: =I50/D50 -> 0.94077933 | K50: =J50-1 -> -0.059220671 | L50: 0.0348 | M50: =AVERAGEIF('Realpage - His. Rent Change'!$A$2:$A$577,'Q2 2026 Summary'!C48,'Realpage - His. Rent Change'!$I$2:$AV$577) -> 0.0823 | N50: =AVERAGE(L50:M50) -> 0.05855 | O50: =MAX(0,-(K50/M50)) -> 0.71957073 | P50: =($P$3*M50)+K50 -> 0.35227933 | Q50: =(1+P50)^(1/$P$3)-1 -> 0.062217084 | R50: =$R$3+P50 -> 0.40327933 | S50: =$S$3*$P$3 -> 0.125 | T50: =SUMIFS(Realpage!$I:$I,Realpage!$A:$A,$C50,Realpage!$F:$F,"NOI % of Revenue") -> 1.0424319 | U50: 1 | V50: =U50-T50 -> -0.042431947 | W50: =U50*(1+R50) -> 1.4032793 | X50: =V50*(1+S50) -> -0.04773594 | Y50: =W50-X50 -> 1.4510153 | Z50: =Y50/T50-1 -> 0.39195203 | AA50: =(Y50/T50)^(1/$P$3)-1 -> 0.068377797 | AB50: =$AB$3 -> 0.05 | AC50: =AB50/$AB$3 -> 1 | AD50: =AC50*(1+$AD$3) -> 1.08 | AE50: =AC50*AB50 -> 0.05 | AF50: =AE50*(1+Z50) -> 0.069597602 | AG50: =AF50/AD50 -> 0.064442224 | AH50: =AG50-AB50 -> 0.014442224 | AI50: =ROUND(AH50,4) -> 0.0144 | AJ50: {=INDEX('Cap Rate to IRR Map'!$F$3:$F$623,MATCH(ROUND(AI50,4),ROUND('Cap Rate to IRR Map'!$E$3:$E$623,4),0))} -> 0.12675 | AK50: =$AK$3 -> 0.05 | AL50: 0.17675
B51: =B50+1 -> 47 | C51: Tampa-St. Petersburg-Clearwater, FL | D51: =SUMIFS(Realpage!$I:$I,Realpage!$A:$A,$C51,Realpage!$F:$F,"Rent Roll (Rev/OSF)") -> 3.9911094 | E51: =SUMIFS(Realpage!$I:$I,Realpage!$A:$A,$C51,Realpage!$F:$F,"Asking RPSF") -> 3.857 | F51: =E51/D51 -> 0.96639797 | G51: {=SUMPRODUCT(('RP - Unit Starts'!$C$2:$C$101=$C51)*('RP - Unit Starts'!$F$2:$F$101="Unit Starts")*'RP - Unit Starts'!$I$2:$L$101)/SUMIFS('RP - Unit Starts'!$L:$L,'RP - Unit Starts'!$C:$C,$C51,'RP - Unit Starts'!$F:$F,"Existing Units")} -> 0.018187611 | H51: =F51-1 -> -0.033602025 | I51: =SUMIFS(Realpage!$I:$I,Realpage!$A:$A,$C51,Realpage!$F:$F,"Effective RPSF") -> 3.75 | J51: =I51/D51 -> 0.93958839 | K51: =J51-1 -> -0.060411614 | L51: 0.0537 | M51: =AVERAGEIF('Realpage - His. Rent Change'!$A$2:$A$577,'Q2 2026 Summary'!C47,'Realpage - His. Rent Change'!$I$2:$AV$577) -> 0.0386 | N51: =AVERAGE(L51:M51) -> 0.04615 | O51: =MAX(0,-(K51/M51)) -> 1.5650677 | P51: =($P$3*M51)+K51 -> 0.13258839 | Q51: =(1+P51)^(1/$P$3)-1 -> 0.025213747 | R51: =$R$3+P51 -> 0.18358839 | S51: =$S$3*$P$3 -> 0.125 | T51: =SUMIFS(Realpage!$I:$I,Realpage!$A:$A,$C51,Realpage!$F:$F,"NOI % of Revenue") -> 1.0906094 | U51: 1 | V51: =U51-T51 -> -0.090609364 | W51: =U51*(1+R51) -> 1.1835884 | X51: =V51*(1+S51) -> -0.10193553 | Y51: =W51-X51 -> 1.2855239 | Z51: =Y51/T51-1 -> 0.17872078 | AA51: =(Y51/T51)^(1/$P$3)-1 -> 0.033432673 | AB51: =$AB$3 -> 0.05 | AC51: =AB51/$AB$3 -> 1 | AD51: =AC51*(1+$AD$3) -> 1.08 | AE51: =AC51*AB51 -> 0.05 | AF51: =AE51*(1+Z51) -> 0.058936039 | AG51: =AF51/AD51 -> 0.054570407 | AH51: =AG51-AB51 -> 0.0045704065 | AI51: =ROUND(AH51,4) -> 0.0046 | AJ51: {=INDEX('Cap Rate to IRR Map'!$F$3:$F$623,MATCH(ROUND(AI51,4),ROUND('Cap Rate to IRR Map'!$E$3:$E$623,4),0))} -> 0.042 | AK51: =$AK$3 -> 0.05 | AL51: 0.14075
B52: =B51+1 -> 48 | C52: San Antonio-New Braunfels, TX | D52: =SUMIFS(Realpage!$I:$I,Realpage!$A:$A,$C52,Realpage!$F:$F,"Rent Roll (Rev/OSF)") -> 2.8593092 | E52: =SUMIFS(Realpage!$I:$I,Realpage!$A:$A,$C52,Realpage!$F:$F,"Asking RPSF") -> 2.761 | F52: =E52/D52 -> 0.96561784 | G52: {=SUMPRODUCT(('RP - Unit Starts'!$C$2:$C$101=$C52)*('RP - Unit Starts'!$F$2:$F$101="Unit Starts")*'RP - Unit Starts'!$I$2:$L$101)/SUMIFS('RP - Unit Starts'!$L:$L,'RP - Unit Starts'!$C:$C,$C52,'RP - Unit Starts'!$F:$F,"Existing Units")} -> 0.0025948699 | H52: =F52-1 -> -0.034382155 | I52: =SUMIFS(Realpage!$I:$I,Realpage!$A:$A,$C52,Realpage!$F:$F,"Effective RPSF") -> 2.643 | J52: =I52/D52 -> 0.92434914 | K52: =J52-1 -> -0.075650864 | L52: 0.0212 | M52: =AVERAGEIF('Realpage - His. Rent Change'!$A$2:$A$577,'Q2 2026 Summary'!C52,'Realpage - His. Rent Change'!$I$2:$AV$577) -> 0.0493 | N52: =AVERAGE(L52:M52) -> 0.03525 | O52: =MAX(0,-(K52/M52)) -> 1.5345003 | P52: =($P$3*M52)+K52 -> 0.17084914 | Q52: =(1+P52)^(1/$P$3)-1 -> 0.032048692 | R52: =$R$3+P52 -> 0.22184914 | S52: =$S$3*$P$3 -> 0.125 | T52: =SUMIFS(Realpage!$I:$I,Realpage!$A:$A,$C52,Realpage!$F:$F,"NOI % of Revenue") -> 0.91780537 | U52: 1 | V52: =U52-T52 -> 0.082194627 | W52: =U52*(1+R52) -> 1.2218491 | X52: =V52*(1+S52) -> 0.092468955 | Y52: =W52-X52 -> 1.1293802 | Z52: =Y52/T52-1 -> 0.23052252 | AA52: =(Y52/T52)^(1/$P$3)-1 -> 0.042360422 | AB52: =$AB$3 -> 0.05 | AC52: =AB52/$AB$3 -> 1 | AD52: =AC52*(1+$AD$3) -> 1.08 | AE52: =AC52*AB52 -> 0.05 | AF52: =AE52*(1+Z52) -> 0.061526126 | AG52: =AF52/AD52 -> 0.056968635 | AH52: =AG52-AB52 -> 0.0069686352 | AI52: =ROUND(AH52,4) -> 0.007 | AJ52: {=INDEX('Cap Rate to IRR Map'!$F$3:$F$623,MATCH(ROUND(AI52,4),ROUND('Cap Rate to IRR Map'!$E$3:$E$623,4),0))} -> 0.065333 | AK52: =$AK$3 -> 0.05 | AL52: 0.0265
B53: =B52+1 -> 49 | C53: Tulsa, OK | D53: =SUMIFS(Realpage!$I:$I,Realpage!$A:$A,$C53,Realpage!$F:$F,"Rent Roll (Rev/OSF)") -> 2.5678354 | E53: =SUMIFS(Realpage!$I:$I,Realpage!$A:$A,$C53,Realpage!$F:$F,"Asking RPSF") -> 2.475 | F53: =E53/D53 -> 0.96384681 | G53: {=SUMPRODUCT(('RP - Unit Starts'!$C$2:$C$101=$C53)*('RP - Unit Starts'!$F$2:$F$101="Unit Starts")*'RP - Unit Starts'!$I$2:$L$101)/SUMIFS('RP - Unit Starts'!$L:$L,'RP - Unit Starts'!$C:$C,$C53,'RP - Unit Starts'!$F:$F,"Existing Units")} -> 0 | H53: =F53-1 -> -0.036153191 | I53: =SUMIFS(Realpage!$I:$I,Realpage!$A:$A,$C53,Realpage!$F:$F,"Effective RPSF") -> 2.46 | J53: =I53/D53 -> 0.95800531 | K53: =J53-1 -> -0.041994687 | M53: =AVERAGEIF('Realpage - His. Rent Change'!$A$2:$A$577,'Q2 2026 Summary'!C33,'Realpage - His. Rent Change'!$I$2:$AV$577) -> 0.0231 | N53: =AVERAGE(L53:M53) -> 0.0231 | O53: =MAX(0,-(K53/M53)) -> 1.8179518 | P53: =($P$3*M53)+K53 -> 0.073505313 | Q53: =(1+P53)^(1/$P$3)-1 -> 0.014286954 | R53: =$R$3+P53 -> 0.12450531 | S53: =$S$3*$P$3 -> 0.125 | T53: =SUMIFS(Realpage!$I:$I,Realpage!$A:$A,$C53,Realpage!$F:$F,"NOI % of Revenue") -> 0.96988967 | U53: 1 | V53: =U53-T53 -> 0.030110331 | W53: =U53*(1+R53) -> 1.1245053 | X53: =V53*(1+S53) -> 0.033874122 | Y53: =W53-X53 -> 1.0906312 | Z53: =Y53/T53-1 -> 0.12448996 | AA53: =(Y53/T53)^(1/$P$3)-1 -> 0.023743403 | AB53: =$AB$3 -> 0.05 | AC53: =AB53/$AB$3 -> 1 | AD53: =AC53*(1+$AD$3) -> 1.08 | AE53: =AC53*AB53 -> 0.05 | AF53: =AE53*(1+Z53) -> 0.056224498 | AG53: =AF53/AD53 -> 0.05205972 | AH53: =AG53-AB53 -> 0.0020597202 | AI53: =ROUND(AH53,4) -> 0.0021 | AJ53: {=INDEX('Cap Rate to IRR Map'!$F$3:$F$623,MATCH(ROUND(AI53,4),ROUND('Cap Rate to IRR Map'!$E$3:$E$623,4),0))} -> 0.017 | AK53: =$AK$3 -> 0.05 | AL53: 0.16675
B54: =B53+1 -> 50 | C54: Greenville/Spartanburg, SC | D54: =SUMIFS(Realpage!$I:$I,Realpage!$A:$A,$C54,Realpage!$F:$F,"Rent Roll (Rev/OSF)") -> 2.975833 | E54: =SUMIFS(Realpage!$I:$I,Realpage!$A:$A,$C54,Realpage!$F:$F,"Asking RPSF") -> 2.779 | F54: =E54/D54 -> 0.93385615 | G54: {=SUMPRODUCT(('RP - Unit Starts'!$C$2:$C$101=$C54)*('RP - Unit Starts'!$F$2:$F$101="Unit Starts")*'RP - Unit Starts'!$I$2:$L$101)/SUMIFS('RP - Unit Starts'!$L:$L,'RP - Unit Starts'!$C:$C,$C54,'RP - Unit Starts'!$F:$F,"Existing Units")} -> 0.0018915354 | H54: =F54-1 -> -0.066143847 | I54: =SUMIFS(Realpage!$I:$I,Realpage!$A:$A,$C54,Realpage!$F:$F,"Effective RPSF") -> 2.731 | J54: =I54/D54 -> 0.91772622 | K54: =J54-1 -> -0.082273784 | M54: =AVERAGEIF('Realpage - His. Rent Change'!$A$2:$A$577,'Q2 2026 Summary'!C54,'Realpage - His. Rent Change'!$I$2:$AV$577) -> 0.0586 | N54: =AVERAGE(L54:M54) -> 0.0586 | O54: =MAX(0,-(K54/M54)) -> 1.4039895 | P54: =($P$3*M54)+K54 -> 0.21072622 | Q54: =(1+P54)^(1/$P$3)-1 -> 0.038984789 | R54: =$R$3+P54 -> 0.26172622 | S54: =$S$3*$P$3 -> 0.125 | T54: =SUMIFS(Realpage!$I:$I,Realpage!$A:$A,$C54,Realpage!$F:$F,"NOI % of Revenue") -> 1.1044923 | U54: 1 | V54: =U54-T54 -> -0.1044923 | W54: =U54*(1+R54) -> 1.2617262 | X54: =V54*(1+S54) -> -0.11755384 | Y54: =W54-X54 -> 1.3792801 | Z54: =Y54/T54-1 -> 0.24879101 | AA54: =(Y54/T54)^(1/$P$3)-1 -> 0.045437207 | AB54: =$AB$3 -> 0.05 | AC54: =AB54/$AB$3 -> 1 | AD54: =AC54*(1+$AD$3) -> 1.08 | AE54: =AC54*AB54 -> 0.05 | AF54: =AE54*(1+Z54) -> 0.06243955 | AG54: =AF54/AD54 -> 0.057814399 | AH54: =AG54-AB54 -> 0.0078143985 | AI54: =ROUND(AH54,4) -> 0.0078 | AJ54: {=INDEX('Cap Rate to IRR Map'!$F$3:$F$623,MATCH(ROUND(AI54,4),ROUND('Cap Rate to IRR Map'!$E$3:$E$623,4),0))} -> 0.073 | AK54: =$AK$3 -> 0.05 | AL54: 0.105 | AO54: Jacksonville
AO56: Denver
D57: Mark-to-market strongly positive; revenue growth flowing directly into NOI | AO57: Austin
D58: Positive parity; effective rents at or above in-place rent roll | AO58: SA
D59: Near parity; modest concession drag; approaching inflection
D60: Negative spread; embedded concession drag suppressing revenue | AN60: Fringe market watch list - which have interesting PF returns, and we need to form an opinion if they are further worth pursuing
AO61: Reno
AO62: Richmond
AO63: KC
AO64: Charleston
AO65: Grand Rapids????

Sheet Realpage
A1: Geography Name | B1: Geography Type | C1: Market Name | D1: Unique ID | E1: Metric Type | F1: Metric Name | G1: Category | H1: Niche | I1: Y2026Q2
A2: Albuquerque, NM | B2: Market | C2: Albuquerque, NM | D2: 10740 | E2: Transaction Data - Operational | F2: Rent Roll (Rev/OSF) | G2: Totals | H2: Totals | I2: 1.628002
A3: Albuquerque, NM | B3: Market | C3: Albuquerque, NM | D3: 10740 | E3: Transaction Data - Financial | F3: NOI % of Revenue | G3: Totals | H3: Totals | I3: 0.61413872
A4: Albuquerque, NM | B4: Market | C4: Albuquerque, NM | D4: 10740 | E4: Performance | F4: Effective RPSF | G4: Totals | H4: Totals | I4: 1.612
A5: Albuquerque, NM | B5: Market | C5: Albuquerque, NM | D5: 10740 | E5: Performance | F5: Asking RPSF | G5: Totals | H5: Totals | I5: 1.628
A6: Atlanta-Sandy Springs-Roswell, GA | B6: Market | C6: Atlanta-Sandy Springs-Roswell, GA | D6: 12060 | E6: Transaction Data - Operational | F6: Rent Roll (Rev/OSF) | G6: Totals | H6: Totals | I6: 1.6321102
A7: Atlanta-Sandy Springs-Roswell, GA | B7: Market | C7: Atlanta-Sandy Springs-Roswell, GA | D7: 12060 | E7: Transaction Data - Financial | F7: NOI % of Revenue | G7: Totals | H7: Totals | I7: 0.51648927
A8: Atlanta-Sandy Springs-Roswell, GA | B8: Market | C8: Atlanta-Sandy Springs-Roswell, GA | D8: 12060 | E8: Performance | F8: Effective RPSF | G8: Totals | H8: Totals | I8: 1.562
A9: Atlanta-Sandy Springs-Roswell, GA | B9: Market | C9: Atlanta-Sandy Springs-Roswell, GA | D9: 12060 | E9: Performance | F9: Asking RPSF | G9: Totals | H9: Totals | I9: 1.607
A10: Austin-Round Rock-San Marcos, TX | B10: Market | C10: Austin-Round Rock-San Marcos, TX | D10: 12420 | E10: Transaction Data - Operational | F10: Rent Roll (Rev/OSF) | G10: Totals | H10: Totals | I10: 1.6921104
A11: Austin-Round Rock-San Marcos, TX | B11: Market | C11: Austin-Round Rock-San Marcos, TX | D11: 12420 | E11: Transaction Data - Financial | F11: NOI % of Revenue | G11: Totals | H11: Totals | I11: 0.45675923
A12: Austin-Round Rock-San Marcos, TX | B12: Market | C12: Austin-Round Rock-San Marcos, TX | D12: 12420 | E12: Performance | F12: Effective RPSF | G12: Totals | H12: Totals | I12: 1.595
A13: Austin-Round Rock-San Marcos, TX | B13: Market | C13: Austin-Round Rock-San Marcos, TX | D13: 12420 | E13: Performance | F13: Asking RPSF | G13: Totals | H13: Totals | I13: 1.691
... A201: Wilmington, NC | B201: Market | C201: Wilmington, NC | D201: 48900 | E201: Performance | F201: Asking RPSF | G201: Totals | H201: Totals | I201: 1.596
A202: Breckenridge, CO | B202: Market | C202: Breckenridge, CO | D202: 14720 | E202: Performance | F202: Effective RPSF | G202: Totals | H202: Totals
A203: Breckenridge, CO | B203: Market | C203: Breckenridge, CO | D203: 14720 | E203: Performance | F203: Asking RPSF | G203: Totals | H203: Totals
A204: Bremerton-Silverdale-Port Orchard, WA | B204: Market | C204: Bremerton-Silverdale-Port Orchard, WA | D204: 14740 | E204: Transaction Data - Operational | F204: Rent Roll (Rev/OSF) | G204: Totals | H204: Totals | I204: 2.1683212
A205: Bremerton-Silverdale-Port Orchard, WA | B205: Market | C205: Bremerton-Silverdale-Port Orchard, WA | D205: 14740 | E205: Performance | F205: Effective RPSF | G205: Totals | H205: Totals | I205: 2.203
A206: Bremerton-Silverdale-Port Orchard, WA | B206: Market | C206: Bremerton-Silverdale-Port Orchard, WA | D206: 14740 | E206: Performance | F206: Asking RPSF | G206: Totals | H206: Totals | I206: 2.219
A207: Brenham, TX | B207: Market | C207: Brenham, TX | D207: 14780 | E207: Performance | F207: Effective RPSF | G207: Totals | H207: Totals
A208: Brenham, TX | B208: Market | C208: Brenham, TX | D208: 14780 | E208: Performance | F208: Asking RPSF | G208: Totals | H208: Totals
A209: Bridgeport-Stamford-Danbury, CT | B209: Market | C209: Bridgeport-Stamford-Danbury, CT | D209: 14860 | E209: Transaction Data - Operational | F209: Rent Roll (Rev/OSF) | G209: Totals | H209: Totals | I209: 3.0912
A210: Bridgeport-Stamford-Danbury, CT | B210: Market | C210: Bridgeport-Stamford-Danbury, CT | D210: 14860 | E210: Transaction Data - Financial | F210: NOI % of Revenue | G210: Totals | H210: Totals | I210: 0.58514459
A211: Bridgeport-Stamford-Danbury, CT | B211: Market | C211: Bridgeport-Stamford-Danbury, CT | D211: 14860 | E211: Performance | F211: Effective RPSF | G211: Totals | H211: Totals | I211: 3.087
A212: Bridgeport-Stamford-Danbury, CT | B212: Market | C212: Bridgeport-Stamford-Danbury, CT | D212: 14860 | E212: Performance | F212: Asking RPSF | G212: Totals | H212: Totals | I212: 3.141
A213: Brookhaven, MS | B213: Market | C213: Brookhaven, MS | D213: 15020 | E213: Performance | F213: Effective RPSF | G213: Totals | H213: Totals
A214: Brookhaven, MS | B214: Market | C214: Brookhaven, MS | D214: 15020 | E214: Performance | F214: Asking RPSF | G214: Totals | H214: Totals
A215: Brookings, SD | B215: Market | C215: Brookings, SD | D215: 15100 | E215: Performance | F215: Effective RPSF | G215: Totals | H215: Totals
A216: Brookings, SD | B216: Market | C216: Brookings, SD | D216: 15100 | E216: Performance | F216: Asking RPSF | G216: Totals | H216: Totals
A217: Brownwood, TX | B217: Market | C217: Brownwood, TX | D217: 15220 | E217: Performance | F217: Effective RPSF | G217: Totals | H217: Totals
A218: Brownwood, TX | B218: Market | C218: Brownwood, TX | D218: 15220 | E218: Performance | F218: Asking RPSF | G218: Totals | H218: Totals
A219: Brunswick-St. Simons, GA | B219: Market | C219: Brunswick-St. Simons, GA | D219: 15260 | E219: Transaction Data - Operational | F219: Rent Roll (Rev/OSF) | G219: Totals | H219: Totals | I219: 1.2320264
A220: Brunswick-St. Simons, GA | B220: Market | C220: Brunswick-St. Simons, GA | D220: 15260 | E220: Performance | F220: Effective RPSF | G220: Totals | H220: Totals | I220: 1.253
A221: Brunswick-St. Simons, GA | B221: Market | C221: Brunswick-St. Simons, GA | D221: 15260 | E221: Performance | F221: Asking RPSF | G221: Totals | H221: Totals | I221: 1.304
A222: Buffalo-Cheektowaga, NY | B222: Market | C222: Buffalo-Cheektowaga, NY | D222: 15380 | E222: Transaction Data - Operational | F222: Rent Roll (Rev/OSF) | G222: Totals | H222: Totals | I222: 1.5429201
A223: Buffalo-Cheektowaga, NY | B223: Market | C223: Buffalo-Cheektowaga, NY | D223: 15380 | E223: Transaction Data - Financial | F223: NOI % of Revenue | G223: Totals | H223: Totals | I223: 0.53133675
A224: Buffalo-Cheektowaga, NY | B224: Market | C224: Buffalo-Cheektowaga, NY | D224: 15380 | E224: Performance | F224: Effective RPSF | G224: Totals | H224: Totals | I224: 1.697
A225: Buffalo-Cheektowaga, NY | B225: Market | C225: Buffalo-Cheektowaga, NY | D225: 15380 | E225: Performance | F225: Asking RPSF | G225: Totals | H225: Totals | I225: 1.701
A226: Burlington, IA-IL | B226: Market | C226: Burlington, IA-IL | D226: 15460 | E226: Performance | F226: Effective RPSF | G226: Totals | H226: Totals
A227: Burlington, IA-IL | B227: Market | C227: Burlington, IA-IL | D227: 15460 | E227: Performance | F227: Asking RPSF | G227: Totals | H227: Totals
A228: Burlington-South Burlington, VT | B228: Market | C228: Burlington-South Burlington, VT | D228: 15540 | E228: Transaction Data - Operational | F228: Rent Roll (Rev/OSF) | G228: Totals | H228: Totals | I228: 2.1362414
A229: Burlington-South Burlington, VT | B229: Market | C229: Burlington-South Burlington, VT | D229: 15540 | E229: Performance | F229: Effective RPSF | G229: Totals | H229: Totals | I229: 2.395
A230: Burlington-South Burlington, VT | B230: Market | C230: Burlington-South Burlington, VT | D230: 15540 | E230: Performance | F230: Asking RPSF | G230: Totals | H230: Totals | I230: 2.4
A231: Canon City, CO | B231: Market | C231: Canon City, CO | D231: 15860 | E231: Performance | F231: Effective RPSF | G231: Totals | H231: Totals
A232: Canon City, CO | B232: Market | C232: Canon City, CO | D232: 15860 | E232: Performance | F232: Asking RPSF | G232: Totals | H232: Totals
A233: Canton-Massillon, OH | B233: Market | C233: Canton-Massillon, OH | D233: 15940 | E233: Transaction Data - Operational | F233: Rent Roll (Rev/OSF) | G233: Totals | H233: Totals | I233: 1.2103324
A234: Canton-Massillon, OH | B234: Market | C234: Canton-Massillon, OH | D234: 15940 | E234: Performance | F234: Effective RPSF | G234: Totals | H234: Totals | I234: 1.339
A235: Canton-Massillon, OH | B235: Market | C235: Canton-Massillon, OH | D235: 15940 | E235: Performance | F235: Asking RPSF | G235: Totals | H235: Totals | I235: 1.352
A236: Cape Coral-Fort Myers, FL | B236: Market | C236: Cape Coral-Fort Myers, FL | D236: 15980 | E236: Transaction Data - Operational | F236: Rent Roll (Rev/OSF) | G236: Totals | H236: Totals | I236: 1.6849004
A237: Cape Coral-Fort Myers, FL | B237: Market | C237: Cape Coral-Fort Myers, FL | D237: 15980 | E237: Transaction Data - Financial | F237: NOI % of Revenue | G237: Totals | H237: Totals | I237: 0.53003328
A238: Cape Coral-Fort Myers, FL | B238: Market | C238: Cape Coral-Fort Myers, FL | D238: 15980 | E238: Performance | F238: Effective RPSF | G238: Totals | H238: Totals | I238: 1.563
A239: Cape Coral-Fort Myers, FL | B239: Market | C239: Cape Coral-Fort Myers, FL | D239: 15980 | E239: Performance | F239: Asking RPSF | G239: Totals | H239: Totals | I239: 1.666
A240: Carbondale/Marion-Herrin, IL | B240: Market | C240: Carbondale/Marion-Herrin, IL | D240: 216060 | E240: Performance | F240: Effective RPSF | G240: Totals | H240: Totals
A241: Carbondale/Marion-Herrin, IL | B241: Market | C241: Carbondale/Marion-Herrin, IL | D241: 216060 | E241: Performance | F241: Asking RPSF | G241: Totals | H241: Totals
A242: Carlsbad-Artesia, NM | B242: Market | C242: Carlsbad-Artesia, NM | D242: 16100 | E242: Performance | F242: Effective RPSF | G242: Totals | H242: Totals | I242: 1.672
A243: Carlsbad-Artesia, NM | B243: Market | C243: Carlsbad-Artesia, NM | D243: 16100 | E243: Performance | F243: Asking RPSF | G243: Totals | H243: Totals | I243: 1.672
A244: Carson City, NV | B244: Market | C244: Carson City, NV | D244: 16180 | E244: Transaction Data - Operational | F244: Rent Roll (Rev/OSF) | G244: Totals | H244: Totals | I244: 1.7585913
A245: Carson City, NV | B245: Market | C245: Carson City, NV | D245: 16180 | E245: Performance | F245: Effective RPSF | G245: Totals | H245: Totals | I245: 2.032
A246: Carson City, NV | B246: Market | C246: Carson City, NV | D246: 16180 | E246: Performance | F246: Asking RPSF | G246: Totals | H246: Totals | I246: 2.078
A247: Casper, WY | B247: Market | C247: Casper, WY | D247: 16220 | E247: Performance | F247: Effective RPSF | G247: Totals | H247: Totals | I247: 1.228
A248: Casper, WY | B248: Market | C248: Casper, WY | D248: 16220 | E248: Performance | F248: Asking RPSF | G248: Totals | H248: Totals | I248: 1.231
A249: Cedar Rapids, IA | B249: Market | C249: Cedar Rapids, IA | D249: 16300 | E249: Transaction Data - Operational | F249: Rent Roll (Rev/OSF) | G249: Totals | H249: Totals | I249: 1.1500395
A250: Cedar Rapids, IA | B250: Market | C250: Cedar Rapids, IA | D250: 16300 | E250: Performance | F250: Effective RPSF | G250: Totals | H250: Totals | I250: 1.24
A251: Cedar Rapids, IA | B251: Market | C251: Cedar Rapids, IA | D251: 16300 | E251: Performance | F251: Asking RPSF | G251: Totals | H251: Totals | I251: 1.24
A252: Chambersburg, PA | B252: Market | C252: Chambersburg, PA | D252: 16540 | E252: Performance | F252: Effective RPSF | G252: Totals | H252: Totals
A253: Chambersburg, PA | B253: Market | C253: Chambersburg, PA | D253: 16540 | E253: Performance | F253: Asking RPSF | G253: Totals | H253: Totals
A254: Champaign-Urbana, IL | B254: Market | C254: Champaign-Urbana, IL | D254: 16580 | E254: Performance | F254: Effective RPSF | G254: Totals | H254: Totals | I254: 1.317
A255: Champaign-Urbana, IL | B255: Market | C255: Champaign-Urbana, IL | D255: 16580 | E255: Performance | F255: Asking RPSF | G255: Totals | H255: Totals | I255: 1.332
A256: Charleston-Mattoon, IL | B256: Market | C256: Charleston-Mattoon, IL | D256: 16660 | E256: Performance | F256: Effective RPSF | G256: Totals | H256: Totals
A257: Charleston-Mattoon, IL | B257: Market | C257: Charleston-Mattoon, IL | D257: 16660 | E257: Performance | F257: Asking RPSF | G257: Totals | H257: Totals
A258: Charleston-North Charleston, SC | B258: Market | C258: Charleston-North Charleston, SC | D258: 16700 | E258: Transaction Data - Operational | F258: Rent Roll (Rev/OSF) | G258: Totals | H258: Totals | I258: 1.824185
A259: Charleston-North Charleston, SC | B259: Market | C259: Charleston-North Charleston, SC | D259: 16700 | E259: Transaction Data - Financial | F259: NOI % of Revenue | G259: Totals | H259: Totals | I259: 0.5471264
A260: Charleston-North Charleston, SC | B260: Market | C260: Charleston-North Charleston, SC | D260: 16700 | E260: Performance | F260: Effective RPSF | G260: Totals | H260: Totals | I260: 1.794
A261: Charleston-North Charleston, SC | B261: Market | C261: Charleston-North Charleston, SC | D261: 16700 | E261: Performance | F261: Asking RPSF | G261: Totals | H261: Totals | I261: 1.825
A262: Charleston, WV | B262: Market | C262: Charleston, WV | D262: 16620 | E262: Transaction Data - Operational | F262: Rent Roll (Rev/OSF) | G262: Totals | H262: Totals | I262: 0.79879218
A263: Charleston, WV | B263: Market | C263: Charleston, WV | D263: 16620 | E263: Performance | F263: Effective RPSF | G263: Totals | H263: Totals
A264: Charleston, WV | B264: Market | C264: Charleston, WV | D264: 16620 | E264: Performance | F264: Asking RPSF | G264: Totals | H264: Totals
A265: Charlotte-Concord-Gastonia, NC-SC | B265: Market | C265: Charlotte-Concord-Gastonia, NC-SC | D265: 16740 | E265: Transaction Data - Operational | F265: Rent Roll (Rev/OSF) | G265: Totals | H265: Totals | I265: 1.6807313
A266: Charlotte-Concord-Gastonia, NC-SC | B266: Market | C266: Charlotte-Concord-Gastonia, NC-SC | D266: 16740 | E266: Transaction Data - Financial | F266: NOI % of Revenue | G266: Totals | H266: Totals | I266: 0.57951662
A267: Charlotte-Concord-Gastonia, NC-SC | B267: Market | C267: Charlotte-Concord-Gastonia, NC-SC | D267: 16740 | E267: Performance | F267: Effective RPSF | G267: Totals | H267: Totals | I267: 1.565
A268: Charlotte-Concord-Gastonia, NC-SC | B268: Market | C268: Charlotte-Concord-Gastonia, NC-SC | D268: 16740 | E268: Performance | F268: Asking RPSF | G268: Totals | H268: Totals | I268: 1.616
A269: Charlottesville, VA | B269: Market | C269: Charlottesville, VA | D269: 16820 | E269: Transaction Data - Operational | F269: Rent Roll (Rev/OSF) | G269: Totals | H269: Totals | I269: 1.8751721
A270: Charlottesville, VA | B270: Market | C270: Charlottesville, VA | D270: 16820 | E270: Transaction Data - Financial | F270: NOI % of Revenue | G270: Totals | H270: Totals | I270: 0.66087457
A271: Charlottesville, VA | B271: Market | C271: Charlottesville, VA | D271: 16820 | E271: Performance | F271: Effective RPSF | G271: Totals | H271: Totals | I271: 1.846
A272: Charlottesville, VA | B272: Market | C272: Charlottesville, VA | D272: 16820 | E272: Performance | F272: Asking RPSF | G272: Totals | H272: Totals | I272: 1.87
A273: Chattanooga, TN-GA | B273: Market | C273: Chattanooga, TN-GA | D273: 16860 | E273: Transaction Data - Operational | F273: Rent Roll (Rev/OSF) | G273: Totals | H273: Totals | I273: 1.3655339
A274: Chattanooga, TN-GA | B274: Market | C274: Chattanooga, TN-GA | D274: 16860 | E274: Transaction Data - Financial | F274: NOI % of Revenue | G274: Totals | H274: Totals | I274: 0.51870588
A275: Chattanooga, TN-GA | B275: Market | C275: Chattanooga, TN-GA | D275: 16860 | E275: Performance | F275: Effective RPSF | G275: Totals | H275: Totals | I275: 1.394
A276: Chattanooga, TN-GA | B276: Market | C276: Chattanooga, TN-GA | D276: 16860 | E276: Performance | F276: Asking RPSF | G276: Totals | H276: Totals | I276: 1.423
... A285: Chico, CA | B285: Market | C285: Chico, CA | D285: 17020 | E285: Performance | F285: Asking RPSF | G285: Totals | H285: Totals | I285: 1.757
A286: Chillicothe, OH | B286: Market | C286: Chillicothe, OH | D286: 17060 | E286: Performance | F286: Effective RPSF | G286: Totals | H286: Totals
A287: Chillicothe, OH | B287: Market | C287: Chillicothe, OH | D287: 17060 | E287: Performance | F287: Asking RPSF | G287: Totals | H287: Totals
A288: Cincinnati, OH-KY-IN | B288: Market | C288: Cincinnati, OH-KY-IN | D288: 17140 | E288: Transaction Data - Operational | F288: Rent Roll (Rev/OSF) | G288: Totals | H288: Totals | I288: 1.586321
A289: Cincinnati, OH-KY-IN | B289: Market | C289: Cincinnati, OH-KY-IN | D289: 17140 | E289: Transaction Data - Financial | F289: NOI % of Revenue | G289: Totals | H289: Totals | I289: 0.53552099
A290: Cincinnati, OH-KY-IN | B290: Market | C290: Cincinnati, OH-KY-IN | D290: 17140 | E290: Performance | F290: Effective RPSF | G290: Totals | H290: Totals | I290: 1.599
A291: Cincinnati, OH-KY-IN | B291: Market | C291: Cincinnati, OH-KY-IN | D291: 17140 | E291: Performance | F291: Asking RPSF | G291: Totals | H291: Totals | I291: 1.608
A292: Clarksville, TN-KY | B292: Market | C292: Clarksville, TN-KY | D292: 17300 | E292: Transaction Data - Operational | F292: Rent Roll (Rev/OSF) | G292: Totals | H292: Totals | I292: 1.1709026
A293: Clarksville, TN-KY | B293: Market | C293: Clarksville, TN-KY | D293: 17300 | E293: Transaction Data - Financial | F293: NOI % of Revenue | G293: Totals | H293: Totals | I293: 0.5037665
A294: Clarksville, TN-KY | B294: Market | C294: Clarksville, TN-KY | D294: 17300 | E294: Performance | F294: Effective RPSF | G294: Totals | H294: Totals | I294: 1.185
A295: Clarksville, TN-KY | B295: Market | C295: Clarksville, TN-KY | D295: 17300 | E295: Performance | F295: Asking RPSF | G295: Totals | H295: Totals | I295: 1.2
...

Sheet RP - Unit Starts
A1: Geography Name | B1: Geography Type | C1: Market Name | D1: Unique ID | E1: Metric Type | F1: Metric Name | G1: Category | H1: Niche | I1: Y2025Q3 | J1: Y2025Q4 | K1: Y2026Q1 | L1: Y2026Q2
A2: Albuquerque, NM | B2: Market | C2: Albuquerque, NM | D2: 10740 | E2: Performance | F2: Existing Units | G2: Totals | H2: Totals | I2: 58433 | J2: 58748 | K2: 58897 | L2: 59079
A3: Albuquerque, NM | B3: Market | C3: Albuquerque, NM | D3: 10740 | E3: Supply & Demand | F3: Unit Starts | G3: Totals | H3: Totals | I3: 37 | J3: 0 | K3: 110 | L3: 128
A4: Atlanta-Sandy Springs-Roswell, GA | B4: Market | C4: Atlanta-Sandy Springs-Roswell, GA | D4: 12060 | E4: Performance | F4: Existing Units | G4: Totals | H4: Totals | I4: 591864 | J4: 595053 | K4: 597135 | L4: 599838
A5: Atlanta-Sandy Springs-Roswell, GA | B5: Market | C5: Atlanta-Sandy Springs-Roswell, GA | D5: 12060 | E5: Supply & Demand | F5: Unit Starts | G5: Totals | H5: Totals | I5: 2750 | J5: 3860 | K5: 1215 | L5: 809
A6: Austin-Round Rock-San Marcos, TX | B6: Market | C6: Austin-Round Rock-San Marcos, TX | D6: 12420 | E6: Performance | F6: Existing Units | G6: Totals | H6: Totals | I6: 344832 | J6: 348323 | K6: 350661 | L6: 353454
A7: Austin-Round Rock-San Marcos, TX | B7: Market | C7: Austin-Round Rock-San Marcos, TX | D7: 12420 | E7: Supply & Demand | F7: Unit Starts | G7: Totals | H7: Totals | I7: 1680 | J7: 2154 | K7: 1118 | L7: 588
A8: Birmingham, AL | B8: Market | C8: Birmingham, AL | D8: 13820 | E8: Performance | F8: Existing Units | G8: Totals | H8: Totals | I8: 81503 | J8: 82044 | K8: 82358 | L8: 82502
A9: Birmingham, AL | B9: Market | C9: Birmingham, AL | D9: 13820 | E9: Supply & Demand | F9: Unit Starts | G9: Totals | H9: Totals | I9: 0 | J9: 0 | K9: 135 | L9: 0
A10: Boise City, ID | B10: Market | C10: Boise City, ID | D10: 14260 | E10: Performance | F10: Existing Units | G10: Totals | H10: Totals | I10: 39551 | J10: 39780 | K10: 40002 | L10: 40146
A11: Boise City, ID | B11: Market | C11: Boise City, ID | D11: 14260 | E11: Supply & Demand | F11: Unit Starts | G11: Totals | H11: Totals | I11: 481 | J11: 0 | K11: 0 | L11: 0
A12: Cape Coral-Fort Myers, FL | B12: Market | C12: Cape Coral-Fort Myers, FL | D12: 15980 | E12: Performance | F12: Existing Units | G12: Totals | H12: Totals | I12: 60520 | J12: 61298 | K12: 62515 | L12: 63421
A13: Cape Coral-Fort Myers, FL | B13: Market | C13: Cape Coral-Fort Myers, FL | D13: 15980 | E13: Supply & Demand | F13: Unit Starts | G13: Totals | H13: Totals | I13: 296 | J13: 430 | K13: 0 | L13: 350
... A101: Wilmington, NC | B101: Market | C101: Wilmington, NC | D101: 48900 | E101: Supply & Demand | F101: Unit Starts | G101: Totals | H101: Totals | I101: 527 | J101: 0 | K101: 253 | L101: 0

Sheet Realpage - His. Rent Change
A1: Geography Name | B1: Geography Type | C1: Market Name | D1: Unique ID | E1: Metric Type | F1: Metric Name | G1: Category | H1: Niche | I1: Y2016Q1 | J1: Y2016Q2 | K1: Y2016Q3 | L1: Y2016Q4 | M1: Y2017Q1 | N1: Y2017Q2 | O1: Y2017Q3 | P1: Y2017Q4 | Q1: Y2018Q1 | R1: Y2018Q2 | S1: Y2018Q3 | T1: Y2018Q4 | U1: Y2019Q1 | V1: Y2019Q2 | W1: Y2019Q3 | X1: Y2019Q4 | Y1: Y2020Q1 | Z1: Y2020Q2 | AA1: Y2020Q3 | AB1: Y2020Q4 | AC1: Y2021Q1 | AD1: Y2021Q2 | AE1: Y2021Q3 | AF1: Y2021Q4 | AG1: Y2022Q1 | AH1: Y2022Q2 | AI1: Y2022Q3 | AJ1: Y2022Q4 | AK1: Y2023Q1 | AL1: Y2023Q2 | AM1: Y2023Q3 | AN1: Y2023Q4 | AO1: Y2024Q1 | AP1: Y2024Q2 | AQ1: Y2024Q3 | AR1: Y2024Q4 | AS1: Y2025Q1 | AT1: Y2025Q2 | AU1: Y2025Q3 | AV1: Y2025Q4
A2: Abilene, TX | B2: Market | C2: Abilene, TX | D2: 10180 | E2: Performance | F2: YOY Effective Rent Change | G2: Totals | H2: Totals | I2: 0.0073 | J2: 0.0061 | K2: 0.0801 | L2: 0.065 | M2: 0.0877 | N2: 0.1047 | O2: 0.0377 | P2: 0.0457 | Q2: 0.0409 | R2: 0.0396 | S2: 0.0375 | T2: 0.0413 | U2: 0.0503 | V2: 0.0538 | W2: 0.0411 | X2: 0.041 | Y2: 0.0269 | Z2: 0.0027 | AA2: 0.0044 | AB2: 0.0211 | AC2: 0.0169 | AD2: 0.0328 | AE2: 0.0626 | AF2: 0.0688 | AG2: 0.0811 | AH2: 0.0935 | AI2: 0.0662 | AJ2: 0.0638 | AK2: 0.0677 | AL2: 0.0625 | AM2: 0.0519 | AN2: 0.0537 | AO2: 0.0376 | AP2: 0.0429 | AQ2: 0.0383 | AR2: 0.0474 | AS2: 0.0657 | AT2: 0.0827 | AU2: 0.1297 | AV2: 0.1869
A3: Akron, OH | B3: Market | C3: Akron, OH | D3: 10420 | E3: Performance | F3: YOY Effective Rent Change | G3: Totals | H3: Totals | I3: 0.0271 | J3: 0.0232 | K3: 0.0279 | L3: 0.0192 | M3: 0.0148 | N3: 0.0068 | O3: 0.0172 | P3: 0.0205 | Q3: 0.0156 | R3: 0.0318 | S3: 0.0277 | T3: 0.03 | U3: 0.0339 | V3: 0.0142 | W3: 0.0215 | X3: 0.0253 | Y3: 0.0392 | Z3: 0.0452 | AA3: 0.0338 | AB3: 0.0438 | AC3: 0.0331 | AD3: 0.0632 | AE3: 0.1079 | AF3: 0.0892 | AG3: 0.1053 | AH3: 0.1152 | AI3: 0.103 | AJ3: 0.1115 | AK3: 0.1004 | AL3: 0.0724 | AM3: 0.0494 | AN3: 0.0466 | AO3: 0.0488 | AP3: 0.0492 | AQ3: 0.0583 | AR3: 0.0519 | AS3: 0.0571 | AT3: 0.0741 | AU3: 0.0806 | AV3: 0.0841
A4: Alamogordo, NM | B4: Market | C4: Alamogordo, NM | D4: 10460 | E4: Performance | F4: YOY Effective Rent Change | G4: Totals | H4: Totals | N4: 0.028 | W4: 0.2314 | X4: 0.2133 | Y4: 0.1963 | Z4: 0.1757 | AA4: -0.0082 | AB4: -0.0011 | AC4: 0.0197 | AD4: 0.0394 | AE4: 0.0546 | AF4: 0.1411 | AG4: 0.1412 | AH4: 0.1447 | AI4: 0.1358 | AJ4: 0.0572 | AK4: 0.0701 | AL4: 0.0236
A5: Albany, GA | B5: Market | C5: Albany, GA | D5: 10500 | E5: Performance | F5: YOY Effective Rent Change | G5: Totals | H5: Totals | I5: 0.0796 | J5: 0.1222 | K5: 0.0445 | L5: 0.0764 | M5: 0.0726 | N5: 0.0353 | O5: 0.0709 | P5: 0.0519 | Q5: 0.0814 | R5: 0.0856 | S5: 0.048 | T5: 0.0284 | U5: 0.0089 | V5: 0.0131 | W5: 0.0336 | X5: 0.0543 | Y5: 0.0823 | Z5: 0.0797 | AA5: 0.0778 | AB5: 0.0821 | AC5: 0.0502 | AD5: 0.0576 | AE5: 0.0538 | AF5: 0.123 | AG5: 0.1603 | AH5: 0.2311 | AI5: 0.2432 | AJ5: 0.1327 | AK5: 0.099 | AL5: 0.02 | AM5: 0.0574 | AN5: 0.081 | AO5: 0.0809 | AP5: 0.0827 | AQ5: 0.0256 | AR5: -0.0096 | AS5: -0.0443 | AT5: 0.0024 | AU5: -0.1087 | AV5: -0.0573
A6: Albany, OR | B6: Market | C6: Albany, OR | D6: 10540 | E6: Performance | F6: YOY Effective Rent Change | G6: Totals | H6: Totals | I6: 0.0362 | J6: 0.0211 | K6: 0.054 | L6: 0.104 | M6: 0.089 | N6: 0.1398 | O6: 0.1514 | P6: 0.1381 | Q6: 0.1202 | R6: 0.071 | S6: 0.0322 | T6: 0.0443 | U6: 0.0521 | V6: 0.0582 | W6: 0.0722 | X6: 0.0068 | Y6: -0.0158 | Z6: -0.0289 | AA6: -0.018 | AB6: 0.0278 | AC6: 0.0567 | AD6: 0.08 | AE6: 0.0798 | AF6: 0.1422 | AG6: 0.1671 | AH6: 0.1676 | AI6: 0.1663 | AJ6: 0.1145 | AK6: 0.0892 | AL6: 0.0672 | AM6: 0.0106 | AN6: 0.0054 | AO6: -0.0026 | AP6: 0.0033 | AQ6: 0.0677 | AR6: 0.0508 | AS6: 0.0483 | AT6: -0.0335 | AU6: -0.1011 | AV6: -0.1371
A7: Albany-Schenectady-Troy, NY | B7: Market | C7: Albany-Schenectady-Troy, NY | D7: 10580 | E7: Performance | F7: YOY Effective Rent Change | G7: Totals | H7: Totals | I7: 0.041 | J7: 0.0335 | K7: 0.0355 | L7: 0.0383 | M7: 0.0336 | N7: 0.0435 | O7: 0.0297 | P7: 0.0262 | Q7: 0.0327 | R7: 0.0231 | S7: 0.0338 | T7: 0.0395 | U7: 0.0294 | V7: 0.0341 | W7: 0.0202 | X7: 0.0109 | Y7: 0.0215 | Z7: 0.0142 | AA7: 0.0184 | AB7: 0.0313 | AC7: 0.0318 | AD7: 0.0406 | AE7: 0.0563 | AF7: 0.0603 | AG7: 0.0741 | AH7: 0.0978 | AI7: 0.1297 | AJ7: 0.109 | AK7: 0.091 | AL7: 0.0939 | AM7: 0.0636 | AN7: 0.0618 | AO7: 0.0637 | AP7: 0.0339 | AQ7: 0.0164 | AR7: 0.0299 | AS7: 0.0323 | AT7: 0.0548 | AU7: 0.0733 | AV7: 0.062
A8: Albert Lea, MN | B8: Market | C8: Albert Lea, MN | D8: 10660 | E8: Performance | F8: YOY Effective Rent Change | G8: Totals | H8: Totals
A9: Albuquerque, NM | B9: Market | C9: Albuquerque, NM | D9: 10740 | E9: Performance | F9: YOY Effective Rent Change | G9: Totals | H9: Totals | I9: 0.0231 | J9: 0.0254 | K9: 0.0244 | L9: 0.0334 | M9: 0.0315 | N9: 0.0393 | O9: 0.0395 | P9: 0.0242 | Q9: 0.0312 | R9: 0.0248 | S9: 0.038 | T9: 0.0505 | U9: 0.0584 | V9: 0.061 | W9: 0.0757 | X9: 0.0676 | Y9: 0.0536 | Z9: 0.0457 | AA9: 0.0491 | AB9: 0.0794 | AC9: 0.0903 | AD9: 0.1436 | AE9: 0.2059 | AF9: 0.2064 | AG9: 0.1955 | AH9: 0.1698 | AI9: 0.1318 | AJ9: 0.0999 | AK9: 0.0882 | AL9: 0.0658 | AM9: 0.0207 | AN9: 0.0149 | AO9: 0.0246 | AP9: 0.0124 | AQ9: 0.0099 | AR9: 0.015 | AS9: 0.0132 | AT9: 0.0201 | AU9: 0.0246 | AV9: 0.009
A10: Alexandria, LA | B10: Market | C10: Alexandria, LA | D10: 10780 | E10: Performance | F10: YOY Effective Rent Change | G10: Totals | H10: Totals | I10: 0.0636 | J10: -0.0479 | K10: -0.0691 | L10: 0.0486 | M10: 0.0021 | N10: 0.0271 | O10: 0.0424 | P10: -0.0372 | Q10: 0.0448 | R10: 0.0343 | S10: -0.0105 | T10: 0.0082 | U10: -0.0043 | V10: 0.0031 | W10: 0.0448 | X10: 0.0336 | Y10: 0.0639 | Z10: 0.0401 | AA10: 0.0133 | AB10: 0.0477 | AC10: 0.0225 | AD10: 0.024 | AE10: 0.0646 | AF10: 0.0488 | AG10: 0.0586 | AH10: 0.1108 | AI10: 0.0747 | AJ10: 0.078 | AK10: 0.0328 | AL10: -0.0143 | AM10: 0.0067 | AN10: 0.0036 | AO10: 0.0185 | AP10: 0.0215 | AQ10: 0.0229 | AR10: 0.0317 | AS10: 0.051 | AT10: 0.1444 | AU10: 0.1573 | AV10: 0.0973
A11: Alexandria, MN | B11: Market | C11: Alexandria, MN | D11: 10820 | E11: Performance | F11: YOY Effective Rent Change | G11: Totals | H11: Totals | AF11: -0.0029 | AG11: -0.0123 | AH11: -0.0156 | AI11: 0.0074 | AS11: 0.1218 | AT11: 0.1341 | AU11: 0.1112 | AV11: 0.0686
A12: Allentown-Bethlehem-Easton, PA-NJ | B12: Market | C12: Allentown-Bethlehem-Easton, PA-NJ | D12: 10900 | E12: Performance | F12: YOY Effective Rent Change | G12: Totals | H12: Totals | I12: 0.0559 | J12: 0.0439 | K12: 0.0286 | L12: 0.0193 | M12: 0.016 | N12: 0.0292 | O12: 0.0398 | P12: 0.0483 | Q12: 0.0501 | R12: 0.0364 | S12: 0.0605 | T12: 0.0604 | U12: 0.0603 | V12: 0.054 | W12: 0.0245 | X12: 0.0258 | Y12: 0.0293 | Z12: 0.0149 | AA12: 0.0349 | AB12: 0.0512 | AC12: 0.0535 | AD12: 0.0744 | AE12: 0.1123 | AF12: 0.146 | AG12: 0.1526 | AH12: 0.1587 | AI12: 0.1282 | AJ12: 0.0875 | AK12: 0.0607 | AL12: 0.0479 | AM12: 0.0352 | AN12: 0.0358 | AO12: 0.0325 | AP12: 0.0242 | AQ12: 0.0311 | AR12: 0.0331 | AS12: 0.0437 | AT12: 0.0641 | AU12: 0.0456 | AV12: 0.0355
A13: Alma, MI | B13: Market | C13: Alma, MI | D13: 10940 | E13: Performance | F13: YOY Effective Rent Change | G13: Totals | H13: Totals
A14: Altoona, PA | B14: Market | C14: Altoona, PA | D14: 11020 | E14: Performance | F14: YOY Effective Rent Change | G14: Totals | H14: Totals
A15: Altus, OK | B15: Market | C15: Altus, OK | D15: 11060 | E15: Performance | F15: YOY Effective Rent Change | G15: Totals | H15: Totals
A16: Amarillo, TX | B16: Market | C16: Amarillo, TX | D16: 11100 | E16: Performance | F16: YOY Effective Rent Change | G16: Totals | H16: Totals | I16: 0.0301 | J16: 0.0177 | K16: 0.0232 | L16: 0.0031 | M16: 0.0103 | N16: 0.0264 | O16: 0.0071 | P16: -0.0004 | Q16: -0.0003 | R16: 0.0049 | S16: 0.0175 | T16: 0.031 | U16: -0.0002 | V16: 0.0022 | W16: -0.0042 | X16: 0.0104 | Y16: 0.0316 | Z16: 0.028 | AA16: 0.03 | AB16: 0.0295 | AC16: 0.0407 | AD16: 0.0712 | AE16: 0.0943 | AF16: 0.1073 | AG16: 0.1291 | AH16: 0.131 | AI16: 0.1454 | AJ16: 0.1226 | AK16: 0.098 | AL16: 0.0552 | AM16: 0.0173 | AN16: 0.0128 | AO16: 0.0062 | AP16: 0.0136 | AQ16: 0.0163 | AR16: 0.0016 | AS16: 0.0131 | AT16: 0.0126 | AU16: 0.0368 | AV16: 0.0682
A17: Ames, IA | B17: Market | C17: Ames, IA | D17: 11180 | E17: Performance | F17: YOY Effective Rent Change | G17: Totals | H17: Totals | I17: -0.0121 | J17: -0.0177 | K17: 0.0294 | L17: 0.0218 | M17: 0.112 | N17: 0.0916 | O17: 0.0731 | P17: 0.0945 | Q17: -0.0226 | R17: 0.0047 | S17: -0.0894 | T17: -0.0957 | U17: -0.0768 | V17: -0.0847 | W17: -0.0414 | X17: -0.0702 | Y17: -0.0796 | Z17: -0.0482 | AA17: 0.029 | AB17: 0.0478 | AC17: 0.1147 | AD17: 0.0611 | AE17: -0.0159 | AF17: 0.0038 | AG17: -0.0513 | AH17: 0.0866 | AI17: 0.1819 | AJ17: 0.2012 | AK17: 0.2223 | AL17: 0.0935 | AM17: 0.0573 | AN17: 0.022 | AO17: -0.0059 | AP17: -0.0154 | AQ17: 0.0091 | AR17: 0.0409 | AS17: 0.0562 | AT17: 0.0806 | AU17: 0.0724 | AV17: 0.02
A18: Anaheim-Santa Ana-Irvine, CA | B18: Market | C18: Anaheim-Santa Ana-Irvine, CA | D18: 11244 | E18: Performance | F18: YOY Effective Rent Change | G18: Totals | H18: Totals | I18: 0.0572 | J18: 0.0597 | K18: 0.0544 | L18: 0.0527 | M18: 0.0397 | N18: 0.0391 | O18: 0.0378 | P18: 0.0308 | Q18: 0.0367 | R18: 0.0273 | S18: 0.0319 | T18: 0.0319 | U18: 0.0256 | V18: 0.0376 | W18: 0.0347 | X18: 0.0325 | Y18: 0.0377 | Z18: -0.0041 | AA18: -0.0157 | AB18: -0.0026 | AC18: 0.0114 | AD18: 0.0634 | AE18: 0.1349 | AF18: 0.174 | AG18: 0.1894 | AH18: 0.1918 | AI18: 0.1474 | AJ18: 0.0865 | AK18: 0.0492 | AL18: 0.025 | AM18: 0.021 | AN18: 0.0317 | AO18: 0.0297 | AP18: 0.0234 | AQ18: 0.0155 | AR18: 0.0083 | AS18: 0.0154 | AT18: 0.03 | AU18: 0.0296 | AV18: 0.0236
A19: Anchorage, AK | B19: Market | C19: Anchorage, AK | D19: 11260 | E19: Performance | F19: YOY Effective Rent Change | G19: Totals | H19: Totals | P19: -0.0018 | Q19: 0.0154 | R19: 0.0453 | S19: 0.0181 | T19: 0.0057 | U19: -0.0044 | V19: -0.0229 | W19: 0.0012 | X19: -0.01 | Y19: 0.0383 | Z19: 0.0415 | AA19: 0.073 | AB19: 0.1047 | AC19: 0.069 | AD19: 0.0972 | AE19: 0.0921 | AF19: 0.0956 | AG19: 0.1329 | AH19: 0.1306 | AI19: 0.1359 | AJ19: 0.1367 | AK19: 0.1073 | AL19: 0.1141 | AM19: 0.1599 | AN19: 0.0944 | AO19: 0.0709 | AP19: 0.0613 | AQ19: -0.006 | AR19: 0.0241 | AS19: 0.0395 | AT19: 0.042 | AU19: 0.0271 | AV19: 0.0231
A20: Andrews, TX | B20: Market | C20: Andrews, TX | D20: 11380 | E20: Performance | F20: YOY Effective Rent Change | G20: Totals | H20: Totals
A21: Angola, IN | B21: Market | C21: Angola, IN | D21: 11420 | E21: Performance | F21: YOY Effective Rent Change | G21: Totals | H21: Totals
A22: Ann Arbor, MI | B22: Market | C22: Ann Arbor, MI | D22: 11460 | E22: Performance | F22: YOY Effective Rent Change | G22: Totals | H22: Totals | I22: 0.0497 | J22: 0.0573 | K22: 0.0333 | L22: 0.0427 | M22: 0.034 | N22: 0.0233 | O22: 0.0625 | P22: 0.032 | Q22: 0.0292 | R22: 0.0427 | S22: 0.0363 | T22: 0.0504 | U22: 0.0552 | V22: 0.0418 | W22: 0.0442 | X22: 0.0458 | Y22: 0.0393 | Z22: 0.0361 | AA22: 0.0078 | AB22: 0.0103 | AC22: 0.004 | AD22: 0.0422 | AE22: 0.1073 | AF22: 0.1452 | AG22: 0.1601 | AH22: 0.1636 | AI22: 0.1339 | AJ22: 0.0884 | AK22: 0.0726 | AL22: 0.0402 | AM22: 0.0223 | AN22: 0.0233 | AO22: 0.0375 | AP22: 0.0421 | AQ22: 0.0395 | AR22: 0.0382 | AS22: 0.021 | AT22: 0.0545 | AU22: 0.0158 | AV22: -0.0388
A23: Anniston-Oxford, AL | B23: Market | C23: Anniston-Oxford, AL | D23: 11500 | E23: Performance | F23: YOY Effective Rent Change | G23: Totals | H23: Totals | K23: -0.0674 | L23: -0.0482 | M23: -0.0577 | N23: -0.0644 | O23: 0.0327 | P23: 0.0379 | Q23: 0.0186 | R23: 0.031 | S23: 0.0486 | T23: 0.0146 | U23: 0.061 | V23: 0.0574 | W23: 0.0569 | X23: 0.0822 | Y23: 0.0626 | Z23: 0.0415 | AA23: 0.0379 | AB23: 0.0363 | AC23: 0.0343 | AD23: 0.0339 | AE23: 0.0572 | AF23: 0.0812 | AG23: 0.101 | AH23: 0.1241 | AI23: 0.1157 | AJ23: 0.1451 | AK23: 0.1654 | AL23: 0.1461 | AM23: 0.1073 | AN23: 0.029 | AO23: -0.0243 | AP23: -0.0401 | AQ23: -0.0097 | AR23: 0.0156 | AS23: 0.0298 | AT23: 0.1139
A24: Appleton, WI | B24: Market | C24: Appleton, WI | D24: 11540 | E24: Performance | F24: YOY Effective Rent Change | G24: Totals | H24: Totals | I24: 0.1246 | J24: 0.1363 | K24: 0.1147 | L24: 0.0739 | M24: 0.0682 | N24: 0.0702 | O24: 0.0612 | P24: 0.0003 | Q24: 0.0089 | R24: 0.012 | S24: 0.0235 | T24: 0.0275 | U24: 0.0336 | V24: 0.0403 | W24: 0.0419 | X24: 0.045 | Y24: 0.056 | Z24: 0.0816 | AA24: 0.0885 | AB24: 0.0592 | AC24: 0.0431 | AD24: 0.028 | AE24: 0.0572 | AF24: 0.1311 | AG24: 0.1421 | AH24: 0.1813 | AI24: 0.2013 | AJ24: 0.1146 | AK24: 0.1194 | AL24: 0.0749 | AM24: 0.1271 | AN24: 0.1572 | AO24: 0.1521 | AP24: 0.1696 | AQ24: 0.0546 | AR24: 0.1071 | AS24: 0.1017 | AT24: 0.1018 | AU24: 0.1366 | AV24: 0.0762
A25: Ardmore, OK | B25: Market | C25: Ardmore, OK | D25: 11620 | E25: Performance | F25: YOY Effective Rent Change | G25: Totals | H25: Totals
A26: Arkansas City-Winfield, KS | B26: Market | C26: Arkansas City-Winfield, KS | D26: 11680 | E26: Performance | F26: YOY Effective Rent Change | G26: Totals | H26: Totals
A27: Asheville/Waynesville, NC | B27: Market | C27: Asheville/Waynesville, NC | D27: 211700 | E27: Performance | F27: YOY Effective Rent Change | G27: Totals | H27: Totals | I27: 0.0659 | J27: 0.0307 | K27: 0.0408 | L27: 0.059 | M27: 0.0411 | N27: 0.0346 | O27: 0.0269 | P27: 0.0246 | Q27: 0.045 | R27: 0.0482 | S27: 0.0582 | T27: 0.0509 | U27: 0.0554 | V27: 0.0512 | W27: 0.0244 | X27: 0.0142 | Y27: 0.0115 | Z27: -0.0141 | AA27: -0.0017 | AB27: 0.0393 | AC27: 0.0463 | AD27: 0.1059 | AE27: 0.1835 | AF27: 0.221 | AG27: 0.2073 | AH27: 0.197 | AI27: 0.1548 | AJ27: 0.0939 | AK27: 0.1012 | AL27: 0.06 | AM27: 0.015 | AN27: 0.0017 | AO27: -0.0143 | AP27: 0.0037 | AQ27: 0.0064 | AR27: 0.0039 | AS27: -0.0242 | AT27: -0.0444 | AU27: -0.0685 | AV27: -0.0623
A28: Ashland, OH | B28: Market | C28: Ashland, OH | D28: 11740 | E28: Performance | F28: YOY Effective Rent Change | G28: Totals | H28: Totals | M28: 0.2309 | N28: 0.2057 | O28: 0.1721 | P28: 0.1918 | Q28: 0.0324 | R28: 0.07 | S28: 0.0478 | T28: 0.0619 | U28: 0.0473 | V28: 0.015 | W28: 0.0398 | X28: 0.0207 | Y28: 0.0324 | Z28: 0.0342 | AA28: 0.0354 | AB28: 0.0758 | AC28: 0.0607 | AD28: 0.0568 | AE28: 0.0477 | AF28: 0.0187 | AG28: 0.0962 | AH28: 0.0758 | AI28: 0.3532 | AJ28: 0.4112 | AK28: 0.3854 | AL28: 0.4224 | AM28: 0.1845 | AN28: 0.1304 | AO28: 0.0657 | AP28: 0.075 | AQ28: 0.0386 | AR28: 0.0512 | AS28: 0.0559 | AT28: 0.0267 | AU28: 0.0402 | AV28: 0.0153
A29: Astoria, OR | B29: Market | C29: Astoria, OR | D29: 11820 | E29: Performance | F29: YOY Effective Rent Change | G29: Totals | H29: Totals
A30: Athens-Clarke County, GA | B30: Market | C30: Athens-Clarke County, GA | D30: 12020 | E30: Performance | F30: YOY Effective Rent Change | G30: Totals | H30: Totals | I30: 0.0548 | J30: 0.0435 | K30: 0.0835 | L30: 0.1128 | M30: 0.1063 | N30: 0.1336 | O30: 0.123 | P30: 0.1083 | Q30: 0.0696 | R30: 0.0417 | S30: 0.034 | T30: 0.0399 | U30: 0.0707 | V30: 0.0566 | W30: 0.0524 | X30: 0.059 | Y30: 0.0671 | Z30: 0.0519 | AA30: 0.0552 | AB30: 0.0545 | AC30: 0.061 | AD30: 0.1096 | AE30: 0.176 | AF30: 0.1578 | AG30: 0.1279 | AH30: 0.1277 | AI30: 0.0911 | AJ30: 0.0512 | AK30: 0.0539 | AL30: 0.091 | AM30: 0.061 | AN30: 0.0884 | AO30: 0.0868 | AP30: 0.026 | AQ30: -0.0204 | AR30: -0.0456 | AS30: -0.0381 | AT30: -0.0365 | AU30: -0.0379 | AV30: -0.0375
A31: Athens, OH | B31: Market | C31: Athens, OH | D31: 11900 | E31: Performance | F31: YOY Effective Rent Change | G31: Totals | H31: Totals | I31: 0.0091 | J31: -0.0156 | K31: -0.0521 | L31: -0.1365 | M31: -0.0674 | N31: -0.0332 | O31: -0.0073 | P31: 0.1152 | Q31: 0.032 | R31: 0.0327 | S31: 0.0367 | T31: 0.018 | U31: 0.0429 | V31: 0.0244 | W31: 0.0326 | X31: 0.0584 | Y31: 0.0235 | Z31: -0.0052 | AA31: -0.0282 | AB31: -0.0199 | AC31: 0.0047 | AD31: 0.0131 | AE31: 0.0915 | AF31: 0.0642 | AG31: 0.053 | AO31: 0.1351 | AP31: 0.1861 | AQ31: 0.1262 | AR31: 0.1873 | AS31: 0.0435
A32: Athens, TN | B32: Market | C32: Athens, TN | D32: 11940 | E32: Performance | F32: YOY Effective Rent Change | G32: Totals | H32: Totals | AN32: 0.3829 | AO32: 0.256 | AP32: -0.0885 | AQ32: 0.0661 | AR32: 0.0319 | AS32: -0.0104
A33: Athens, TX | B33: Market | C33: Athens, TX | D33: 11980 | E33: Performance | F33: YOY Effective Rent Change | G33: Totals | H33: Totals | AI33: 0.1193 | AJ33: 0.0975 | AK33: 0.1356 | AL33: 0.0977 | AM33: 0.0716 | AN33: 0.0724 | AO33: 0.0661 | AP33: 0.079 | AQ33: 0.0748 | AR33: 0.0499 | AS33: -0.0118 | AT33: -0.0157 | AU33: -0.0233 | AV33: -0.0076
A34: Atlanta-Sandy Springs-Roswell, GA | B34: Market | C34: Atlanta-Sandy Springs-Roswell, GA | D34: 12060 | E34: Performance | F34: YOY Effective Rent Change | G34: Totals | H34: Totals | I34: 0.0721 | J34: 0.0666 | K34: 0.0645 | L34: 0.0627 | M34: 0.0615 | N34: 0.0615 | O34: 0.0524 | P34: 0.0506 | Q34: 0.0609 | R34: 0.0537 | S34: 0.0628 | T34: 0.0698 | U34: 0.069 | V34: 0.0678 | W34: 0.0595 | X34: 0.0488 | Y34: 0.0348 | Z34: 0.0005 | AA34: 0.0039 | AB34: 0.0247 | AC34: 0.046 | AD34: 0.1202 | AE34: 0.1904 | AF34: 0.2267 | AG34: 0.2246 | AH34: 0.1916 | AI34: 0.1232 | AJ34: 0.0575 | AK34: 0.0318 | AL34: 0.0084 | AM34: -0.0272 | AN34: -0.039 | AO34: -0.0389 | AP34: -0.0417 | AQ34: -0.0377 | AR34: -0.0336 | AS34: -0.0252 | AT34: -0.0158 | AU34: -0.0019 | AV34: 0.0051
A35: Atlantic City-Hammonton, NJ | B35: Market | C35: Atlantic City-Hammonton, NJ | D35: 12100 | E35: Performance | F35: YOY Effective Rent Change | G35: Totals | H35: Totals | I35: 0.0688 | J35: -0.0418 | K35: 0.0801 | L35: 0.1279 | M35: 0.0661 | N35: 0.075 | O35: 0.0352 | P35: -0.0115 | Q35: 0.0125 | R35: 0.0784 | S35: 0.0955 | T35: 0.0699 | U35: 0.0611 | V35: 0.0285 | W35: 0.042 | X35: 0.0612 | Y35: 0.0523 | Z35: 0.0212 | AA35: 0.0073 | AB35: 0.0307 | AC35: 0.0789 | AD35: 0.1007 | AE35: 0.151 | AF35: 0.14 | AG35: 0.1123 | AH35: 0.1446 | AI35: 0.1642 | AJ35: 0.1641 | AK35: 0.1618 | AL35: 0.1584 | AM35: 0.0791 | AN35: 0.0791 | AO35: 0.0769 | AP35: 0.032 | AQ35: 0.0533 | AR35: 0.0364 | AS35: 0.0331 | AT35: 0.0498 | AU35: 0.0196 | AV35: 0.0023
A36: Auburn, NY | B36: Market | C36: Auburn, NY | D36: 12180 | E36: Performance | F36: YOY Effective Rent Change | G36: Totals | H36: Totals | I36: 0.0169 | J36: 0.0169 | K36: 0.0393 | L36: 0.0179 | M36: 0.0029 | N36: 0.0029 | O36: 0.0015 | P36: -0.0021 | Q36: 0.0006 | R36: 0.0006 | S36: 0.0005 | T36: 0.0013 | U36: 0.0022 | V36: 0.0022
A37: Auburn-Opelika, AL | B37: Market | C37: Auburn-Opelika, AL | D37: 12220 | E37: Performance | F37: YOY Effective Rent Change | G37: Totals | H37: Totals | I37: 0.0042 | J37: 0.0162 | K37: 0.006 | L37: 0.0015 | M37: 0.0313 | N37: 0.0298 | O37: 0.0592 | P37: 0.0557 | Q37: 0.0406 | R37: 0.0253 | S37: 0.0246 | T37: 0.0017 | U37: 0.0097 | V37: -0.0404 | W37: -0.0036 | X37: -0.0118 | Y37: -0.0067 | Z37: 0.0709 | AA37: 0.0264 | AB37: 0.0518 | AC37: 0.0455 | AD37: 0.0592 | AE37: 0.0696 | AF37: 0.1091 | AG37: 0.1069 | AH37: 0.1436 | AI37: 0.1726 | AJ37: 0.1309 | AK37: 0.1803 | AL37: 0.1339 | AM37: 0.1144 | AN37: 0.1135 | AO37: 0.0627 | AP37: 0.059 | AQ37: 0.057 | AR37: 0.0909 | AS37: 0.0805 | AT37: 0.0842 | AU37: 0.072 | AV37: 0.0297
A38: Augusta-Richmond County, GA-SC | B38: Market | C38: Augusta-Richmond County, GA-SC | D38: 12260 | E38: Performance | F38: YOY Effective Rent Change | G38: Totals | H38: Totals | I38: 0.0352 | J38: 0.0465 | K38: 0.0406 | L38: 0.0315 | M38: 0.0351 | N38: 0.046 | O38: 0.05 | P38: 0.0581 | Q38: 0.0246 | R38: 0.0163 | S38: 0.0245 | T38: 0.0227 | U38: 0.0441 | V38: 0.0624 | W38: 0.0549 | X38: 0.066 | Y38: 0.0806 | Z38: 0.0531 | AA38: 0.0747 | AB38: 0.0876 | AC38: 0.0724 | AD38: 0.1149 | AE38: 0.1303 | AF38: 0.1441 | AG38: 0.1565 | AH38: 0.1488 | AI38: 0.1162 | AJ38: 0.075 | AK38: 0.0366 | AL38: 0.0044 | AM38: 0.0015 | AN38: 0.0021 | AO38: 0.0067 | AP38: 0.0182 | AQ38: 0.0133 | AR38: 0.0259 | AS38: 0.0472 | AT38: 0.0383 | AU38: 0.03 | AV38: 0.0058
A39: Austin, MN | B39: Market | C39: Austin, MN | D39: 12380 | E39: Performance | F39: YOY Effective Rent Change | G39: Totals | H39: Totals
A40: Austin-Round Rock-San Marcos, TX | B40: Market | C40: Austin-Round Rock-San Marcos, TX | D40: 12420 | E40: Performance | F40: YOY Effective Rent Change | G40: Totals | H40: Totals | I40: 0.0767 | J40: 0.0651 | K40: 0.0444 | L40: 0.0381 | M40: 0.0272 | N40: 0.0219 | O40: 0.0268 | P40: 0.0188 | Q40: 0.0114 | R40: 0.0207 | S40: 0.038 | T40: 0.0523 | U40: 0.0583 | V40: 0.0568 | W40: 0.0487 | X40: 0.0419 | Y40: 0.0374 | Z40: -0.0066 | AA40: -0.042 | AB40: -0.0419 | AC40: -0.021 | AD40: 0.0713 | AE40: 0.189 | AF40: 0.2504 | AG40: 0.2487 | AH40: 0.2118 | AI40: 0.1301 | AJ40: 0.055 | AK40: 0.0295 | AL40: -0.0073 | AM40: -0.0384 | AN40: -0.0481 | AO40: -0.0597 | AP40: -0.0694 | AQ40: -0.0773 | AR40: -0.0701 | AS40: -0.0638 | AT40: -0.0647 | AU40: -0.055 | AV40: -0.0552
A41: Bakersfield-Delano, CA | B41: Market | C41: Bakersfield-Delano, CA | D41: 12540 | E41: Performance | F41: YOY Effective Rent Change | G41: Totals | H41: Totals | I41: 0.0195 | J41: 0.0442 | K41: 0.0352 | L41: 0.0544 | M41: 0.0539 | N41: 0.0392 | O41: 0.0454 | P41: 0.0207 | Q41: 0.0341 | R41: 0.0492 | S41: 0.0392 | T41: 0.0462 | U41: 0.0479 | V41: 0.051 | W41: 0.0692 | X41: 0.0754 | Y41: 0.0728 | Z41: 0.0593 | AA41: 0.0562 | AB41: 0.0609 | AC41: 0.0676 | AD41: 0.0983 | AE41: 0.1416 | AF41: 0.1763 | AG41: 0.2018 | AH41: 0.1918 | AI41: 0.1329 | AJ41: 0.0823 | AK41: 0.047 | AL41: 0.0231 | AM41: 0.0175 | AN41: 0.0156 | AO41: 0.0065 | AP41: 0.009 | AQ41: 0.0051 | AR41: 0.0174 | AS41: 0.0223 | AT41: 0.0647 | AU41: 0.0782 | AV41: 0.0605
A42: Baltimore-Columbia-Towson, MD | B42: Market | C42: Baltimore-Columbia-Towson, MD | D42: 12580 | E42: Performance | F42: YOY Effective Rent Change | G42: Totals | H42: Totals | I42: 0.0116 | J42: 0.0118 | K42: -0.0025 | L42: -0.0044 | M42: 0.0083 | N42: 0.0052 | O42: 0.0224 | P42: 0.0278 | Q42: 0.021 | R42: 0.0208 | S42: 0.0234 | T42: 0.0309 | U42: 0.0391 | V42: 0.0403 | W42: 0.0393 | X42: 0.0267 | Y42: 0.0185 | Z42: -0.0023 | AA42: 0.002 | AB42: 0.0263 | AC42: 0.0432 | AD42: 0.0837 | AE42: 0.1211 | AF42: 0.1301 | AG42: 0.1273 | AH42: 0.1115 | AI42: 0.0753 | AJ42: 0.0549 | AK42: 0.0442 | AL42: 0.0314 | AM42: 0.0206 | AN42: 0.0147 | AO42: 0.0127 | AP42: 0.0149 | AQ42: 0.0224 | AR42: 0.0223 | AS42: 0.0306 | AT42: 0.0327 | AU42: 0.0215 | AV42: 0.0165
A43: Bangor, ME | B43: Market | C43: Bangor, ME | D43: 12620 | E43: Performance | F43: YOY Effective Rent Change | G43: Totals | H43: Totals
A44: Baraboo, WI | B44: Market | C44: Baraboo, WI | D44: 12660 | E44: Performance | F44: YOY Effective Rent Change | G44: Totals | H44: Totals | AP44: 0.0429 | AQ44: 0.0369 | AR44: 0.0398 | AS44: 0.0355 | AT44: 0.0378 | AU44: -0.0248 | AV44: -0.0119
A45: Barnstable Town, MA | B45: Market | C45: Barnstable Town, MA | D45: 12700 | E45: Performance | F45: YOY Effective Rent Change | G45: Totals | H45: Totals
A46: Bartlesville, OK | B46: Market | C46: Bartlesville, OK | D46: 12780 | E46: Performance | F46: YOY Effective Rent Change | G46: Totals | H46: Totals | I46: -0.1736 | J46: -0.1511 | K46: -0.0372 | L46: -0.0013 | M46: 0.0075 | N46: -0.017 | O46: -0.0469 | P46: -0.0512 | AC46: 0.2154 | AD46: 0.2263 | AE46: 0.2179 | AF46: 0.2274 | AG46: 0.0755 | AH46: 0.0982 | AI46: 0.1211 | AJ46: 0.1211 | AK46: 0.0318 | AL46: 0.025 | AM46: 0.0049 | AN46: -0.0169 | AO46: 0.0344 | AP46: 0.0393 | AQ46: 0.0365 | AR46: 0.05 | AS46: 0.0432 | AT46: 0.0606 | AU46: 0.1109 | AV46: 0.0494
A47: Batavia, NY | B47: Market | C47: Batavia, NY | D47: 12860 | E47: Performance | F47: YOY Effective Rent Change | G47: Totals | H47: Totals
A48: Baton Rouge, LA | B48: Market | C48: Baton Rouge, LA | D48: 12940 | E48: Performance | F48: YOY Effective Rent Change | G48: Totals | H48: Totals | I48: 0.0046 | J48: 0.0151 | K48: 0.0409 | L48: 0.1201 | M48: 0.1371 | N48: 0.1049 | O48: 0.0595 | P48: -0.0414 | Q48: -0.0649 | R48: -0.0447 | S48: -0.0239 | T48: -0.0079 | U48: 0.0078 | V48: -0.0036 | W48: -0.0177 | X48: 0.0179 | Y48: 0.0123 | Z48: 0.0115 | AA48: 0.0406 | AB48: 0.0403 | AC48: 0.032 | AD48: 0.0535 | AE48: 0.0809 | AF48: 0.1142 | AG48: 0.1149 | AH48: 0.1171 | AI48: 0.115 | AJ48: 0.0632 | AK48: 0.0523 | AL48: 0.0599 | AM48: 0.0196 | AN48: 0.0128 | AO48: 0.012 | AP48: -0.0066 | AQ48: -0.0082 | AR48: -0.0051 | AS48: 0.0048 | AT48: 0.0245 | AU48: 0.0265 | AV48: 0.0136
A49: Bay City, TX | B49: Market | C49: Bay City, TX | D49: 13060 | E49: Performance | F49: YOY Effective Rent Change | G49: Totals | H49: Totals | I49: 0.1636 | J49: 0.2439 | L49: -0.0433 | M49: 0.041 | N49: 0.0187 | O49: 0.1403 | P49: 0.1279 | Q49: -0.0024 | R49: -0.0094 | S49: -0.0463 | T49: -0.0284 | U49: 0.0087 | V49: 0.0003 | W49: -0.001 | X49: -0.0456 | Y49: -0.0786 | Z49: -0.0609 | AA49: -0.0608 | AB49: -0.0086 | AC49: -0.0353 | AD49: -0.0619 | AE49: 0.0715 | AF49: 0.0648 | AG49: 0.125 | AH49: 0.1862 | AI49: 0.1689 | AJ49: 0.0689 | AK49: 0.0408 | AL49: -0.102 | AM49: -0.1671 | AN49: -0.0258 | AO49: -0.0643 | AP49: -0.0429 | AQ49: 0.0183 | AR49: -0.0686 | AS49: -0.05 | AT49: 0.0436 | AU49: -0.084 | AV49: -0.0595
A50: Beaumont-Port Arthur, TX | B50: Market | C50: Beaumont-Port Arthur, TX | D50: 13140 | E50: Performance | F50: YOY Effective Rent Change | G50: Totals | H50: Totals | I50: -0.0186 | J50: 0.0111 | K50: 0.0143 | L50: 0.007 | M50: 0.0072 | N50: 0.0234 | O50: 0.0247 | P50: 0.0549 | Q50: 0.0786 | R50: 0.0794 | S50: 0.0807 | T50: 0.0432 | U50: 0.0191 | V50: 0.0041 | W50: 0.0119 | X50: 0.0603 | Y50: 0.0512 | Z50: 0.0345 | AA50: 0.0168 | AB50: 0.0024 | AC50: 0.0113 | AD50: 0.0313 | AE50: 0.0612 | AF50: 0.0753 | AG50: 0.0866 | AH50: 0.1031 | AI50: 0.0709 | AJ50: 0.024 | AK50: 0.0209 | AL50: 0.0188 | AM50: 0.0446 | AN50: 0.0598 | AO50: 0.0738 | AP50: 0.0527 | AQ50: 0.0259 | AR50: 0.0282 | AS50: 0.0056 | AT50: 0.0271 | AU50: 0.0617 | AV50: 0.0546
A51: Beaver Dam, WI | B51: Market | C51: Beaver Dam, WI | D51: 13180 | E51: Performance | F51: YOY Effective Rent Change | G51: Totals | H51: Totals
A52: Beckley, WV | B52: Market | C52: Beckley, WV | D52: 13220 | E52: Performance | F52: YOY Effective Rent Change | G52: Totals | H52: Totals
A53: Beeville, TX | B53: Market | C53: Beeville, TX | D53: 13300 | E53: Performance | F53: YOY Effective Rent Change | G53: Totals | H53: Totals | J53: -0.0872 | K53: -0.0526 | L53: -0.0943 | M53: -0.0891 | N53: -0.0462 | O53: -0.0954 | P53: -0.0874 | Q53: 0.0228 | R53: 0.0845 | S53: 0.0327 | T53: 0.0539 | U53: 0.0092 | V53: -0.0323 | W53: 0.0034 | X53: 0.0248 | Y53: 0.0122 | Z53: 0.0219 | AA53: -0.004 | AB53: 0.0074 | AC53: -0.0186 | AD53: -0.0124 | AE53: 0.0528 | AF53: 0.0476 | AG53: 0.0744 | AH53: 0.0637 | AI53: 0.0136 | AJ53: 0.0088 | AK53: 0.0124 | AL53: 0.0317 | AM53: 0.0787 | AN53: 0.0873 | AO53: 0.0935 | AP53: 0.0667 | AQ53: 0.0974 | AR53: 0.0587 | AS53: -0.0028 | AT53: 0.0349 | AU53: -0.1232 | AV53: -0.1473
A54: Bellefontaine, OH | B54: Market | C54: Bellefontaine, OH | D54: 13340 | E54: Performance | F54: YOY Effective Rent Change | G54: Totals | H54: Totals | I54: 0.0408 | J54: 0.0337 | K54: 0.0324 | L54: 0.0227 | M54: 0.0154 | N54: 0.0309 | O54: 0.0478 | P54: 0.0471 | Q54: 0.0278 | R54: -0.0745 | S54: -0.0729 | T54: -0.0781 | U54: -0.0695 | V54: 0.0411 | W54: 0.021 | X54: 0.0204 | Y54: 0.0019 | Z54: -0.0089 | AA54: 0.0049 | AB54: 0.021 | AC54: 0.0441 | AD54: 0.0399 | AE54: 0.0364 | AF54: 0.0355 | AG54: 0.128 | AH54: 0.1567 | AI54: 0.1574 | AJ54: 0.1434 | AK54: 0.0469 | AL54: 0.0621 | AM54: 0.1002 | AN54: 0.1001 | AO54: 0.1004 | AP54: 0.0605 | AQ54: 0.0439 | AR54: 0.0558 | AS54: 0.0763 | AT54: 0.0959 | AU54: 0.0903 | AV54: 0.0823
A55: Bellingham, WA | B55: Market | C55: Bellingham, WA | D55: 13380 | E55: Performance | F55: YOY Effective Rent Change | G55: Totals | H55: Totals | I55: 0.0653 | J55: 0.0793 | K55: 0.0384 | L55: 0.0873 | M55: 0.1248 | N55: 0.1001 | O55: 0.1147 | P55: 0.0881 | Q55: 0.0437 | R55: 0.0269 | S55: 0.038 | T55: 0.0503 | U55: 0.067 | V55: 0.088 | W55: 0.0652 | X55: 0.0593 | Y55: 0.0595 | Z55: 0.0285 | AA55: 0.0329 | AB55: 0.0602 | AC55: 0.0619 | AD55: 0.0672 | AE55: 0.1084 | AF55: 0.1135 | AG55: 0.1481 | AH55: 0.1609 | AI55: 0.1478 | AJ55: 0.1459 | AK55: 0.0956 | AL55: 0.0934 | AM55: 0.0582 | AN55: 0.0187 | AO55: 0.0531 | AP55: 0.0439 | AQ55: 0.0391 | AR55: 0.0504 | AS55: 0.0248 | AT55: 0.0466 | AU55: 0.0535 | AV55: 0.0353
A56: Bend, OR | B56: Market | C56: Bend, OR | D56: 13460 | E56: Performance | F56: YOY Effective Rent Change | G56: Totals | H56: Totals | O56: 0.0163 | P56: 0.0273 | Q56: 0.0547 | R56: 0.018 | S56: 0.0532 | T56: 0.0787 | U56: 0.0973 | V56: 0.1098 | W56: 0.1035 | X56: 0.0857 | Y56: 0.0601 | Z56: 0.0442 | AA56: 0.0627 | AB56: 0.0871 | AC56: 0.1107 | AD56: 0.2303 | AE56: 0.2349 | AF56: 0.1236 | AG56: 0.1219 | AH56: 0.0091 | AI56: -0.0227 | AJ56: 0.0486 | AK56: -0.0034 | AL56: 0.0107 | AM56: 0.023 | AN56: 0.0045 | AO56: 0.0284 | AP56: 0.0051 | AQ56: -0.0224 | AR56: -0.0206 | AS56: -0.0097 | AT56: 0.045 | AU56: 0.0317 | AV56: 0.0281
A57: Big Rapids, MI | B57: Market | C57: Big Rapids, MI | D57: 13660 | E57: Performance | F57: YOY Effective Rent Change | G57: Totals | H57: Totals
A58: Big Spring, TX | B58: Market | C58: Big Spring, TX | D58: 13700 | E58: Performance | F58: YOY Effective Rent Change | G58: Totals | H58: Totals | J58: -0.0972 | L58: -0.0924 | M58: 0.0126 | N58: 0.0358 | P58: 0.1521 | Q58: 0.1527 | R58: 0.2341 | S58: 0.3012 | T58: 0.2047 | U58: 0.1627 | V58: 0.1104 | W58: 0.0452 | X58: 0.0236 | Y58: 0.0008 | Z58: -0.0215 | AA58: -0.1266 | AB58: -0.2274 | AC58: -0.0855 | AD58: -0.1072 | AE58: 0.0011 | AF58: 0.1385 | AG58: -0.034 | AH58: 0.0808 | AI58: 0.0928 | AJ58: 0.0859 | AK58: -0.0126 | AL58: -0.0029 | AM58: 0.0194 | AN58: 0.0256 | AO58: 0.0983 | AP58: 0.2712 | AQ58: 0.2708 | AR58: 0.3196 | AS58: 0.2217 | AT58: -0.0437 | AU58: -0.0923 | AV58: -0.1776
A59: Billings, MT | B59: Market | C59: Billings, MT | D59: 13740 | E59: Performance | F59: YOY Effective Rent Change | G59: Totals | H59: Totals | I59: 0.1851 | J59: 0.2032 | K59: 0.2088 | L59: -0.0208 | M59: 0.0683 | N59: 0.046 | O59: -0.026 | P59: -0.0166 | Q59: -0.0666 | R59: -0.0778 | S59: 0.0328 | T59: 0.0752 | U59: 0.0585 | V59: 0.0799 | W59: 0.0383 | X59: 0.055 | Y59: 0.0874 | Z59: 0.0859 | AA59: 0.1343 | AB59: 0.1267 | AC59: 0.1268 | AD59: 0.1537 | AE59: 0.1555 | AF59: 0.1237 | AG59: 0.1467 | AH59: 0.1679 | AI59: 0.1352 | AJ59: 0.104 | AK59: 0.052 | AL59: 0.0189 | AM59: -0.0091 | AN59: 0.008 | AO59: -0.0072 | AP59: -0.003 | AQ59: 0.0031 | AR59: -0.0061 | AS59: 0.0249 | AT59: 0.0638 | AU59: 0.0642 | AV59: 0.048
A60: Binghamton, NY | B60: Market | C60: Binghamton, NY | D60: 13780 | E60: Performance | F60: YOY Effective Rent Change | G60: Totals | H60: Totals | L60: 0.0565 | M60: 0.0389 | N60: 0.0431 | O60: 0.0466 | P60: 0.0507 | Q60: 0.0136 | R60: 0.0096 | S60: 0.0033 | T60: 0.0123 | U60: -0.0006 | V60: 0.0072 | W60: 0.0162 | X60: 0.0114 | Y60: 0.1817 | Z60: 0.1372 | AA60: 0.2122 | AB60: 0.2305 | AC60: 0.0571 | AD60: 0.0938 | AE60: 0.0286 | AF60: 0.0016 | AG60: 0.0152 | AH60: 0.2134 | AI60: 0.297 | AJ60: 0.2641 | AK60: 0.2894 | AL60: 0.1493 | AM60: 0.0736 | AN60: 0.0748 | AO60: 0.0487 | AP60: -0.0283 | AQ60: -0.0354 | AR60: 0.0039 | AS60: 0.0095 | AT60: 0.0223
A61: Birmingham, AL | B61: Market | C61: Birmingham, AL | D61: 13820 | E61: Performance | F61: YOY Effective Rent Change | G61: Totals | H61: Totals | I61: 0.0419 | J61: 0.0525 | K61: 0.0168 | L61: 0.0032 | M61: 0.0224 | N61: 0.0274 | O61: 0.0399 | P61: 0.032 | Q61: 0.0293 | R61: 0.0474 | S61: 0.0635 | T61: 0.0806 | U61: 0.0777 | V61: 0.0654 | W61: 0.0658 | X61: 0.0718 | Y61: 0.068 | Z61: 0.0234 | AA61: 0.0319 | AB61: 0.0278 | AC61: 0.0255 | AD61: 0.0636 | AE61: 0.0901 | AF61: 0.107 | AG61: 0.1463 | AH61: 0.1522 | AI61: 0.1335 | AJ61: 0.0962 | AK61: 0.0546 | AL61: 0.0292 | AM61: 0.0059 | AN61: 0.0076 | AO61: 0.0095 | AP61: 0.0148 | AQ61: -0.0008 | AR61: 0.0033 | AS61: 0.0061 | AT61: 0.0022 | AU61: 0.0068 | AV61: 0.0049
A62: Bismarck, ND | B62: Market | C62: Bismarck, ND | D62: 13900 | E62: Performance | F62: YOY Effective Rent Change | G62: Totals | H62: Totals | O62: -0.028 | P62: 0.0191 | Q62: -0.0513 | R62: -0.02 | S62: 0.0277 | T62: 0.0336 | U62: 0.0476 | V62: 0.0154 | W62: -0.0035 | X62: 0.0009 | Y62: -0.0401 | Z62: -0.0248 | AA62: -0.0197 | AB62: -0.0204 | AC62: 0.0302 | AD62: 0.022 | AE62: 0.0283 | AF62: 0.0382 | AG62: 0.0543 | AH62: 0.0643 | AI62: 0.1011 | AJ62: 0.1053 | AK62: 0.0793 | AL62: 0.0792 | AM62: 0.0537 | AN62: 0.0616 | AO62: 0.0755 | AP62: 0.0753 | AQ62: 0.082 | AR62: 0.0707 | AS62: 0.0761 | AT62: 0.0834 | AU62: 0.074 | AV62: 0.0676
A63: Blacksburg-Christiansburg-Radford, VA | B63: Market | C63: Blacksburg-Christiansburg-Radford, VA | D63: 13980 | E63: Performance | F63: YOY Effective Rent Change | G63: Totals | H63: Totals | I63: 0.0126 | J63: 0.0002 | K63: -0.0001 | L63: 0.0426 | M63: 0.0296 | N63: 0.0377 | O63: 0.0453 | P63: 0.0447 | Q63: 0.0501 | R63: 0.0366 | S63: 0.0304 | T63: 0.0244 | U63: 0.0307 | V63: 0.0545 | W63: 0.0681 | X63: 0.1004 | Y63: 0.1203 | Z63: 0.1024 | AA63: 0.1 | AB63: 0.0628 | AC63: 0.0378 | AD63: 0.0419 | AE63: 0.0431 | AF63: 0.0445 | AG63: -0.0352 | AH63: -0.0488 | AI63: -0.0583 | AJ63: -0.0573 | AK63: 0.0204 | AL63: 0.0627 | AM63: 0.0973 | AN63: 0.0876 | AO63: 0.0811 | AP63: 0.0513 | AQ63: 0.0213 | AR63: 0.0315 | AS63: 0.0447 | AT63: 0.046 | AU63: 0.0498 | AV63: 0.0652
A64: Bloomington, IL | B64: Market | C64: Bloomington, IL | D64: 14010 | E64: Performance | F64: YOY Effective Rent Change | G64: Totals | H64: Totals | I64: 0.0226 | J64: -0.0947 | K64: 0.0219 | L64: -0.034 | M64: -0.0193 | N64: 0.0881 | O64: 0.0274 | P64: 0.0298 | Q64: -0.0062 | R64: -0.0043 | S64: -0.0263 | T64: -0.0138 | U64: -0.0141 | V64: 0.0404 | W64: 0.017 | X64: 0.0622 | Y64: 0.0057 | Z64: -0.0172 | AA64: 0.0478 | AB64: 0.003 | AC64: 0.0798 | AD64: 0.1177 | AE64: 0.1797 | AF64: 0.2936 | AG64: 0.2362 | AH64: 0.2599 | AI64: 0.1838 | AJ64: 0.0164 | AK64: 0.0502 | AL64: 0.0189 | AM64: 0.0324 | AN64: 0.1058 | AO64: 0.1037 | AP64: 0.123 | AQ64: 0.0834 | AR64: 0.0615 | AS64: 0.0474 | AT64: -0.017 | AU64: -0.0481 | AV64: -0.0239
A65: Bloomington, IN | B65: Market | C65: Bloomington, IN | D65: 14020 | E65: Performance | F65: YOY Effective Rent Change | G65: Totals | H65: Totals | I65: 0.0235 | J65: 0.0181 | K65: 0.0525 | L65: 0.0655 | M65: 0.0326 | N65: 0.0464 | O65: 0.0266 | P65: 0.0324 | Q65: 0.0437 | R65: 0.0638 | S65: 0.0531 | T65: -0.0189 | U65: -0.0179 | V65: -0.0344 | W65: -0.0113 | X65: 0.0359 | Y65: 0.0369 | Z65: 0.024 | AA65: 0.018 | AB65: 0.0321 | AC65: 0.0427 | AD65: 0.0608 | AE65: 0.0837 | AF65: 0.0842 | AG65: 0.1083 | AH65: 0.1062 | AI65: 0.0823 | AJ65: 0.0748 | AK65: 0.0468 | AL65: 0.0415 | AM65: 0.0415 | AN65: 0.0539 | AO65: 0.0519 | AP65: 0.046 | AQ65: 0.0078 | AR65: 0.0114 | AS65: 0.0249 | AT65: 0.0066 | AU65: 0.0451 | AV65: 0.0242
A66: Boise City, ID | B66: Market | C66: Boise City, ID | D66: 14260 | E66: Performance | F66: YOY Effective Rent Change | G66: Totals | H66: Totals | I66: 0.0663 | J66: 0.086 | K66: 0.0723 | L66: 0.0878 | M66: 0.0553 | N66: 0.0418 | O66: 0.0439 | P66: 0.0205 | Q66: 0.05 | R66: 0.0532 | S66: 0.0677 | T66: 0.0995 | U66: 0.0926 | V66: 0.096 | W66: 0.1049 | X66: 0.0787 | Y66: 0.0863 | Z66: 0.0777 | AA66: 0.0672 | AB66: 0.0983 | AC66: 0.1261 | AD66: 0.1964 | AE66: 0.2678 | AF66: 0.2442 | AG66: 0.2071 | AH66: 0.1762 | AI66: 0.0982 | AJ66: 0.0344 | AK66: 0.0223 | AL66: -0.0302 | AM66: -0.0621 | AN66: -0.047 | AO66: -0.0468 | AP66: -0.017 | AQ66: 0.0028 | AR66: 0.0163 | AS66: 0.0318 | AT66: 0.0277 | AU66: 0.0327 | AV66: 0.0318
A67: Bonham, TX | B67: Market | C67: Bonham, TX | D67: 14300 | E67: Performance | F67: YOY Effective Rent Change | G67: Totals | H67: Totals
A68: Boone, NC | B68: Market | C68: Boone, NC | D68: 14380 | E68: Performance | F68: YOY Effective Rent Change | G68: Totals | H68: Totals | T68: 0.1012 | U68: 0.1057 | V68: 0.2222 | W68: 0.2799 | X68: 0.1508 | Y68: 0.1426 | Z68: 0.035 | AA68: -0.0084 | AB68: 0.0426 | AC68: 0.0459 | AD68: 0.0379 | AE68: 0.0345 | AF68: 0.0029 | AG68: 0.0383 | AL68: 0.2577 | AM68: 0.2647 | AN68: 0.2229 | AO68: 0.1626 | AP68: 0.092 | AQ68: 0.1044 | AR68: 0.1155 | AS68: 0.0887 | AV68: 0.0281
A69: Boston-Cambridge-Newton, MA-NH | B69: Market | C69: Boston-Cambridge-Newton, MA-NH | D69: 14460 | E69: Performance | F69: YOY Effective Rent Change | G69: Totals | H69: Totals | I69: 0.0664 | J69: 0.0567 | K69: 0.0402 | L69: 0.027 | M69: 0.0268 | N69: 0.0247 | O69: 0.0355 | P69: 0.0287 | Q69: 0.0396 | R69: 0.0379 | S69: 0.0405 | T69: 0.0603 | U69: 0.0507 | V69: 0.049 | W69: 0.0607 | X69: 0.0449 | Y69: 0.0455 | Z69: -0.005 | AA69: -0.0592 | AB69: -0.0801 | AC69: -0.0849 | AD69: -0.0228 | AE69: 0.0744 | AF69: 0.1403 | AG69: 0.1715 | AH69: 0.1675 | AI69: 0.1193 | AJ69: 0.0959 | AK69: 0.0755 | AL69: 0.0558 | AM69: 0.0493 | AN69: 0.0463 | AO69: 0.0456 | AP69: 0.0336 | AQ69: 0.0322 | AR69: 0.0238 | AS69: 0.0244 | AT69: 0.0362 | AU69: 0.0216 | AV69: 0.0078
A70: Boulder, CO | B70: Market | C70: Boulder, CO | D70: 14500 | E70: Performance | F70: YOY Effective Rent Change | G70: Totals | H70: Totals | I70: 0.0684 | J70: 0.0211 | K70: 0.009 | L70: 0.0274 | M70: 0.033 | N70: 0.0626 | O70: 0.065 | P70: 0.064 | Q70: 0.0468 | R70: 0.0238 | S70: 0.0277 | T70: 0.022 | U70: 0.0257 | V70: 0.0393 | W70: 0.0333 | X70: 0.0309 | Y70: 0.0285 | Z70: -0.0288 | AA70: -0.0328 | AB70: -0.0353 | AC70: -0.0279 | AD70: 0.0445 | AE70: 0.1008 | AF70: 0.1465 | AG70: 0.1735 | AH70: 0.1463 | AI70: 0.1165 | AJ70: 0.0822 | AK70: 0.0502 | AL70: 0.0395 | AM70: 0.0254 | AN70: 0.0089 | AO70: 0.0036 | AP70: 0.0002 | AQ70: -0.0023 | AR70: -0.0149 | AS70: -0.0072 | AT70: 0.0159 | AU70: -0.009 | AV70: -0.0373
A71: Bowling Green, KY | B71: Market | C71: Bowling Green, KY | D71: 14540 | E71: Performance | F71: YOY Effective Rent Change | G71: Totals | H71: Totals | I71: 0.0589 | J71: 0.023 | K71: 0.1311 | L71: 0.0992 | M71: 0.0909 | N71: 0.0186 | O71: -0.049 | P71: -0.0545 | Q71: -0.0643 | R71: 0.007 | S71: -0.0149 | T71: 0.0303 | U71: 0.0267 | V71: 0.006 | W71: -0.0005 | X71: -0.0409 | Y71: 0.045 | Z71: 0.0775 | AA71: 0.0866 | AB71: 0.0984 | AC71: 0.0571 | AD71: 0.0712 | AE71: 0.1461 | AF71: 0.1888 | AG71: 0.25 | AH71: 0.2565 | AI71: 0.1684 | AJ71: 0.0926 | AK71: 0.0295 | AL71: 0.0426 | AM71: 0.0398 | AN71: 0.0749 | AO71: 0.0427 | AP71: 0.019 | AQ71: -0.0088 | AR71: -0.026 | AS71: -0.0143 | AT71: -0.0191 | AU71: -0.0382 | AV71: -0.0451
A72: Bozeman, MT | B72: Market | C72: Bozeman, MT | D72: 14580 | E72: Performance | F72: YOY Effective Rent Change | G72: Totals | H72: Totals | I72: 0.0238 | J72: 0.0939 | K72: 0.0967 | L72: 0.0929 | M72: 0.0904 | N72: 0.0388 | O72: 0.0385 | P72: 0.0488 | Q72: 0.0708 | R72: 0.0741 | S72: 0.0636 | T72: 0.0453 | U72: 0.0428 | V72: 0.0385 | W72: 0.0176 | X72: 0.0328 | Y72: 0.0192 | AA72: 0.1242 | AB72: 0.1358 | AC72: 0.184 | AD72: 0.1335 | AE72: 0.4521 | AF72: 0.5638 | AG72: 0.3976 | AH72: 0.4921 | AI72: 0.2272 | AJ72: 0.0037 | AK72: 0.065 | AL72: -0.0004 | AM72: -0.0612 | AN72: -0.0137 | AO72: -0.0404 | AP72: -0.056 | AQ72: -0.0361 | AR72: -0.0079 | AS72: -0.0208 | AT72: -0.0217 | AU72: -0.1072 | AV72: -0.1087
A73: Brainerd, MN | B73: Market | C73: Brainerd, MN | D73: 14660 | E73: Performance | F73: YOY Effective Rent Change | G73: Totals | H73: Totals | AR73: 0.2065 | AS73: 0.169 | AT73: 0.1285 | AU73: 0.077 | AV73: 0.021
A74: Branson, MO | B74: Market | C74: Branson, MO | D74: 14700 | E74: Performance | F74: YOY Effective Rent Change | G74: Totals | H74: Totals | P74: -0.0434 | Q74: -0.0032 | R74: 0.0098 | S74: 0.0144 | T74: 0.0283 | U74: 0.0281 | V74: 0.018 | W74: 0.0221 | X74: 0.0211 | Y74: 0.0211 | Z74: 0.0141 | AA74: 0.0145 | AB74: 0.0211 | AC74: 0.0214 | AD74: 0.036 | AE74: 0.0511 | AF74: -0.0058 | AG74: -0.0153 | AH74: -0.0139 | AI74: 0.0194 | AJ74: 0.087 | AK74: 0.1104 | AL74: 0.1008 | AM74: 0.0518 | AN74: 0.0452 | AO74: 0.0393 | AP74: 0.0642 | AQ74: 0.0699 | AR74: 0.0439 | AS74: 0.0455 | AT74: 0.0214
A75: Breckenridge, CO | B75: Market | C75: Breckenridge, CO | D75: 14720 | E75: Performance | F75: YOY Effective Rent Change | G75: Totals | H75: Totals
A76: Bremerton-Silverdale-Port Orchard, WA | B76: Market | C76: Bremerton-Silverdale-Port Orchard, WA | D76: 14740 | E76: Performance | F76: YOY Effective Rent Change | G76: Totals | H76: Totals | I76: 0.1125 | J76: 0.1498 | K76: 0.1246 | L76: 0.0916 | M76: 0.0941 | N76: 0.049 | O76: 0.0265 | P76: 0.0317 | Q76: 0.0532 | R76: 0.0465 | S76: 0.0483 | T76: 0.0681 | U76: 0.0894 | V76: 0.0953 | W76: 0.0921 | X76: 0.0676 | Y76: 0.0404 | Z76: -0.0237 | AA76: -0.0058 | AB76: 0.0161 | AC76: 0.0327 | AD76: 0.1466 | AE76: 0.2208 | AF76: 0.2744 | AG76: 0.2179 | AH76: 0.1363 | AI76: 0.0533 | AJ76: -0.0417 | AK76: -0.0727 | AL76: -0.0847 | AM76: -0.0836 | AN76: -0.0276 | AO76: 0.0137 | AP76: 0.0604 | AQ76: 0.0602 | AR76: 0.0642 | AS76: 0.0594 | AT76: 0.033 | AU76: 0.019 | AV76: -0.0113
A77: Brenham, TX | B77: Market | C77: Brenham, TX | D77: 14780 | E77: Performance | F77: YOY Effective Rent Change | G77: Totals | H77: Totals | J77: -0.0232 | N77: -0.0081 | O77: -0.0717 | P77: -0.0405 | Q77: 0.002 | R77: 0.0903 | S77: 0.056 | T77: 0.1037 | U77: 0.0653 | V77: 0.0359 | W77: 0.063 | X77: -0.0051 | Y77: -0.0148 | Z77: -0.0079 | AA77: 0.0033 | AB77: 0.0173
A78: Bridgeport-Stamford-Danbury, CT | B78: Market | C78: Bridgeport-Stamford-Danbury, CT | D78: 14860 | E78: Performance | F78: YOY Effective Rent Change | G78: Totals | H78: Totals | I78: 0.042 | J78: 0.0066 | K78: 0.0003 | L78: 0.002 | M78: 0.0118 | N78: 0.0291 | O78: 0.0196 | P78: 0.0127 | Q78: 0.0127 | R78: 0.0076 | S78: 0.0156 | T78: 0.031 | U78: 0.0128 | V78: 0.0149 | W78: 0.029 | X78: 0.0171 | Y78: 0.0068 | Z78: -0.025 | AA78: -0.0323 | AB78: -0.0171 | AC78: -0.0015 | AD78: 0.0438 | AE78: 0.0844 | AF78: 0.099 | AG78: 0.1078 | AH78: 0.1045 | AI78: 0.0883 | AJ78: 0.0907 | AK78: 0.0737 | AL78: 0.0714 | AM78: 0.0519 | AN78: 0.0243 | AO78: 0.027 | AP78: 0.019 | AQ78: 0.0372 | AR78: 0.0412 | AS78: 0.0517 | AT78: 0.0485 | AU78: 0.0306 | AV78: 0.0269
A79: Brookhaven, MS | B79: Market | C79: Brookhaven, MS | D79: 15020 | E79: Performance | F79: YOY Effective Rent Change | G79: Totals | H79: Totals
A80: Brookings, SD | B80: Market | C80: Brookings, SD | D80: 15100 | E80: Performance | F80: YOY Effective Rent Change | G80: Totals | H80: Totals
A81: Brownwood, TX | B81: Market | C81: Brownwood, TX | D81: 15220 | E81: Performance | F81: YOY Effective Rent Change | G81: Totals | H81: Totals | I81: 0.0419 | N81: 0.0351 | Z81: -0.0685 | AA81: -0.0605 | AB81: -0.0566 | AC81: -0.0224
A82: Brunswick-St. Simons, GA | B82: Market | C82: Brunswick-St. Simons, GA | D82: 15260 | E82: Performance | F82: YOY Effective Rent Change | G82: Totals | H82: Totals | I82: 0.0844 | J82: 0.0778 | K82: 0.0667 | L82: 0.0423 | M82: 0.0715 | N82: 0.1033 | O82: 0.1207 | P82: 0.1155 | Q82: 0.0857 | R82: 0.1215 | S82: 0.125 | T82: 0.0999 | U82: 0.0632 | V82: 0.0052 | W82: 0.0048 | X82: -0.0002 | Y82: 0.0197 | Z82: -0.0319 | AA82: -0.0406 | AB82: -0.0074 | AC82: 0.0024 | AD82: 0.1208 | AE82: 0.2007 | AF82: 0.3063 | AG82: 0.2924 | AH82: 0.2177 | AI82: 0.198 | AJ82: 0.0569 | AK82: 0.0753 | AL82: 0.0551 | AM82: -0.058 | AN82: -0.0519 | AO82: -0.0811 | AP82: -0.045 | AQ82: 0.0063 | AR82: 0.0568 | AS82: 0.0748 | AT82: 0.0307 | AU82: 0.0226 | AV82: -0.0089
A83: Buffalo-Cheektowaga, NY | B83: Market | C83: Buffalo-Cheektowaga, NY | D83: 15380 | E83: Performance | F83: YOY Effective Rent Change | G83: Totals | H83: Totals | I83: 0.0469 | J83: 0.0327 | K83: 0.0316 | L83: 0.0304 | M83: 0.0385 | N83: 0.0082 | O83: -0.0121 | P83: -0.0015 | Q83: -0.018 | R83: 0.0197 | S83: 0.0303 | T83: 0.0202 | U83: 0.0329 | V83: 0.0088 | W83: 0.0302 | X83: 0.0369 | Y83: 0.0367 | Z83: 0.0328 | AA83: 0.024 | AB83: 0.0333 | AC83: 0.0381 | AD83: 0.0465 | AE83: 0.0582 | AF83: 0.0684 | AG83: 0.0731 | AH83: 0.1011 | AI83: 0.1086 | AJ83: 0.0905 | AK83: 0.0817 | AL83: 0.0483 | AM83: 0.0429 | AN83: 0.0503 | AO83: 0.0581 | AP83: 0.0705 | AQ83: 0.0606 | AR83: 0.0534 | AS83: 0.0489 | AT83: 0.0571 | AU83: 0.0494 | AV83: 0.049
A84: Burlington, IA-IL | B84: Market | C84: Burlington, IA-IL | D84: 15460 | E84: Performance | F84: YOY Effective Rent Change | G84: Totals | H84: Totals | N84: 0.1046
A85: Burlington-South Burlington, VT | B85: Market | C85: Burlington-South Burlington, VT | D85: 15540 | E85: Performance | F85: YOY Effective Rent Change | G85: Totals | H85: Totals | I85: 0.0412 | J85: 0.0609 | K85: 0.0113 | L85: 0.0501 | M85: 0.067 | N85: 0.0578 | O85: 0.0548 | P85: 0.0148 | Q85: -0.0538 | R85: -0.0496 | S85: -0.01 | T85: -0.0328 | U85: -0.0047 | V85: -0.0071 | W85: -0.0467 | X85: -0.0058 | Y85: 0.0013 | Z85: 0.0014 | AA85: 0.0519 | AB85: 0.0379 | AC85: 0.0067 | AD85: 0.0062 | AE85: -0.0051 | AF85: -0.001 | AG85: 0.0161 | AH85: 0.0164 | AI85: 0.0418 | AU85: 0.1498 | AV85: 0.1106
A86: Canon City, CO | B86: Market | C86: Canon City, CO | D86: 15860 | E86: Performance | F86: YOY Effective Rent Change | G86: Totals | H86: Totals
A87: Canton-Massillon, OH | B87: Market | C87: Canton-Massillon, OH | D87: 15940 | E87: Performance | F87: YOY Effective Rent Change | G87: Totals | H87: Totals | I87: 0.0429 | J87: 0.0339 | K87: 0.0876 | L87: 0.0679 | M87: 0.014 | N87: 0.0688 | O87: -0.0127 | P87: -0.0197 | Q87: 0.0413 | R87: -0.0098 | S87: 0.0593 | T87: 0.0582 | U87: 0.0579 | V87: 0.0461 | W87: 0.0152 | X87: 0.0586 | Y87: 0.0705 | Z87: 0.0764 | AA87: 0.094 | AB87: 0.0443 | AC87: 0.0364 | AD87: 0.0542 | AE87: 0.0563 | AF87: 0.077 | AG87: 0.0889 | AH87: 0.0683 | AI87: 0.0722 | AJ87: 0.1179 | AK87: 0.2376 | AL87: 0.2609 | AM87: 0.1635 | AN87: 0.1196 | AO87: 0.0066 | AP87: -0.004 | AQ87: 0.0397 | AR87: 0.0184 | AS87: 0.0176 | AT87: 0.0718 | AU87: 0.0694 | AV87: 0.0628
A88: Cape Coral-Fort Myers, FL | B88: Market | C88: Cape Coral-Fort Myers, FL | D88: 15980 | E88: Performance | F88: YOY Effective Rent Change | G88: Totals | H88: Totals | I88: 0.0898 | J88: 0.1071 | K88: 0.0781 | L88: 0.0485 | M88: 0.0456 | N88: 0.0179 | O88: 0.0248 | P88: 0.0588 | Q88: 0.0655 | R88: 0.076 | S88: 0.0706 | T88: 0.0395 | U88: 0.0196 | V88: 0.0251 | W88: 0.0207 | X88: 0.0291 | Y88: 0.0436 | Z88: 0.0147 | AA88: -0.012 | AB88: -0.0006 | AC88: 0.0116 | AD88: 0.0765 | AE88: 0.2414 | AF88: 0.3459 | AG88: 0.414 | AH88: 0.4176 | AI88: 0.2865 | AJ88: 0.1983 | AK88: 0.1407 | AL88: 0.0678 | AM88: 0.0064 | AN88: -0.0496 | AO88: -0.0819 | AP88: -0.095 | AQ88: -0.0899 | AR88: -0.0883 | AS88: -0.0765 | AT88: -0.0487 | AU88: -0.0639 | AV88: -0.0767
A89: Carbondale/Marion-Herrin, IL | B89: Market | C89: Carbondale/Marion-Herrin, IL | D89: 216060 | E89: Performance | F89: YOY Effective Rent Change | G89: Totals | H89: Totals | L89: -0.1901 | M89: -0.1891 | N89: -0.141 | O89: -0.1049 | P89: 0.0122 | Q89: -0.0063 | R89: 0.0479
A90: Carlsbad-Artesia, NM | B90: Market | C90: Carlsbad-Artesia, NM | D90: 16100 | E90: Performance | F90: YOY Effective Rent Change | G90: Totals | H90: Totals | AH90: -0.0318 | AI90: -0.0023 | AJ90: 0.0747 | AK90: 0.1263 | AL90: 0.084 | AM90: 0.0874 | AN90: 0.09 | AO90: 0.081 | AP90: 0.0639 | AQ90: 0.0601 | AR90: 0.0189 | AS90: 0.0065 | AT90: 0.0171 | AU90: 0.0197 | AV90: 0.0288
A91: Carson City, NV | B91: Market | C91: Carson City, NV | D91: 16180 | E91: Performance | F91: YOY Effective Rent Change | G91: Totals | H91: Totals | I91: -0.0226 | J91: 0.0754 | K91: 0.0793 | L91: 0.1009 | M91: 0.131 | N91: 0.1295 | O91: 0.1811 | P91: 0.1651 | Q91: 0.1421 | R91: 0.09 | S91: 0.0553 | T91: 0.0845 | U91: 0.0433 | V91: 0.0204 | W91: 0.0066 | X91: -0.0261 | Y91: -0.0075 | Z91: 0.0075 | AA91: 0.0094 | AB91: 0.0563 | AC91: 0.0653 | AD91: 0.1021 | AE91: 0.1954 | AF91: 0.1291 | AG91: 0.1136 | AH91: 0.1232 | AI91: 0.0583 | AJ91: 0.0262 | AK91: -0.0041 | AL91: -0.0218 | AM91: -0.0449 | AN91: 0.0066 | AO91: 0.0407 | AP91: 0.0197 | AQ91: 0.013 | AR91: 0.0438 | AS91: 0.0518 | AT91: 0.0918 | AU91: 0.0766 | AV91: 0.0182
A92: Casper, WY | B92: Market | C92: Casper, WY | D92: 16220 | E92: Performance | F92: YOY Effective Rent Change | G92: Totals | H92: Totals | I92: -0.1237 | J92: -0.1676 | K92: -0.1573 | L92: -0.0983 | M92: -0.0826 | N92: -0.0046 | O92: 0.037 | P92: 0.011 | Q92: 0.0311 | R92: 0.0666 | S92: 0.0269 | T92: 0.0316 | U92: 0.0717 | V92: 0.0586 | W92: 0.0892 | X92: 0.091 | Y92: 0.0676 | Z92: 0.0094 | AA92: -0.0574 | AB92: -0.042 | AC92: -0.0625 | AD92: 0.0453 | AE92: 0.1324 | AF92: 0.1005 | AG92: 0.1152 | AH92: 0.1396 | AI92: 0.0941 | AJ92: 0.0728 | AK92: 0.0821 | AL92: 0.0195 | AM92: 0.0395 | AN92: 0.0418 | AO92: 0.037 | AP92: 0.0397 | AQ92: 0.0506 | AR92: 0.0344 | AS92: 0.0529 | AT92: 0.0703 | AU92: 0.0204 | AV92: 0.0484
A93: Cedar Rapids, IA | B93: Market | C93: Cedar Rapids, IA | D93: 16300 | E93: Performance | F93: YOY Effective Rent Change | G93: Totals | H93: Totals | I93: 0.1134 | J93: 0.0504 | K93: 0.0576 | L93: 0.1179 | M93: -0.0048 | N93: -0.0015 | O93: 0.0354 | P93: 0.0293 | Q93: 0.0267 | R93: 0.036 | S93: 0.0397 | T93: 0.033 | U93: 0.0137 | V93: -0.0042 | W93: -0.0333 | X93: -0.0222 | Y93: -0.0037 | Z93: -0.0101 | AA93: 0.0287 | AB93: 0.0644 | AC93: 0.0795 | AD93: 0.1135 | AE93: 0.103 | AF93: 0.0631 | AG93: 0.0423 | AH93: 0.0354 | AI93: 0.0211 | AJ93: 0.0237 | AK93: 0.011 | AL93: -0.008 | AM93: 0.0273 | AN93: 0.0229 | AO93: 0.0579 | AP93: 0.0885 | AQ93: 0.0501 | AR93: 0.0416 | AS93: 0.0399 | AT93: 0.0529 | AU93: 0.076 | AV93: 0.126
A94: Chambersburg, PA | B94: Market | C94: Chambersburg, PA | D94: 16540 | E94: Performance | F94: YOY Effective Rent Change | G94: Totals | H94: Totals
A95: Champaign-Urbana, IL | B95: Market | C95: Champaign-Urbana, IL | D95: 16580 | E95: Performance | F95: YOY Effective Rent Change | G95: Totals | H95: Totals | I95: 0.0326 | J95: 0.0312 | K95: 0.0139 | L95: -0.0019 | M95: 0.0038 | N95: -0.0012 | O95: 0.0025 | P95: 0.0059 | Q95: 0.0367 | R95: 0.0397 | S95: 0.0476 | T95: 0.0307 | U95: 0.0392 | V95: 0.0353 | W95: 0.0324 | X95: 0.0458 | Y95: 0.0135 | Z95: 0.0022 | AA95: -0.0104 | AB95: -0.0067 | AC95: -0.0149 | AD95: -0.002 | AE95: 0.0104 | AF95: 0.0604 | AG95: 0.0468 | AH95: 0.0674 | AI95: 0.1193 | AJ95: 0.1007 | AK95: 0.1217 | AL95: 0.1019 | AM95: 0.0626 | AN95: 0.0316 | AO95: 0.0397 | AP95: 0.032 | AQ95: 0.0523 | AR95: 0.063 | AS95: 0.0722 | AT95: 0.1725 | AU95: 0.1197 | AV95: 0.1295
A96: Charleston-Mattoon, IL | B96: Market | C96: Charleston-Mattoon, IL | D96: 16660 | E96: Performance | F96: YOY Effective Rent Change | G96: Totals | H96: Totals | W96: 0.1695 | X96: 0.1487 | Y96: 0.1249 | Z96: 0.1429 | AA96: -0.0015 | AB96: 0.0143 | AC96: 0.0408 | AD96: 0.0245 | AE96: 0.0373 | AF96: 0.0626
A97: Charleston-North Charleston, SC | B97: Market | C97: Charleston-North Charleston, SC | D97: 16700 | E97: Performance | F97: YOY Effective Rent Change | G97: Totals | H97: Totals | I97: 0.0618 | J97: 0.0683 | K97: 0.0464 | L97: 0.0558 | M97: 0.0588 | N97: 0.037 | O97: 0.042 | P97: 0.0245 | Q97: 0.03 | R97: 0.0447 | S97: 0.0415 | T97: 0.0362 | U97: 0.0447 | V97: 0.0476 | W97: 0.0511 | X97: 0.0775 | Y97: 0.0621 | Z97: 0.0144 | AA97: 0.0107 | AB97: 0.0033 | AC97: 0.0167 | AD97: 0.1019 | AE97: 0.1865 | AF97: 0.2305 | AG97: 0.2453 | AH97: 0.2227 | AI97: 0.1734 | AJ97: 0.1309 | AK97: 0.1064 | AL97: 0.0681 | AM97: 0.0362 | AN97: 0.0253 | AO97: 0.016 | AP97: 0.0091 | AQ97: 0.0041 | AR97: -0.0033 | AS97: 0.0026 | AT97: 0.006 | AU97: -0.0079 | AV97: 0.0039
A98: Charleston, WV | B98: Market | C98: Charleston, WV | D98: 16620 | E98: Performance | F98: YOY Effective Rent Change | G98: Totals | H98: Totals | J98: -0.0789 | K98: -0.2278 | L98: -0.2043 | M98: -0.119 | O98: 0.1578 | P98: 0.1507 | Q98: -0.0744 | R98: -0.1414 | S98: -0.0475 | T98: -0.0473 | U98: -0.0004 | V98: 0.0046 | W98: 0.2324 | X98: 0.1627 | Y98: 0.1602 | Z98: 0.1524 | AA98: -0.0589 | AB98: 0.058 | AC98: 0.0652 | AD98: 0.0934 | AE98: 0.0743 | AF98: 0.0632 | AG98: 0.1135 | AH98: 0.1205 | AI98: 0.1677 | AJ98: 0.1155 | AK98: 0.0868 | AL98: 0.0812 | AM98: 0.0606 | AN98: 0.0558 | AO98: 0.0258 | AP98: 0.0447 | AQ98: 0.0983 | AR98: 0.1309 | AS98: 0.1307
A99: Charlotte-Concord-Gastonia, NC-SC | B99: Market | C99: Charlotte-Concord-Gastonia, NC-SC | D99: 16740 | E99: Performance | F99: YOY Effective Rent Change | G99: Totals | H99: Totals | I99: 0.0823 | J99: 0.0703 | K99: 0.0531 | L99: 0.049 | M99: 0.0468 | N99: 0.04 | O99: 0.0461 | P99: 0.0384 | Q99: 0.0383 | R99: 0.0457 | S99: 0.05 | T99: 0.0562 | U99: 0.0605 | V99: 0.0654 | W99: 0.0677 | X99: 0.0704 | Y99: 0.0638 | Z99: 0.0145 | AA99: 0.0073 | AB99: 0.0222 | AC99: 0.0277 | AD99: 0.0965 | AE99: 0.1623 | AF99: 0.1969 | AG99: 0.2061 | AH99: 0.1937 | AI99: 0.1667 | AJ99: 0.1015 | AK99: 0.0724 | AL99: 0.0387 | AM99: -0.0093 | AN99: -0.0207 | AO99: -0.0201 | AP99: -0.0263 | AQ99: -0.0267 | AR99: -0.0069 | AS99: -0.0027 | AT99: 0.0014 | AU99: -0.0032 | AV99: -0.019
A100: Charlottesville, VA | B100: Market | C100: Charlottesville, VA | D100: 16820 | E100: Performance | F100: YOY Effective Rent Change | G100: Totals | H100: Totals | I100: 0.0136 | J100: 0.041 | K100: 0.0393 | L100: 0.0404 | M100: 0.0507 | N100: 0.0455 | O100: 0.0459 | P100: 0.0258 | Q100: 0.026 | R100: 0.0254 | S100: 0.0297 | T100: 0.0421 | U100: 0.0624 | V100: 0.0639 | W100: 0.0621 | X100: 0.0537 | Y100: 0.0352 | Z100: 0.0054 | AA100: 0.0039 | AB100: 0.0104 | AC100: 0.0166 | AD100: 0.0616 | AE100: 0.0959 | AF100: 0.1044 | AG100: 0.1095 | AH100: 0.1155 | AI100: 0.0772 | AJ100: 0.0706 | AK100: 0.0733 | AL100: 0.0631 | AM100: 0.0465 | AN100: 0.0576 | AO100: 0.0504 | AP100: 0.0417 | AQ100: 0.0565 | AR100: 0.0388 | AS100: 0.0432 | AT100: 0.0462 | AU100: 0.0265 | AV100: 0.0047
...

Sheet Cap Rate to IRR Map
C1: =AVERAGE(C66:C407) -> 0.00088011696 | H1: Extrapolation step (avg bottom-edge ΔIRR)
A2: Cap Rate Growth | B2: IRR From Appreciation | H2: =(INDEX($B:$B,85)-INDEX($B:$B,65))/20 -> 0.0014
A3: -0.012 | B3: =B4-$H$2 -> -0.1698 | E3: =A3 -> -0.012 | F3: =B3 -> -0.1698 | H3: Top extrapolation step (avg top-edge ΔIRR)
A4: -0.0119 | B4: =B5-$H$2 -> -0.1684 | C4: =B4-B3 -> 0.0014 | E4: =A4 -> -0.0119 | F4: =B4 -> -0.1684 | H4: =(INDEX($B:$B,456)-INDEX($B:$B,436))/20 -> 0.00088011696
A5: -0.0118 | B5: =B6-$H$2 -> -0.167 | C5: =B5-B4 -> 0.0014 | E5: =A5 -> -0.0118 | F5: =B5 -> -0.167
A6: -0.0117 | B6: =B7-$H$2 -> -0.1656 | C6: =B6-B5 -> 0.0014 | E6: =A6 -> -0.0117 | F6: =B6 -> -0.1656
A7: -0.0116 | B7: =B8-$H$2 -> -0.1642 | C7: =B7-B6 -> 0.0014 | E7: =A7 -> -0.0116 | F7: =B7 -> -0.1642
A8: -0.0115 | B8: =B9-$H$2 -> -0.1628 | C8: =B8-B7 -> 0.0014 | E8: =A8 -> -0.0115 | F8: =B8 -> -0.1628
A9: -0.0114 | B9: =B10-$H$2 -> -0.1614 | C9: =B9-B8 -> 0.0014 | E9: =A9 -> -0.0114 | F9: =B9 -> -0.1614
A10: -0.0113 | B10: =B11-$H$2 -> -0.16 | C10: =B10-B9 -> 0.0014 | E10: =A10 -> -0.0113 | F10: =B10 -> -0.16
A11: -0.0112 | B11: =B12-$H$2 -> -0.1586 | C11: =B11-B10 -> 0.0014 | E11: =A11 -> -0.0112 | F11: =B11 -> -0.1586
A12: -0.0111 | B12: =B13-$H$2 -> -0.1572 | C12: =B12-B11 -> 0.0014 | E12: =A12 -> -0.0111 | F12: =B12 -> -0.1572
A13: -0.011 | B13: =B14-$H$2 -> -0.1558 | C13: =B13-B12 -> 0.0014 | E13: =A13 -> -0.011 | F13: =B13 -> -0.1558
A14: -0.0109 | B14: =B15-$H$2 -> -0.1544 | C14: =B14-B13 -> 0.0014 | E14: =A14 -> -0.0109 | F14: =B14 -> -0.1544
A15: -0.0108 | B15: =B16-$H$2 -> -0.153 | C15: =B15-B14 -> 0.0014 | E15: =A15 -> -0.0108 | F15: =B15 -> -0.153
A16: -0.0107 | B16: =B17-$H$2 -> -0.1516 | C16: =B16-B15 -> 0.0014 | E16: =A16 -> -0.0107 | F16: =B16 -> -0.1516
... A64: -0.0059 | B64: =B65-$H$2 -> -0.0844 | C64: =B64-B63 -> 0.0014 | E64: =A64 -> -0.0059 | F64: =B64 -> -0.0844
A65: -0.0058 | B65: -0.083 | C65: =B65-B64 -> 0.0014 | E65: =A65 -> -0.0058 | F65: =B65 -> -0.083
A66: -0.0057 | B66: -0.081667 | C66: =B66-B65 -> 0.001333 | E66: =A66 -> -0.0057 | F66: =B66 -> -0.081667
A67: -0.0056 | B67: -0.080333 | C67: =B67-B66 -> 0.001334 | E67: =A67 -> -0.0056 | F67: =B67 -> -0.080333
A68: -0.0055 | B68: -0.079 | C68: =B68-B67 -> 0.001333 | E68: =A68 -> -0.0055 | F68: =B68 -> -0.079
A69: -0.0054 | B69: -0.0775 | C69: =B69-B68 -> 0.0015 | E69: =A69 -> -0.0054 | F69: =B69 -> -0.0775
A70: -0.0053 | B70: -0.076 | C70: =B70-B69 -> 0.0015 | E70: =A70 -> -0.0053 | F70: =B70 -> -0.076
A71: -0.0052 | B71: -0.074 | C71: =B71-B70 -> 0.002 | E71: =A71 -> -0.0052 | F71: =B71 -> -0.074
A72: -0.0051 | B72: -0.072 | C72: =B72-B71 -> 0.002 | E72: =A72 -> -0.0051 | F72: =B72 -> -0.072
A73: -0.005 | B73: -0.071 | C73: =B73-B72 -> 0.001 | E73: =A73 -> -0.005 | F73: =B73 -> -0.071
A74: -0.0049 | B74: -0.07 | C74: =B74-B73 -> 0.001 | E74: =A74 -> -0.0049 | F74: =B74 -> -0.07
A75: -0.0048 | B75: -0.069 | C75: =B75-B74 -> 0.001 | E75: =A75 -> -0.0048 | F75: =B75 -> -0.069
A76: -0.0047 | B76: -0.067 | C76: =B76-B75 -> 0.002 | E76: =A76 -> -0.0047 | F76: =B76 -> -0.067
... A200: 0.0077 | B200: 0.072 | C200: =B200-B199 -> 0.001 | E200: =A200 -> 0.0077 | F200: =B200 -> 0.072
A201: 0.0078 | B201: 0.073 | C201: =B201-B200 -> 0.001 | E201: 0.0078 | F201: =B201 -> 0.073
A202: 0.0079 | B202: 0.074 | C202: =B202-B201 -> 0.001 | E202: =A202 -> 0.0079 | F202: =B202 -> 0.074
A203: 0.008 | B203: 0.075 | C203: =B203-B202 -> 0.001 | E203: =A203 -> 0.008 | F203: =B203 -> 0.075
A204: 0.0081 | B204: 0.075667 | C204: =B204-B203 -> 0.000667 | E204: =A204 -> 0.0081 | F204: =B204 -> 0.075667
A205: 0.0082 | B205: 0.076333 | C205: =B205-B204 -> 0.000666 | E205: =A205 -> 0.0082 | F205: =B205 -> 0.076333
A206: 0.0083 | B206: 0.077 | C206: =B206-B205 -> 0.000667 | E206: =A206 -> 0.0083 | F206: =B206 -> 0.077
A207: 0.0084 | B207: 0.078 | C207: =B207-B206 -> 0.001 | E207: =A207 -> 0.0084 | F207: =B207 -> 0.078
A208: 0.0085 | B208: 0.079 | C208: =B208-B207 -> 0.001 | E208: =A208 -> 0.0085 | F208: =B208 -> 0.079
A209: 0.0086 | B209: 0.08 | C209: =B209-B208 -> 0.001 | E209: =A209 -> 0.0086 | F209: =B209 -> 0.08
A210: 0.0087 | B210: 0.081 | C210: =B210-B209 -> 0.001 | E210: =A210 -> 0.0087 | F210: =B210 -> 0.081
A211: 0.0088 | B211: 0.082 | C211: =B211-B210 -> 0.001 | E211: =A211 -> 0.0088 | F211: =B211 -> 0.082
A212: 0.0089 | B212: 0.083 | C212: =B212-B211 -> 0.001 | E212: =A212 -> 0.0089 | F212: =B212 -> 0.083
A213: 0.009 | B213: 0.083667 | C213: =B213-B212 -> 0.000667 | E213: =A213 -> 0.009 | F213: =B213 -> 0.083667
... A215: 0.0092 | B215: 0.085 | C215: =B215-B214 -> 0.000667 | E215: =A215 -> 0.0092 | F215: =B215 -> 0.085
A216: 0.0093 | B216: 0.086 | C216: =B216-B215 -> 0.001 | E216: 0.0093 | F216: =B216 -> 0.086
A217: 0.0094 | B217: 0.087 | C217: =B217-B216 -> 0.001 | E217: =A217 -> 0.0094 | F217: =B217 -> 0.087
A218: 0.0095 | B218: 0.088 | C218: =B218-B217 -> 0.001 | E218: =A218 -> 0.0095 | F218: =B218 -> 0.088
A219: 0.0096 | B219: 0.088667 | C219: =B219-B218 -> 0.000667 | E219: =A219 -> 0.0096 | F219: =B219 -> 0.088667
A220: 0.0097 | B220: 0.089333 | C220: =B220-B219 -> 0.000666 | E220: =A220 -> 0.0097 | F220: =B220 -> 0.089333
A221: 0.0098 | B221: 0.09 | C221: =B221-B220 -> 0.000667 | E221: =A221 -> 0.0098 | F221: =B221 -> 0.09
A222: 0.0099 | B222: 0.09075 | C222: =B222-B221 -> 0.00075 | E222: =A222 -> 0.0099 | F222: =B222 -> 0.09075
A223: 0.01 | B223: 0.0915 | C223: =B223-B222 -> 0.00075 | E223: =A223 -> 0.01 | F223: =B223 -> 0.0915
A224: 0.0101 | B224: 0.09225 | C224: =B224-B223 -> 0.00075 | E224: =A224 -> 0.0101 | F224: =B224 -> 0.09225
A225: 0.0102 | B225: 0.093 | C225: =B225-B224 -> 0.00075 | E225: =A225 -> 0.0102 | F225: =B225 -> 0.093
A226: 0.0103 | B226: 0.094 | C226: =B226-B225 -> 0.001 | E226: =A226 -> 0.0103 | F226: =B226 -> 0.094
A227: 0.0104 | B227: 0.095 | C227: =B227-B226 -> 0.001 | E227: =A227 -> 0.0104 | F227: =B227 -> 0.095
A228: 0.0105 | B228: 0.096 | C228: =B228-B227 -> 0.001 | E228: =A228 -> 0.0105 | F228: =B228 -> 0.096
... A407: 0.0284 | B407: 0.218 | C407: =B407-B406 -> 0.0005 | E407: =A407 -> 0.0284 | F407: =B407 -> 0.218
A408: =A407+0.01% -> 0.0285 | B408: =B407+$C$1 -> 0.21888012 | E408: =A408 -> 0.0285 | F408: =B408 -> 0.21888012
A409: =A408+0.01% -> 0.0286 | B409: =B408+$C$1 -> 0.21976023 | E409: =A409 -> 0.0286 | F409: =B409 -> 0.21976023
A410: =A409+0.01% -> 0.0287 | B410: =B409+$C$1 -> 0.22064035 | E410: =A410 -> 0.0287 | F410: =B410 -> 0.22064035
A411: =A410+0.01% -> 0.0288 | B411: =B410+$C$1 -> 0.22152047 | E411: =A411 -> 0.0288 | F411: =B411 -> 0.22152047
A412: =A411+0.01% -> 0.0289 | B412: =B411+$C$1 -> 0.22240058 | E412: =A412 -> 0.0289 | F412: =B412 -> 0.22240058
A413: =A412+0.01% -> 0.029 | B413: =B412+$C$1 -> 0.2232807 | E413: =A413 -> 0.029 | F413: =B413 -> 0.2232807
A414: =A413+0.01% -> 0.0291 | B414: =B413+$C$1 -> 0.22416082 | E414: =A414 -> 0.0291 | F414: =B414 -> 0.22416082
A415: =A414+0.01% -> 0.0292 | B415: =B414+$C$1 -> 0.22504094 | E415: =A415 -> 0.0292 | F415: =B415 -> 0.22504094
A416: =A415+0.01% -> 0.0293 | B416: =B415+$C$1 -> 0.22592105 | E416: =A416 -> 0.0293 | F416: =B416 -> 0.22592105
A417: =A416+0.01% -> 0.0294 | B417: =B416+$C$1 -> 0.22680117 | E417: =A417 -> 0.0294 | F417: =B417 -> 0.22680117
A418: =A417+0.01% -> 0.0295 | B418: =B417+$C$1 -> 0.22768129 | E418: =A418 -> 0.0295 | F418: =B418 -> 0.22768129
A419: =A418+0.01% -> 0.0296 | B419: =B418+$C$1 -> 0.2285614 | E419: =A419 -> 0.0296 | F419: =B419 -> 0.2285614
... A446: =A445+0.01% -> 0.0323 | B446: =B445+$C$1 -> 0.25232456 | E446: =A446 -> 0.0323 | F446: =B446 -> 0.25232456
A447: 0.0324 | B447: =B446+$C$1 -> 0.25320468 | E447: =A447 -> 0.0324 | F447: =B447 -> 0.25320468
A448: =A447+0.01% -> 0.0325 | B448: =B447+$C$1 -> 0.2540848 | E448: =A448 -> 0.0325 | F448: =B448 -> 0.2540848
A449: =A448+0.01% -> 0.0326 | B449: =B448+$C$1 -> 0.25496491 | E449: =A449 -> 0.0326 | F449: =B449 -> 0.25496491
A450: =A449+0.01% -> 0.0327 | B450: =B449+$C$1 -> 0.25584503 | E450: =A450 -> 0.0327 | F450: =B450 -> 0.25584503
A451: =A450+0.01% -> 0.0328 | B451: =B450+$C$1 -> 0.25672515 | E451: =A451 -> 0.0328 | F451: =B451 -> 0.25672515
A452: =A451+0.01% -> 0.0329 | B452: =B451+$C$1 -> 0.25760526 | E452: =A452 -> 0.0329 | F452: =B452 -> 0.25760526
A453: =A452+0.01% -> 0.033 | B453: =B452+$C$1 -> 0.25848538 | E453: =A453 -> 0.033 | F453: =B453 -> 0.25848538
A454: =A453+0.01% -> 0.0331 | B454: =B453+$C$1 -> 0.2593655 | E454: =A454 -> 0.0331 | F454: =B454 -> 0.2593655
A455: =A454+0.01% -> 0.0332 | B455: =B454+$C$1 -> 0.26024561 | E455: =A455 -> 0.0332 | F455: =B455 -> 0.26024561
A456: =A455+0.01% -> 0.0333 | B456: =B455+$C$1 -> 0.26112573 | E456: =A456 -> 0.0333 | F456: =B456 -> 0.26112573
A457: 0.0334 | B457: =B456+$H$4 -> 0.26200585 | C457: =B457-B456 -> 0.00088011696 | E457: =A457 -> 0.0334 | F457: =B457 -> 0.26200585
A458: 0.0335 | B458: =B457+$H$4 -> 0.26288596 | C458: =B458-B457 -> 0.00088011696 | E458: =A458 -> 0.0335 | F458: =B458 -> 0.26288596
A459: 0.0336 | B459: =B458+$H$4 -> 0.26376608 | C459: =B459-B458 -> 0.00088011696 | E459: =A459 -> 0.0336 | F459: =B459 -> 0.26376608
A460: 0.0337 | B460: =B459+$H$4 -> 0.2646462 | C460: =B460-B459 -> 0.00088011696 | E460: =A460 -> 0.0337 | F460: =B460 -> 0.2646462
A461: 0.0338 | B461: =B460+$H$4 -> 0.26552632 | C461: =B461-B460 -> 0.00088011696 | E461: =A461 -> 0.0338 | F461: =B461 -> 0.26552632
A462: 0.0339 | B462: =B461+$H$4 -> 0.26640643 | C462: =B462-B461 -> 0.00088011696 | E462: =A462 -> 0.0339 | F462: =B462 -> 0.26640643
A463: 0.034 | B463: =B462+$H$4 -> 0.26728655 | C463: =B463-B462 -> 0.00088011696 | E463: =A463 -> 0.034 | F463: =B463 -> 0.26728655
A464: 0.0341 | B464: =B463+$H$4 -> 0.26816667 | C464: =B464-B463 -> 0.00088011696 | E464: =A464 -> 0.0341 | F464: =B464 -> 0.26816667
A465: 0.0342 | B465: =B464+$H$4 -> 0.26904678 | C465: =B465-B464 -> 0.00088011696 | E465: =A465 -> 0.0342 | F465: =B465 -> 0.26904678
A466: 0.0343 | B466: =B465+$H$4 -> 0.2699269 | C466: =B466-B465 -> 0.00088011696 | E466: =A466 -> 0.0343 | F466: =B466 -> 0.2699269
A467: 0.0344 | B467: =B466+$H$4 -> 0.27080702 | C467: =B467-B466 -> 0.00088011696 | E467: =A467 -> 0.0344 | F467: =B467 -> 0.27080702
A468: 0.0345 | B468: =B467+$H$4 -> 0.27168713 | C468: =B468-B467 -> 0.00088011696 | E468: =A468 -> 0.0345 | F468: =B468 -> 0.27168713
... A623: 0.05 | B623: =B622+$H$4 -> 0.40810526 | C623: =B623-B622 -> 0.00088011696 | E623: =A623 -> 0.05 | F623: =B623 -> 0.40810526
