Workbook

Sheet Q2 2026 Summary
C2: Multifamily Market Summary — Recovery Screen
C3: Effective RPSF | Rent Roll (Rev/OSF) — RealPage Q2 2026 actuals + RealPage same-store forecast through 2029Q4. Rent roll held flat per CB spec (directional / conservative). Sorted by forecast years back to even.
B4: # | C4: Market | D4: Rent Roll PSF | E4: Asking RPSF | F4: Effective RPSF | G4: Gross Embedded RR Mark to Market | H4: Effective Embedded RR Mark to Market | I4: TTM Unit Starts as % of Inv | J4: Fwd 12-Mo Inventory Growth (RP Fcst) | K4: Fcst Rent Growth Yr 1 (26Q2→27Q2) | L4: Fcst Rent Growth Yr 2 (27Q2→28Q2) | M4: Fcst Rent Growth Yr 3 (28Q2→29Q2) | N4: Fcst MtM +1 Yr | O4: Fcst MtM +2 Yrs | P4: Fcst MtM +3 Yrs | Q4: Years to Rent Roll Even (RP Forecast) | S4: 10-Yr Hist Avg Rent Growth (RP) | T4: 10-Yr Hist Avg Rent Growth (GSA) | U4: 10-Yr Avg Hist. Rent Growth (GSA & RP) | V4: Years to Even (Old Method: 10-Yr Hist Avg)
B5: =ROW()-4 -> 1 | C5: Madison, WI | D5: =SUMIFS('Realpage Data'!$R$2:$R$899,'Realpage Data'!$A$2:$A$899,$C5,'Realpage Data'!$F$2:$F$899,"Rent Roll (Rev/OSF)") -> 1.5625838 | E5: =SUMIFS('Realpage Data'!$R$2:$R$899,'Realpage Data'!$A$2:$A$899,$C5,'Realpage Data'!$F$2:$F$899,"Asking RPSF") -> 1.882 | F5: =SUMIFS('Realpage Data'!$R$2:$R$899,'Realpage Data'!$A$2:$A$899,$C5,'Realpage Data'!$F$2:$F$899,"Effective RPSF") -> 1.861 | G5: =E5/$D5-1 -> 0.20441542 | H5: =F5/$D5-1 -> 0.19097614 | I5: =SUMIFS('RP - Unit Starts'!$AC$2:$AC$451,'RP - Unit Starts'!$A$2:$A$451,$C5,'RP - Unit Starts'!$F$2:$F$451,"Annual Unit Starts")/SUMIFS('RP - Unit Starts'!$AC$2:$AC$451,'RP - Unit Starts'!$A$2:$A$451,$C5,'RP - Unit Starts'!$F$2:$F$451,"Existing Units") -> 0.034117814 | J5: =SUMIFS('Realpage Data'!$V$2:$V$899,'Realpage Data'!$A$2:$A$899,$C5,'Realpage Data'!$F$2:$F$899,"Existing Units")/SUMIFS('Realpage Data'!$R$2:$R$899,'Realpage Data'!$A$2:$A$899,$C5,'Realpage Data'!$F$2:$F$899,"Existing Units")-1 -> 0.035301638 | K5: =INDEX('Fcst Walk'!$J$5:$J$69,MATCH($C5,'Fcst Walk'!$A$5:$A$69,0))/INDEX('Fcst Walk'!$F$5:$F$69,MATCH($C5,'Fcst Walk'!$A$5:$A$69,0))-1 -> 0.027 | L5: =INDEX('Fcst Walk'!$N$5:$N$69,MATCH($C5,'Fcst Walk'!$A$5:$A$69,0))/INDEX('Fcst Walk'!$J$5:$J$69,MATCH($C5,'Fcst Walk'!$A$5:$A$69,0))-1 -> 0.027 | M5: =INDEX('Fcst Walk'!$R$5:$R$69,MATCH($C5,'Fcst Walk'!$A$5:$A$69,0))/INDEX('Fcst Walk'!$N$5:$N$69,MATCH($C5,'Fcst Walk'!$A$5:$A$69,0))-1 -> 0.028 | N5: =INDEX('Fcst Walk'!$J$5:$J$69,MATCH($C5,'Fcst Walk'!$A$5:$A$69,0))/$D5-1 -> 0.22313249 | O5: =INDEX('Fcst Walk'!$N$5:$N$69,MATCH($C5,'Fcst Walk'!$A$5:$A$69,0))/$D5-1 -> 0.25615707 | P5: =INDEX('Fcst Walk'!$R$5:$R$69,MATCH($C5,'Fcst Walk'!$A$5:$A$69,0))/$D5-1 -> 0.29132947 | Q5: =INDEX('Fcst Walk'!$AM$5:$AM$69,MATCH($C5,'Fcst Walk'!$A$5:$A$69,0)) -> 0 | R5: =INDEX('Fcst Walk'!$AN$5:$AN$69,MATCH($C5,'Fcst Walk'!$A$5:$A$69,0)) | S5: =AVERAGE(INDEX('Realpage - His. Rent Change'!$I$2:$AV$577,MATCH($C5,'Realpage - His. Rent Change'!$A$2:$A$577,0),0)) -> 0.051645 | U5: =IF(T5="",S5,AVERAGE(S5,T5)) -> 0.051645 | V5: =IF(H5>=0,0,-H5/U5) -> 0
B6: =ROW()-4 -> 2 | C6: Sioux Falls, SD-MN | D6: =SUMIFS('Realpage Data'!$R$2:$R$899,'Realpage Data'!$A$2:$A$899,$C6,'Realpage Data'!$F$2:$F$899,"Rent Roll (Rev/OSF)") -> 1.1192592 | E6: =SUMIFS('Realpage Data'!$R$2:$R$899,'Realpage Data'!$A$2:$A$899,$C6,'Realpage Data'!$F$2:$F$899,"Asking RPSF") -> 1.303 | F6: =SUMIFS('Realpage Data'!$R$2:$R$899,'Realpage Data'!$A$2:$A$899,$C6,'Realpage Data'!$F$2:$F$899,"Effective RPSF") -> 1.284 | G6: =E6/$D6-1 -> 0.16416289 | H6: =F6/$D6-1 -> 0.14718738 | I6: =SUMIFS('RP - Unit Starts'!$AC$2:$AC$451,'RP - Unit Starts'!$A$2:$A$451,$C6,'RP - Unit Starts'!$F$2:$F$451,"Annual Unit Starts")/SUMIFS('RP - Unit Starts'!$AC$2:$AC$451,'RP - Unit Starts'!$A$2:$A$451,$C6,'RP - Unit Starts'!$F$2:$F$451,"Existing Units") -> 0.0021427697 | J6: =SUMIFS('Realpage Data'!$V$2:$V$899,'Realpage Data'!$A$2:$A$899,$C6,'Realpage Data'!$F$2:$F$899,"Existing Units")/SUMIFS('Realpage Data'!$R$2:$R$899,'Realpage Data'!$A$2:$A$899,$C6,'Realpage Data'!$F$2:$F$899,"Existing Units")-1 -> 0.006550753 | K6: =INDEX('Fcst Walk'!$J$5:$J$69,MATCH($C6,'Fcst Walk'!$A$5:$A$69,0))/INDEX('Fcst Walk'!$F$5:$F$69,MATCH($C6,'Fcst Walk'!$A$5:$A$69,0))-1 -> 0.028 | L6: =INDEX('Fcst Walk'!$N$5:$N$69,MATCH($C6,'Fcst Walk'!$A$5:$A$69,0))/INDEX('Fcst Walk'!$J$5:$J$69,MATCH($C6,'Fcst Walk'!$A$5:$A$69,0))-1 -> 0.022 | M6: =INDEX('Fcst Walk'!$R$5:$R$69,MATCH($C6,'Fcst Walk'!$A$5:$A$69,0))/INDEX('Fcst Walk'!$N$5:$N$69,MATCH($C6,'Fcst Walk'!$A$5:$A$69,0))-1 -> 0.021 | N6: =INDEX('Fcst Walk'!$J$5:$J$69,MATCH($C6,'Fcst Walk'!$A$5:$A$69,0))/$D6-1 -> 0.17930862 | O6: =INDEX('Fcst Walk'!$N$5:$N$69,MATCH($C6,'Fcst Walk'!$A$5:$A$69,0))/$D6-1 -> 0.20525341 | P6: =INDEX('Fcst Walk'!$R$5:$R$69,MATCH($C6,'Fcst Walk'!$A$5:$A$69,0))/$D6-1 -> 0.23056374 | Q6: =INDEX('Fcst Walk'!$AM$5:$AM$69,MATCH($C6,'Fcst Walk'!$A$5:$A$69,0)) -> 0 | R6: =INDEX('Fcst Walk'!$AN$5:$AN$69,MATCH($C6,'Fcst Walk'!$A$5:$A$69,0)) | S6: =AVERAGE(INDEX('Realpage - His. Rent Change'!$I$2:$AV$577,MATCH($C6,'Realpage - His. Rent Change'!$A$2:$A$577,0),0)) -> 0.03717 | U6: =IF(T6="",S6,AVERAGE(S6,T6)) -> 0.03717 | V6: =IF(H6>=0,0,-H6/U6) -> 0
B7: =ROW()-4 -> 3 | C7: Milwaukee-Waukesha/Racine, WI | D7: =SUMIFS('Realpage Data'!$R$2:$R$899,'Realpage Data'!$A$2:$A$899,$C7,'Realpage Data'!$F$2:$F$899,"Rent Roll (Rev/OSF)") -> 1.6017733 | E7: =SUMIFS('Realpage Data'!$R$2:$R$899,'Realpage Data'!$A$2:$A$899,$C7,'Realpage Data'!$F$2:$F$899,"Asking RPSF") -> 1.819 | F7: =SUMIFS('Realpage Data'!$R$2:$R$899,'Realpage Data'!$A$2:$A$899,$C7,'Realpage Data'!$F$2:$F$899,"Effective RPSF") -> 1.807 | G7: =E7/$D7-1 -> 0.13561636 | H7: =F7/$D7-1 -> 0.12812466 | I7: =SUMIFS('RP - Unit Starts'!$AC$2:$AC$451,'RP - Unit Starts'!$A$2:$A$451,$C7,'RP - Unit Starts'!$F$2:$F$451,"Annual Unit Starts")/SUMIFS('RP - Unit Starts'!$AC$2:$AC$451,'RP - Unit Starts'!$A$2:$A$451,$C7,'RP - Unit Starts'!$F$2:$F$451,"Existing Units") -> 0.011136083 | J7: =SUMIFS('Realpage Data'!$V$2:$V$899,'Realpage Data'!$A$2:$A$899,$C7,'Realpage Data'!$F$2:$F$899,"Existing Units")/SUMIFS('Realpage Data'!$R$2:$R$899,'Realpage Data'!$A$2:$A$899,$C7,'Realpage Data'!$F$2:$F$899,"Existing Units")-1 -> 0.01303184 | K7: =INDEX('Fcst Walk'!$J$5:$J$69,MATCH($C7,'Fcst Walk'!$A$5:$A$69,0))/INDEX('Fcst Walk'!$F$5:$F$69,MATCH($C7,'Fcst Walk'!$A$5:$A$69,0))-1 -> 0.035 | L7: =INDEX('Fcst Walk'!$N$5:$N$69,MATCH($C7,'Fcst Walk'!$A$5:$A$69,0))/INDEX('Fcst Walk'!$J$5:$J$69,MATCH($C7,'Fcst Walk'!$A$5:$A$69,0))-1 -> 0.025 | M7: =INDEX('Fcst Walk'!$R$5:$R$69,MATCH($C7,'Fcst Walk'!$A$5:$A$69,0))/INDEX('Fcst Walk'!$N$5:$N$69,MATCH($C7,'Fcst Walk'!$A$5:$A$69,0))-1 -> 0.022 | N7: =INDEX('Fcst Walk'!$J$5:$J$69,MATCH($C7,'Fcst Walk'!$A$5:$A$69,0))/$D7-1 -> 0.16760903 | O7: =INDEX('Fcst Walk'!$N$5:$N$69,MATCH($C7,'Fcst Walk'!$A$5:$A$69,0))/$D7-1 -> 0.19679925 | P7: =INDEX('Fcst Walk'!$R$5:$R$69,MATCH($C7,'Fcst Walk'!$A$5:$A$69,0))/$D7-1 -> 0.22312884 | Q7: =INDEX('Fcst Walk'!$AM$5:$AM$69,MATCH($C7,'Fcst Walk'!$A$5:$A$69,0)) -> 0 | R7: =INDEX('Fcst Walk'!$AN$5:$AN$69,MATCH($C7,'Fcst Walk'!$A$5:$A$69,0)) | S7: =AVERAGE(INDEX('Realpage - His. Rent Change'!$I$2:$AV$577,MATCH($C7,'Realpage - His. Rent Change'!$A$2:$A$577,0),0)) -> 0.050155 | U7: =IF(T7="",S7,AVERAGE(S7,T7)) -> 0.050155 | V7: =IF(H7>=0,0,-H7/U7) -> 0
B8: =ROW()-4 -> 4 | C8: Reno, NV | D8: =SUMIFS('Realpage Data'!$R$2:$R$899,'Realpage Data'!$A$2:$A$899,$C8,'Realpage Data'!$F$2:$F$899,"Rent Roll (Rev/OSF)") -> 1.8196774 | E8: =SUMIFS('Realpage Data'!$R$2:$R$899,'Realpage Data'!$A$2:$A$899,$C8,'Realpage Data'!$F$2:$F$899,"Asking RPSF") -> 2.025 | F8: =SUMIFS('Realpage Data'!$R$2:$R$899,'Realpage Data'!$A$2:$A$899,$C8,'Realpage Data'!$F$2:$F$899,"Effective RPSF") -> 2.008 | G8: =E8/$D8-1 -> 0.11283464 | H8: =F8/$D8-1 -> 0.10349233 | I8: =SUMIFS('RP - Unit Starts'!$AC$2:$AC$451,'RP - Unit Starts'!$A$2:$A$451,$C8,'RP - Unit Starts'!$F$2:$F$451,"Annual Unit Starts")/SUMIFS('RP - Unit Starts'!$AC$2:$AC$451,'RP - Unit Starts'!$A$2:$A$451,$C8,'RP - Unit Starts'!$F$2:$F$451,"Existing Units") -> 0.023921244 | J8: =SUMIFS('Realpage Data'!$V$2:$V$899,'Realpage Data'!$A$2:$A$899,$C8,'Realpage Data'!$F$2:$F$899,"Existing Units")/SUMIFS('Realpage Data'!$R$2:$R$899,'Realpage Data'!$A$2:$A$899,$C8,'Realpage Data'!$F$2:$F$899,"Existing Units")-1 -> 0.0056306928 | K8: =INDEX('Fcst Walk'!$J$5:$J$69,MATCH($C8,'Fcst Walk'!$A$5:$A$69,0))/INDEX('Fcst Walk'!$F$5:$F$69,MATCH($C8,'Fcst Walk'!$A$5:$A$69,0))-1 -> 0.034 | L8: =INDEX('Fcst Walk'!$N$5:$N$69,MATCH($C8,'Fcst Walk'!$A$5:$A$69,0))/INDEX('Fcst Walk'!$J$5:$J$69,MATCH($C8,'Fcst Walk'!$A$5:$A$69,0))-1 -> 0.037 | M8: =INDEX('Fcst Walk'!$R$5:$R$69,MATCH($C8,'Fcst Walk'!$A$5:$A$69,0))/INDEX('Fcst Walk'!$N$5:$N$69,MATCH($C8,'Fcst Walk'!$A$5:$A$69,0))-1 -> 0.05 | N8: =INDEX('Fcst Walk'!$J$5:$J$69,MATCH($C8,'Fcst Walk'!$A$5:$A$69,0))/$D8-1 -> 0.14101107 | O8: =INDEX('Fcst Walk'!$N$5:$N$69,MATCH($C8,'Fcst Walk'!$A$5:$A$69,0))/$D8-1 -> 0.18322847 | P8: =INDEX('Fcst Walk'!$R$5:$R$69,MATCH($C8,'Fcst Walk'!$A$5:$A$69,0))/$D8-1 -> 0.2423899 | Q8: =INDEX('Fcst Walk'!$AM$5:$AM$69,MATCH($C8,'Fcst Walk'!$A$5:$A$69,0)) -> 0 | R8: =INDEX('Fcst Walk'!$AN$5:$AN$69,MATCH($C8,'Fcst Walk'!$A$5:$A$69,0)) | S8: =AVERAGE(INDEX('Realpage - His. Rent Change'!$I$2:$AV$577,MATCH($C8,'Realpage - His. Rent Change'!$A$2:$A$577,0),0)) -> 0.068635 | U8: =IF(T8="",S8,AVERAGE(S8,T8)) -> 0.068635 | V8: =IF(H8>=0,0,-H8/U8) -> 0
B9: =ROW()-4 -> 5 | C9: Wichita, KS | D9: =SUMIFS('Realpage Data'!$R$2:$R$899,'Realpage Data'!$A$2:$A$899,$C9,'Realpage Data'!$F$2:$F$899,"Rent Roll (Rev/OSF)") -> 1.0723395 | E9: =SUMIFS('Realpage Data'!$R$2:$R$899,'Realpage Data'!$A$2:$A$899,$C9,'Realpage Data'!$F$2:$F$899,"Asking RPSF") -> 1.176 | F9: =SUMIFS('Realpage Data'!$R$2:$R$899,'Realpage Data'!$A$2:$A$899,$C9,'Realpage Data'!$F$2:$F$899,"Effective RPSF") -> 1.173 | G9: =E9/$D9-1 -> 0.096667613 | H9: =F9/$D9-1 -> 0.093869991 | I9: =SUMIFS('RP - Unit Starts'!$AC$2:$AC$451,'RP - Unit Starts'!$A$2:$A$451,$C9,'RP - Unit Starts'!$F$2:$F$451,"Annual Unit Starts")/SUMIFS('RP - Unit Starts'!$AC$2:$AC$451,'RP - Unit Starts'!$A$2:$A$451,$C9,'RP - Unit Starts'!$F$2:$F$451,"Existing Units") -> 0.0038874164 | J9: =SUMIFS('Realpage Data'!$V$2:$V$899,'Realpage Data'!$A$2:$A$899,$C9,'Realpage Data'!$F$2:$F$899,"Existing Units")/SUMIFS('Realpage Data'!$R$2:$R$899,'Realpage Data'!$A$2:$A$899,$C9,'Realpage Data'!$F$2:$F$899,"Existing Units")-1 -> 0.0081534772 | K9: =INDEX('Fcst Walk'!$J$5:$J$69,MATCH($C9,'Fcst Walk'!$A$5:$A$69,0))/INDEX('Fcst Walk'!$F$5:$F$69,MATCH($C9,'Fcst Walk'!$A$5:$A$69,0))-1 -> 0.025 | L9: =INDEX('Fcst Walk'!$N$5:$N$69,MATCH($C9,'Fcst Walk'!$A$5:$A$69,0))/INDEX('Fcst Walk'!$J$5:$J$69,MATCH($C9,'Fcst Walk'!$A$5:$A$69,0))-1 -> 0.026 | M9: =INDEX('Fcst Walk'!$R$5:$R$69,MATCH($C9,'Fcst Walk'!$A$5:$A$69,0))/INDEX('Fcst Walk'!$N$5:$N$69,MATCH($C9,'Fcst Walk'!$A$5:$A$69,0))-1 -> 0.026 | N9: =INDEX('Fcst Walk'!$J$5:$J$69,MATCH($C9,'Fcst Walk'!$A$5:$A$69,0))/$D9-1 -> 0.12121674 | O9: =INDEX('Fcst Walk'!$N$5:$N$69,MATCH($C9,'Fcst Walk'!$A$5:$A$69,0))/$D9-1 -> 0.15036838 | P9: =INDEX('Fcst Walk'!$R$5:$R$69,MATCH($C9,'Fcst Walk'!$A$5:$A$69,0))/$D9-1 -> 0.18027795 | Q9: =INDEX('Fcst Walk'!$AM$5:$AM$69,MATCH($C9,'Fcst Walk'!$A$5:$A$69,0)) -> 0 | R9: =INDEX('Fcst Walk'!$AN$5:$AN$69,MATCH($C9,'Fcst Walk'!$A$5:$A$69,0)) | S9: =AVERAGE(INDEX('Realpage - His. Rent Change'!$I$2:$AV$577,MATCH($C9,'Realpage - His. Rent Change'!$A$2:$A$577,0),0)) -> 0.0425925 | U9: =IF(T9="",S9,AVERAGE(S9,T9)) -> 0.0425925 | V9: =IF(H9>=0,0,-H9/U9) -> 0
B10: =ROW()-4 -> 6 | C10: Salt Lake City/Ogden/Brigham City, UT-ID | D10: =SUMIFS('Realpage Data'!$R$2:$R$899,'Realpage Data'!$A$2:$A$899,$C10,'Realpage Data'!$F$2:$F$899,"Rent Roll (Rev/OSF)") -> 1.5782176 | E10: =SUMIFS('Realpage Data'!$R$2:$R$899,'Realpage Data'!$A$2:$A$899,$C10,'Realpage Data'!$F$2:$F$899,"Asking RPSF") -> 1.744 | F10: =SUMIFS('Realpage Data'!$R$2:$R$899,'Realpage Data'!$A$2:$A$899,$C10,'Realpage Data'!$F$2:$F$899,"Effective RPSF") -> 1.695 | G10: =E10/$D10-1 -> 0.10504407 | H10: =F10/$D10-1 -> 0.073996388 | I10: =SUMIFS('RP - Unit Starts'!$AC$2:$AC$451,'RP - Unit Starts'!$A$2:$A$451,$C10,'RP - Unit Starts'!$F$2:$F$451,"Annual Unit Starts")/SUMIFS('RP - Unit Starts'!$AC$2:$AC$451,'RP - Unit Starts'!$A$2:$A$451,$C10,'RP - Unit Starts'!$F$2:$F$451,"Existing Units") -> 0.011486296 | J10: =SUMIFS('Realpage Data'!$V$2:$V$899,'Realpage Data'!$A$2:$A$899,$C10,'Realpage Data'!$F$2:$F$899,"Existing Units")/SUMIFS('Realpage Data'!$R$2:$R$899,'Realpage Data'!$A$2:$A$899,$C10,'Realpage Data'!$F$2:$F$899,"Existing Units")-1 -> 0.027027409 | K10: =INDEX('Fcst Walk'!$J$5:$J$69,MATCH($C10,'Fcst Walk'!$A$5:$A$69,0))/INDEX('Fcst Walk'!$F$5:$F$69,MATCH($C10,'Fcst Walk'!$A$5:$A$69,0))-1 -> 0.021 | L10: =INDEX('Fcst Walk'!$N$5:$N$69,MATCH($C10,'Fcst Walk'!$A$5:$A$69,0))/INDEX('Fcst Walk'!$J$5:$J$69,MATCH($C10,'Fcst Walk'!$A$5:$A$69,0))-1 -> 0.023 | M10: =INDEX('Fcst Walk'!$R$5:$R$69,MATCH($C10,'Fcst Walk'!$A$5:$A$69,0))/INDEX('Fcst Walk'!$N$5:$N$69,MATCH($C10,'Fcst Walk'!$A$5:$A$69,0))-1 -> 0.024 | N10: =INDEX('Fcst Walk'!$J$5:$J$69,MATCH($C10,'Fcst Walk'!$A$5:$A$69,0))/$D10-1 -> 0.096550312 | O10: =INDEX('Fcst Walk'!$N$5:$N$69,MATCH($C10,'Fcst Walk'!$A$5:$A$69,0))/$D10-1 -> 0.12177097 | P10: =INDEX('Fcst Walk'!$R$5:$R$69,MATCH($C10,'Fcst Walk'!$A$5:$A$69,0))/$D10-1 -> 0.14869347 | Q10: =INDEX('Fcst Walk'!$AM$5:$AM$69,MATCH($C10,'Fcst Walk'!$A$5:$A$69,0)) -> 0 | R10: =INDEX('Fcst Walk'!$AN$5:$AN$69,MATCH($C10,'Fcst Walk'!$A$5:$A$69,0)) | S10: =AVERAGE(INDEX('Realpage - His. Rent Change'!$I$2:$AV$577,MATCH($C10,'Realpage - His. Rent Change'!$A$2:$A$577,0),0)) -> 0.05343 | T10: 0.0423 | U10: =IF(T10="",S10,AVERAGE(S10,T10)) -> 0.047865 | V10: =IF(H10>=0,0,-H10/U10) -> 0
B11: =ROW()-4 -> 7 | C11: Port St. Lucie/Sebastian-Vero Beach, FL | D11: =SUMIFS('Realpage Data'!$R$2:$R$899,'Realpage Data'!$A$2:$A$899,$C11,'Realpage Data'!$F$2:$F$899,"Rent Roll (Rev/OSF)") -> 1.763379 | E11: =SUMIFS('Realpage Data'!$R$2:$R$899,'Realpage Data'!$A$2:$A$899,$C11,'Realpage Data'!$F$2:$F$899,"Asking RPSF") -> 1.923 | F11: =SUMIFS('Realpage Data'!$R$2:$R$899,'Realpage Data'!$A$2:$A$899,$C11,'Realpage Data'!$F$2:$F$899,"Effective RPSF") -> 1.877 | G11: =E11/$D11-1 -> 0.090519951 | H11: =F11/$D11-1 -> 0.06443367 | I11: =SUMIFS('RP - Unit Starts'!$AC$2:$AC$451,'RP - Unit Starts'!$A$2:$A$451,$C11,'RP - Unit Starts'!$F$2:$F$451,"Annual Unit Starts")/SUMIFS('RP - Unit Starts'!$AC$2:$AC$451,'RP - Unit Starts'!$A$2:$A$451,$C11,'RP - Unit Starts'!$F$2:$F$451,"Existing Units") -> 0.0091623434 | J11: =SUMIFS('Realpage Data'!$V$2:$V$899,'Realpage Data'!$A$2:$A$899,$C11,'Realpage Data'!$F$2:$F$899,"Existing Units")/SUMIFS('Realpage Data'!$R$2:$R$899,'Realpage Data'!$A$2:$A$899,$C11,'Realpage Data'!$F$2:$F$899,"Existing Units")-1 -> 0.011862504 | K11: =INDEX('Fcst Walk'!$J$5:$J$69,MATCH($C11,'Fcst Walk'!$A$5:$A$69,0))/INDEX('Fcst Walk'!$F$5:$F$69,MATCH($C11,'Fcst Walk'!$A$5:$A$69,0))-1 -> 0.02 | L11: =INDEX('Fcst Walk'!$N$5:$N$69,MATCH($C11,'Fcst Walk'!$A$5:$A$69,0))/INDEX('Fcst Walk'!$J$5:$J$69,MATCH($C11,'Fcst Walk'!$A$5:$A$69,0))-1 -> 0.039 | M11: =INDEX('Fcst Walk'!$R$5:$R$69,MATCH($C11,'Fcst Walk'!$A$5:$A$69,0))/INDEX('Fcst Walk'!$N$5:$N$69,MATCH($C11,'Fcst Walk'!$A$5:$A$69,0))-1 -> 0.042 | N11: =INDEX('Fcst Walk'!$J$5:$J$69,MATCH($C11,'Fcst Walk'!$A$5:$A$69,0))/$D11-1 -> 0.085722343 | O11: =INDEX('Fcst Walk'!$N$5:$N$69,MATCH($C11,'Fcst Walk'!$A$5:$A$69,0))/$D11-1 -> 0.12806551 | P11: =INDEX('Fcst Walk'!$R$5:$R$69,MATCH($C11,'Fcst Walk'!$A$5:$A$69,0))/$D11-1 -> 0.17544427 | Q11: =INDEX('Fcst Walk'!$AM$5:$AM$69,MATCH($C11,'Fcst Walk'!$A$5:$A$69,0)) -> 0 | R11: =INDEX('Fcst Walk'!$AN$5:$AN$69,MATCH($C11,'Fcst Walk'!$A$5:$A$69,0)) | S11: =AVERAGE(INDEX('Realpage - His. Rent Change'!$I$2:$AV$577,MATCH($C11,'Realpage - His. Rent Change'!$A$2:$A$577,0),0)) -> 0.07217 | U11: =IF(T11="",S11,AVERAGE(S11,T11)) -> 0.07217 | V11: =IF(H11>=0,0,-H11/U11) -> 0
B12: =ROW()-4 -> 8 | C12: Columbus, OH | D12: =SUMIFS('Realpage Data'!$R$2:$R$899,'Realpage Data'!$A$2:$A$899,$C12,'Realpage Data'!$F$2:$F$899,"Rent Roll (Rev/OSF)") -> 1.4232332 | E12: =SUMIFS('Realpage Data'!$R$2:$R$899,'Realpage Data'!$A$2:$A$899,$C12,'Realpage Data'!$F$2:$F$899,"Asking RPSF") -> 1.511 | F12: =SUMIFS('Realpage Data'!$R$2:$R$899,'Realpage Data'!$A$2:$A$899,$C12,'Realpage Data'!$F$2:$F$899,"Effective RPSF") -> 1.494 | G12: =E12/$D12-1 -> 0.061667189 | H12: =F12/$D12-1 -> 0.049722555 | I12: =SUMIFS('RP - Unit Starts'!$AC$2:$AC$451,'RP - Unit Starts'!$A$2:$A$451,$C12,'RP - Unit Starts'!$F$2:$F$451,"Annual Unit Starts")/SUMIFS('RP - Unit Starts'!$AC$2:$AC$451,'RP - Unit Starts'!$A$2:$A$451,$C12,'RP - Unit Starts'!$F$2:$F$451,"Existing Units") -> 0.018135846 | J12: =SUMIFS('Realpage Data'!$V$2:$V$899,'Realpage Data'!$A$2:$A$899,$C12,'Realpage Data'!$F$2:$F$899,"Existing Units")/SUMIFS('Realpage Data'!$R$2:$R$899,'Realpage Data'!$A$2:$A$899,$C12,'Realpage Data'!$F$2:$F$899,"Existing Units")-1 -> 0.02854986 | K12: =INDEX('Fcst Walk'!$J$5:$J$69,MATCH($C12,'Fcst Walk'!$A$5:$A$69,0))/INDEX('Fcst Walk'!$F$5:$F$69,MATCH($C12,'Fcst Walk'!$A$5:$A$69,0))-1 -> 0.021 | L12: =INDEX('Fcst Walk'!$N$5:$N$69,MATCH($C12,'Fcst Walk'!$A$5:$A$69,0))/INDEX('Fcst Walk'!$J$5:$J$69,MATCH($C12,'Fcst Walk'!$A$5:$A$69,0))-1 -> 0.031 | M12: =INDEX('Fcst Walk'!$R$5:$R$69,MATCH($C12,'Fcst Walk'!$A$5:$A$69,0))/INDEX('Fcst Walk'!$N$5:$N$69,MATCH($C12,'Fcst Walk'!$A$5:$A$69,0))-1 -> 0.031 | N12: =INDEX('Fcst Walk'!$J$5:$J$69,MATCH($C12,'Fcst Walk'!$A$5:$A$69,0))/$D12-1 -> 0.071766729 | O12: =INDEX('Fcst Walk'!$N$5:$N$69,MATCH($C12,'Fcst Walk'!$A$5:$A$69,0))/$D12-1 -> 0.1049915 | P12: =INDEX('Fcst Walk'!$R$5:$R$69,MATCH($C12,'Fcst Walk'!$A$5:$A$69,0))/$D12-1 -> 0.13924623 | Q12: =INDEX('Fcst Walk'!$AM$5:$AM$69,MATCH($C12,'Fcst Walk'!$A$5:$A$69,0)) -> 0 | R12: =INDEX('Fcst Walk'!$AN$5:$AN$69,MATCH($C12,'Fcst Walk'!$A$5:$A$69,0)) | S12: =AVERAGE(INDEX('Realpage - His. Rent Change'!$I$2:$AV$577,MATCH($C12,'Realpage - His. Rent Change'!$A$2:$A$577,0),0)) -> 0.057095 | T12: 0.044 | U12: =IF(T12="",S12,AVERAGE(S12,T12)) -> 0.0505475 | V12: =IF(H12>=0,0,-H12/U12) -> 0
B13: =ROW()-4 -> 9 | C13: Boise City, ID | D13: =SUMIFS('Realpage Data'!$R$2:$R$899,'Realpage Data'!$A$2:$A$899,$C13,'Realpage Data'!$F$2:$F$899,"Rent Roll (Rev/OSF)") -> 1.7432193 | E13: =SUMIFS('Realpage Data'!$R$2:$R$899,'Realpage Data'!$A$2:$A$899,$C13,'Realpage Data'!$F$2:$F$899,"Asking RPSF") -> 1.838 | F13: =SUMIFS('Realpage Data'!$R$2:$R$899,'Realpage Data'!$A$2:$A$899,$C13,'Realpage Data'!$F$2:$F$899,"Effective RPSF") -> 1.824 | G13: =E13/$D13-1 -> 0.054371047 | H13: =F13/$D13-1 -> 0.046339929 | I13: =SUMIFS('RP - Unit Starts'!$AC$2:$AC$451,'RP - Unit Starts'!$A$2:$A$451,$C13,'RP - Unit Starts'!$F$2:$F$451,"Annual Unit Starts")/SUMIFS('RP - Unit Starts'!$AC$2:$AC$451,'RP - Unit Starts'!$A$2:$A$451,$C13,'RP - Unit Starts'!$F$2:$F$451,"Existing Units") -> 0.011981268 | J13: =SUMIFS('Realpage Data'!$V$2:$V$899,'Realpage Data'!$A$2:$A$899,$C13,'Realpage Data'!$F$2:$F$899,"Existing Units")/SUMIFS('Realpage Data'!$R$2:$R$899,'Realpage Data'!$A$2:$A$899,$C13,'Realpage Data'!$F$2:$F$899,"Existing Units")-1 -> 0.014347631 | K13: =INDEX('Fcst Walk'!$J$5:$J$69,MATCH($C13,'Fcst Walk'!$A$5:$A$69,0))/INDEX('Fcst Walk'!$F$5:$F$69,MATCH($C13,'Fcst Walk'!$A$5:$A$69,0))-1 -> 0.055 | L13: =INDEX('Fcst Walk'!$N$5:$N$69,MATCH($C13,'Fcst Walk'!$A$5:$A$69,0))/INDEX('Fcst Walk'!$J$5:$J$69,MATCH($C13,'Fcst Walk'!$A$5:$A$69,0))-1 -> 0.044 | M13: =INDEX('Fcst Walk'!$R$5:$R$69,MATCH($C13,'Fcst Walk'!$A$5:$A$69,0))/INDEX('Fcst Walk'!$N$5:$N$69,MATCH($C13,'Fcst Walk'!$A$5:$A$69,0))-1 -> 0.044 | N13: =INDEX('Fcst Walk'!$J$5:$J$69,MATCH($C13,'Fcst Walk'!$A$5:$A$69,0))/$D13-1 -> 0.10388863 | O13: =INDEX('Fcst Walk'!$N$5:$N$69,MATCH($C13,'Fcst Walk'!$A$5:$A$69,0))/$D13-1 -> 0.15245972 | P13: =INDEX('Fcst Walk'!$R$5:$R$69,MATCH($C13,'Fcst Walk'!$A$5:$A$69,0))/$D13-1 -> 0.20316795 | Q13: =INDEX('Fcst Walk'!$AM$5:$AM$69,MATCH($C13,'Fcst Walk'!$A$5:$A$69,0)) -> 0 | R13: =INDEX('Fcst Walk'!$AN$5:$AN$69,MATCH($C13,'Fcst Walk'!$A$5:$A$69,0)) | S13: =AVERAGE(INDEX('Realpage - His. Rent Change'!$I$2:$AV$577,MATCH($C13,'Realpage - His. Rent Change'!$A$2:$A$577,0),0)) -> 0.0689675 | U13: =IF(T13="",S13,AVERAGE(S13,T13)) -> 0.0689675 | V13: =IF(H13>=0,0,-H13/U13) -> 0
B14: =ROW()-4 -> 10 | C14: Richmond, VA | D14: =SUMIFS('Realpage Data'!$R$2:$R$899,'Realpage Data'!$A$2:$A$899,$C14,'Realpage Data'!$F$2:$F$899,"Rent Roll (Rev/OSF)") -> 1.7161987 | E14: =SUMIFS('Realpage Data'!$R$2:$R$899,'Realpage Data'!$A$2:$A$899,$C14,'Realpage Data'!$F$2:$F$899,"Asking RPSF") -> 1.812 | F14: =SUMIFS('Realpage Data'!$R$2:$R$899,'Realpage Data'!$A$2:$A$899,$C14,'Realpage Data'!$F$2:$F$899,"Effective RPSF") -> 1.793 | G14: =E14/$D14-1 -> 0.055821774 | H14: =F14/$D14-1 -> 0.044750795 | I14: =SUMIFS('RP - Unit Starts'!$AC$2:$AC$451,'RP - Unit Starts'!$A$2:$A$451,$C14,'RP - Unit Starts'!$F$2:$F$451,"Annual Unit Starts")/SUMIFS('RP - Unit Starts'!$AC$2:$AC$451,'RP - Unit Starts'!$A$2:$A$451,$C14,'RP - Unit Starts'!$F$2:$F$451,"Existing Units") -> 0.013758423 | J14: =SUMIFS('Realpage Data'!$V$2:$V$899,'Realpage Data'!$A$2:$A$899,$C14,'Realpage Data'!$F$2:$F$899,"Existing Units")/SUMIFS('Realpage Data'!$R$2:$R$899,'Realpage Data'!$A$2:$A$899,$C14,'Realpage Data'!$F$2:$F$899,"Existing Units")-1 -> 0.030935706 | K14: =INDEX('Fcst Walk'!$J$5:$J$69,MATCH($C14,'Fcst Walk'!$A$5:$A$69,0))/INDEX('Fcst Walk'!$F$5:$F$69,MATCH($C14,'Fcst Walk'!$A$5:$A$69,0))-1 -> 0.021 | L14: =INDEX('Fcst Walk'!$N$5:$N$69,MATCH($C14,'Fcst Walk'!$A$5:$A$69,0))/INDEX('Fcst Walk'!$J$5:$J$69,MATCH($C14,'Fcst Walk'!$A$5:$A$69,0))-1 -> 0.036 | M14: =INDEX('Fcst Walk'!$R$5:$R$69,MATCH($C14,'Fcst Walk'!$A$5:$A$69,0))/INDEX('Fcst Walk'!$N$5:$N$69,MATCH($C14,'Fcst Walk'!$A$5:$A$69,0))-1 -> 0.033 | N14: =INDEX('Fcst Walk'!$J$5:$J$69,MATCH($C14,'Fcst Walk'!$A$5:$A$69,0))/$D14-1 -> 0.066690562 | O14: =INDEX('Fcst Walk'!$N$5:$N$69,MATCH($C14,'Fcst Walk'!$A$5:$A$69,0))/$D14-1 -> 0.10509142 | P14: =INDEX('Fcst Walk'!$R$5:$R$69,MATCH($C14,'Fcst Walk'!$A$5:$A$69,0))/$D14-1 -> 0.14155944 | Q14: =INDEX('Fcst Walk'!$AM$5:$AM$69,MATCH($C14,'Fcst Walk'!$A$5:$A$69,0)) -> 0 | R14: =INDEX('Fcst Walk'!$AN$5:$AN$69,MATCH($C14,'Fcst Walk'!$A$5:$A$69,0)) | S14: =AVERAGE(INDEX('Realpage - His. Rent Change'!$I$2:$AV$577,MATCH($C14,'Realpage - His. Rent Change'!$A$2:$A$577,0),0)) -> 0.0551825 | T14: 0.0451 | U14: =IF(T14="",S14,AVERAGE(S14,T14)) -> 0.05014125 | V14: =IF(H14>=0,0,-H14/U14) -> 0
B15: =ROW()-4 -> 11 | C15: Virginia Beach-Chesapeake-Norfolk, VA-NC | D15: =SUMIFS('Realpage Data'!$R$2:$R$899,'Realpage Data'!$A$2:$A$899,$C15,'Realpage Data'!$F$2:$F$899,"Rent Roll (Rev/OSF)") -> 1.6742534 | E15: =SUMIFS('Realpage Data'!$R$2:$R$899,'Realpage Data'!$A$2:$A$899,$C15,'Realpage Data'!$F$2:$F$899,"Asking RPSF") -> 1.752 | F15: =SUMIFS('Realpage Data'!$R$2:$R$899,'Realpage Data'!$A$2:$A$899,$C15,'Realpage Data'!$F$2:$F$899,"Effective RPSF") -> 1.746 | G15: =E15/$D15-1 -> 0.046436552 | H15: =F15/$D15-1 -> 0.042852865 | I15: =SUMIFS('RP - Unit Starts'!$AC$2:$AC$451,'RP - Unit Starts'!$A$2:$A$451,$C15,'RP - Unit Starts'!$F$2:$F$451,"Annual Unit Starts")/SUMIFS('RP - Unit Starts'!$AC$2:$AC$451,'RP - Unit Starts'!$A$2:$A$451,$C15,'RP - Unit Starts'!$F$2:$F$451,"Existing Units") -> 0.0039863635 | J15: =SUMIFS('Realpage Data'!$V$2:$V$899,'Realpage Data'!$A$2:$A$899,$C15,'Realpage Data'!$F$2:$F$899,"Existing Units")/SUMIFS('Realpage Data'!$R$2:$R$899,'Realpage Data'!$A$2:$A$899,$C15,'Realpage Data'!$F$2:$F$899,"Existing Units")-1 -> 0.0026892674 | K15: =INDEX('Fcst Walk'!$J$5:$J$69,MATCH($C15,'Fcst Walk'!$A$5:$A$69,0))/INDEX('Fcst Walk'!$F$5:$F$69,MATCH($C15,'Fcst Walk'!$A$5:$A$69,0))-1 -> 0.023 | L15: =INDEX('Fcst Walk'!$N$5:$N$69,MATCH($C15,'Fcst Walk'!$A$5:$A$69,0))/INDEX('Fcst Walk'!$J$5:$J$69,MATCH($C15,'Fcst Walk'!$A$5:$A$69,0))-1 -> 0.021 | M15: =INDEX('Fcst Walk'!$R$5:$R$69,MATCH($C15,'Fcst Walk'!$A$5:$A$69,0))/INDEX('Fcst Walk'!$N$5:$N$69,MATCH($C15,'Fcst Walk'!$A$5:$A$69,0))-1 -> 0.019 | N15: =INDEX('Fcst Walk'!$J$5:$J$69,MATCH($C15,'Fcst Walk'!$A$5:$A$69,0))/$D15-1 -> 0.066838481 | O15: =INDEX('Fcst Walk'!$N$5:$N$69,MATCH($C15,'Fcst Walk'!$A$5:$A$69,0))/$D15-1 -> 0.089242089 | P15: =INDEX('Fcst Walk'!$R$5:$R$69,MATCH($C15,'Fcst Walk'!$A$5:$A$69,0))/$D15-1 -> 0.10993769 | Q15: =INDEX('Fcst Walk'!$AM$5:$AM$69,MATCH($C15,'Fcst Walk'!$A$5:$A$69,0)) -> 0 | R15: =INDEX('Fcst Walk'!$AN$5:$AN$69,MATCH($C15,'Fcst Walk'!$A$5:$A$69,0)) | S15: =AVERAGE(INDEX('Realpage - His. Rent Change'!$I$2:$AV$577,MATCH($C15,'Realpage - His. Rent Change'!$A$2:$A$577,0),0)) -> 0.04796 | U15: =IF(T15="",S15,AVERAGE(S15,T15)) -> 0.04796 | V15: =IF(H15>=0,0,-H15/U15) -> 0
B16: =ROW()-4 -> 12 | C16: Miami-Miami Beach-Kendall, FL | D16: =SUMIFS('Realpage Data'!$R$2:$R$899,'Realpage Data'!$A$2:$A$899,$C16,'Realpage Data'!$F$2:$F$899,"Rent Roll (Rev/OSF)") -> 2.8346507 | E16: =SUMIFS('Realpage Data'!$R$2:$R$899,'Realpage Data'!$A$2:$A$899,$C16,'Realpage Data'!$F$2:$F$899,"Asking RPSF") -> 3.003 | F16: =SUMIFS('Realpage Data'!$R$2:$R$899,'Realpage Data'!$A$2:$A$899,$C16,'Realpage Data'!$F$2:$F$899,"Effective RPSF") -> 2.946 | G16: =E16/$D16-1 -> 0.059389778 | H16: =F16/$D16-1 -> 0.03928148 | I16: =SUMIFS('RP - Unit Starts'!$AC$2:$AC$451,'RP - Unit Starts'!$A$2:$A$451,$C16,'RP - Unit Starts'!$F$2:$F$451,"Annual Unit Starts")/SUMIFS('RP - Unit Starts'!$AC$2:$AC$451,'RP - Unit Starts'!$A$2:$A$451,$C16,'RP - Unit Starts'!$F$2:$F$451,"Existing Units") -> 0.024001428 | J16: =SUMIFS('Realpage Data'!$V$2:$V$899,'Realpage Data'!$A$2:$A$899,$C16,'Realpage Data'!$F$2:$F$899,"Existing Units")/SUMIFS('Realpage Data'!$R$2:$R$899,'Realpage Data'!$A$2:$A$899,$C16,'Realpage Data'!$F$2:$F$899,"Existing Units")-1 -> 0.019251805 | K16: =INDEX('Fcst Walk'!$J$5:$J$69,MATCH($C16,'Fcst Walk'!$A$5:$A$69,0))/INDEX('Fcst Walk'!$F$5:$F$69,MATCH($C16,'Fcst Walk'!$A$5:$A$69,0))-1 -> 0.034 | L16: =INDEX('Fcst Walk'!$N$5:$N$69,MATCH($C16,'Fcst Walk'!$A$5:$A$69,0))/INDEX('Fcst Walk'!$J$5:$J$69,MATCH($C16,'Fcst Walk'!$A$5:$A$69,0))-1 -> 0.032 | M16: =INDEX('Fcst Walk'!$R$5:$R$69,MATCH($C16,'Fcst Walk'!$A$5:$A$69,0))/INDEX('Fcst Walk'!$N$5:$N$69,MATCH($C16,'Fcst Walk'!$A$5:$A$69,0))-1 -> 0.038 | N16: =INDEX('Fcst Walk'!$J$5:$J$69,MATCH($C16,'Fcst Walk'!$A$5:$A$69,0))/$D16-1 -> 0.074617051 | O16: =INDEX('Fcst Walk'!$N$5:$N$69,MATCH($C16,'Fcst Walk'!$A$5:$A$69,0))/$D16-1 -> 0.1090048 | P16: =INDEX('Fcst Walk'!$R$5:$R$69,MATCH($C16,'Fcst Walk'!$A$5:$A$69,0))/$D16-1 -> 0.15114698 | Q16: =INDEX('Fcst Walk'!$AM$5:$AM$69,MATCH($C16,'Fcst Walk'!$A$5:$A$69,0)) -> 0 | R16: =INDEX('Fcst Walk'!$AN$5:$AN$69,MATCH($C16,'Fcst Walk'!$A$5:$A$69,0)) | S16: =AVERAGE(INDEX('Realpage - His. Rent Change'!$I$2:$AV$577,MATCH($C16,'Realpage - His. Rent Change'!$A$2:$A$577,0),0)) -> 0.060015 | U16: =IF(T16="",S16,AVERAGE(S16,T16)) -> 0.060015 | V16: =IF(H16>=0,0,-H16/U16) -> 0
B17: =ROW()-4 -> 13 | C17: Omaha, NE-IA | D17: =SUMIFS('Realpage Data'!$R$2:$R$899,'Realpage Data'!$A$2:$A$899,$C17,'Realpage Data'!$F$2:$F$899,"Rent Roll (Rev/OSF)") -> 1.3838771 | E17: =SUMIFS('Realpage Data'!$R$2:$R$899,'Realpage Data'!$A$2:$A$899,$C17,'Realpage Data'!$F$2:$F$899,"Asking RPSF") -> 1.445 | F17: =SUMIFS('Realpage Data'!$R$2:$R$899,'Realpage Data'!$A$2:$A$899,$C17,'Realpage Data'!$F$2:$F$899,"Effective RPSF") -> 1.431 | G17: =E17/$D17-1 -> 0.04416784 | H17: =F17/$D17-1 -> 0.034051335 | I17: =SUMIFS('RP - Unit Starts'!$AC$2:$AC$451,'RP - Unit Starts'!$A$2:$A$451,$C17,'RP - Unit Starts'!$F$2:$F$451,"Annual Unit Starts")/SUMIFS('RP - Unit Starts'!$AC$2:$AC$451,'RP - Unit Starts'!$A$2:$A$451,$C17,'RP - Unit Starts'!$F$2:$F$451,"Existing Units") -> 0.03111465 | J17: =SUMIFS('Realpage Data'!$V$2:$V$899,'Realpage Data'!$A$2:$A$899,$C17,'Realpage Data'!$F$2:$F$899,"Existing Units")/SUMIFS('Realpage Data'!$R$2:$R$899,'Realpage Data'!$A$2:$A$899,$C17,'Realpage Data'!$F$2:$F$899,"Existing Units")-1 -> 0.035063694 | K17: =INDEX('Fcst Walk'!$J$5:$J$69,MATCH($C17,'Fcst Walk'!$A$5:$A$69,0))/INDEX('Fcst Walk'!$F$5:$F$69,MATCH($C17,'Fcst Walk'!$A$5:$A$69,0))-1 -> 0.028 | L17: =INDEX('Fcst Walk'!$N$5:$N$69,MATCH($C17,'Fcst Walk'!$A$5:$A$69,0))/INDEX('Fcst Walk'!$J$5:$J$69,MATCH($C17,'Fcst Walk'!$A$5:$A$69,0))-1 -> 0.029 | M17: =INDEX('Fcst Walk'!$R$5:$R$69,MATCH($C17,'Fcst Walk'!$A$5:$A$69,0))/INDEX('Fcst Walk'!$N$5:$N$69,MATCH($C17,'Fcst Walk'!$A$5:$A$69,0))-1 -> 0.03 | N17: =INDEX('Fcst Walk'!$J$5:$J$69,MATCH($C17,'Fcst Walk'!$A$5:$A$69,0))/$D17-1 -> 0.063004772 | O17: =INDEX('Fcst Walk'!$N$5:$N$69,MATCH($C17,'Fcst Walk'!$A$5:$A$69,0))/$D17-1 -> 0.093831911 | P17: =INDEX('Fcst Walk'!$R$5:$R$69,MATCH($C17,'Fcst Walk'!$A$5:$A$69,0))/$D17-1 -> 0.12664687 | Q17: =INDEX('Fcst Walk'!$AM$5:$AM$69,MATCH($C17,'Fcst Walk'!$A$5:$A$69,0)) -> 0 | R17: =INDEX('Fcst Walk'!$AN$5:$AN$69,MATCH($C17,'Fcst Walk'!$A$5:$A$69,0)) | S17: =AVERAGE(INDEX('Realpage - His. Rent Change'!$I$2:$AV$577,MATCH($C17,'Realpage - His. Rent Change'!$A$2:$A$577,0),0)) -> 0.04881 | U17: =IF(T17="",S17,AVERAGE(S17,T17)) -> 0.04881 | V17: =IF(H17>=0,0,-H17/U17) -> 0
B18: =ROW()-4 -> 14 | C18: Wilmington, NC | D18: =SUMIFS('Realpage Data'!$R$2:$R$899,'Realpage Data'!$A$2:$A$899,$C18,'Realpage Data'!$F$2:$F$899,"Rent Roll (Rev/OSF)") -> 1.5148793 | E18: =SUMIFS('Realpage Data'!$R$2:$R$899,'Realpage Data'!$A$2:$A$899,$C18,'Realpage Data'!$F$2:$F$899,"Asking RPSF") -> 1.596 | F18: =SUMIFS('Realpage Data'!$R$2:$R$899,'Realpage Data'!$A$2:$A$899,$C18,'Realpage Data'!$F$2:$F$899,"Effective RPSF") -> 1.559 | G18: =E18/$D18-1 -> 0.053549305 | H18: =F18/$D18-1 -> 0.029124916 | I18: =SUMIFS('RP - Unit Starts'!$AC$2:$AC$451,'RP - Unit Starts'!$A$2:$A$451,$C18,'RP - Unit Starts'!$F$2:$F$451,"Annual Unit Starts")/SUMIFS('RP - Unit Starts'!$AC$2:$AC$451,'RP - Unit Starts'!$A$2:$A$451,$C18,'RP - Unit Starts'!$F$2:$F$451,"Existing Units") -> 0.018594007 | J18: =SUMIFS('Realpage Data'!$V$2:$V$899,'Realpage Data'!$A$2:$A$899,$C18,'Realpage Data'!$F$2:$F$899,"Existing Units")/SUMIFS('Realpage Data'!$R$2:$R$899,'Realpage Data'!$A$2:$A$899,$C18,'Realpage Data'!$F$2:$F$899,"Existing Units")-1 -> 0.054304036 | K18: =INDEX('Fcst Walk'!$J$5:$J$69,MATCH($C18,'Fcst Walk'!$A$5:$A$69,0))/INDEX('Fcst Walk'!$F$5:$F$69,MATCH($C18,'Fcst Walk'!$A$5:$A$69,0))-1 -> 0.021 | L18: =INDEX('Fcst Walk'!$N$5:$N$69,MATCH($C18,'Fcst Walk'!$A$5:$A$69,0))/INDEX('Fcst Walk'!$J$5:$J$69,MATCH($C18,'Fcst Walk'!$A$5:$A$69,0))-1 -> 0.028 | M18: =INDEX('Fcst Walk'!$R$5:$R$69,MATCH($C18,'Fcst Walk'!$A$5:$A$69,0))/INDEX('Fcst Walk'!$N$5:$N$69,MATCH($C18,'Fcst Walk'!$A$5:$A$69,0))-1 -> 0.031 | N18: =INDEX('Fcst Walk'!$J$5:$J$69,MATCH($C18,'Fcst Walk'!$A$5:$A$69,0))/$D18-1 -> 0.050736539 | O18: =INDEX('Fcst Walk'!$N$5:$N$69,MATCH($C18,'Fcst Walk'!$A$5:$A$69,0))/$D18-1 -> 0.080157163 | P18: =INDEX('Fcst Walk'!$R$5:$R$69,MATCH($C18,'Fcst Walk'!$A$5:$A$69,0))/$D18-1 -> 0.11364203 | Q18: =INDEX('Fcst Walk'!$AM$5:$AM$69,MATCH($C18,'Fcst Walk'!$A$5:$A$69,0)) -> 0 | R18: =INDEX('Fcst Walk'!$AN$5:$AN$69,MATCH($C18,'Fcst Walk'!$A$5:$A$69,0)) | S18: =AVERAGE(INDEX('Realpage - His. Rent Change'!$I$2:$AV$577,MATCH($C18,'Realpage - His. Rent Change'!$A$2:$A$577,0),0)) -> 0.060755 | U18: =IF(T18="",S18,AVERAGE(S18,T18)) -> 0.060755 | V18: =IF(H18>=0,0,-H18/U18) -> 0
B19: =ROW()-4 -> 15 | C19: Fayetteville-Springdale-Rogers, AR | D19: =SUMIFS('Realpage Data'!$R$2:$R$899,'Realpage Data'!$A$2:$A$899,$C19,'Realpage Data'!$F$2:$F$899,"Rent Roll (Rev/OSF)") -> 1.3361114 | E19: =SUMIFS('Realpage Data'!$R$2:$R$899,'Realpage Data'!$A$2:$A$899,$C19,'Realpage Data'!$F$2:$F$899,"Asking RPSF") -> 1.392 | F19: =SUMIFS('Realpage Data'!$R$2:$R$899,'Realpage Data'!$A$2:$A$899,$C19,'Realpage Data'!$F$2:$F$899,"Effective RPSF") -> 1.372 | G19: =E19/$D19-1 -> 0.041829323 | H19: =F19/$D19-1 -> 0.026860511 | I19: =SUMIFS('RP - Unit Starts'!$AC$2:$AC$451,'RP - Unit Starts'!$A$2:$A$451,$C19,'RP - Unit Starts'!$F$2:$F$451,"Annual Unit Starts")/SUMIFS('RP - Unit Starts'!$AC$2:$AC$451,'RP - Unit Starts'!$A$2:$A$451,$C19,'RP - Unit Starts'!$F$2:$F$451,"Existing Units") -> 0.020668596 | J19: =SUMIFS('Realpage Data'!$V$2:$V$899,'Realpage Data'!$A$2:$A$899,$C19,'Realpage Data'!$F$2:$F$899,"Existing Units")/SUMIFS('Realpage Data'!$R$2:$R$899,'Realpage Data'!$A$2:$A$899,$C19,'Realpage Data'!$F$2:$F$899,"Existing Units")-1 -> 0.041747374 | K19: =INDEX('Fcst Walk'!$J$5:$J$69,MATCH($C19,'Fcst Walk'!$A$5:$A$69,0))/INDEX('Fcst Walk'!$F$5:$F$69,MATCH($C19,'Fcst Walk'!$A$5:$A$69,0))-1 -> 0 | L19: =INDEX('Fcst Walk'!$N$5:$N$69,MATCH($C19,'Fcst Walk'!$A$5:$A$69,0))/INDEX('Fcst Walk'!$J$5:$J$69,MATCH($C19,'Fcst Walk'!$A$5:$A$69,0))-1 -> 0.024 | M19: =INDEX('Fcst Walk'!$R$5:$R$69,MATCH($C19,'Fcst Walk'!$A$5:$A$69,0))/INDEX('Fcst Walk'!$N$5:$N$69,MATCH($C19,'Fcst Walk'!$A$5:$A$69,0))-1 -> 0.024 | N19: =INDEX('Fcst Walk'!$J$5:$J$69,MATCH($C19,'Fcst Walk'!$A$5:$A$69,0))/$D19-1 -> 0.026860511 | O19: =INDEX('Fcst Walk'!$N$5:$N$69,MATCH($C19,'Fcst Walk'!$A$5:$A$69,0))/$D19-1 -> 0.051505163 | P19: =INDEX('Fcst Walk'!$R$5:$R$69,MATCH($C19,'Fcst Walk'!$A$5:$A$69,0))/$D19-1 -> 0.076741287 | Q19: =INDEX('Fcst Walk'!$AM$5:$AM$69,MATCH($C19,'Fcst Walk'!$A$5:$A$69,0)) -> 0 | R19: =INDEX('Fcst Walk'!$AN$5:$AN$69,MATCH($C19,'Fcst Walk'!$A$5:$A$69,0)) | S19: =AVERAGE(INDEX('Realpage - His. Rent Change'!$I$2:$AV$577,MATCH($C19,'Realpage - His. Rent Change'!$A$2:$A$577,0),0)) -> 0.069365 | U19: =IF(T19="",S19,AVERAGE(S19,T19)) -> 0.069365 | V19: =IF(H19>=0,0,-H19/U19) -> 0
B20: =ROW()-4 -> 16 | C20: Savannah, GA | D20: =SUMIFS('Realpage Data'!$R$2:$R$899,'Realpage Data'!$A$2:$A$899,$C20,'Realpage Data'!$F$2:$F$899,"Rent Roll (Rev/OSF)") -> 1.4982507 | E20: =SUMIFS('Realpage Data'!$R$2:$R$899,'Realpage Data'!$A$2:$A$899,$C20,'Realpage Data'!$F$2:$F$899,"Asking RPSF") -> 1.593 | F20: =SUMIFS('Realpage Data'!$R$2:$R$899,'Realpage Data'!$A$2:$A$899,$C20,'Realpage Data'!$F$2:$F$899,"Effective RPSF") -> 1.538 | G20: =E20/$D20-1 -> 0.063239927 | H20: =F20/$D20-1 -> 0.02653045 | I20: =SUMIFS('RP - Unit Starts'!$AC$2:$AC$451,'RP - Unit Starts'!$A$2:$A$451,$C20,'RP - Unit Starts'!$F$2:$F$451,"Annual Unit Starts")/SUMIFS('RP - Unit Starts'!$AC$2:$AC$451,'RP - Unit Starts'!$A$2:$A$451,$C20,'RP - Unit Starts'!$F$2:$F$451,"Existing Units") -> 0.018218772 | J20: =SUMIFS('Realpage Data'!$V$2:$V$899,'Realpage Data'!$A$2:$A$899,$C20,'Realpage Data'!$F$2:$F$899,"Existing Units")/SUMIFS('Realpage Data'!$R$2:$R$899,'Realpage Data'!$A$2:$A$899,$C20,'Realpage Data'!$F$2:$F$899,"Existing Units")-1 -> 0.038176164 | K20: =INDEX('Fcst Walk'!$J$5:$J$69,MATCH($C20,'Fcst Walk'!$A$5:$A$69,0))/INDEX('Fcst Walk'!$F$5:$F$69,MATCH($C20,'Fcst Walk'!$A$5:$A$69,0))-1 -> 0.004 | L20: =INDEX('Fcst Walk'!$N$5:$N$69,MATCH($C20,'Fcst Walk'!$A$5:$A$69,0))/INDEX('Fcst Walk'!$J$5:$J$69,MATCH($C20,'Fcst Walk'!$A$5:$A$69,0))-1 -> 0.03 | M20: =INDEX('Fcst Walk'!$R$5:$R$69,MATCH($C20,'Fcst Walk'!$A$5:$A$69,0))/INDEX('Fcst Walk'!$N$5:$N$69,MATCH($C20,'Fcst Walk'!$A$5:$A$69,0))-1 -> 0.037 | N20: =INDEX('Fcst Walk'!$J$5:$J$69,MATCH($C20,'Fcst Walk'!$A$5:$A$69,0))/$D20-1 -> 0.030636572 | O20: =INDEX('Fcst Walk'!$N$5:$N$69,MATCH($C20,'Fcst Walk'!$A$5:$A$69,0))/$D20-1 -> 0.061555669 | P20: =INDEX('Fcst Walk'!$R$5:$R$69,MATCH($C20,'Fcst Walk'!$A$5:$A$69,0))/$D20-1 -> 0.10083323 | Q20: =INDEX('Fcst Walk'!$AM$5:$AM$69,MATCH($C20,'Fcst Walk'!$A$5:$A$69,0)) -> 0 | R20: =INDEX('Fcst Walk'!$AN$5:$AN$69,MATCH($C20,'Fcst Walk'!$A$5:$A$69,0)) | S20: =AVERAGE(INDEX('Realpage - His. Rent Change'!$I$2:$AV$577,MATCH($C20,'Realpage - His. Rent Change'!$A$2:$A$577,0),0)) -> 0.058045 | U20: =IF(T20="",S20,AVERAGE(S20,T20)) -> 0.058045 | V20: =IF(H20>=0,0,-H20/U20) -> 0
B21: =ROW()-4 -> 17 | C21: Cincinnati, OH-KY-IN | D21: =SUMIFS('Realpage Data'!$R$2:$R$899,'Realpage Data'!$A$2:$A$899,$C21,'Realpage Data'!$F$2:$F$899,"Rent Roll (Rev/OSF)") -> 1.578633 | E21: =SUMIFS('Realpage Data'!$R$2:$R$899,'Realpage Data'!$A$2:$A$899,$C21,'Realpage Data'!$F$2:$F$899,"Asking RPSF") -> 1.63 | F21: =SUMIFS('Realpage Data'!$R$2:$R$899,'Realpage Data'!$A$2:$A$899,$C21,'Realpage Data'!$F$2:$F$899,"Effective RPSF") -> 1.619 | G21: =E21/$D21-1 -> 0.032538929 | H21: =F21/$D21-1 -> 0.025570875 | I21: =SUMIFS('RP - Unit Starts'!$AC$2:$AC$451,'RP - Unit Starts'!$A$2:$A$451,$C21,'RP - Unit Starts'!$F$2:$F$451,"Annual Unit Starts")/SUMIFS('RP - Unit Starts'!$AC$2:$AC$451,'RP - Unit Starts'!$A$2:$A$451,$C21,'RP - Unit Starts'!$F$2:$F$451,"Existing Units") -> 0.014331659 | J21: =SUMIFS('Realpage Data'!$V$2:$V$899,'Realpage Data'!$A$2:$A$899,$C21,'Realpage Data'!$F$2:$F$899,"Existing Units")/SUMIFS('Realpage Data'!$R$2:$R$899,'Realpage Data'!$A$2:$A$899,$C21,'Realpage Data'!$F$2:$F$899,"Existing Units")-1 -> 0.014348919 | K21: =INDEX('Fcst Walk'!$J$5:$J$69,MATCH($C21,'Fcst Walk'!$A$5:$A$69,0))/INDEX('Fcst Walk'!$F$5:$F$69,MATCH($C21,'Fcst Walk'!$A$5:$A$69,0))-1 -> 0.029 | L21: =INDEX('Fcst Walk'!$N$5:$N$69,MATCH($C21,'Fcst Walk'!$A$5:$A$69,0))/INDEX('Fcst Walk'!$J$5:$J$69,MATCH($C21,'Fcst Walk'!$A$5:$A$69,0))-1 -> 0.027 | M21: =INDEX('Fcst Walk'!$R$5:$R$69,MATCH($C21,'Fcst Walk'!$A$5:$A$69,0))/INDEX('Fcst Walk'!$N$5:$N$69,MATCH($C21,'Fcst Walk'!$A$5:$A$69,0))-1 -> 0.028 | N21: =INDEX('Fcst Walk'!$J$5:$J$69,MATCH($C21,'Fcst Walk'!$A$5:$A$69,0))/$D21-1 -> 0.05531243 | O21: =INDEX('Fcst Walk'!$N$5:$N$69,MATCH($C21,'Fcst Walk'!$A$5:$A$69,0))/$D21-1 -> 0.083805866 | P21: =INDEX('Fcst Walk'!$R$5:$R$69,MATCH($C21,'Fcst Walk'!$A$5:$A$69,0))/$D21-1 -> 0.11415243 | Q21: =INDEX('Fcst Walk'!$AM$5:$AM$69,MATCH($C21,'Fcst Walk'!$A$5:$A$69,0)) -> 0 | R21: =INDEX('Fcst Walk'!$AN$5:$AN$69,MATCH($C21,'Fcst Walk'!$A$5:$A$69,0)) | S21: =AVERAGE(INDEX('Realpage - His. Rent Change'!$I$2:$AV$577,MATCH($C21,'Realpage - His. Rent Change'!$A$2:$A$577,0),0)) -> 0.060255 | U21: =IF(T21="",S21,AVERAGE(S21,T21)) -> 0.060255 | V21: =IF(H21>=0,0,-H21/U21) -> 0
B22: =ROW()-4 -> 18 | C22: Chattanooga, TN-GA | D22: =SUMIFS('Realpage Data'!$R$2:$R$899,'Realpage Data'!$A$2:$A$899,$C22,'Realpage Data'!$F$2:$F$899,"Rent Roll (Rev/OSF)") -> 1.3606319 | E22: =SUMIFS('Realpage Data'!$R$2:$R$899,'Realpage Data'!$A$2:$A$899,$C22,'Realpage Data'!$F$2:$F$899,"Asking RPSF") -> 1.44 | F22: =SUMIFS('Realpage Data'!$R$2:$R$899,'Realpage Data'!$A$2:$A$899,$C22,'Realpage Data'!$F$2:$F$899,"Effective RPSF") -> 1.395 | G22: =E22/$D22-1 -> 0.058331758 | H22: =F22/$D22-1 -> 0.025258891 | I22: =SUMIFS('RP - Unit Starts'!$AC$2:$AC$451,'RP - Unit Starts'!$A$2:$A$451,$C22,'RP - Unit Starts'!$F$2:$F$451,"Annual Unit Starts")/SUMIFS('RP - Unit Starts'!$AC$2:$AC$451,'RP - Unit Starts'!$A$2:$A$451,$C22,'RP - Unit Starts'!$F$2:$F$451,"Existing Units") -> 0.014355683 | J22: =SUMIFS('Realpage Data'!$V$2:$V$899,'Realpage Data'!$A$2:$A$899,$C22,'Realpage Data'!$F$2:$F$899,"Existing Units")/SUMIFS('Realpage Data'!$R$2:$R$899,'Realpage Data'!$A$2:$A$899,$C22,'Realpage Data'!$F$2:$F$899,"Existing Units")-1 -> 0.0063052412 | K22: =INDEX('Fcst Walk'!$J$5:$J$69,MATCH($C22,'Fcst Walk'!$A$5:$A$69,0))/INDEX('Fcst Walk'!$F$5:$F$69,MATCH($C22,'Fcst Walk'!$A$5:$A$69,0))-1 -> 0.023 | L22: =INDEX('Fcst Walk'!$N$5:$N$69,MATCH($C22,'Fcst Walk'!$A$5:$A$69,0))/INDEX('Fcst Walk'!$J$5:$J$69,MATCH($C22,'Fcst Walk'!$A$5:$A$69,0))-1 -> 0.026 | M22: =INDEX('Fcst Walk'!$R$5:$R$69,MATCH($C22,'Fcst Walk'!$A$5:$A$69,0))/INDEX('Fcst Walk'!$N$5:$N$69,MATCH($C22,'Fcst Walk'!$A$5:$A$69,0))-1 -> 0.019 | N22: =INDEX('Fcst Walk'!$J$5:$J$69,MATCH($C22,'Fcst Walk'!$A$5:$A$69,0))/$D22-1 -> 0.048839845 | O22: =INDEX('Fcst Walk'!$N$5:$N$69,MATCH($C22,'Fcst Walk'!$A$5:$A$69,0))/$D22-1 -> 0.076109681 | P22: =INDEX('Fcst Walk'!$R$5:$R$69,MATCH($C22,'Fcst Walk'!$A$5:$A$69,0))/$D22-1 -> 0.096555765 | Q22: =INDEX('Fcst Walk'!$AM$5:$AM$69,MATCH($C22,'Fcst Walk'!$A$5:$A$69,0)) -> 0 | R22: =INDEX('Fcst Walk'!$AN$5:$AN$69,MATCH($C22,'Fcst Walk'!$A$5:$A$69,0)) | S22: =AVERAGE(INDEX('Realpage - His. Rent Change'!$I$2:$AV$577,MATCH($C22,'Realpage - His. Rent Change'!$A$2:$A$577,0),0)) -> 0.0574675 | U22: =IF(T22="",S22,AVERAGE(S22,T22)) -> 0.0574675 | V22: =IF(H22>=0,0,-H22/U22) -> 0
B23: =ROW()-4 -> 19 | C23: Baton Rouge, LA | D23: =SUMIFS('Realpage Data'!$R$2:$R$899,'Realpage Data'!$A$2:$A$899,$C23,'Realpage Data'!$F$2:$F$899,"Rent Roll (Rev/OSF)") -> 1.2681901 | E23: =SUMIFS('Realpage Data'!$R$2:$R$899,'Realpage Data'!$A$2:$A$899,$C23,'Realpage Data'!$F$2:$F$899,"Asking RPSF") -> 1.316 | F23: =SUMIFS('Realpage Data'!$R$2:$R$899,'Realpage Data'!$A$2:$A$899,$C23,'Realpage Data'!$F$2:$F$899,"Effective RPSF") -> 1.3 | G23: =E23/$D23-1 -> 0.037699298 | H23: =F23/$D23-1 -> 0.025082893 | I23: =SUMIFS('RP - Unit Starts'!$AC$2:$AC$451,'RP - Unit Starts'!$A$2:$A$451,$C23,'RP - Unit Starts'!$F$2:$F$451,"Annual Unit Starts")/SUMIFS('RP - Unit Starts'!$AC$2:$AC$451,'RP - Unit Starts'!$A$2:$A$451,$C23,'RP - Unit Starts'!$F$2:$F$451,"Existing Units") -> 0.0059971168 | J23: =SUMIFS('Realpage Data'!$V$2:$V$899,'Realpage Data'!$A$2:$A$899,$C23,'Realpage Data'!$F$2:$F$899,"Existing Units")/SUMIFS('Realpage Data'!$R$2:$R$899,'Realpage Data'!$A$2:$A$899,$C23,'Realpage Data'!$F$2:$F$899,"Existing Units")-1 -> 0.0059971168 | K23: =INDEX('Fcst Walk'!$J$5:$J$69,MATCH($C23,'Fcst Walk'!$A$5:$A$69,0))/INDEX('Fcst Walk'!$F$5:$F$69,MATCH($C23,'Fcst Walk'!$A$5:$A$69,0))-1 -> 0.03 | L23: =INDEX('Fcst Walk'!$N$5:$N$69,MATCH($C23,'Fcst Walk'!$A$5:$A$69,0))/INDEX('Fcst Walk'!$J$5:$J$69,MATCH($C23,'Fcst Walk'!$A$5:$A$69,0))-1 -> 0.023 | M23: =INDEX('Fcst Walk'!$R$5:$R$69,MATCH($C23,'Fcst Walk'!$A$5:$A$69,0))/INDEX('Fcst Walk'!$N$5:$N$69,MATCH($C23,'Fcst Walk'!$A$5:$A$69,0))-1 -> 0.016 | N23: =INDEX('Fcst Walk'!$J$5:$J$69,MATCH($C23,'Fcst Walk'!$A$5:$A$69,0))/$D23-1 -> 0.05583538 | O23: =INDEX('Fcst Walk'!$N$5:$N$69,MATCH($C23,'Fcst Walk'!$A$5:$A$69,0))/$D23-1 -> 0.080119594 | P23: =INDEX('Fcst Walk'!$R$5:$R$69,MATCH($C23,'Fcst Walk'!$A$5:$A$69,0))/$D23-1 -> 0.097401507 | Q23: =INDEX('Fcst Walk'!$AM$5:$AM$69,MATCH($C23,'Fcst Walk'!$A$5:$A$69,0)) -> 0 | R23: =INDEX('Fcst Walk'!$AN$5:$AN$69,MATCH($C23,'Fcst Walk'!$A$5:$A$69,0)) | S23: =AVERAGE(INDEX('Realpage - His. Rent Change'!$I$2:$AV$577,MATCH($C23,'Realpage - His. Rent Change'!$A$2:$A$577,0),0)) -> 0.032635 | U23: =IF(T23="",S23,AVERAGE(S23,T23)) -> 0.032635 | V23: =IF(H23>=0,0,-H23/U23) -> 0
B24: =ROW()-4 -> 20 | C24: Kansas City, MO-KS | D24: =SUMIFS('Realpage Data'!$R$2:$R$899,'Realpage Data'!$A$2:$A$899,$C24,'Realpage Data'!$F$2:$F$899,"Rent Roll (Rev/OSF)") -> 1.4911626 | E24: =SUMIFS('Realpage Data'!$R$2:$R$899,'Realpage Data'!$A$2:$A$899,$C24,'Realpage Data'!$F$2:$F$899,"Asking RPSF") -> 1.536 | F24: =SUMIFS('Realpage Data'!$R$2:$R$899,'Realpage Data'!$A$2:$A$899,$C24,'Realpage Data'!$F$2:$F$899,"Effective RPSF") -> 1.523 | G24: =E24/$D24-1 -> 0.030068776 | H24: =F24/$D24-1 -> 0.021350746 | I24: =SUMIFS('RP - Unit Starts'!$AC$2:$AC$451,'RP - Unit Starts'!$A$2:$A$451,$C24,'RP - Unit Starts'!$F$2:$F$451,"Annual Unit Starts")/SUMIFS('RP - Unit Starts'!$AC$2:$AC$451,'RP - Unit Starts'!$A$2:$A$451,$C24,'RP - Unit Starts'!$F$2:$F$451,"Existing Units") -> 0.025479466 | J24: =SUMIFS('Realpage Data'!$V$2:$V$899,'Realpage Data'!$A$2:$A$899,$C24,'Realpage Data'!$F$2:$F$899,"Existing Units")/SUMIFS('Realpage Data'!$R$2:$R$899,'Realpage Data'!$A$2:$A$899,$C24,'Realpage Data'!$F$2:$F$899,"Existing Units")-1 -> 0.019850949 | K24: =INDEX('Fcst Walk'!$J$5:$J$69,MATCH($C24,'Fcst Walk'!$A$5:$A$69,0))/INDEX('Fcst Walk'!$F$5:$F$69,MATCH($C24,'Fcst Walk'!$A$5:$A$69,0))-1 -> 0.022 | L24: =INDEX('Fcst Walk'!$N$5:$N$69,MATCH($C24,'Fcst Walk'!$A$5:$A$69,0))/INDEX('Fcst Walk'!$J$5:$J$69,MATCH($C24,'Fcst Walk'!$A$5:$A$69,0))-1 -> 0.02 | M24: =INDEX('Fcst Walk'!$R$5:$R$69,MATCH($C24,'Fcst Walk'!$A$5:$A$69,0))/INDEX('Fcst Walk'!$N$5:$N$69,MATCH($C24,'Fcst Walk'!$A$5:$A$69,0))-1 -> 0.019 | N24: =INDEX('Fcst Walk'!$J$5:$J$69,MATCH($C24,'Fcst Walk'!$A$5:$A$69,0))/$D24-1 -> 0.043820462 | O24: =INDEX('Fcst Walk'!$N$5:$N$69,MATCH($C24,'Fcst Walk'!$A$5:$A$69,0))/$D24-1 -> 0.064696871 | P24: =INDEX('Fcst Walk'!$R$5:$R$69,MATCH($C24,'Fcst Walk'!$A$5:$A$69,0))/$D24-1 -> 0.084926112 | Q24: =INDEX('Fcst Walk'!$AM$5:$AM$69,MATCH($C24,'Fcst Walk'!$A$5:$A$69,0)) -> 0 | R24: =INDEX('Fcst Walk'!$AN$5:$AN$69,MATCH($C24,'Fcst Walk'!$A$5:$A$69,0)) | S24: =AVERAGE(INDEX('Realpage - His. Rent Change'!$I$2:$AV$577,MATCH($C24,'Realpage - His. Rent Change'!$A$2:$A$577,0),0)) -> 0.05285 | T24: 0.0367 | U24: =IF(T24="",S24,AVERAGE(S24,T24)) -> 0.044775 | V24: =IF(H24>=0,0,-H24/U24) -> 0
B25: =ROW()-4 -> 21 | C25: Minneapolis-St. Paul-Bloomington, MN-WI | D25: =SUMIFS('Realpage Data'!$R$2:$R$899,'Realpage Data'!$A$2:$A$899,$C25,'Realpage Data'!$F$2:$F$899,"Rent Roll (Rev/OSF)") -> 1.8554404 | E25: =SUMIFS('Realpage Data'!$R$2:$R$899,'Realpage Data'!$A$2:$A$899,$C25,'Realpage Data'!$F$2:$F$899,"Asking RPSF") -> 1.911 | F25: =SUMIFS('Realpage Data'!$R$2:$R$899,'Realpage Data'!$A$2:$A$899,$C25,'Realpage Data'!$F$2:$F$899,"Effective RPSF") -> 1.884 | G25: =E25/$D25-1 -> 0.029944173 | H25: =F25/$D25-1 -> 0.015392371 | I25: =SUMIFS('RP - Unit Starts'!$AC$2:$AC$451,'RP - Unit Starts'!$A$2:$A$451,$C25,'RP - Unit Starts'!$F$2:$F$451,"Annual Unit Starts")/SUMIFS('RP - Unit Starts'!$AC$2:$AC$451,'RP - Unit Starts'!$A$2:$A$451,$C25,'RP - Unit Starts'!$F$2:$F$451,"Existing Units") -> 0.0093966239 | J25: =SUMIFS('Realpage Data'!$V$2:$V$899,'Realpage Data'!$A$2:$A$899,$C25,'Realpage Data'!$F$2:$F$899,"Existing Units")/SUMIFS('Realpage Data'!$R$2:$R$899,'Realpage Data'!$A$2:$A$899,$C25,'Realpage Data'!$F$2:$F$899,"Existing Units")-1 -> 0.0072399254 | K25: =INDEX('Fcst Walk'!$J$5:$J$69,MATCH($C25,'Fcst Walk'!$A$5:$A$69,0))/INDEX('Fcst Walk'!$F$5:$F$69,MATCH($C25,'Fcst Walk'!$A$5:$A$69,0))-1 -> 0.019 | L25: =INDEX('Fcst Walk'!$N$5:$N$69,MATCH($C25,'Fcst Walk'!$A$5:$A$69,0))/INDEX('Fcst Walk'!$J$5:$J$69,MATCH($C25,'Fcst Walk'!$A$5:$A$69,0))-1 -> 0.021 | M25: =INDEX('Fcst Walk'!$R$5:$R$69,MATCH($C25,'Fcst Walk'!$A$5:$A$69,0))/INDEX('Fcst Walk'!$N$5:$N$69,MATCH($C25,'Fcst Walk'!$A$5:$A$69,0))-1 -> 0.021 | N25: =INDEX('Fcst Walk'!$J$5:$J$69,MATCH($C25,'Fcst Walk'!$A$5:$A$69,0))/$D25-1 -> 0.034684826 | O25: =INDEX('Fcst Walk'!$N$5:$N$69,MATCH($C25,'Fcst Walk'!$A$5:$A$69,0))/$D25-1 -> 0.056413208 | P25: =INDEX('Fcst Walk'!$R$5:$R$69,MATCH($C25,'Fcst Walk'!$A$5:$A$69,0))/$D25-1 -> 0.078597885 | Q25: =INDEX('Fcst Walk'!$AM$5:$AM$69,MATCH($C25,'Fcst Walk'!$A$5:$A$69,0)) -> 0 | R25: =INDEX('Fcst Walk'!$AN$5:$AN$69,MATCH($C25,'Fcst Walk'!$A$5:$A$69,0)) | S25: =AVERAGE(INDEX('Realpage - His. Rent Change'!$I$2:$AV$577,MATCH($C25,'Realpage - His. Rent Change'!$A$2:$A$577,0),0)) -> 0.0401575 | T25: 0.0264 | U25: =IF(T25="",S25,AVERAGE(S25,T25)) -> 0.03327875 | V25: =IF(H25>=0,0,-H25/U25) -> 0
B26: =ROW()-4 -> 22 | C26: West Palm Beach-Boca Raton-Delray Beach, FL | D26: =SUMIFS('Realpage Data'!$R$2:$R$899,'Realpage Data'!$A$2:$A$899,$C26,'Realpage Data'!$F$2:$F$899,"Rent Roll (Rev/OSF)") -> 2.4319646 | E26: =SUMIFS('Realpage Data'!$R$2:$R$899,'Realpage Data'!$A$2:$A$899,$C26,'Realpage Data'!$F$2:$F$899,"Asking RPSF") -> 2.461 | F26: =SUMIFS('Realpage Data'!$R$2:$R$899,'Realpage Data'!$A$2:$A$899,$C26,'Realpage Data'!$F$2:$F$899,"Effective RPSF") -> 2.449 | G26: =E26/$D26-1 -> 0.011939077 | H26: =F26/$D26-1 -> 0.007004795 | I26: =SUMIFS('RP - Unit Starts'!$AC$2:$AC$451,'RP - Unit Starts'!$A$2:$A$451,$C26,'RP - Unit Starts'!$F$2:$F$451,"Annual Unit Starts")/SUMIFS('RP - Unit Starts'!$AC$2:$AC$451,'RP - Unit Starts'!$A$2:$A$451,$C26,'RP - Unit Starts'!$F$2:$F$451,"Existing Units") -> 0.022218027 | J26: =SUMIFS('Realpage Data'!$V$2:$V$899,'Realpage Data'!$A$2:$A$899,$C26,'Realpage Data'!$F$2:$F$899,"Existing Units")/SUMIFS('Realpage Data'!$R$2:$R$899,'Realpage Data'!$A$2:$A$899,$C26,'Realpage Data'!$F$2:$F$899,"Existing Units")-1 -> 0.024090926 | K26: =INDEX('Fcst Walk'!$J$5:$J$69,MATCH($C26,'Fcst Walk'!$A$5:$A$69,0))/INDEX('Fcst Walk'!$F$5:$F$69,MATCH($C26,'Fcst Walk'!$A$5:$A$69,0))-1 -> 0.027 | L26: =INDEX('Fcst Walk'!$N$5:$N$69,MATCH($C26,'Fcst Walk'!$A$5:$A$69,0))/INDEX('Fcst Walk'!$J$5:$J$69,MATCH($C26,'Fcst Walk'!$A$5:$A$69,0))-1 -> 0.031 | M26: =INDEX('Fcst Walk'!$R$5:$R$69,MATCH($C26,'Fcst Walk'!$A$5:$A$69,0))/INDEX('Fcst Walk'!$N$5:$N$69,MATCH($C26,'Fcst Walk'!$A$5:$A$69,0))-1 -> 0.036 | N26: =INDEX('Fcst Walk'!$J$5:$J$69,MATCH($C26,'Fcst Walk'!$A$5:$A$69,0))/$D26-1 -> 0.034193925 | O26: =INDEX('Fcst Walk'!$N$5:$N$69,MATCH($C26,'Fcst Walk'!$A$5:$A$69,0))/$D26-1 -> 0.066253936 | P26: =INDEX('Fcst Walk'!$R$5:$R$69,MATCH($C26,'Fcst Walk'!$A$5:$A$69,0))/$D26-1 -> 0.10463908 | Q26: =INDEX('Fcst Walk'!$AM$5:$AM$69,MATCH($C26,'Fcst Walk'!$A$5:$A$69,0)) -> 0 | R26: =INDEX('Fcst Walk'!$AN$5:$AN$69,MATCH($C26,'Fcst Walk'!$A$5:$A$69,0)) | S26: =AVERAGE(INDEX('Realpage - His. Rent Change'!$I$2:$AV$577,MATCH($C26,'Realpage - His. Rent Change'!$A$2:$A$577,0),0)) -> 0.0611375 | T26: 0.0503 | U26: =IF(T26="",S26,AVERAGE(S26,T26)) -> 0.05571875 | V26: =IF(H26>=0,0,-H26/U26) -> 0
B27: =ROW()-4 -> 23 | C27: Myrtle Beach-Conway-North Myrtle Beach, SC | D27: =SUMIFS('Realpage Data'!$R$2:$R$899,'Realpage Data'!$A$2:$A$899,$C27,'Realpage Data'!$F$2:$F$899,"Rent Roll (Rev/OSF)") -> 1.4608809 | E27: =SUMIFS('Realpage Data'!$R$2:$R$899,'Realpage Data'!$A$2:$A$899,$C27,'Realpage Data'!$F$2:$F$899,"Asking RPSF") -> 1.531 | F27: =SUMIFS('Realpage Data'!$R$2:$R$899,'Realpage Data'!$A$2:$A$899,$C27,'Realpage Data'!$F$2:$F$899,"Effective RPSF") -> 1.466 | G27: =E27/$D27-1 -> 0.047997809 | H27: =F27/$D27-1 -> 0.0035041075 | I27: =SUMIFS('RP - Unit Starts'!$AC$2:$AC$451,'RP - Unit Starts'!$A$2:$A$451,$C27,'RP - Unit Starts'!$F$2:$F$451,"Annual Unit Starts")/SUMIFS('RP - Unit Starts'!$AC$2:$AC$451,'RP - Unit Starts'!$A$2:$A$451,$C27,'RP - Unit Starts'!$F$2:$F$451,"Existing Units") -> 0.010620863 | J27: =SUMIFS('Realpage Data'!$V$2:$V$899,'Realpage Data'!$A$2:$A$899,$C27,'Realpage Data'!$F$2:$F$899,"Existing Units")/SUMIFS('Realpage Data'!$R$2:$R$899,'Realpage Data'!$A$2:$A$899,$C27,'Realpage Data'!$F$2:$F$899,"Existing Units")-1 -> 0.0055977694 | K27: =INDEX('Fcst Walk'!$J$5:$J$69,MATCH($C27,'Fcst Walk'!$A$5:$A$69,0))/INDEX('Fcst Walk'!$F$5:$F$69,MATCH($C27,'Fcst Walk'!$A$5:$A$69,0))-1 -> 0.016 | L27: =INDEX('Fcst Walk'!$N$5:$N$69,MATCH($C27,'Fcst Walk'!$A$5:$A$69,0))/INDEX('Fcst Walk'!$J$5:$J$69,MATCH($C27,'Fcst Walk'!$A$5:$A$69,0))-1 -> 0.025 | M27: =INDEX('Fcst Walk'!$R$5:$R$69,MATCH($C27,'Fcst Walk'!$A$5:$A$69,0))/INDEX('Fcst Walk'!$N$5:$N$69,MATCH($C27,'Fcst Walk'!$A$5:$A$69,0))-1 -> 0.032 | N27: =INDEX('Fcst Walk'!$J$5:$J$69,MATCH($C27,'Fcst Walk'!$A$5:$A$69,0))/$D27-1 -> 0.019560173 | O27: =INDEX('Fcst Walk'!$N$5:$N$69,MATCH($C27,'Fcst Walk'!$A$5:$A$69,0))/$D27-1 -> 0.045049178 | P27: =INDEX('Fcst Walk'!$R$5:$R$69,MATCH($C27,'Fcst Walk'!$A$5:$A$69,0))/$D27-1 -> 0.078490751 | Q27: =INDEX('Fcst Walk'!$AM$5:$AM$69,MATCH($C27,'Fcst Walk'!$A$5:$A$69,0)) -> 0 | R27: =INDEX('Fcst Walk'!$AN$5:$AN$69,MATCH($C27,'Fcst Walk'!$A$5:$A$69,0)) | S27: =AVERAGE(INDEX('Realpage - His. Rent Change'!$I$2:$AV$577,MATCH($C27,'Realpage - His. Rent Change'!$A$2:$A$577,0),0)) -> 0.061405 | U27: =IF(T27="",S27,AVERAGE(S27,T27)) -> 0.061405 | V27: =IF(H27>=0,0,-H27/U27) -> 0
B28: =ROW()-4 -> 24 | C28: Lakeland-Winter Haven, FL | D28: =SUMIFS('Realpage Data'!$R$2:$R$899,'Realpage Data'!$A$2:$A$899,$C28,'Realpage Data'!$F$2:$F$899,"Rent Roll (Rev/OSF)") -> 1.4876528 | E28: =SUMIFS('Realpage Data'!$R$2:$R$899,'Realpage Data'!$A$2:$A$899,$C28,'Realpage Data'!$F$2:$F$899,"Asking RPSF") -> 1.539 | F28: =SUMIFS('Realpage Data'!$R$2:$R$899,'Realpage Data'!$A$2:$A$899,$C28,'Realpage Data'!$F$2:$F$899,"Effective RPSF") -> 1.485 | G28: =E28/$D28-1 -> 0.034515603 | H28: =F28/$D28-1 -> -0.00178319 | I28: =SUMIFS('RP - Unit Starts'!$AC$2:$AC$451,'RP - Unit Starts'!$A$2:$A$451,$C28,'RP - Unit Starts'!$F$2:$F$451,"Annual Unit Starts")/SUMIFS('RP - Unit Starts'!$AC$2:$AC$451,'RP - Unit Starts'!$A$2:$A$451,$C28,'RP - Unit Starts'!$F$2:$F$451,"Existing Units") -> 0.004371926 | J28: =SUMIFS('Realpage Data'!$V$2:$V$899,'Realpage Data'!$A$2:$A$899,$C28,'Realpage Data'!$F$2:$F$899,"Existing Units")/SUMIFS('Realpage Data'!$R$2:$R$899,'Realpage Data'!$A$2:$A$899,$C28,'Realpage Data'!$F$2:$F$899,"Existing Units")-1 -> 0.038748796 | K28: =INDEX('Fcst Walk'!$J$5:$J$69,MATCH($C28,'Fcst Walk'!$A$5:$A$69,0))/INDEX('Fcst Walk'!$F$5:$F$69,MATCH($C28,'Fcst Walk'!$A$5:$A$69,0))-1 -> 0.016 | L28: =INDEX('Fcst Walk'!$N$5:$N$69,MATCH($C28,'Fcst Walk'!$A$5:$A$69,0))/INDEX('Fcst Walk'!$J$5:$J$69,MATCH($C28,'Fcst Walk'!$A$5:$A$69,0))-1 -> 0.02 | M28: =INDEX('Fcst Walk'!$R$5:$R$69,MATCH($C28,'Fcst Walk'!$A$5:$A$69,0))/INDEX('Fcst Walk'!$N$5:$N$69,MATCH($C28,'Fcst Walk'!$A$5:$A$69,0))-1 -> 0.021 | N28: =INDEX('Fcst Walk'!$J$5:$J$69,MATCH($C28,'Fcst Walk'!$A$5:$A$69,0))/$D28-1 -> 0.014188279 | O28: =INDEX('Fcst Walk'!$N$5:$N$69,MATCH($C28,'Fcst Walk'!$A$5:$A$69,0))/$D28-1 -> 0.034472045 | P28: =INDEX('Fcst Walk'!$R$5:$R$69,MATCH($C28,'Fcst Walk'!$A$5:$A$69,0))/$D28-1 -> 0.056195957 | Q28: =INDEX('Fcst Walk'!$AM$5:$AM$69,MATCH($C28,'Fcst Walk'!$A$5:$A$69,0)) -> 0.049355652 | R28: =INDEX('Fcst Walk'!$AN$5:$AN$69,MATCH($C28,'Fcst Walk'!$A$5:$A$69,0)) | S28: =AVERAGE(INDEX('Realpage - His. Rent Change'!$I$2:$AV$577,MATCH($C28,'Realpage - His. Rent Change'!$A$2:$A$577,0),0)) -> 0.061055 | U28: =IF(T28="",S28,AVERAGE(S28,T28)) -> 0.061055 | V28: =IF(H28>=0,0,-H28/U28) -> 0.02920629
B29: =ROW()-4 -> 25 | C29: St. Louis, MO-IL | D29: =SUMIFS('Realpage Data'!$R$2:$R$899,'Realpage Data'!$A$2:$A$899,$C29,'Realpage Data'!$F$2:$F$899,"Rent Roll (Rev/OSF)") -> 1.5559508 | E29: =SUMIFS('Realpage Data'!$R$2:$R$899,'Realpage Data'!$A$2:$A$899,$C29,'Realpage Data'!$F$2:$F$899,"Asking RPSF") -> 1.573 | F29: =SUMIFS('Realpage Data'!$R$2:$R$899,'Realpage Data'!$A$2:$A$899,$C29,'Realpage Data'!$F$2:$F$899,"Effective RPSF") -> 1.559 | G29: =E29/$D29-1 -> 0.010957396 | H29: =F29/$D29-1 -> 0.0019596825 | I29: =SUMIFS('RP - Unit Starts'!$AC$2:$AC$451,'RP - Unit Starts'!$A$2:$A$451,$C29,'RP - Unit Starts'!$F$2:$F$451,"Annual Unit Starts")/SUMIFS('RP - Unit Starts'!$AC$2:$AC$451,'RP - Unit Starts'!$A$2:$A$451,$C29,'RP - Unit Starts'!$F$2:$F$451,"Existing Units") -> 0.011046634 | J29: =SUMIFS('Realpage Data'!$V$2:$V$899,'Realpage Data'!$A$2:$A$899,$C29,'Realpage Data'!$F$2:$F$899,"Existing Units")/SUMIFS('Realpage Data'!$R$2:$R$899,'Realpage Data'!$A$2:$A$899,$C29,'Realpage Data'!$F$2:$F$899,"Existing Units")-1 -> 0.0085189179 | K29: =INDEX('Fcst Walk'!$J$5:$J$69,MATCH($C29,'Fcst Walk'!$A$5:$A$69,0))/INDEX('Fcst Walk'!$F$5:$F$69,MATCH($C29,'Fcst Walk'!$A$5:$A$69,0))-1 -> 0.023 | L29: =INDEX('Fcst Walk'!$N$5:$N$69,MATCH($C29,'Fcst Walk'!$A$5:$A$69,0))/INDEX('Fcst Walk'!$J$5:$J$69,MATCH($C29,'Fcst Walk'!$A$5:$A$69,0))-1 -> 0.023 | M29: =INDEX('Fcst Walk'!$R$5:$R$69,MATCH($C29,'Fcst Walk'!$A$5:$A$69,0))/INDEX('Fcst Walk'!$N$5:$N$69,MATCH($C29,'Fcst Walk'!$A$5:$A$69,0))-1 -> 0.025 | N29: =INDEX('Fcst Walk'!$J$5:$J$69,MATCH($C29,'Fcst Walk'!$A$5:$A$69,0))/$D29-1 -> 0.025004755 | O29: =INDEX('Fcst Walk'!$N$5:$N$69,MATCH($C29,'Fcst Walk'!$A$5:$A$69,0))/$D29-1 -> 0.048579865 | P29: =INDEX('Fcst Walk'!$R$5:$R$69,MATCH($C29,'Fcst Walk'!$A$5:$A$69,0))/$D29-1 -> 0.074794361 | Q29: =INDEX('Fcst Walk'!$AM$5:$AM$69,MATCH($C29,'Fcst Walk'!$A$5:$A$69,0)) -> 0.53469497 | R29: =INDEX('Fcst Walk'!$AN$5:$AN$69,MATCH($C29,'Fcst Walk'!$A$5:$A$69,0)) | S29: =AVERAGE(INDEX('Realpage - His. Rent Change'!$I$2:$AV$577,MATCH($C29,'Realpage - His. Rent Change'!$A$2:$A$577,0),0)) -> 0.0515725 | U29: =IF(T29="",S29,AVERAGE(S29,T29)) -> 0.0515725 | V29: =IF(H29>=0,0,-H29/U29) -> 0
B30: =ROW()-4 -> 26 | C30: Greensboro-High Point/Winston-Salem/Burlington, NC | D30: =SUMIFS('Realpage Data'!$R$2:$R$899,'Realpage Data'!$A$2:$A$899,$C30,'Realpage Data'!$F$2:$F$899,"Rent Roll (Rev/OSF)") -> 1.3173564 | E30: =SUMIFS('Realpage Data'!$R$2:$R$899,'Realpage Data'!$A$2:$A$899,$C30,'Realpage Data'!$F$2:$F$899,"Asking RPSF") -> 1.34 | F30: =SUMIFS('Realpage Data'!$R$2:$R$899,'Realpage Data'!$A$2:$A$899,$C30,'Realpage Data'!$F$2:$F$899,"Effective RPSF") -> 1.323 | G30: =E30/$D30-1 -> 0.017188641 | H30: =F30/$D30-1 -> 0.0042840088 | I30: =SUMIFS('RP - Unit Starts'!$AC$2:$AC$451,'RP - Unit Starts'!$A$2:$A$451,$C30,'RP - Unit Starts'!$F$2:$F$451,"Annual Unit Starts")/SUMIFS('RP - Unit Starts'!$AC$2:$AC$451,'RP - Unit Starts'!$A$2:$A$451,$C30,'RP - Unit Starts'!$F$2:$F$451,"Existing Units") -> 0.015879717 | J30: =SUMIFS('Realpage Data'!$V$2:$V$899,'Realpage Data'!$A$2:$A$899,$C30,'Realpage Data'!$F$2:$F$899,"Existing Units")/SUMIFS('Realpage Data'!$R$2:$R$899,'Realpage Data'!$A$2:$A$899,$C30,'Realpage Data'!$F$2:$F$899,"Existing Units")-1 -> 0.011752542 | K30: =INDEX('Fcst Walk'!$J$5:$J$69,MATCH($C30,'Fcst Walk'!$A$5:$A$69,0))/INDEX('Fcst Walk'!$F$5:$F$69,MATCH($C30,'Fcst Walk'!$A$5:$A$69,0))-1 -> 0.026 | L30: =INDEX('Fcst Walk'!$N$5:$N$69,MATCH($C30,'Fcst Walk'!$A$5:$A$69,0))/INDEX('Fcst Walk'!$J$5:$J$69,MATCH($C30,'Fcst Walk'!$A$5:$A$69,0))-1 -> 0.028 | M30: =INDEX('Fcst Walk'!$R$5:$R$69,MATCH($C30,'Fcst Walk'!$A$5:$A$69,0))/INDEX('Fcst Walk'!$N$5:$N$69,MATCH($C30,'Fcst Walk'!$A$5:$A$69,0))-1 -> 0.027 | N30: =INDEX('Fcst Walk'!$J$5:$J$69,MATCH($C30,'Fcst Walk'!$A$5:$A$69,0))/$D30-1 -> 0.030395393 | O30: =INDEX('Fcst Walk'!$N$5:$N$69,MATCH($C30,'Fcst Walk'!$A$5:$A$69,0))/$D30-1 -> 0.059246464 | P30: =INDEX('Fcst Walk'!$R$5:$R$69,MATCH($C30,'Fcst Walk'!$A$5:$A$69,0))/$D30-1 -> 0.087846119 | Q30: =INDEX('Fcst Walk'!$AM$5:$AM$69,MATCH($C30,'Fcst Walk'!$A$5:$A$69,0)) -> 0.60584901 | R30: =INDEX('Fcst Walk'!$AN$5:$AN$69,MATCH($C30,'Fcst Walk'!$A$5:$A$69,0)) | S30: =AVERAGE(INDEX('Realpage - His. Rent Change'!$I$2:$AV$577,MATCH($C30,'Realpage - His. Rent Change'!$A$2:$A$577,0),0)) -> 0.05962 | U30: =IF(T30="",S30,AVERAGE(S30,T30)) -> 0.05962 | V30: =IF(H30>=0,0,-H30/U30) -> 0
B31: =ROW()-4 -> 27 | C31: Charleston-North Charleston, SC | D31: =SUMIFS('Realpage Data'!$R$2:$R$899,'Realpage Data'!$A$2:$A$899,$C31,'Realpage Data'!$F$2:$F$899,"Rent Roll (Rev/OSF)") -> 1.8198717 | E31: =SUMIFS('Realpage Data'!$R$2:$R$899,'Realpage Data'!$A$2:$A$899,$C31,'Realpage Data'!$F$2:$F$899,"Asking RPSF") -> 1.867 | F31: =SUMIFS('Realpage Data'!$R$2:$R$899,'Realpage Data'!$A$2:$A$899,$C31,'Realpage Data'!$F$2:$F$899,"Effective RPSF") -> 1.83 | G31: =E31/$D31-1 -> 0.02589652 | H31: =F31/$D31-1 -> 0.0055654159 | I31: =SUMIFS('RP - Unit Starts'!$AC$2:$AC$451,'RP - Unit Starts'!$A$2:$A$451,$C31,'RP - Unit Starts'!$F$2:$F$451,"Annual Unit Starts")/SUMIFS('RP - Unit Starts'!$AC$2:$AC$451,'RP - Unit Starts'!$A$2:$A$451,$C31,'RP - Unit Starts'!$F$2:$F$451,"Existing Units") -> 0.029310723 | J31: =SUMIFS('Realpage Data'!$V$2:$V$899,'Realpage Data'!$A$2:$A$899,$C31,'Realpage Data'!$F$2:$F$899,"Existing Units")/SUMIFS('Realpage Data'!$R$2:$R$899,'Realpage Data'!$A$2:$A$899,$C31,'Realpage Data'!$F$2:$F$899,"Existing Units")-1 -> 0.023974856 | K31: =INDEX('Fcst Walk'!$J$5:$J$69,MATCH($C31,'Fcst Walk'!$A$5:$A$69,0))/INDEX('Fcst Walk'!$F$5:$F$69,MATCH($C31,'Fcst Walk'!$A$5:$A$69,0))-1 -> 0.025 | L31: =INDEX('Fcst Walk'!$N$5:$N$69,MATCH($C31,'Fcst Walk'!$A$5:$A$69,0))/INDEX('Fcst Walk'!$J$5:$J$69,MATCH($C31,'Fcst Walk'!$A$5:$A$69,0))-1 -> 0.024 | M31: =INDEX('Fcst Walk'!$R$5:$R$69,MATCH($C31,'Fcst Walk'!$A$5:$A$69,0))/INDEX('Fcst Walk'!$N$5:$N$69,MATCH($C31,'Fcst Walk'!$A$5:$A$69,0))-1 -> 0.022 | N31: =INDEX('Fcst Walk'!$J$5:$J$69,MATCH($C31,'Fcst Walk'!$A$5:$A$69,0))/$D31-1 -> 0.030704551 | O31: =INDEX('Fcst Walk'!$N$5:$N$69,MATCH($C31,'Fcst Walk'!$A$5:$A$69,0))/$D31-1 -> 0.055441461 | P31: =INDEX('Fcst Walk'!$R$5:$R$69,MATCH($C31,'Fcst Walk'!$A$5:$A$69,0))/$D31-1 -> 0.078661173 | Q31: =INDEX('Fcst Walk'!$AM$5:$AM$69,MATCH($C31,'Fcst Walk'!$A$5:$A$69,0)) -> 0.6128969 | R31: =INDEX('Fcst Walk'!$AN$5:$AN$69,MATCH($C31,'Fcst Walk'!$A$5:$A$69,0)) | S31: =AVERAGE(INDEX('Realpage - His. Rent Change'!$I$2:$AV$577,MATCH($C31,'Realpage - His. Rent Change'!$A$2:$A$577,0),0)) -> 0.06082 | U31: =IF(T31="",S31,AVERAGE(S31,T31)) -> 0.06082 | V31: =IF(H31>=0,0,-H31/U31) -> 0
B32: =ROW()-4 -> 28 | C32: Fort Collins-Loveland, CO | D32: =SUMIFS('Realpage Data'!$R$2:$R$899,'Realpage Data'!$A$2:$A$899,$C32,'Realpage Data'!$F$2:$F$899,"Rent Roll (Rev/OSF)") -> 1.9199955 | E32: =SUMIFS('Realpage Data'!$R$2:$R$899,'Realpage Data'!$A$2:$A$899,$C32,'Realpage Data'!$F$2:$F$899,"Asking RPSF") -> 2.045 | F32: =SUMIFS('Realpage Data'!$R$2:$R$899,'Realpage Data'!$A$2:$A$899,$C32,'Realpage Data'!$F$2:$F$899,"Effective RPSF") -> 2.024 | G32: =E32/$D32-1 -> 0.065106638 | H32: =F32/$D32-1 -> 0.054169112 | I32: =SUMIFS('RP - Unit Starts'!$AC$2:$AC$451,'RP - Unit Starts'!$A$2:$A$451,$C32,'RP - Unit Starts'!$F$2:$F$451,"Annual Unit Starts")/SUMIFS('RP - Unit Starts'!$AC$2:$AC$451,'RP - Unit Starts'!$A$2:$A$451,$C32,'RP - Unit Starts'!$F$2:$F$451,"Existing Units") -> 0.028676145 | J32: =SUMIFS('Realpage Data'!$V$2:$V$899,'Realpage Data'!$A$2:$A$899,$C32,'Realpage Data'!$F$2:$F$899,"Existing Units")/SUMIFS('Realpage Data'!$R$2:$R$899,'Realpage Data'!$A$2:$A$899,$C32,'Realpage Data'!$F$2:$F$899,"Existing Units")-1 -> 0.046840388 | K32: =INDEX('Fcst Walk'!$J$5:$J$69,MATCH($C32,'Fcst Walk'!$A$5:$A$69,0))/INDEX('Fcst Walk'!$F$5:$F$69,MATCH($C32,'Fcst Walk'!$A$5:$A$69,0))-1 -> 0.015 | L32: =INDEX('Fcst Walk'!$N$5:$N$69,MATCH($C32,'Fcst Walk'!$A$5:$A$69,0))/INDEX('Fcst Walk'!$J$5:$J$69,MATCH($C32,'Fcst Walk'!$A$5:$A$69,0))-1 -> 0.018 | M32: =INDEX('Fcst Walk'!$R$5:$R$69,MATCH($C32,'Fcst Walk'!$A$5:$A$69,0))/INDEX('Fcst Walk'!$N$5:$N$69,MATCH($C32,'Fcst Walk'!$A$5:$A$69,0))-1 -> 0.019 | N32: =INDEX('Fcst Walk'!$J$5:$J$69,MATCH($C32,'Fcst Walk'!$A$5:$A$69,0))/$D32-1 -> 0.069981649 | O32: =INDEX('Fcst Walk'!$N$5:$N$69,MATCH($C32,'Fcst Walk'!$A$5:$A$69,0))/$D32-1 -> 0.089241319 | P32: =INDEX('Fcst Walk'!$R$5:$R$69,MATCH($C32,'Fcst Walk'!$A$5:$A$69,0))/$D32-1 -> 0.1099369 | Q32: =INDEX('Fcst Walk'!$AM$5:$AM$69,MATCH($C32,'Fcst Walk'!$A$5:$A$69,0)) -> 0.6287735 | R32: =INDEX('Fcst Walk'!$AN$5:$AN$69,MATCH($C32,'Fcst Walk'!$A$5:$A$69,0)) | S32: =AVERAGE(INDEX('Realpage - His. Rent Change'!$I$2:$AV$577,MATCH($C32,'Realpage - His. Rent Change'!$A$2:$A$577,0),0)) -> 0.037485 | U32: =IF(T32="",S32,AVERAGE(S32,T32)) -> 0.037485 | V32: =IF(H32>=0,0,-H32/U32) -> 0
B33: =ROW()-4 -> 29 | C33: Louisville/Jefferson County, KY-IN | D33: =SUMIFS('Realpage Data'!$R$2:$R$899,'Realpage Data'!$A$2:$A$899,$C33,'Realpage Data'!$F$2:$F$899,"Rent Roll (Rev/OSF)") -> 1.3246433 | E33: =SUMIFS('Realpage Data'!$R$2:$R$899,'Realpage Data'!$A$2:$A$899,$C33,'Realpage Data'!$F$2:$F$899,"Asking RPSF") -> 1.36 | F33: =SUMIFS('Realpage Data'!$R$2:$R$899,'Realpage Data'!$A$2:$A$899,$C33,'Realpage Data'!$F$2:$F$899,"Effective RPSF") -> 1.335 | G33: =E33/$D33-1 -> 0.026691481 | H33: =F33/$D33-1 -> 0.0078184763 | I33: =SUMIFS('RP - Unit Starts'!$AC$2:$AC$451,'RP - Unit Starts'!$A$2:$A$451,$C33,'RP - Unit Starts'!$F$2:$F$451,"Annual Unit Starts")/SUMIFS('RP - Unit Starts'!$AC$2:$AC$451,'RP - Unit Starts'!$A$2:$A$451,$C33,'RP - Unit Starts'!$F$2:$F$451,"Existing Units") -> 0.021078337 | J33: =SUMIFS('Realpage Data'!$V$2:$V$899,'Realpage Data'!$A$2:$A$899,$C33,'Realpage Data'!$F$2:$F$899,"Existing Units")/SUMIFS('Realpage Data'!$R$2:$R$899,'Realpage Data'!$A$2:$A$899,$C33,'Realpage Data'!$F$2:$F$899,"Existing Units")-1 -> 0.027456426 | K33: =INDEX('Fcst Walk'!$J$5:$J$69,MATCH($C33,'Fcst Walk'!$A$5:$A$69,0))/INDEX('Fcst Walk'!$F$5:$F$69,MATCH($C33,'Fcst Walk'!$A$5:$A$69,0))-1 -> 0.015 | L33: =INDEX('Fcst Walk'!$N$5:$N$69,MATCH($C33,'Fcst Walk'!$A$5:$A$69,0))/INDEX('Fcst Walk'!$J$5:$J$69,MATCH($C33,'Fcst Walk'!$A$5:$A$69,0))-1 -> 0.016 | M33: =INDEX('Fcst Walk'!$R$5:$R$69,MATCH($C33,'Fcst Walk'!$A$5:$A$69,0))/INDEX('Fcst Walk'!$N$5:$N$69,MATCH($C33,'Fcst Walk'!$A$5:$A$69,0))-1 -> 0.017 | N33: =INDEX('Fcst Walk'!$J$5:$J$69,MATCH($C33,'Fcst Walk'!$A$5:$A$69,0))/$D33-1 -> 0.022935753 | O33: =INDEX('Fcst Walk'!$N$5:$N$69,MATCH($C33,'Fcst Walk'!$A$5:$A$69,0))/$D33-1 -> 0.039302725 | P33: =INDEX('Fcst Walk'!$R$5:$R$69,MATCH($C33,'Fcst Walk'!$A$5:$A$69,0))/$D33-1 -> 0.056970872 | Q33: =INDEX('Fcst Walk'!$AM$5:$AM$69,MATCH($C33,'Fcst Walk'!$A$5:$A$69,0)) -> 0.65944263 | R33: =INDEX('Fcst Walk'!$AN$5:$AN$69,MATCH($C33,'Fcst Walk'!$A$5:$A$69,0)) | S33: =AVERAGE(INDEX('Realpage - His. Rent Change'!$I$2:$AV$577,MATCH($C33,'Realpage - His. Rent Change'!$A$2:$A$577,0),0)) -> 0.0499425 | U33: =IF(T33="",S33,AVERAGE(S33,T33)) -> 0.0499425 | V33: =IF(H33>=0,0,-H33/U33) -> 0
B34: =ROW()-4 -> 30 | C34: Columbia, SC | D34: =SUMIFS('Realpage Data'!$R$2:$R$899,'Realpage Data'!$A$2:$A$899,$C34,'Realpage Data'!$F$2:$F$899,"Rent Roll (Rev/OSF)") -> 1.3548819 | E34: =SUMIFS('Realpage Data'!$R$2:$R$899,'Realpage Data'!$A$2:$A$899,$C34,'Realpage Data'!$F$2:$F$899,"Asking RPSF") -> 1.375 | F34: =SUMIFS('Realpage Data'!$R$2:$R$899,'Realpage Data'!$A$2:$A$899,$C34,'Realpage Data'!$F$2:$F$899,"Effective RPSF") -> 1.364 | G34: =E34/$D34-1 -> 0.014848573 | H34: =F34/$D34-1 -> 0.0067297843 | I34: =SUMIFS('RP - Unit Starts'!$AC$2:$AC$451,'RP - Unit Starts'!$A$2:$A$451,$C34,'RP - Unit Starts'!$F$2:$F$451,"Annual Unit Starts")/SUMIFS('RP - Unit Starts'!$AC$2:$AC$451,'RP - Unit Starts'!$A$2:$A$451,$C34,'RP - Unit Starts'!$F$2:$F$451,"Existing Units") -> 0.016225482 | J34: =SUMIFS('Realpage Data'!$V$2:$V$899,'Realpage Data'!$A$2:$A$899,$C34,'Realpage Data'!$F$2:$F$899,"Existing Units")/SUMIFS('Realpage Data'!$R$2:$R$899,'Realpage Data'!$A$2:$A$899,$C34,'Realpage Data'!$F$2:$F$899,"Existing Units")-1 -> 0.0098269813 | K34: =INDEX('Fcst Walk'!$J$5:$J$69,MATCH($C34,'Fcst Walk'!$A$5:$A$69,0))/INDEX('Fcst Walk'!$F$5:$F$69,MATCH($C34,'Fcst Walk'!$A$5:$A$69,0))-1 -> 0.005 | L34: =INDEX('Fcst Walk'!$N$5:$N$69,MATCH($C34,'Fcst Walk'!$A$5:$A$69,0))/INDEX('Fcst Walk'!$J$5:$J$69,MATCH($C34,'Fcst Walk'!$A$5:$A$69,0))-1 -> 0.017 | M34: =INDEX('Fcst Walk'!$R$5:$R$69,MATCH($C34,'Fcst Walk'!$A$5:$A$69,0))/INDEX('Fcst Walk'!$N$5:$N$69,MATCH($C34,'Fcst Walk'!$A$5:$A$69,0))-1 -> 0.023 | N34: =INDEX('Fcst Walk'!$J$5:$J$69,MATCH($C34,'Fcst Walk'!$A$5:$A$69,0))/$D34-1 -> 0.011763433 | O34: =INDEX('Fcst Walk'!$N$5:$N$69,MATCH($C34,'Fcst Walk'!$A$5:$A$69,0))/$D34-1 -> 0.028963412 | P34: =INDEX('Fcst Walk'!$R$5:$R$69,MATCH($C34,'Fcst Walk'!$A$5:$A$69,0))/$D34-1 -> 0.05262957 | Q34: =INDEX('Fcst Walk'!$AM$5:$AM$69,MATCH($C34,'Fcst Walk'!$A$5:$A$69,0)) -> 0.75202167 | R34: =INDEX('Fcst Walk'!$AN$5:$AN$69,MATCH($C34,'Fcst Walk'!$A$5:$A$69,0)) | S34: =AVERAGE(INDEX('Realpage - His. Rent Change'!$I$2:$AV$577,MATCH($C34,'Realpage - His. Rent Change'!$A$2:$A$577,0),0)) -> 0.0495175 | U34: =IF(T34="",S34,AVERAGE(S34,T34)) -> 0.0495175 | V34: =IF(H34>=0,0,-H34/U34) -> 0
B35: =ROW()-4 -> 31 | C35: Nashville-Davidson--Murfreesboro--Franklin, TN | D35: =SUMIFS('Realpage Data'!$R$2:$R$899,'Realpage Data'!$A$2:$A$899,$C35,'Realpage Data'!$F$2:$F$899,"Rent Roll (Rev/OSF)") -> 1.685523 | E35: =SUMIFS('Realpage Data'!$R$2:$R$899,'Realpage Data'!$A$2:$A$899,$C35,'Realpage Data'!$F$2:$F$899,"Asking RPSF") -> 1.763 | F35: =SUMIFS('Realpage Data'!$R$2:$R$899,'Realpage Data'!$A$2:$A$899,$C35,'Realpage Data'!$F$2:$F$899,"Effective RPSF") -> 1.693 | G35: =E35/$D35-1 -> 0.045966154 | H35: =F35/$D35-1 -> 0.0044360177 | I35: =SUMIFS('RP - Unit Starts'!$AC$2:$AC$451,'RP - Unit Starts'!$A$2:$A$451,$C35,'RP - Unit Starts'!$F$2:$F$451,"Annual Unit Starts")/SUMIFS('RP - Unit Starts'!$AC$2:$AC$451,'RP - Unit Starts'!$A$2:$A$451,$C35,'RP - Unit Starts'!$F$2:$F$451,"Existing Units") -> 0.028013395 | J35: =SUMIFS('Realpage Data'!$V$2:$V$899,'Realpage Data'!$A$2:$A$899,$C35,'Realpage Data'!$F$2:$F$899,"Existing Units")/SUMIFS('Realpage Data'!$R$2:$R$899,'Realpage Data'!$A$2:$A$899,$C35,'Realpage Data'!$F$2:$F$899,"Existing Units")-1 -> 0.024463145 | K35: =INDEX('Fcst Walk'!$J$5:$J$69,MATCH($C35,'Fcst Walk'!$A$5:$A$69,0))/INDEX('Fcst Walk'!$F$5:$F$69,MATCH($C35,'Fcst Walk'!$A$5:$A$69,0))-1 -> 0.023 | L35: =INDEX('Fcst Walk'!$N$5:$N$69,MATCH($C35,'Fcst Walk'!$A$5:$A$69,0))/INDEX('Fcst Walk'!$J$5:$J$69,MATCH($C35,'Fcst Walk'!$A$5:$A$69,0))-1 -> 0.027 | M35: =INDEX('Fcst Walk'!$R$5:$R$69,MATCH($C35,'Fcst Walk'!$A$5:$A$69,0))/INDEX('Fcst Walk'!$N$5:$N$69,MATCH($C35,'Fcst Walk'!$A$5:$A$69,0))-1 -> 0.029 | N35: =INDEX('Fcst Walk'!$J$5:$J$69,MATCH($C35,'Fcst Walk'!$A$5:$A$69,0))/$D35-1 -> 0.027538046 | O35: =INDEX('Fcst Walk'!$N$5:$N$69,MATCH($C35,'Fcst Walk'!$A$5:$A$69,0))/$D35-1 -> 0.055281573 | P35: =INDEX('Fcst Walk'!$R$5:$R$69,MATCH($C35,'Fcst Walk'!$A$5:$A$69,0))/$D35-1 -> 0.085884739 | Q35: =INDEX('Fcst Walk'!$AM$5:$AM$69,MATCH($C35,'Fcst Walk'!$A$5:$A$69,0)) -> 0.76105752 | R35: =INDEX('Fcst Walk'!$AN$5:$AN$69,MATCH($C35,'Fcst Walk'!$A$5:$A$69,0)) | S35: =AVERAGE(INDEX('Realpage - His. Rent Change'!$I$2:$AV$577,MATCH($C35,'Realpage - His. Rent Change'!$A$2:$A$577,0),0)) -> 0.04817 | T35: 0.0365 | U35: =IF(T35="",S35,AVERAGE(S35,T35)) -> 0.042335 | V35: =IF(H35>=0,0,-H35/U35) -> 0
B36: =ROW()-4 -> 32 | C36: Birmingham, AL | D36: =SUMIFS('Realpage Data'!$R$2:$R$899,'Realpage Data'!$A$2:$A$899,$C36,'Realpage Data'!$F$2:$F$899,"Rent Roll (Rev/OSF)") -> 1.2671121 | E36: =SUMIFS('Realpage Data'!$R$2:$R$899,'Realpage Data'!$A$2:$A$899,$C36,'Realpage Data'!$F$2:$F$899,"Asking RPSF") -> 1.303 | F36: =SUMIFS('Realpage Data'!$R$2:$R$899,'Realpage Data'!$A$2:$A$899,$C36,'Realpage Data'!$F$2:$F$899,"Effective RPSF") -> 1.273 | G36: =E36/$D36-1 -> 0.028322553 | H36: =F36/$D36-1 -> 0.0046466691 | I36: =SUMIFS('RP - Unit Starts'!$AC$2:$AC$451,'RP - Unit Starts'!$A$2:$A$451,$C36,'RP - Unit Starts'!$F$2:$F$451,"Annual Unit Starts")/SUMIFS('RP - Unit Starts'!$AC$2:$AC$451,'RP - Unit Starts'!$A$2:$A$451,$C36,'RP - Unit Starts'!$F$2:$F$451,"Existing Units") -> 0.001636324 | J36: =SUMIFS('Realpage Data'!$V$2:$V$899,'Realpage Data'!$A$2:$A$899,$C36,'Realpage Data'!$F$2:$F$899,"Existing Units")/SUMIFS('Realpage Data'!$R$2:$R$899,'Realpage Data'!$A$2:$A$899,$C36,'Realpage Data'!$F$2:$F$899,"Existing Units")-1 -> 0.0053089622 | K36: =INDEX('Fcst Walk'!$J$5:$J$69,MATCH($C36,'Fcst Walk'!$A$5:$A$69,0))/INDEX('Fcst Walk'!$F$5:$F$69,MATCH($C36,'Fcst Walk'!$A$5:$A$69,0))-1 -> 0.012 | L36: =INDEX('Fcst Walk'!$N$5:$N$69,MATCH($C36,'Fcst Walk'!$A$5:$A$69,0))/INDEX('Fcst Walk'!$J$5:$J$69,MATCH($C36,'Fcst Walk'!$A$5:$A$69,0))-1 -> 0.029 | M36: =INDEX('Fcst Walk'!$R$5:$R$69,MATCH($C36,'Fcst Walk'!$A$5:$A$69,0))/INDEX('Fcst Walk'!$N$5:$N$69,MATCH($C36,'Fcst Walk'!$A$5:$A$69,0))-1 -> 0.022 | N36: =INDEX('Fcst Walk'!$J$5:$J$69,MATCH($C36,'Fcst Walk'!$A$5:$A$69,0))/$D36-1 -> 0.016702429 | O36: =INDEX('Fcst Walk'!$N$5:$N$69,MATCH($C36,'Fcst Walk'!$A$5:$A$69,0))/$D36-1 -> 0.0461868 | P36: =INDEX('Fcst Walk'!$R$5:$R$69,MATCH($C36,'Fcst Walk'!$A$5:$A$69,0))/$D36-1 -> 0.069202909 | Q36: =INDEX('Fcst Walk'!$AM$5:$AM$69,MATCH($C36,'Fcst Walk'!$A$5:$A$69,0)) -> 0.76976795 | R36: =INDEX('Fcst Walk'!$AN$5:$AN$69,MATCH($C36,'Fcst Walk'!$A$5:$A$69,0)) | S36: =AVERAGE(INDEX('Realpage - His. Rent Change'!$I$2:$AV$577,MATCH($C36,'Realpage - His. Rent Change'!$A$2:$A$577,0),0)) -> 0.04618 | U36: =IF(T36="",S36,AVERAGE(S36,T36)) -> 0.04618 | V36: =IF(H36>=0,0,-H36/U36) -> 0
B37: =ROW()-4 -> 33 | C37: Fort Lauderdale-Pompano Beach-Sunrise, FL | D37: =SUMIFS('Realpage Data'!$R$2:$R$899,'Realpage Data'!$A$2:$A$899,$C37,'Realpage Data'!$F$2:$F$899,"Rent Roll (Rev/OSF)") -> 2.4479067 | E37: =SUMIFS('Realpage Data'!$R$2:$R$899,'Realpage Data'!$A$2:$A$899,$C37,'Realpage Data'!$F$2:$F$899,"Asking RPSF") -> 2.461 | F37: =SUMIFS('Realpage Data'!$R$2:$R$899,'Realpage Data'!$A$2:$A$899,$C37,'Realpage Data'!$F$2:$F$899,"Effective RPSF") -> 2.43 | G37: =E37/$D37-1 -> 0.0053487706 | H37: =F37/$D37-1 -> -0.0073151107 | I37: =SUMIFS('RP - Unit Starts'!$AC$2:$AC$451,'RP - Unit Starts'!$A$2:$A$451,$C37,'RP - Unit Starts'!$F$2:$F$451,"Annual Unit Starts")/SUMIFS('RP - Unit Starts'!$AC$2:$AC$451,'RP - Unit Starts'!$A$2:$A$451,$C37,'RP - Unit Starts'!$F$2:$F$451,"Existing Units") -> 0.0097416072 | J37: =SUMIFS('Realpage Data'!$V$2:$V$899,'Realpage Data'!$A$2:$A$899,$C37,'Realpage Data'!$F$2:$F$899,"Existing Units")/SUMIFS('Realpage Data'!$R$2:$R$899,'Realpage Data'!$A$2:$A$899,$C37,'Realpage Data'!$F$2:$F$899,"Existing Units")-1 -> 0.020411209 | K37: =INDEX('Fcst Walk'!$J$5:$J$69,MATCH($C37,'Fcst Walk'!$A$5:$A$69,0))/INDEX('Fcst Walk'!$F$5:$F$69,MATCH($C37,'Fcst Walk'!$A$5:$A$69,0))-1 -> 0.028 | L37: =INDEX('Fcst Walk'!$N$5:$N$69,MATCH($C37,'Fcst Walk'!$A$5:$A$69,0))/INDEX('Fcst Walk'!$J$5:$J$69,MATCH($C37,'Fcst Walk'!$A$5:$A$69,0))-1 -> 0.026 | M37: =INDEX('Fcst Walk'!$R$5:$R$69,MATCH($C37,'Fcst Walk'!$A$5:$A$69,0))/INDEX('Fcst Walk'!$N$5:$N$69,MATCH($C37,'Fcst Walk'!$A$5:$A$69,0))-1 -> 0.02 | N37: =INDEX('Fcst Walk'!$J$5:$J$69,MATCH($C37,'Fcst Walk'!$A$5:$A$69,0))/$D37-1 -> 0.020480066 | O37: =INDEX('Fcst Walk'!$N$5:$N$69,MATCH($C37,'Fcst Walk'!$A$5:$A$69,0))/$D37-1 -> 0.047012548 | P37: =INDEX('Fcst Walk'!$R$5:$R$69,MATCH($C37,'Fcst Walk'!$A$5:$A$69,0))/$D37-1 -> 0.067952799 | Q37: =INDEX('Fcst Walk'!$AM$5:$AM$69,MATCH($C37,'Fcst Walk'!$A$5:$A$69,0)) -> 0.786616 | R37: =INDEX('Fcst Walk'!$AN$5:$AN$69,MATCH($C37,'Fcst Walk'!$A$5:$A$69,0)) | S37: =AVERAGE(INDEX('Realpage - His. Rent Change'!$I$2:$AV$577,MATCH($C37,'Realpage - His. Rent Change'!$A$2:$A$577,0),0)) -> 0.05794 | T37: 0.0444 | U37: =IF(T37="",S37,AVERAGE(S37,T37)) -> 0.05117 | V37: =IF(H37>=0,0,-H37/U37) -> 0.14295702
B38: =ROW()-4 -> 34 | C38: Tucson, AZ | D38: =SUMIFS('Realpage Data'!$R$2:$R$899,'Realpage Data'!$A$2:$A$899,$C38,'Realpage Data'!$F$2:$F$899,"Rent Roll (Rev/OSF)") -> 1.4713929 | E38: =SUMIFS('Realpage Data'!$R$2:$R$899,'Realpage Data'!$A$2:$A$899,$C38,'Realpage Data'!$F$2:$F$899,"Asking RPSF") -> 1.506 | F38: =SUMIFS('Realpage Data'!$R$2:$R$899,'Realpage Data'!$A$2:$A$899,$C38,'Realpage Data'!$F$2:$F$899,"Effective RPSF") -> 1.474 | G38: =E38/$D38-1 -> 0.023519985 | H38: =F38/$D38-1 -> 0.0017718847 | I38: =SUMIFS('RP - Unit Starts'!$AC$2:$AC$451,'RP - Unit Starts'!$A$2:$A$451,$C38,'RP - Unit Starts'!$F$2:$F$451,"Annual Unit Starts")/SUMIFS('RP - Unit Starts'!$AC$2:$AC$451,'RP - Unit Starts'!$A$2:$A$451,$C38,'RP - Unit Starts'!$F$2:$F$451,"Existing Units") -> 0.0050482755 | J38: =SUMIFS('Realpage Data'!$V$2:$V$899,'Realpage Data'!$A$2:$A$899,$C38,'Realpage Data'!$F$2:$F$899,"Existing Units")/SUMIFS('Realpage Data'!$R$2:$R$899,'Realpage Data'!$A$2:$A$899,$C38,'Realpage Data'!$F$2:$F$899,"Existing Units")-1 -> 0.009824895 | K38: =INDEX('Fcst Walk'!$J$5:$J$69,MATCH($C38,'Fcst Walk'!$A$5:$A$69,0))/INDEX('Fcst Walk'!$F$5:$F$69,MATCH($C38,'Fcst Walk'!$A$5:$A$69,0))-1 -> 0.029 | L38: =INDEX('Fcst Walk'!$N$5:$N$69,MATCH($C38,'Fcst Walk'!$A$5:$A$69,0))/INDEX('Fcst Walk'!$J$5:$J$69,MATCH($C38,'Fcst Walk'!$A$5:$A$69,0))-1 -> 0.039 | M38: =INDEX('Fcst Walk'!$R$5:$R$69,MATCH($C38,'Fcst Walk'!$A$5:$A$69,0))/INDEX('Fcst Walk'!$N$5:$N$69,MATCH($C38,'Fcst Walk'!$A$5:$A$69,0))-1 -> 0.039 | N38: =INDEX('Fcst Walk'!$J$5:$J$69,MATCH($C38,'Fcst Walk'!$A$5:$A$69,0))/$D38-1 -> 0.030823269 | O38: =INDEX('Fcst Walk'!$N$5:$N$69,MATCH($C38,'Fcst Walk'!$A$5:$A$69,0))/$D38-1 -> 0.071025377 | P38: =INDEX('Fcst Walk'!$R$5:$R$69,MATCH($C38,'Fcst Walk'!$A$5:$A$69,0))/$D38-1 -> 0.11279537 | Q38: =INDEX('Fcst Walk'!$AM$5:$AM$69,MATCH($C38,'Fcst Walk'!$A$5:$A$69,0)) -> 0.82426986 | R38: =INDEX('Fcst Walk'!$AN$5:$AN$69,MATCH($C38,'Fcst Walk'!$A$5:$A$69,0)) | S38: =AVERAGE(INDEX('Realpage - His. Rent Change'!$I$2:$AV$577,MATCH($C38,'Realpage - His. Rent Change'!$A$2:$A$577,0),0)) -> 0.0635425 | U38: =IF(T38="",S38,AVERAGE(S38,T38)) -> 0.0635425 | V38: =IF(H38>=0,0,-H38/U38) -> 0
B39: =ROW()-4 -> 35 | C39: Albuquerque, NM | D39: =SUMIFS('Realpage Data'!$R$2:$R$899,'Realpage Data'!$A$2:$A$899,$C39,'Realpage Data'!$F$2:$F$899,"Rent Roll (Rev/OSF)") -> 1.627998 | E39: =SUMIFS('Realpage Data'!$R$2:$R$899,'Realpage Data'!$A$2:$A$899,$C39,'Realpage Data'!$F$2:$F$899,"Asking RPSF") -> 1.628 | F39: =SUMIFS('Realpage Data'!$R$2:$R$899,'Realpage Data'!$A$2:$A$899,$C39,'Realpage Data'!$F$2:$F$899,"Effective RPSF") -> 1.612 | G39: =E39/$D39-1 -> 1.2228985e-06 | H39: =F39/$D39-1 -> -0.0098267989 | I39: =SUMIFS('RP - Unit Starts'!$AC$2:$AC$451,'RP - Unit Starts'!$A$2:$A$451,$C39,'RP - Unit Starts'!$F$2:$F$451,"Annual Unit Starts")/SUMIFS('RP - Unit Starts'!$AC$2:$AC$451,'RP - Unit Starts'!$A$2:$A$451,$C39,'RP - Unit Starts'!$F$2:$F$451,"Existing Units") -> 0.0046547843 | J39: =SUMIFS('Realpage Data'!$V$2:$V$899,'Realpage Data'!$A$2:$A$899,$C39,'Realpage Data'!$F$2:$F$899,"Existing Units")/SUMIFS('Realpage Data'!$R$2:$R$899,'Realpage Data'!$A$2:$A$899,$C39,'Realpage Data'!$F$2:$F$899,"Existing Units")-1 -> 0.0056873001 | K39: =INDEX('Fcst Walk'!$J$5:$J$69,MATCH($C39,'Fcst Walk'!$A$5:$A$69,0))/INDEX('Fcst Walk'!$F$5:$F$69,MATCH($C39,'Fcst Walk'!$A$5:$A$69,0))-1 -> 0.018 | L39: =INDEX('Fcst Walk'!$N$5:$N$69,MATCH($C39,'Fcst Walk'!$A$5:$A$69,0))/INDEX('Fcst Walk'!$J$5:$J$69,MATCH($C39,'Fcst Walk'!$A$5:$A$69,0))-1 -> 0.036 | M39: =INDEX('Fcst Walk'!$R$5:$R$69,MATCH($C39,'Fcst Walk'!$A$5:$A$69,0))/INDEX('Fcst Walk'!$N$5:$N$69,MATCH($C39,'Fcst Walk'!$A$5:$A$69,0))-1 -> 0.037 | N39: =INDEX('Fcst Walk'!$J$5:$J$69,MATCH($C39,'Fcst Walk'!$A$5:$A$69,0))/$D39-1 -> 0.0079963187 | O39: =INDEX('Fcst Walk'!$N$5:$N$69,MATCH($C39,'Fcst Walk'!$A$5:$A$69,0))/$D39-1 -> 0.044284186 | P39: =INDEX('Fcst Walk'!$R$5:$R$69,MATCH($C39,'Fcst Walk'!$A$5:$A$69,0))/$D39-1 -> 0.082922701 | Q39: =INDEX('Fcst Walk'!$AM$5:$AM$69,MATCH($C39,'Fcst Walk'!$A$5:$A$69,0)) -> 0.92660794 | R39: =INDEX('Fcst Walk'!$AN$5:$AN$69,MATCH($C39,'Fcst Walk'!$A$5:$A$69,0)) | S39: =AVERAGE(INDEX('Realpage - His. Rent Change'!$I$2:$AV$577,MATCH($C39,'Realpage - His. Rent Change'!$A$2:$A$577,0),0)) -> 0.060935 | U39: =IF(T39="",S39,AVERAGE(S39,T39)) -> 0.060935 | V39: =IF(H39>=0,0,-H39/U39) -> 0.16126691
B40: =ROW()-4 -> 36 | C40: Indianapolis-Carmel-Greenwood/Greencastle, IN | D40: =SUMIFS('Realpage Data'!$R$2:$R$899,'Realpage Data'!$A$2:$A$899,$C40,'Realpage Data'!$F$2:$F$899,"Rent Roll (Rev/OSF)") -> 1.465558 | E40: =SUMIFS('Realpage Data'!$R$2:$R$899,'Realpage Data'!$A$2:$A$899,$C40,'Realpage Data'!$F$2:$F$899,"Asking RPSF") -> 1.449 | F40: =SUMIFS('Realpage Data'!$R$2:$R$899,'Realpage Data'!$A$2:$A$899,$C40,'Realpage Data'!$F$2:$F$899,"Effective RPSF") -> 1.435 | G40: =E40/$D40-1 -> -0.011298075 | H40: =F40/$D40-1 -> -0.02085075 | I40: =SUMIFS('RP - Unit Starts'!$AC$2:$AC$451,'RP - Unit Starts'!$A$2:$A$451,$C40,'RP - Unit Starts'!$F$2:$F$451,"Annual Unit Starts")/SUMIFS('RP - Unit Starts'!$AC$2:$AC$451,'RP - Unit Starts'!$A$2:$A$451,$C40,'RP - Unit Starts'!$F$2:$F$451,"Existing Units") -> 0.016665342 | J40: =SUMIFS('Realpage Data'!$V$2:$V$899,'Realpage Data'!$A$2:$A$899,$C40,'Realpage Data'!$F$2:$F$899,"Existing Units")/SUMIFS('Realpage Data'!$R$2:$R$899,'Realpage Data'!$A$2:$A$899,$C40,'Realpage Data'!$F$2:$F$899,"Existing Units")-1 -> 0.018821348 | K40: =INDEX('Fcst Walk'!$J$5:$J$69,MATCH($C40,'Fcst Walk'!$A$5:$A$69,0))/INDEX('Fcst Walk'!$F$5:$F$69,MATCH($C40,'Fcst Walk'!$A$5:$A$69,0))-1 -> 0.028 | L40: =INDEX('Fcst Walk'!$N$5:$N$69,MATCH($C40,'Fcst Walk'!$A$5:$A$69,0))/INDEX('Fcst Walk'!$J$5:$J$69,MATCH($C40,'Fcst Walk'!$A$5:$A$69,0))-1 -> 0.031 | M40: =INDEX('Fcst Walk'!$R$5:$R$69,MATCH($C40,'Fcst Walk'!$A$5:$A$69,0))/INDEX('Fcst Walk'!$N$5:$N$69,MATCH($C40,'Fcst Walk'!$A$5:$A$69,0))-1 -> 0.032 | N40: =INDEX('Fcst Walk'!$J$5:$J$69,MATCH($C40,'Fcst Walk'!$A$5:$A$69,0))/$D40-1 -> 0.0065654286 | O40: =INDEX('Fcst Walk'!$N$5:$N$69,MATCH($C40,'Fcst Walk'!$A$5:$A$69,0))/$D40-1 -> 0.037768957 | P40: =INDEX('Fcst Walk'!$R$5:$R$69,MATCH($C40,'Fcst Walk'!$A$5:$A$69,0))/$D40-1 -> 0.070977564 | Q40: =INDEX('Fcst Walk'!$AM$5:$AM$69,MATCH($C40,'Fcst Walk'!$A$5:$A$69,0)) -> 0.92943873 | R40: =INDEX('Fcst Walk'!$AN$5:$AN$69,MATCH($C40,'Fcst Walk'!$A$5:$A$69,0)) | S40: =AVERAGE(INDEX('Realpage - His. Rent Change'!$I$2:$AV$577,MATCH($C40,'Realpage - His. Rent Change'!$A$2:$A$577,0),0)) -> 0.055975 | T40: 0.0459 | U40: =IF(T40="",S40,AVERAGE(S40,T40)) -> 0.0509375 | V40: =IF(H40>=0,0,-H40/U40) -> 0.40933988
B41: =ROW()-4 -> 37 | C41: Oklahoma City, OK | D41: =SUMIFS('Realpage Data'!$R$2:$R$899,'Realpage Data'!$A$2:$A$899,$C41,'Realpage Data'!$F$2:$F$899,"Rent Roll (Rev/OSF)") -> 1.274613 | E41: =SUMIFS('Realpage Data'!$R$2:$R$899,'Realpage Data'!$A$2:$A$899,$C41,'Realpage Data'!$F$2:$F$899,"Asking RPSF") -> 1.244 | F41: =SUMIFS('Realpage Data'!$R$2:$R$899,'Realpage Data'!$A$2:$A$899,$C41,'Realpage Data'!$F$2:$F$899,"Effective RPSF") -> 1.232 | G41: =E41/$D41-1 -> -0.02401752 | H41: =F41/$D41-1 -> -0.033432142 | I41: =SUMIFS('RP - Unit Starts'!$AC$2:$AC$451,'RP - Unit Starts'!$A$2:$A$451,$C41,'RP - Unit Starts'!$F$2:$F$451,"Annual Unit Starts")/SUMIFS('RP - Unit Starts'!$AC$2:$AC$451,'RP - Unit Starts'!$A$2:$A$451,$C41,'RP - Unit Starts'!$F$2:$F$451,"Existing Units") -> 0 | J41: =SUMIFS('Realpage Data'!$V$2:$V$899,'Realpage Data'!$A$2:$A$899,$C41,'Realpage Data'!$F$2:$F$899,"Existing Units")/SUMIFS('Realpage Data'!$R$2:$R$899,'Realpage Data'!$A$2:$A$899,$C41,'Realpage Data'!$F$2:$F$899,"Existing Units")-1 -> 0.0023471715 | K41: =INDEX('Fcst Walk'!$J$5:$J$69,MATCH($C41,'Fcst Walk'!$A$5:$A$69,0))/INDEX('Fcst Walk'!$F$5:$F$69,MATCH($C41,'Fcst Walk'!$A$5:$A$69,0))-1 -> 0.032 | L41: =INDEX('Fcst Walk'!$N$5:$N$69,MATCH($C41,'Fcst Walk'!$A$5:$A$69,0))/INDEX('Fcst Walk'!$J$5:$J$69,MATCH($C41,'Fcst Walk'!$A$5:$A$69,0))-1 -> 0.034 | M41: =INDEX('Fcst Walk'!$R$5:$R$69,MATCH($C41,'Fcst Walk'!$A$5:$A$69,0))/INDEX('Fcst Walk'!$N$5:$N$69,MATCH($C41,'Fcst Walk'!$A$5:$A$69,0))-1 -> 0.037 | N41: =INDEX('Fcst Walk'!$J$5:$J$69,MATCH($C41,'Fcst Walk'!$A$5:$A$69,0))/$D41-1 -> -0.0025019703 | O41: =INDEX('Fcst Walk'!$N$5:$N$69,MATCH($C41,'Fcst Walk'!$A$5:$A$69,0))/$D41-1 -> 0.031412963 | P41: =INDEX('Fcst Walk'!$R$5:$R$69,MATCH($C41,'Fcst Walk'!$A$5:$A$69,0))/$D41-1 -> 0.069575242 | Q41: =INDEX('Fcst Walk'!$AM$5:$AM$69,MATCH($C41,'Fcst Walk'!$A$5:$A$69,0)) -> 1.049282 | R41: =INDEX('Fcst Walk'!$AN$5:$AN$69,MATCH($C41,'Fcst Walk'!$A$5:$A$69,0)) | S41: =AVERAGE(INDEX('Realpage - His. Rent Change'!$I$2:$AV$577,MATCH($C41,'Realpage - His. Rent Change'!$A$2:$A$577,0),0)) -> 0.0419075 | U41: =IF(T41="",S41,AVERAGE(S41,T41)) -> 0.0419075 | V41: =IF(H41>=0,0,-H41/U41) -> 0.79776035
B42: =ROW()-4 -> 38 | C42: Naples-Marco Island, FL | D42: =SUMIFS('Realpage Data'!$R$2:$R$899,'Realpage Data'!$A$2:$A$899,$C42,'Realpage Data'!$F$2:$F$899,"Rent Roll (Rev/OSF)") -> 1.9260124 | E42: =SUMIFS('Realpage Data'!$R$2:$R$899,'Realpage Data'!$A$2:$A$899,$C42,'Realpage Data'!$F$2:$F$899,"Asking RPSF") -> 1.991 | F42: =SUMIFS('Realpage Data'!$R$2:$R$899,'Realpage Data'!$A$2:$A$899,$C42,'Realpage Data'!$F$2:$F$899,"Effective RPSF") -> 1.899 | G42: =E42/$D42-1 -> 0.033742048 | H42: =F42/$D42-1 -> -0.014025038 | I42: =SUMIFS('RP - Unit Starts'!$AC$2:$AC$451,'RP - Unit Starts'!$A$2:$A$451,$C42,'RP - Unit Starts'!$F$2:$F$451,"Annual Unit Starts")/SUMIFS('RP - Unit Starts'!$AC$2:$AC$451,'RP - Unit Starts'!$A$2:$A$451,$C42,'RP - Unit Starts'!$F$2:$F$451,"Existing Units") -> 0.01577783 | J42: =SUMIFS('Realpage Data'!$V$2:$V$899,'Realpage Data'!$A$2:$A$899,$C42,'Realpage Data'!$F$2:$F$899,"Existing Units")/SUMIFS('Realpage Data'!$R$2:$R$899,'Realpage Data'!$A$2:$A$899,$C42,'Realpage Data'!$F$2:$F$899,"Existing Units")-1 -> 0.043898463 | K42: =INDEX('Fcst Walk'!$J$5:$J$69,MATCH($C42,'Fcst Walk'!$A$5:$A$69,0))/INDEX('Fcst Walk'!$F$5:$F$69,MATCH($C42,'Fcst Walk'!$A$5:$A$69,0))-1 -> 0.017 | L42: =INDEX('Fcst Walk'!$N$5:$N$69,MATCH($C42,'Fcst Walk'!$A$5:$A$69,0))/INDEX('Fcst Walk'!$J$5:$J$69,MATCH($C42,'Fcst Walk'!$A$5:$A$69,0))-1 -> 0.026 | M42: =INDEX('Fcst Walk'!$R$5:$R$69,MATCH($C42,'Fcst Walk'!$A$5:$A$69,0))/INDEX('Fcst Walk'!$N$5:$N$69,MATCH($C42,'Fcst Walk'!$A$5:$A$69,0))-1 -> 0.03 | N42: =INDEX('Fcst Walk'!$J$5:$J$69,MATCH($C42,'Fcst Walk'!$A$5:$A$69,0))/$D42-1 -> 0.0027365364 | O42: =INDEX('Fcst Walk'!$N$5:$N$69,MATCH($C42,'Fcst Walk'!$A$5:$A$69,0))/$D42-1 -> 0.028807686 | P42: =INDEX('Fcst Walk'!$R$5:$R$69,MATCH($C42,'Fcst Walk'!$A$5:$A$69,0))/$D42-1 -> 0.059671917 | Q42: =INDEX('Fcst Walk'!$AM$5:$AM$69,MATCH($C42,'Fcst Walk'!$A$5:$A$69,0)) -> 1.4101287 | R42: =INDEX('Fcst Walk'!$AN$5:$AN$69,MATCH($C42,'Fcst Walk'!$A$5:$A$69,0)) | S42: =AVERAGE(INDEX('Realpage - His. Rent Change'!$I$2:$AV$577,MATCH($C42,'Realpage - His. Rent Change'!$A$2:$A$577,0),0)) -> 0.0683875 | U42: =IF(T42="",S42,AVERAGE(S42,T42)) -> 0.0683875 | V42: =IF(H42>=0,0,-H42/U42) -> 0.20508189
B43: =ROW()-4 -> 39 | C43: Huntsville, AL | D43: =SUMIFS('Realpage Data'!$R$2:$R$899,'Realpage Data'!$A$2:$A$899,$C43,'Realpage Data'!$F$2:$F$899,"Rent Roll (Rev/OSF)") -> 1.1607967 | E43: =SUMIFS('Realpage Data'!$R$2:$R$899,'Realpage Data'!$A$2:$A$899,$C43,'Realpage Data'!$F$2:$F$899,"Asking RPSF") -> 1.233 | F43: =SUMIFS('Realpage Data'!$R$2:$R$899,'Realpage Data'!$A$2:$A$899,$C43,'Realpage Data'!$F$2:$F$899,"Effective RPSF") -> 1.175 | G43: =E43/$D43-1 -> 0.062201542 | H43: =F43/$D43-1 -> 0.012235857 | I43: =SUMIFS('RP - Unit Starts'!$AC$2:$AC$451,'RP - Unit Starts'!$A$2:$A$451,$C43,'RP - Unit Starts'!$F$2:$F$451,"Annual Unit Starts")/SUMIFS('RP - Unit Starts'!$AC$2:$AC$451,'RP - Unit Starts'!$A$2:$A$451,$C43,'RP - Unit Starts'!$F$2:$F$451,"Existing Units") -> 0.028401115 | J43: =SUMIFS('Realpage Data'!$V$2:$V$899,'Realpage Data'!$A$2:$A$899,$C43,'Realpage Data'!$F$2:$F$899,"Existing Units")/SUMIFS('Realpage Data'!$R$2:$R$899,'Realpage Data'!$A$2:$A$899,$C43,'Realpage Data'!$F$2:$F$899,"Existing Units")-1 -> 0.021171041 | K43: =INDEX('Fcst Walk'!$J$5:$J$69,MATCH($C43,'Fcst Walk'!$A$5:$A$69,0))/INDEX('Fcst Walk'!$F$5:$F$69,MATCH($C43,'Fcst Walk'!$A$5:$A$69,0))-1 -> 0.021 | L43: =INDEX('Fcst Walk'!$N$5:$N$69,MATCH($C43,'Fcst Walk'!$A$5:$A$69,0))/INDEX('Fcst Walk'!$J$5:$J$69,MATCH($C43,'Fcst Walk'!$A$5:$A$69,0))-1 -> 0.026 | M43: =INDEX('Fcst Walk'!$R$5:$R$69,MATCH($C43,'Fcst Walk'!$A$5:$A$69,0))/INDEX('Fcst Walk'!$N$5:$N$69,MATCH($C43,'Fcst Walk'!$A$5:$A$69,0))-1 -> 0.021 | N43: =INDEX('Fcst Walk'!$J$5:$J$69,MATCH($C43,'Fcst Walk'!$A$5:$A$69,0))/$D43-1 -> 0.03349281 | O43: =INDEX('Fcst Walk'!$N$5:$N$69,MATCH($C43,'Fcst Walk'!$A$5:$A$69,0))/$D43-1 -> 0.060363623 | P43: =INDEX('Fcst Walk'!$R$5:$R$69,MATCH($C43,'Fcst Walk'!$A$5:$A$69,0))/$D43-1 -> 0.08263126 | Q43: =INDEX('Fcst Walk'!$AM$5:$AM$69,MATCH($C43,'Fcst Walk'!$A$5:$A$69,0)) -> 1.5059257 | R43: =INDEX('Fcst Walk'!$AN$5:$AN$69,MATCH($C43,'Fcst Walk'!$A$5:$A$69,0)) | S43: =AVERAGE(INDEX('Realpage - His. Rent Change'!$I$2:$AV$577,MATCH($C43,'Realpage - His. Rent Change'!$A$2:$A$577,0),0)) -> 0.0543775 | U43: =IF(T43="",S43,AVERAGE(S43,T43)) -> 0.0543775 | V43: =IF(H43>=0,0,-H43/U43) -> 0
B44: =ROW()-4 -> 40 | C44: Spokane-Spokane Valley, WA | D44: =SUMIFS('Realpage Data'!$R$2:$R$899,'Realpage Data'!$A$2:$A$899,$C44,'Realpage Data'!$F$2:$F$899,"Rent Roll (Rev/OSF)") -> 1.6332269 | E44: =SUMIFS('Realpage Data'!$R$2:$R$899,'Realpage Data'!$A$2:$A$899,$C44,'Realpage Data'!$F$2:$F$899,"Asking RPSF") -> 1.592 | F44: =SUMIFS('Realpage Data'!$R$2:$R$899,'Realpage Data'!$A$2:$A$899,$C44,'Realpage Data'!$F$2:$F$899,"Effective RPSF") -> 1.562 | G44: =E44/$D44-1 -> -0.025242593 | H44: =F44/$D44-1 -> -0.043611137 | I44: =SUMIFS('RP - Unit Starts'!$AC$2:$AC$451,'RP - Unit Starts'!$A$2:$A$451,$C44,'RP - Unit Starts'!$F$2:$F$451,"Annual Unit Starts")/SUMIFS('RP - Unit Starts'!$AC$2:$AC$451,'RP - Unit Starts'!$A$2:$A$451,$C44,'RP - Unit Starts'!$F$2:$F$451,"Existing Units") -> 0.0018892634 | J44: =SUMIFS('Realpage Data'!$V$2:$V$899,'Realpage Data'!$A$2:$A$899,$C44,'Realpage Data'!$F$2:$F$899,"Existing Units")/SUMIFS('Realpage Data'!$R$2:$R$899,'Realpage Data'!$A$2:$A$899,$C44,'Realpage Data'!$F$2:$F$899,"Existing Units")-1 -> 0.0057536658 | K44: =INDEX('Fcst Walk'!$J$5:$J$69,MATCH($C44,'Fcst Walk'!$A$5:$A$69,0))/INDEX('Fcst Walk'!$F$5:$F$69,MATCH($C44,'Fcst Walk'!$A$5:$A$69,0))-1 -> 0.026 | L44: =INDEX('Fcst Walk'!$N$5:$N$69,MATCH($C44,'Fcst Walk'!$A$5:$A$69,0))/INDEX('Fcst Walk'!$J$5:$J$69,MATCH($C44,'Fcst Walk'!$A$5:$A$69,0))-1 -> 0.026 | M44: =INDEX('Fcst Walk'!$R$5:$R$69,MATCH($C44,'Fcst Walk'!$A$5:$A$69,0))/INDEX('Fcst Walk'!$N$5:$N$69,MATCH($C44,'Fcst Walk'!$A$5:$A$69,0))-1 -> 0.026 | N44: =INDEX('Fcst Walk'!$J$5:$J$69,MATCH($C44,'Fcst Walk'!$A$5:$A$69,0))/$D44-1 -> -0.018745026 | O44: =INDEX('Fcst Walk'!$N$5:$N$69,MATCH($C44,'Fcst Walk'!$A$5:$A$69,0))/$D44-1 -> 0.0067676029 | P44: =INDEX('Fcst Walk'!$R$5:$R$69,MATCH($C44,'Fcst Walk'!$A$5:$A$69,0))/$D44-1 -> 0.032943561 | Q44: =INDEX('Fcst Walk'!$AM$5:$AM$69,MATCH($C44,'Fcst Walk'!$A$5:$A$69,0)) -> 1.7399589 | R44: =INDEX('Fcst Walk'!$AN$5:$AN$69,MATCH($C44,'Fcst Walk'!$A$5:$A$69,0)) | S44: =AVERAGE(INDEX('Realpage - His. Rent Change'!$I$2:$AV$577,MATCH($C44,'Realpage - His. Rent Change'!$A$2:$A$577,0),0)) -> 0.0634375 | U44: =IF(T44="",S44,AVERAGE(S44,T44)) -> 0.0634375 | V44: =IF(H44>=0,0,-H44/U44) -> 0.6874662
B45: =ROW()-4 -> 41 | C45: Jacksonville, FL | D45: =SUMIFS('Realpage Data'!$R$2:$R$899,'Realpage Data'!$A$2:$A$899,$C45,'Realpage Data'!$F$2:$F$899,"Rent Roll (Rev/OSF)") -> 1.4920507 | E45: =SUMIFS('Realpage Data'!$R$2:$R$899,'Realpage Data'!$A$2:$A$899,$C45,'Realpage Data'!$F$2:$F$899,"Asking RPSF") -> 1.503 | F45: =SUMIFS('Realpage Data'!$R$2:$R$899,'Realpage Data'!$A$2:$A$899,$C45,'Realpage Data'!$F$2:$F$899,"Effective RPSF") -> 1.464 | G45: =E45/$D45-1 -> 0.0073384001 | H45: =F45/$D45-1 -> -0.018800121 | I45: =SUMIFS('RP - Unit Starts'!$AC$2:$AC$451,'RP - Unit Starts'!$A$2:$A$451,$C45,'RP - Unit Starts'!$F$2:$F$451,"Annual Unit Starts")/SUMIFS('RP - Unit Starts'!$AC$2:$AC$451,'RP - Unit Starts'!$A$2:$A$451,$C45,'RP - Unit Starts'!$F$2:$F$451,"Existing Units") -> 0.010989511 | J45: =SUMIFS('Realpage Data'!$V$2:$V$899,'Realpage Data'!$A$2:$A$899,$C45,'Realpage Data'!$F$2:$F$899,"Existing Units")/SUMIFS('Realpage Data'!$R$2:$R$899,'Realpage Data'!$A$2:$A$899,$C45,'Realpage Data'!$F$2:$F$899,"Existing Units")-1 -> 0.015668664 | K45: =INDEX('Fcst Walk'!$J$5:$J$69,MATCH($C45,'Fcst Walk'!$A$5:$A$69,0))/INDEX('Fcst Walk'!$F$5:$F$69,MATCH($C45,'Fcst Walk'!$A$5:$A$69,0))-1 -> 0.01 | L45: =INDEX('Fcst Walk'!$N$5:$N$69,MATCH($C45,'Fcst Walk'!$A$5:$A$69,0))/INDEX('Fcst Walk'!$J$5:$J$69,MATCH($C45,'Fcst Walk'!$A$5:$A$69,0))-1 -> 0.03 | M45: =INDEX('Fcst Walk'!$R$5:$R$69,MATCH($C45,'Fcst Walk'!$A$5:$A$69,0))/INDEX('Fcst Walk'!$N$5:$N$69,MATCH($C45,'Fcst Walk'!$A$5:$A$69,0))-1 -> 0.035 | N45: =INDEX('Fcst Walk'!$J$5:$J$69,MATCH($C45,'Fcst Walk'!$A$5:$A$69,0))/$D45-1 -> -0.0089881225 | O45: =INDEX('Fcst Walk'!$N$5:$N$69,MATCH($C45,'Fcst Walk'!$A$5:$A$69,0))/$D45-1 -> 0.020742234 | P45: =INDEX('Fcst Walk'!$R$5:$R$69,MATCH($C45,'Fcst Walk'!$A$5:$A$69,0))/$D45-1 -> 0.056468212 | Q45: =INDEX('Fcst Walk'!$AM$5:$AM$69,MATCH($C45,'Fcst Walk'!$A$5:$A$69,0)) -> 1.7864115 | R45: =INDEX('Fcst Walk'!$AN$5:$AN$69,MATCH($C45,'Fcst Walk'!$A$5:$A$69,0)) | S45: =AVERAGE(INDEX('Realpage - His. Rent Change'!$I$2:$AV$577,MATCH($C45,'Realpage - His. Rent Change'!$A$2:$A$577,0),0)) -> 0.0546025 | T45: 0.0435 | U45: =IF(T45="",S45,AVERAGE(S45,T45)) -> 0.04905125 | V45: =IF(H45>=0,0,-H45/U45) -> 0.38327507
B46: =ROW()-4 -> 42 | C46: Las Vegas-Henderson-North Las Vegas, NV | D46: =SUMIFS('Realpage Data'!$R$2:$R$899,'Realpage Data'!$A$2:$A$899,$C46,'Realpage Data'!$F$2:$F$899,"Rent Roll (Rev/OSF)") -> 1.5938584 | E46: =SUMIFS('Realpage Data'!$R$2:$R$899,'Realpage Data'!$A$2:$A$899,$C46,'Realpage Data'!$F$2:$F$899,"Asking RPSF") -> 1.588 | F46: =SUMIFS('Realpage Data'!$R$2:$R$899,'Realpage Data'!$A$2:$A$899,$C46,'Realpage Data'!$F$2:$F$899,"Effective RPSF") -> 1.541 | G46: =E46/$D46-1 -> -0.0036756071 | H46: =F46/$D46-1 -> -0.033163798 | I46: =SUMIFS('RP - Unit Starts'!$AC$2:$AC$451,'RP - Unit Starts'!$A$2:$A$451,$C46,'RP - Unit Starts'!$F$2:$F$451,"Annual Unit Starts")/SUMIFS('RP - Unit Starts'!$AC$2:$AC$451,'RP - Unit Starts'!$A$2:$A$451,$C46,'RP - Unit Starts'!$F$2:$F$451,"Existing Units") -> 0.0063787321 | J46: =SUMIFS('Realpage Data'!$V$2:$V$899,'Realpage Data'!$A$2:$A$899,$C46,'Realpage Data'!$F$2:$F$899,"Existing Units")/SUMIFS('Realpage Data'!$R$2:$R$899,'Realpage Data'!$A$2:$A$899,$C46,'Realpage Data'!$F$2:$F$899,"Existing Units")-1 -> 0.010753308 | K46: =INDEX('Fcst Walk'!$J$5:$J$69,MATCH($C46,'Fcst Walk'!$A$5:$A$69,0))/INDEX('Fcst Walk'!$F$5:$F$69,MATCH($C46,'Fcst Walk'!$A$5:$A$69,0))-1 -> 0.026 | L46: =INDEX('Fcst Walk'!$N$5:$N$69,MATCH($C46,'Fcst Walk'!$A$5:$A$69,0))/INDEX('Fcst Walk'!$J$5:$J$69,MATCH($C46,'Fcst Walk'!$A$5:$A$69,0))-1 -> 0.025 | M46: =INDEX('Fcst Walk'!$R$5:$R$69,MATCH($C46,'Fcst Walk'!$A$5:$A$69,0))/INDEX('Fcst Walk'!$N$5:$N$69,MATCH($C46,'Fcst Walk'!$A$5:$A$69,0))-1 -> 0.027 | N46: =INDEX('Fcst Walk'!$J$5:$J$69,MATCH($C46,'Fcst Walk'!$A$5:$A$69,0))/$D46-1 -> -0.0080260563 | O46: =INDEX('Fcst Walk'!$N$5:$N$69,MATCH($C46,'Fcst Walk'!$A$5:$A$69,0))/$D46-1 -> 0.016773292 | P46: =INDEX('Fcst Walk'!$R$5:$R$69,MATCH($C46,'Fcst Walk'!$A$5:$A$69,0))/$D46-1 -> 0.044226171 | Q46: =INDEX('Fcst Walk'!$AM$5:$AM$69,MATCH($C46,'Fcst Walk'!$A$5:$A$69,0)) -> 1.8008141 | R46: =INDEX('Fcst Walk'!$AN$5:$AN$69,MATCH($C46,'Fcst Walk'!$A$5:$A$69,0)) | S46: =AVERAGE(INDEX('Realpage - His. Rent Change'!$I$2:$AV$577,MATCH($C46,'Realpage - His. Rent Change'!$A$2:$A$577,0),0)) -> 0.06004 | T46: 0.0492 | U46: =IF(T46="",S46,AVERAGE(S46,T46)) -> 0.05462 | V46: =IF(H46>=0,0,-H46/U46) -> 0.60717315
B47: =ROW()-4 -> 43 | C47: Asheville/Waynesville, NC | D47: =SUMIFS('Realpage Data'!$R$2:$R$899,'Realpage Data'!$A$2:$A$899,$C47,'Realpage Data'!$F$2:$F$899,"Rent Roll (Rev/OSF)") -> 1.566481 | E47: =SUMIFS('Realpage Data'!$R$2:$R$899,'Realpage Data'!$A$2:$A$899,$C47,'Realpage Data'!$F$2:$F$899,"Asking RPSF") -> 1.564 | F47: =SUMIFS('Realpage Data'!$R$2:$R$899,'Realpage Data'!$A$2:$A$899,$C47,'Realpage Data'!$F$2:$F$899,"Effective RPSF") -> 1.513 | G47: =E47/$D47-1 -> -0.0015838048 | H47: =F47/$D47-1 -> -0.034140855 | I47: =SUMIFS('RP - Unit Starts'!$AC$2:$AC$451,'RP - Unit Starts'!$A$2:$A$451,$C47,'RP - Unit Starts'!$F$2:$F$451,"Annual Unit Starts")/SUMIFS('RP - Unit Starts'!$AC$2:$AC$451,'RP - Unit Starts'!$A$2:$A$451,$C47,'RP - Unit Starts'!$F$2:$F$451,"Existing Units") -> 0.070382197 | J47: =SUMIFS('Realpage Data'!$V$2:$V$899,'Realpage Data'!$A$2:$A$899,$C47,'Realpage Data'!$F$2:$F$899,"Existing Units")/SUMIFS('Realpage Data'!$R$2:$R$899,'Realpage Data'!$A$2:$A$899,$C47,'Realpage Data'!$F$2:$F$899,"Existing Units")-1 -> 0.048688152 | K47: =INDEX('Fcst Walk'!$J$5:$J$69,MATCH($C47,'Fcst Walk'!$A$5:$A$69,0))/INDEX('Fcst Walk'!$F$5:$F$69,MATCH($C47,'Fcst Walk'!$A$5:$A$69,0))-1 -> 0.008 | L47: =INDEX('Fcst Walk'!$N$5:$N$69,MATCH($C47,'Fcst Walk'!$A$5:$A$69,0))/INDEX('Fcst Walk'!$J$5:$J$69,MATCH($C47,'Fcst Walk'!$A$5:$A$69,0))-1 -> 0.033 | M47: =INDEX('Fcst Walk'!$R$5:$R$69,MATCH($C47,'Fcst Walk'!$A$5:$A$69,0))/INDEX('Fcst Walk'!$N$5:$N$69,MATCH($C47,'Fcst Walk'!$A$5:$A$69,0))-1 -> 0.036 | N47: =INDEX('Fcst Walk'!$J$5:$J$69,MATCH($C47,'Fcst Walk'!$A$5:$A$69,0))/$D47-1 -> -0.026413981 | O47: =INDEX('Fcst Walk'!$N$5:$N$69,MATCH($C47,'Fcst Walk'!$A$5:$A$69,0))/$D47-1 -> 0.0057143571 | P47: =INDEX('Fcst Walk'!$R$5:$R$69,MATCH($C47,'Fcst Walk'!$A$5:$A$69,0))/$D47-1 -> 0.041920074 | Q47: =INDEX('Fcst Walk'!$AM$5:$AM$69,MATCH($C47,'Fcst Walk'!$A$5:$A$69,0)) -> 1.8111025 | R47: =INDEX('Fcst Walk'!$AN$5:$AN$69,MATCH($C47,'Fcst Walk'!$A$5:$A$69,0)) | S47: =AVERAGE(INDEX('Realpage - His. Rent Change'!$I$2:$AV$577,MATCH($C47,'Realpage - His. Rent Change'!$A$2:$A$577,0),0)) -> 0.04735 | U47: =IF(T47="",S47,AVERAGE(S47,T47)) -> 0.04735 | V47: =IF(H47>=0,0,-H47/U47) -> 0.72103178
B48: =ROW()-4 -> 44 | C48: Orlando-Kissimmee-Sanford, FL | D48: =SUMIFS('Realpage Data'!$R$2:$R$899,'Realpage Data'!$A$2:$A$899,$C48,'Realpage Data'!$F$2:$F$899,"Rent Roll (Rev/OSF)") -> 1.8116328 | E48: =SUMIFS('Realpage Data'!$R$2:$R$899,'Realpage Data'!$A$2:$A$899,$C48,'Realpage Data'!$F$2:$F$899,"Asking RPSF") -> 1.819 | F48: =SUMIFS('Realpage Data'!$R$2:$R$899,'Realpage Data'!$A$2:$A$899,$C48,'Realpage Data'!$F$2:$F$899,"Effective RPSF") -> 1.776 | G48: =E48/$D48-1 -> 0.0040666231 | H48: =F48/$D48-1 -> -0.019668872 | I48: =SUMIFS('RP - Unit Starts'!$AC$2:$AC$451,'RP - Unit Starts'!$A$2:$A$451,$C48,'RP - Unit Starts'!$F$2:$F$451,"Annual Unit Starts")/SUMIFS('RP - Unit Starts'!$AC$2:$AC$451,'RP - Unit Starts'!$A$2:$A$451,$C48,'RP - Unit Starts'!$F$2:$F$451,"Existing Units") -> 0.019573331 | J48: =SUMIFS('Realpage Data'!$V$2:$V$899,'Realpage Data'!$A$2:$A$899,$C48,'Realpage Data'!$F$2:$F$899,"Existing Units")/SUMIFS('Realpage Data'!$R$2:$R$899,'Realpage Data'!$A$2:$A$899,$C48,'Realpage Data'!$F$2:$F$899,"Existing Units")-1 -> 0.025395522 | K48: =INDEX('Fcst Walk'!$J$5:$J$69,MATCH($C48,'Fcst Walk'!$A$5:$A$69,0))/INDEX('Fcst Walk'!$F$5:$F$69,MATCH($C48,'Fcst Walk'!$A$5:$A$69,0))-1 -> 0.015 | L48: =INDEX('Fcst Walk'!$N$5:$N$69,MATCH($C48,'Fcst Walk'!$A$5:$A$69,0))/INDEX('Fcst Walk'!$J$5:$J$69,MATCH($C48,'Fcst Walk'!$A$5:$A$69,0))-1 -> 0.023 | M48: =INDEX('Fcst Walk'!$R$5:$R$69,MATCH($C48,'Fcst Walk'!$A$5:$A$69,0))/INDEX('Fcst Walk'!$N$5:$N$69,MATCH($C48,'Fcst Walk'!$A$5:$A$69,0))-1 -> 0.03 | N48: =INDEX('Fcst Walk'!$J$5:$J$69,MATCH($C48,'Fcst Walk'!$A$5:$A$69,0))/$D48-1 -> -0.0049639046 | O48: =INDEX('Fcst Walk'!$N$5:$N$69,MATCH($C48,'Fcst Walk'!$A$5:$A$69,0))/$D48-1 -> 0.017921926 | P48: =INDEX('Fcst Walk'!$R$5:$R$69,MATCH($C48,'Fcst Walk'!$A$5:$A$69,0))/$D48-1 -> 0.048459583 | Q48: =INDEX('Fcst Walk'!$AM$5:$AM$69,MATCH($C48,'Fcst Walk'!$A$5:$A$69,0)) -> 1.8359168 | R48: =INDEX('Fcst Walk'!$AN$5:$AN$69,MATCH($C48,'Fcst Walk'!$A$5:$A$69,0)) | S48: =AVERAGE(INDEX('Realpage - His. Rent Change'!$I$2:$AV$577,MATCH($C48,'Realpage - His. Rent Change'!$A$2:$A$577,0),0)) -> 0.05637 | T48: 0.047 | U48: =IF(T48="",S48,AVERAGE(S48,T48)) -> 0.051685 | V48: =IF(H48>=0,0,-H48/U48) -> 0.3805528
B49: =ROW()-4 -> 45 | C49: Knoxville, TN | D49: =SUMIFS('Realpage Data'!$R$2:$R$899,'Realpage Data'!$A$2:$A$899,$C49,'Realpage Data'!$F$2:$F$899,"Rent Roll (Rev/OSF)") -> 1.5906893 | E49: =SUMIFS('Realpage Data'!$R$2:$R$899,'Realpage Data'!$A$2:$A$899,$C49,'Realpage Data'!$F$2:$F$899,"Asking RPSF") -> 1.557 | F49: =SUMIFS('Realpage Data'!$R$2:$R$899,'Realpage Data'!$A$2:$A$899,$C49,'Realpage Data'!$F$2:$F$899,"Effective RPSF") -> 1.534 | G49: =E49/$D49-1 -> -0.021179039 | H49: =F49/$D49-1 -> -0.035638179 | I49: =SUMIFS('RP - Unit Starts'!$AC$2:$AC$451,'RP - Unit Starts'!$A$2:$A$451,$C49,'RP - Unit Starts'!$F$2:$F$451,"Annual Unit Starts")/SUMIFS('RP - Unit Starts'!$AC$2:$AC$451,'RP - Unit Starts'!$A$2:$A$451,$C49,'RP - Unit Starts'!$F$2:$F$451,"Existing Units") -> 0 | J49: =SUMIFS('Realpage Data'!$V$2:$V$899,'Realpage Data'!$A$2:$A$899,$C49,'Realpage Data'!$F$2:$F$899,"Existing Units")/SUMIFS('Realpage Data'!$R$2:$R$899,'Realpage Data'!$A$2:$A$899,$C49,'Realpage Data'!$F$2:$F$899,"Existing Units")-1 -> 0.0059037634 | K49: =INDEX('Fcst Walk'!$J$5:$J$69,MATCH($C49,'Fcst Walk'!$A$5:$A$69,0))/INDEX('Fcst Walk'!$F$5:$F$69,MATCH($C49,'Fcst Walk'!$A$5:$A$69,0))-1 -> 0.016 | L49: =INDEX('Fcst Walk'!$N$5:$N$69,MATCH($C49,'Fcst Walk'!$A$5:$A$69,0))/INDEX('Fcst Walk'!$J$5:$J$69,MATCH($C49,'Fcst Walk'!$A$5:$A$69,0))-1 -> 0.034 | M49: =INDEX('Fcst Walk'!$R$5:$R$69,MATCH($C49,'Fcst Walk'!$A$5:$A$69,0))/INDEX('Fcst Walk'!$N$5:$N$69,MATCH($C49,'Fcst Walk'!$A$5:$A$69,0))-1 -> 0.036 | N49: =INDEX('Fcst Walk'!$J$5:$J$69,MATCH($C49,'Fcst Walk'!$A$5:$A$69,0))/$D49-1 -> -0.02020839 | O49: =INDEX('Fcst Walk'!$N$5:$N$69,MATCH($C49,'Fcst Walk'!$A$5:$A$69,0))/$D49-1 -> 0.013104524 | P49: =INDEX('Fcst Walk'!$R$5:$R$69,MATCH($C49,'Fcst Walk'!$A$5:$A$69,0))/$D49-1 -> 0.049576287 | Q49: =INDEX('Fcst Walk'!$AM$5:$AM$69,MATCH($C49,'Fcst Walk'!$A$5:$A$69,0)) -> 1.8831013 | R49: =INDEX('Fcst Walk'!$AN$5:$AN$69,MATCH($C49,'Fcst Walk'!$A$5:$A$69,0)) | S49: =AVERAGE(INDEX('Realpage - His. Rent Change'!$I$2:$AV$577,MATCH($C49,'Realpage - His. Rent Change'!$A$2:$A$577,0),0)) -> 0.0715925 | U49: =IF(T49="",S49,AVERAGE(S49,T49)) -> 0.0715925 | V49: =IF(H49>=0,0,-H49/U49) -> 0.49779208
B50: =ROW()-4 -> 46 | C50: Washington-Arlington-Alexandria, DC-VA-MD-WV | D50: =SUMIFS('Realpage Data'!$R$2:$R$899,'Realpage Data'!$A$2:$A$899,$C50,'Realpage Data'!$F$2:$F$899,"Rent Roll (Rev/OSF)") -> 2.6036908 | E50: =SUMIFS('Realpage Data'!$R$2:$R$899,'Realpage Data'!$A$2:$A$899,$C50,'Realpage Data'!$F$2:$F$899,"Asking RPSF") -> 2.576 | F50: =SUMIFS('Realpage Data'!$R$2:$R$899,'Realpage Data'!$A$2:$A$899,$C50,'Realpage Data'!$F$2:$F$899,"Effective RPSF") -> 2.531 | G50: =E50/$D50-1 -> -0.010635204 | H50: =F50/$D50-1 -> -0.027918362 | I50: =SUMIFS('RP - Unit Starts'!$AC$2:$AC$451,'RP - Unit Starts'!$A$2:$A$451,$C50,'RP - Unit Starts'!$F$2:$F$451,"Annual Unit Starts")/SUMIFS('RP - Unit Starts'!$AC$2:$AC$451,'RP - Unit Starts'!$A$2:$A$451,$C50,'RP - Unit Starts'!$F$2:$F$451,"Existing Units") -> 0.01047627 | J50: =SUMIFS('Realpage Data'!$V$2:$V$899,'Realpage Data'!$A$2:$A$899,$C50,'Realpage Data'!$F$2:$F$899,"Existing Units")/SUMIFS('Realpage Data'!$R$2:$R$899,'Realpage Data'!$A$2:$A$899,$C50,'Realpage Data'!$F$2:$F$899,"Existing Units")-1 -> 0.007188046 | K50: =INDEX('Fcst Walk'!$J$5:$J$69,MATCH($C50,'Fcst Walk'!$A$5:$A$69,0))/INDEX('Fcst Walk'!$F$5:$F$69,MATCH($C50,'Fcst Walk'!$A$5:$A$69,0))-1 -> 0.011 | L50: =INDEX('Fcst Walk'!$N$5:$N$69,MATCH($C50,'Fcst Walk'!$A$5:$A$69,0))/INDEX('Fcst Walk'!$J$5:$J$69,MATCH($C50,'Fcst Walk'!$A$5:$A$69,0))-1 -> 0.026 | M50: =INDEX('Fcst Walk'!$R$5:$R$69,MATCH($C50,'Fcst Walk'!$A$5:$A$69,0))/INDEX('Fcst Walk'!$N$5:$N$69,MATCH($C50,'Fcst Walk'!$A$5:$A$69,0))-1 -> 0.025 | N50: =INDEX('Fcst Walk'!$J$5:$J$69,MATCH($C50,'Fcst Walk'!$A$5:$A$69,0))/$D50-1 -> -0.017225464 | O50: =INDEX('Fcst Walk'!$N$5:$N$69,MATCH($C50,'Fcst Walk'!$A$5:$A$69,0))/$D50-1 -> 0.0083266741 | P50: =INDEX('Fcst Walk'!$R$5:$R$69,MATCH($C50,'Fcst Walk'!$A$5:$A$69,0))/$D50-1 -> 0.033534841 | Q50: =INDEX('Fcst Walk'!$AM$5:$AM$69,MATCH($C50,'Fcst Walk'!$A$5:$A$69,0)) -> 1.8919855 | R50: =INDEX('Fcst Walk'!$AN$5:$AN$69,MATCH($C50,'Fcst Walk'!$A$5:$A$69,0)) | S50: =AVERAGE(INDEX('Realpage - His. Rent Change'!$I$2:$AV$577,MATCH($C50,'Realpage - His. Rent Change'!$A$2:$A$577,0),0)) -> 0.0328 | T50: 0.0275 | U50: =IF(T50="",S50,AVERAGE(S50,T50)) -> 0.03015 | V50: =IF(H50>=0,0,-H50/U50) -> 0.92598215
B51: =ROW()-4 -> 47 | C51: Charlotte-Concord-Gastonia, NC-SC | D51: =SUMIFS('Realpage Data'!$R$2:$R$899,'Realpage Data'!$A$2:$A$899,$C51,'Realpage Data'!$F$2:$F$899,"Rent Roll (Rev/OSF)") -> 1.660578 | E51: =SUMIFS('Realpage Data'!$R$2:$R$899,'Realpage Data'!$A$2:$A$899,$C51,'Realpage Data'!$F$2:$F$899,"Asking RPSF") -> 1.642 | F51: =SUMIFS('Realpage Data'!$R$2:$R$899,'Realpage Data'!$A$2:$A$899,$C51,'Realpage Data'!$F$2:$F$899,"Effective RPSF") -> 1.585 | G51: =E51/$D51-1 -> -0.011187675 | H51: =F51/$D51-1 -> -0.045513072 | I51: =SUMIFS('RP - Unit Starts'!$AC$2:$AC$451,'RP - Unit Starts'!$A$2:$A$451,$C51,'RP - Unit Starts'!$F$2:$F$451,"Annual Unit Starts")/SUMIFS('RP - Unit Starts'!$AC$2:$AC$451,'RP - Unit Starts'!$A$2:$A$451,$C51,'RP - Unit Starts'!$F$2:$F$451,"Existing Units") -> 0.019942911 | J51: =SUMIFS('Realpage Data'!$V$2:$V$899,'Realpage Data'!$A$2:$A$899,$C51,'Realpage Data'!$F$2:$F$899,"Existing Units")/SUMIFS('Realpage Data'!$R$2:$R$899,'Realpage Data'!$A$2:$A$899,$C51,'Realpage Data'!$F$2:$F$899,"Existing Units")-1 -> 0.044175155 | K51: =INDEX('Fcst Walk'!$J$5:$J$69,MATCH($C51,'Fcst Walk'!$A$5:$A$69,0))/INDEX('Fcst Walk'!$F$5:$F$69,MATCH($C51,'Fcst Walk'!$A$5:$A$69,0))-1 -> 0.019 | L51: =INDEX('Fcst Walk'!$N$5:$N$69,MATCH($C51,'Fcst Walk'!$A$5:$A$69,0))/INDEX('Fcst Walk'!$J$5:$J$69,MATCH($C51,'Fcst Walk'!$A$5:$A$69,0))-1 -> 0.037 | M51: =INDEX('Fcst Walk'!$R$5:$R$69,MATCH($C51,'Fcst Walk'!$A$5:$A$69,0))/INDEX('Fcst Walk'!$N$5:$N$69,MATCH($C51,'Fcst Walk'!$A$5:$A$69,0))-1 -> 0.045 | N51: =INDEX('Fcst Walk'!$J$5:$J$69,MATCH($C51,'Fcst Walk'!$A$5:$A$69,0))/$D51-1 -> -0.027377821 | O51: =INDEX('Fcst Walk'!$N$5:$N$69,MATCH($C51,'Fcst Walk'!$A$5:$A$69,0))/$D51-1 -> 0.0086091998 | P51: =INDEX('Fcst Walk'!$R$5:$R$69,MATCH($C51,'Fcst Walk'!$A$5:$A$69,0))/$D51-1 -> 0.053996614 | Q51: =INDEX('Fcst Walk'!$AM$5:$AM$69,MATCH($C51,'Fcst Walk'!$A$5:$A$69,0)) -> 1.9363939 | R51: =INDEX('Fcst Walk'!$AN$5:$AN$69,MATCH($C51,'Fcst Walk'!$A$5:$A$69,0)) | S51: =AVERAGE(INDEX('Realpage - His. Rent Change'!$I$2:$AV$577,MATCH($C51,'Realpage - His. Rent Change'!$A$2:$A$577,0),0)) -> 0.052925 | T51: 0.0361 | U51: =IF(T51="",S51,AVERAGE(S51,T51)) -> 0.0445125 | V51: =IF(H51>=0,0,-H51/U51) -> 1.0224785
B52: =ROW()-4 -> 48 | C52: Palm Bay-Melbourne-Titusville, FL | D52: =SUMIFS('Realpage Data'!$R$2:$R$899,'Realpage Data'!$A$2:$A$899,$C52,'Realpage Data'!$F$2:$F$899,"Rent Roll (Rev/OSF)") -> 1.6682975 | E52: =SUMIFS('Realpage Data'!$R$2:$R$899,'Realpage Data'!$A$2:$A$899,$C52,'Realpage Data'!$F$2:$F$899,"Asking RPSF") -> 1.66 | F52: =SUMIFS('Realpage Data'!$R$2:$R$899,'Realpage Data'!$A$2:$A$899,$C52,'Realpage Data'!$F$2:$F$899,"Effective RPSF") -> 1.612 | G52: =E52/$D52-1 -> -0.0049736573 | H52: =F52/$D52-1 -> -0.033745503 | I52: =SUMIFS('RP - Unit Starts'!$AC$2:$AC$451,'RP - Unit Starts'!$A$2:$A$451,$C52,'RP - Unit Starts'!$F$2:$F$451,"Annual Unit Starts")/SUMIFS('RP - Unit Starts'!$AC$2:$AC$451,'RP - Unit Starts'!$A$2:$A$451,$C52,'RP - Unit Starts'!$F$2:$F$451,"Existing Units") -> 0 | J52: =SUMIFS('Realpage Data'!$V$2:$V$899,'Realpage Data'!$A$2:$A$899,$C52,'Realpage Data'!$F$2:$F$899,"Existing Units")/SUMIFS('Realpage Data'!$R$2:$R$899,'Realpage Data'!$A$2:$A$899,$C52,'Realpage Data'!$F$2:$F$899,"Existing Units")-1 -> 0.039548899 | K52: =INDEX('Fcst Walk'!$J$5:$J$69,MATCH($C52,'Fcst Walk'!$A$5:$A$69,0))/INDEX('Fcst Walk'!$F$5:$F$69,MATCH($C52,'Fcst Walk'!$A$5:$A$69,0))-1 -> 0.007 | L52: =INDEX('Fcst Walk'!$N$5:$N$69,MATCH($C52,'Fcst Walk'!$A$5:$A$69,0))/INDEX('Fcst Walk'!$J$5:$J$69,MATCH($C52,'Fcst Walk'!$A$5:$A$69,0))-1 -> 0.029 | M52: =INDEX('Fcst Walk'!$R$5:$R$69,MATCH($C52,'Fcst Walk'!$A$5:$A$69,0))/INDEX('Fcst Walk'!$N$5:$N$69,MATCH($C52,'Fcst Walk'!$A$5:$A$69,0))-1 -> 0.037 | N52: =INDEX('Fcst Walk'!$J$5:$J$69,MATCH($C52,'Fcst Walk'!$A$5:$A$69,0))/$D52-1 -> -0.026981722 | O52: =INDEX('Fcst Walk'!$N$5:$N$69,MATCH($C52,'Fcst Walk'!$A$5:$A$69,0))/$D52-1 -> 0.0012358082 | P52: =INDEX('Fcst Walk'!$R$5:$R$69,MATCH($C52,'Fcst Walk'!$A$5:$A$69,0))/$D52-1 -> 0.038281533 | Q52: =INDEX('Fcst Walk'!$AM$5:$AM$69,MATCH($C52,'Fcst Walk'!$A$5:$A$69,0)) -> 1.9558389 | R52: =INDEX('Fcst Walk'!$AN$5:$AN$69,MATCH($C52,'Fcst Walk'!$A$5:$A$69,0)) | S52: =AVERAGE(INDEX('Realpage - His. Rent Change'!$I$2:$AV$577,MATCH($C52,'Realpage - His. Rent Change'!$A$2:$A$577,0),0)) -> 0.0674325 | U52: =IF(T52="",S52,AVERAGE(S52,T52)) -> 0.0674325 | V52: =IF(H52>=0,0,-H52/U52) -> 0.50043382
B53: =ROW()-4 -> 49 | C53: Tallahassee, FL | D53: =SUMIFS('Realpage Data'!$R$2:$R$899,'Realpage Data'!$A$2:$A$899,$C53,'Realpage Data'!$F$2:$F$899,"Rent Roll (Rev/OSF)") -> 1.3999812 | E53: =SUMIFS('Realpage Data'!$R$2:$R$899,'Realpage Data'!$A$2:$A$899,$C53,'Realpage Data'!$F$2:$F$899,"Asking RPSF") -> 1.376 | F53: =SUMIFS('Realpage Data'!$R$2:$R$899,'Realpage Data'!$A$2:$A$899,$C53,'Realpage Data'!$F$2:$F$899,"Effective RPSF") -> 1.358 | G53: =E53/$D53-1 -> -0.017129646 | H53: =F53/$D53-1 -> -0.029986961 | I53: =SUMIFS('RP - Unit Starts'!$AC$2:$AC$451,'RP - Unit Starts'!$A$2:$A$451,$C53,'RP - Unit Starts'!$F$2:$F$451,"Annual Unit Starts")/SUMIFS('RP - Unit Starts'!$AC$2:$AC$451,'RP - Unit Starts'!$A$2:$A$451,$C53,'RP - Unit Starts'!$F$2:$F$451,"Existing Units") -> 0.023289211 | J53: =SUMIFS('Realpage Data'!$V$2:$V$899,'Realpage Data'!$A$2:$A$899,$C53,'Realpage Data'!$F$2:$F$899,"Existing Units")/SUMIFS('Realpage Data'!$R$2:$R$899,'Realpage Data'!$A$2:$A$899,$C53,'Realpage Data'!$F$2:$F$899,"Existing Units")-1 -> 0.023726274 | K53: =INDEX('Fcst Walk'!$J$5:$J$69,MATCH($C53,'Fcst Walk'!$A$5:$A$69,0))/INDEX('Fcst Walk'!$F$5:$F$69,MATCH($C53,'Fcst Walk'!$A$5:$A$69,0))-1 -> 0.014 | L53: =INDEX('Fcst Walk'!$N$5:$N$69,MATCH($C53,'Fcst Walk'!$A$5:$A$69,0))/INDEX('Fcst Walk'!$J$5:$J$69,MATCH($C53,'Fcst Walk'!$A$5:$A$69,0))-1 -> 0.016 | M53: =INDEX('Fcst Walk'!$R$5:$R$69,MATCH($C53,'Fcst Walk'!$A$5:$A$69,0))/INDEX('Fcst Walk'!$N$5:$N$69,MATCH($C53,'Fcst Walk'!$A$5:$A$69,0))-1 -> 0.017 | N53: =INDEX('Fcst Walk'!$J$5:$J$69,MATCH($C53,'Fcst Walk'!$A$5:$A$69,0))/$D53-1 -> -0.016406779 | O53: =INDEX('Fcst Walk'!$N$5:$N$69,MATCH($C53,'Fcst Walk'!$A$5:$A$69,0))/$D53-1 -> -0.00066928724 | P53: =INDEX('Fcst Walk'!$R$5:$R$69,MATCH($C53,'Fcst Walk'!$A$5:$A$69,0))/$D53-1 -> 0.016319335 | Q53: =INDEX('Fcst Walk'!$AM$5:$AM$69,MATCH($C53,'Fcst Walk'!$A$5:$A$69,0)) -> 2.0241306 | R53: =INDEX('Fcst Walk'!$AN$5:$AN$69,MATCH($C53,'Fcst Walk'!$A$5:$A$69,0)) | S53: =AVERAGE(INDEX('Realpage - His. Rent Change'!$I$2:$AV$577,MATCH($C53,'Realpage - His. Rent Change'!$A$2:$A$577,0),0)) -> 0.055385 | U53: =IF(T53="",S53,AVERAGE(S53,T53)) -> 0.055385 | V53: =IF(H53>=0,0,-H53/U53) -> 0.54142749
B54: =ROW()-4 -> 50 | C54: Fort Worth-Arlington-Grapevine/Granbury, TX | D54: =SUMIFS('Realpage Data'!$R$2:$R$899,'Realpage Data'!$A$2:$A$899,$C54,'Realpage Data'!$F$2:$F$899,"Rent Roll (Rev/OSF)") -> 1.6278588 | E54: =SUMIFS('Realpage Data'!$R$2:$R$899,'Realpage Data'!$A$2:$A$899,$C54,'Realpage Data'!$F$2:$F$899,"Asking RPSF") -> 1.607 | F54: =SUMIFS('Realpage Data'!$R$2:$R$899,'Realpage Data'!$A$2:$A$899,$C54,'Realpage Data'!$F$2:$F$899,"Effective RPSF") -> 1.566 | G54: =E54/$D54-1 -> -0.012813626 | H54: =F54/$D54-1 -> -0.038000086 | I54: =SUMIFS('RP - Unit Starts'!$AC$2:$AC$451,'RP - Unit Starts'!$A$2:$A$451,$C54,'RP - Unit Starts'!$F$2:$F$451,"Annual Unit Starts")/SUMIFS('RP - Unit Starts'!$AC$2:$AC$451,'RP - Unit Starts'!$A$2:$A$451,$C54,'RP - Unit Starts'!$F$2:$F$451,"Existing Units") -> 0.021879053 | J54: =SUMIFS('Realpage Data'!$V$2:$V$899,'Realpage Data'!$A$2:$A$899,$C54,'Realpage Data'!$F$2:$F$899,"Existing Units")/SUMIFS('Realpage Data'!$R$2:$R$899,'Realpage Data'!$A$2:$A$899,$C54,'Realpage Data'!$F$2:$F$899,"Existing Units")-1 -> 0.0207851 | K54: =INDEX('Fcst Walk'!$J$5:$J$69,MATCH($C54,'Fcst Walk'!$A$5:$A$69,0))/INDEX('Fcst Walk'!$F$5:$F$69,MATCH($C54,'Fcst Walk'!$A$5:$A$69,0))-1 -> 0.001 | L54: =INDEX('Fcst Walk'!$N$5:$N$69,MATCH($C54,'Fcst Walk'!$A$5:$A$69,0))/INDEX('Fcst Walk'!$J$5:$J$69,MATCH($C54,'Fcst Walk'!$A$5:$A$69,0))-1 -> 0.03 | M54: =INDEX('Fcst Walk'!$R$5:$R$69,MATCH($C54,'Fcst Walk'!$A$5:$A$69,0))/INDEX('Fcst Walk'!$N$5:$N$69,MATCH($C54,'Fcst Walk'!$A$5:$A$69,0))-1 -> 0.03 | N54: =INDEX('Fcst Walk'!$J$5:$J$69,MATCH($C54,'Fcst Walk'!$A$5:$A$69,0))/$D54-1 -> -0.037038086 | O54: =INDEX('Fcst Walk'!$N$5:$N$69,MATCH($C54,'Fcst Walk'!$A$5:$A$69,0))/$D54-1 -> -0.0081492288 | P54: =INDEX('Fcst Walk'!$R$5:$R$69,MATCH($C54,'Fcst Walk'!$A$5:$A$69,0))/$D54-1 -> 0.021606294 | Q54: =INDEX('Fcst Walk'!$AM$5:$AM$69,MATCH($C54,'Fcst Walk'!$A$5:$A$69,0)) -> 2.1690743 | R54: =INDEX('Fcst Walk'!$AN$5:$AN$69,MATCH($C54,'Fcst Walk'!$A$5:$A$69,0)) | S54: =AVERAGE(INDEX('Realpage - His. Rent Change'!$I$2:$AV$577,MATCH($C54,'Realpage - His. Rent Change'!$A$2:$A$577,0),0)) -> 0.04816 | U54: =IF(T54="",S54,AVERAGE(S54,T54)) -> 0.04816 | V54: =IF(H54>=0,0,-H54/U54) -> 0.78903833
B55: =ROW()-4 -> 51 | C55: Colorado Springs, CO | D55: =SUMIFS('Realpage Data'!$R$2:$R$899,'Realpage Data'!$A$2:$A$899,$C55,'Realpage Data'!$F$2:$F$899,"Rent Roll (Rev/OSF)") -> 1.7188733 | E55: =SUMIFS('Realpage Data'!$R$2:$R$899,'Realpage Data'!$A$2:$A$899,$C55,'Realpage Data'!$F$2:$F$899,"Asking RPSF") -> 1.737 | F55: =SUMIFS('Realpage Data'!$R$2:$R$899,'Realpage Data'!$A$2:$A$899,$C55,'Realpage Data'!$F$2:$F$899,"Effective RPSF") -> 1.682 | G55: =E55/$D55-1 -> 0.010545702 | H55: =F55/$D55-1 -> -0.021452003 | I55: =SUMIFS('RP - Unit Starts'!$AC$2:$AC$451,'RP - Unit Starts'!$A$2:$A$451,$C55,'RP - Unit Starts'!$F$2:$F$451,"Annual Unit Starts")/SUMIFS('RP - Unit Starts'!$AC$2:$AC$451,'RP - Unit Starts'!$A$2:$A$451,$C55,'RP - Unit Starts'!$F$2:$F$451,"Existing Units") -> 0.0067899973 | J55: =SUMIFS('Realpage Data'!$V$2:$V$899,'Realpage Data'!$A$2:$A$899,$C55,'Realpage Data'!$F$2:$F$899,"Existing Units")/SUMIFS('Realpage Data'!$R$2:$R$899,'Realpage Data'!$A$2:$A$899,$C55,'Realpage Data'!$F$2:$F$899,"Existing Units")-1 -> 0.0059412477 | K55: =INDEX('Fcst Walk'!$J$5:$J$69,MATCH($C55,'Fcst Walk'!$A$5:$A$69,0))/INDEX('Fcst Walk'!$F$5:$F$69,MATCH($C55,'Fcst Walk'!$A$5:$A$69,0))-1 -> 0.021 | L55: =INDEX('Fcst Walk'!$N$5:$N$69,MATCH($C55,'Fcst Walk'!$A$5:$A$69,0))/INDEX('Fcst Walk'!$J$5:$J$69,MATCH($C55,'Fcst Walk'!$A$5:$A$69,0))-1 -> 0.02 | M55: =INDEX('Fcst Walk'!$R$5:$R$69,MATCH($C55,'Fcst Walk'!$A$5:$A$69,0))/INDEX('Fcst Walk'!$N$5:$N$69,MATCH($C55,'Fcst Walk'!$A$5:$A$69,0))-1 -> 0.017 | N55: =INDEX('Fcst Walk'!$J$5:$J$69,MATCH($C55,'Fcst Walk'!$A$5:$A$69,0))/$D55-1 -> -0.00090249543 | O55: =INDEX('Fcst Walk'!$N$5:$N$69,MATCH($C55,'Fcst Walk'!$A$5:$A$69,0))/$D55-1 -> 0.019079455 | P55: =INDEX('Fcst Walk'!$R$5:$R$69,MATCH($C55,'Fcst Walk'!$A$5:$A$69,0))/$D55-1 -> 0.036403805 | Q55: =INDEX('Fcst Walk'!$AM$5:$AM$69,MATCH($C55,'Fcst Walk'!$A$5:$A$69,0)) -> 2.5354832 | R55: =INDEX('Fcst Walk'!$AN$5:$AN$69,MATCH($C55,'Fcst Walk'!$A$5:$A$69,0)) | S55: =AVERAGE(INDEX('Realpage - His. Rent Change'!$I$2:$AV$577,MATCH($C55,'Realpage - His. Rent Change'!$A$2:$A$577,0),0)) -> 0.0542425 | U55: =IF(T55="",S55,AVERAGE(S55,T55)) -> 0.0542425 | V55: =IF(H55>=0,0,-H55/U55) -> 0.39548331
B56: =ROW()-4 -> 52 | C56: Raleigh/Durham, NC | D56: =SUMIFS('Realpage Data'!$R$2:$R$899,'Realpage Data'!$A$2:$A$899,$C56,'Realpage Data'!$F$2:$F$899,"Rent Roll (Rev/OSF)") -> 1.570647 | E56: =SUMIFS('Realpage Data'!$R$2:$R$899,'Realpage Data'!$A$2:$A$899,$C56,'Realpage Data'!$F$2:$F$899,"Asking RPSF") -> 1.571 | F56: =SUMIFS('Realpage Data'!$R$2:$R$899,'Realpage Data'!$A$2:$A$899,$C56,'Realpage Data'!$F$2:$F$899,"Effective RPSF") -> 1.526 | G56: =E56/$D56-1 -> 0.00022476053 | H56: =F56/$D56-1 -> -0.028425853 | I56: =SUMIFS('RP - Unit Starts'!$AC$2:$AC$451,'RP - Unit Starts'!$A$2:$A$451,$C56,'RP - Unit Starts'!$F$2:$F$451,"Annual Unit Starts")/SUMIFS('RP - Unit Starts'!$AC$2:$AC$451,'RP - Unit Starts'!$A$2:$A$451,$C56,'RP - Unit Starts'!$F$2:$F$451,"Existing Units") -> 0.046989443 | J56: =SUMIFS('Realpage Data'!$V$2:$V$899,'Realpage Data'!$A$2:$A$899,$C56,'Realpage Data'!$F$2:$F$899,"Existing Units")/SUMIFS('Realpage Data'!$R$2:$R$899,'Realpage Data'!$A$2:$A$899,$C56,'Realpage Data'!$F$2:$F$899,"Existing Units")-1 -> 0.027948905 | K56: =INDEX('Fcst Walk'!$J$5:$J$69,MATCH($C56,'Fcst Walk'!$A$5:$A$69,0))/INDEX('Fcst Walk'!$F$5:$F$69,MATCH($C56,'Fcst Walk'!$A$5:$A$69,0))-1 -> 0.02 | L56: =INDEX('Fcst Walk'!$N$5:$N$69,MATCH($C56,'Fcst Walk'!$A$5:$A$69,0))/INDEX('Fcst Walk'!$J$5:$J$69,MATCH($C56,'Fcst Walk'!$A$5:$A$69,0))-1 -> 0.027 | M56: =INDEX('Fcst Walk'!$R$5:$R$69,MATCH($C56,'Fcst Walk'!$A$5:$A$69,0))/INDEX('Fcst Walk'!$N$5:$N$69,MATCH($C56,'Fcst Walk'!$A$5:$A$69,0))-1 -> 0.029 | N56: =INDEX('Fcst Walk'!$J$5:$J$69,MATCH($C56,'Fcst Walk'!$A$5:$A$69,0))/$D56-1 -> -0.0089943703 | O56: =INDEX('Fcst Walk'!$N$5:$N$69,MATCH($C56,'Fcst Walk'!$A$5:$A$69,0))/$D56-1 -> 0.017762782 | P56: =INDEX('Fcst Walk'!$R$5:$R$69,MATCH($C56,'Fcst Walk'!$A$5:$A$69,0))/$D56-1 -> 0.047277902 | Q56: =INDEX('Fcst Walk'!$AM$5:$AM$69,MATCH($C56,'Fcst Walk'!$A$5:$A$69,0)) -> 2.536408 | R56: =INDEX('Fcst Walk'!$AN$5:$AN$69,MATCH($C56,'Fcst Walk'!$A$5:$A$69,0)) | S56: =AVERAGE(INDEX('Realpage - His. Rent Change'!$I$2:$AV$577,MATCH($C56,'Realpage - His. Rent Change'!$A$2:$A$577,0),0)) -> 0.0470675 | T56: 0.0373 | U56: =IF(T56="",S56,AVERAGE(S56,T56)) -> 0.04218375 | V56: =IF(H56>=0,0,-H56/U56) -> 0.6738579
B57: =ROW()-4 -> 53 | C57: Tulsa, OK | D57: =SUMIFS('Realpage Data'!$R$2:$R$899,'Realpage Data'!$A$2:$A$899,$C57,'Realpage Data'!$F$2:$F$899,"Rent Roll (Rev/OSF)") -> 1.3010797 | E57: =SUMIFS('Realpage Data'!$R$2:$R$899,'Realpage Data'!$A$2:$A$899,$C57,'Realpage Data'!$F$2:$F$899,"Asking RPSF") -> 1.241 | F57: =SUMIFS('Realpage Data'!$R$2:$R$899,'Realpage Data'!$A$2:$A$899,$C57,'Realpage Data'!$F$2:$F$899,"Effective RPSF") -> 1.235 | G57: =E57/$D57-1 -> -0.046176835 | H57: =F57/$D57-1 -> -0.050788389 | I57: =SUMIFS('RP - Unit Starts'!$AC$2:$AC$451,'RP - Unit Starts'!$A$2:$A$451,$C57,'RP - Unit Starts'!$F$2:$F$451,"Annual Unit Starts")/SUMIFS('RP - Unit Starts'!$AC$2:$AC$451,'RP - Unit Starts'!$A$2:$A$451,$C57,'RP - Unit Starts'!$F$2:$F$451,"Existing Units") -> 0 | J57: =SUMIFS('Realpage Data'!$V$2:$V$899,'Realpage Data'!$A$2:$A$899,$C57,'Realpage Data'!$F$2:$F$899,"Existing Units")/SUMIFS('Realpage Data'!$R$2:$R$899,'Realpage Data'!$A$2:$A$899,$C57,'Realpage Data'!$F$2:$F$899,"Existing Units")-1 -> 0 | K57: =INDEX('Fcst Walk'!$J$5:$J$69,MATCH($C57,'Fcst Walk'!$A$5:$A$69,0))/INDEX('Fcst Walk'!$F$5:$F$69,MATCH($C57,'Fcst Walk'!$A$5:$A$69,0))-1 -> 0.029 | L57: =INDEX('Fcst Walk'!$N$5:$N$69,MATCH($C57,'Fcst Walk'!$A$5:$A$69,0))/INDEX('Fcst Walk'!$J$5:$J$69,MATCH($C57,'Fcst Walk'!$A$5:$A$69,0))-1 -> 0.023 | M57: =INDEX('Fcst Walk'!$R$5:$R$69,MATCH($C57,'Fcst Walk'!$A$5:$A$69,0))/INDEX('Fcst Walk'!$N$5:$N$69,MATCH($C57,'Fcst Walk'!$A$5:$A$69,0))-1 -> 0.019 | N57: =INDEX('Fcst Walk'!$J$5:$J$69,MATCH($C57,'Fcst Walk'!$A$5:$A$69,0))/$D57-1 -> -0.023261252 | O57: =INDEX('Fcst Walk'!$N$5:$N$69,MATCH($C57,'Fcst Walk'!$A$5:$A$69,0))/$D57-1 -> -0.00079626105 | P57: =INDEX('Fcst Walk'!$R$5:$R$69,MATCH($C57,'Fcst Walk'!$A$5:$A$69,0))/$D57-1 -> 0.01818861 | Q57: =INDEX('Fcst Walk'!$AM$5:$AM$69,MATCH($C57,'Fcst Walk'!$A$5:$A$69,0)) -> 2.5484907 | R57: =INDEX('Fcst Walk'!$AN$5:$AN$69,MATCH($C57,'Fcst Walk'!$A$5:$A$69,0)) | S57: =AVERAGE(INDEX('Realpage - His. Rent Change'!$I$2:$AV$577,MATCH($C57,'Realpage - His. Rent Change'!$A$2:$A$577,0),0)) -> 0.0424425 | U57: =IF(T57="",S57,AVERAGE(S57,T57)) -> 0.0424425 | V57: =IF(H57>=0,0,-H57/U57) -> 1.1966399
B58: =ROW()-4 -> 54 | C58: Phoenix-Mesa-Chandler, AZ | D58: =SUMIFS('Realpage Data'!$R$2:$R$899,'Realpage Data'!$A$2:$A$899,$C58,'Realpage Data'!$F$2:$F$899,"Rent Roll (Rev/OSF)") -> 1.7398462 | E58: =SUMIFS('Realpage Data'!$R$2:$R$899,'Realpage Data'!$A$2:$A$899,$C58,'Realpage Data'!$F$2:$F$899,"Asking RPSF") -> 1.742 | F58: =SUMIFS('Realpage Data'!$R$2:$R$899,'Realpage Data'!$A$2:$A$899,$C58,'Realpage Data'!$F$2:$F$899,"Effective RPSF") -> 1.677 | G58: =E58/$D58-1 -> 0.0012378997 | H58: =F58/$D58-1 -> -0.036121723 | I58: =SUMIFS('RP - Unit Starts'!$AC$2:$AC$451,'RP - Unit Starts'!$A$2:$A$451,$C58,'RP - Unit Starts'!$F$2:$F$451,"Annual Unit Starts")/SUMIFS('RP - Unit Starts'!$AC$2:$AC$451,'RP - Unit Starts'!$A$2:$A$451,$C58,'RP - Unit Starts'!$F$2:$F$451,"Existing Units") -> 0.029425989 | J58: =SUMIFS('Realpage Data'!$V$2:$V$899,'Realpage Data'!$A$2:$A$899,$C58,'Realpage Data'!$F$2:$F$899,"Existing Units")/SUMIFS('Realpage Data'!$R$2:$R$899,'Realpage Data'!$A$2:$A$899,$C58,'Realpage Data'!$F$2:$F$899,"Existing Units")-1 -> 0.030367449 | K58: =INDEX('Fcst Walk'!$J$5:$J$69,MATCH($C58,'Fcst Walk'!$A$5:$A$69,0))/INDEX('Fcst Walk'!$F$5:$F$69,MATCH($C58,'Fcst Walk'!$A$5:$A$69,0))-1 -> 0.011 | L58: =INDEX('Fcst Walk'!$N$5:$N$69,MATCH($C58,'Fcst Walk'!$A$5:$A$69,0))/INDEX('Fcst Walk'!$J$5:$J$69,MATCH($C58,'Fcst Walk'!$A$5:$A$69,0))-1 -> 0.029 | M58: =INDEX('Fcst Walk'!$R$5:$R$69,MATCH($C58,'Fcst Walk'!$A$5:$A$69,0))/INDEX('Fcst Walk'!$N$5:$N$69,MATCH($C58,'Fcst Walk'!$A$5:$A$69,0))-1 -> 0.036 | N58: =INDEX('Fcst Walk'!$J$5:$J$69,MATCH($C58,'Fcst Walk'!$A$5:$A$69,0))/$D58-1 -> -0.025519062 | O58: =INDEX('Fcst Walk'!$N$5:$N$69,MATCH($C58,'Fcst Walk'!$A$5:$A$69,0))/$D58-1 -> 0.0027408848 | P58: =INDEX('Fcst Walk'!$R$5:$R$69,MATCH($C58,'Fcst Walk'!$A$5:$A$69,0))/$D58-1 -> 0.038839557 | Q58: =INDEX('Fcst Walk'!$AM$5:$AM$69,MATCH($C58,'Fcst Walk'!$A$5:$A$69,0)) -> 2.5604765 | R58: =INDEX('Fcst Walk'!$AN$5:$AN$69,MATCH($C58,'Fcst Walk'!$A$5:$A$69,0)) | S58: =AVERAGE(INDEX('Realpage - His. Rent Change'!$I$2:$AV$577,MATCH($C58,'Realpage - His. Rent Change'!$A$2:$A$577,0),0)) -> 0.0620425 | T58: 0.0507 | U58: =IF(T58="",S58,AVERAGE(S58,T58)) -> 0.05637125 | V58: =IF(H58>=0,0,-H58/U58) -> 0.64078273
B59: =ROW()-4 -> 55 | C59: Des Moines-West Des Moines, IA | D59: =SUMIFS('Realpage Data'!$R$2:$R$899,'Realpage Data'!$A$2:$A$899,$C59,'Realpage Data'!$F$2:$F$899,"Rent Roll (Rev/OSF)") -> 1.3282056 | E59: =SUMIFS('Realpage Data'!$R$2:$R$899,'Realpage Data'!$A$2:$A$899,$C59,'Realpage Data'!$F$2:$F$899,"Asking RPSF") -> 1.324 | F59: =SUMIFS('Realpage Data'!$R$2:$R$899,'Realpage Data'!$A$2:$A$899,$C59,'Realpage Data'!$F$2:$F$899,"Effective RPSF") -> 1.297 | G59: =E59/$D59-1 -> -0.0031663609 | H59: =F59/$D59-1 -> -0.023494539 | I59: =SUMIFS('RP - Unit Starts'!$AC$2:$AC$451,'RP - Unit Starts'!$A$2:$A$451,$C59,'RP - Unit Starts'!$F$2:$F$451,"Annual Unit Starts")/SUMIFS('RP - Unit Starts'!$AC$2:$AC$451,'RP - Unit Starts'!$A$2:$A$451,$C59,'RP - Unit Starts'!$F$2:$F$451,"Existing Units") -> 0.011765675 | J59: =SUMIFS('Realpage Data'!$V$2:$V$899,'Realpage Data'!$A$2:$A$899,$C59,'Realpage Data'!$F$2:$F$899,"Existing Units")/SUMIFS('Realpage Data'!$R$2:$R$899,'Realpage Data'!$A$2:$A$899,$C59,'Realpage Data'!$F$2:$F$899,"Existing Units")-1 -> 0.025475818 | K59: =INDEX('Fcst Walk'!$J$5:$J$69,MATCH($C59,'Fcst Walk'!$A$5:$A$69,0))/INDEX('Fcst Walk'!$F$5:$F$69,MATCH($C59,'Fcst Walk'!$A$5:$A$69,0))-1 -> 0.021 | L59: =INDEX('Fcst Walk'!$N$5:$N$69,MATCH($C59,'Fcst Walk'!$A$5:$A$69,0))/INDEX('Fcst Walk'!$J$5:$J$69,MATCH($C59,'Fcst Walk'!$A$5:$A$69,0))-1 -> 0.024 | M59: =INDEX('Fcst Walk'!$R$5:$R$69,MATCH($C59,'Fcst Walk'!$A$5:$A$69,0))/INDEX('Fcst Walk'!$N$5:$N$69,MATCH($C59,'Fcst Walk'!$A$5:$A$69,0))-1 -> 0.025 | N59: =INDEX('Fcst Walk'!$J$5:$J$69,MATCH($C59,'Fcst Walk'!$A$5:$A$69,0))/$D59-1 -> -0.0029879246 | O59: =INDEX('Fcst Walk'!$N$5:$N$69,MATCH($C59,'Fcst Walk'!$A$5:$A$69,0))/$D59-1 -> 0.020940365 | P59: =INDEX('Fcst Walk'!$R$5:$R$69,MATCH($C59,'Fcst Walk'!$A$5:$A$69,0))/$D59-1 -> 0.046463874 | Q59: =INDEX('Fcst Walk'!$AM$5:$AM$69,MATCH($C59,'Fcst Walk'!$A$5:$A$69,0)) -> 2.6002543 | R59: =INDEX('Fcst Walk'!$AN$5:$AN$69,MATCH($C59,'Fcst Walk'!$A$5:$A$69,0)) | S59: =AVERAGE(INDEX('Realpage - His. Rent Change'!$I$2:$AV$577,MATCH($C59,'Realpage - His. Rent Change'!$A$2:$A$577,0),0)) -> 0.0380625 | U59: =IF(T59="",S59,AVERAGE(S59,T59)) -> 0.0380625 | V59: =IF(H59>=0,0,-H59/U59) -> 0.61726212
B60: =ROW()-4 -> 56 | C60: Tampa-St. Petersburg-Clearwater, FL | D60: =SUMIFS('Realpage Data'!$R$2:$R$899,'Realpage Data'!$A$2:$A$899,$C60,'Realpage Data'!$F$2:$F$899,"Rent Roll (Rev/OSF)") -> 1.9939364 | E60: =SUMIFS('Realpage Data'!$R$2:$R$899,'Realpage Data'!$A$2:$A$899,$C60,'Realpage Data'!$F$2:$F$899,"Asking RPSF") -> 1.931 | F60: =SUMIFS('Realpage Data'!$R$2:$R$899,'Realpage Data'!$A$2:$A$899,$C60,'Realpage Data'!$F$2:$F$899,"Effective RPSF") -> 1.874 | G60: =E60/$D60-1 -> -0.031563889 | H60: =F60/$D60-1 -> -0.060150558 | I60: =SUMIFS('RP - Unit Starts'!$AC$2:$AC$451,'RP - Unit Starts'!$A$2:$A$451,$C60,'RP - Unit Starts'!$F$2:$F$451,"Annual Unit Starts")/SUMIFS('RP - Unit Starts'!$AC$2:$AC$451,'RP - Unit Starts'!$A$2:$A$451,$C60,'RP - Unit Starts'!$F$2:$F$451,"Existing Units") -> 0.018187611 | J60: =SUMIFS('Realpage Data'!$V$2:$V$899,'Realpage Data'!$A$2:$A$899,$C60,'Realpage Data'!$F$2:$F$899,"Existing Units")/SUMIFS('Realpage Data'!$R$2:$R$899,'Realpage Data'!$A$2:$A$899,$C60,'Realpage Data'!$F$2:$F$899,"Existing Units")-1 -> 0.017685046 | K60: =INDEX('Fcst Walk'!$J$5:$J$69,MATCH($C60,'Fcst Walk'!$A$5:$A$69,0))/INDEX('Fcst Walk'!$F$5:$F$69,MATCH($C60,'Fcst Walk'!$A$5:$A$69,0))-1 -> 0.008 | L60: =INDEX('Fcst Walk'!$N$5:$N$69,MATCH($C60,'Fcst Walk'!$A$5:$A$69,0))/INDEX('Fcst Walk'!$J$5:$J$69,MATCH($C60,'Fcst Walk'!$A$5:$A$69,0))-1 -> 0.034 | M60: =INDEX('Fcst Walk'!$R$5:$R$69,MATCH($C60,'Fcst Walk'!$A$5:$A$69,0))/INDEX('Fcst Walk'!$N$5:$N$69,MATCH($C60,'Fcst Walk'!$A$5:$A$69,0))-1 -> 0.035 | N60: =INDEX('Fcst Walk'!$J$5:$J$69,MATCH($C60,'Fcst Walk'!$A$5:$A$69,0))/$D60-1 -> -0.052631762 | O60: =INDEX('Fcst Walk'!$N$5:$N$69,MATCH($C60,'Fcst Walk'!$A$5:$A$69,0))/$D60-1 -> -0.020421242 | P60: =INDEX('Fcst Walk'!$R$5:$R$69,MATCH($C60,'Fcst Walk'!$A$5:$A$69,0))/$D60-1 -> 0.013864014 | Q60: =INDEX('Fcst Walk'!$AM$5:$AM$69,MATCH($C60,'Fcst Walk'!$A$5:$A$69,0)) -> 2.8100718 | R60: =INDEX('Fcst Walk'!$AN$5:$AN$69,MATCH($C60,'Fcst Walk'!$A$5:$A$69,0)) | S60: =AVERAGE(INDEX('Realpage - His. Rent Change'!$I$2:$AV$577,MATCH($C60,'Realpage - His. Rent Change'!$A$2:$A$577,0),0)) -> 0.065445 | T60: 0.0537 | U60: =IF(T60="",S60,AVERAGE(S60,T60)) -> 0.0595725 | V60: =IF(H60>=0,0,-H60/U60) -> 1.0097034
B61: =ROW()-4 -> 57 | C61: Dallas-Plano-Irving, TX | D61: =SUMIFS('Realpage Data'!$R$2:$R$899,'Realpage Data'!$A$2:$A$899,$C61,'Realpage Data'!$F$2:$F$899,"Rent Roll (Rev/OSF)") -> 1.7975387 | E61: =SUMIFS('Realpage Data'!$R$2:$R$899,'Realpage Data'!$A$2:$A$899,$C61,'Realpage Data'!$F$2:$F$899,"Asking RPSF") -> 1.749 | F61: =SUMIFS('Realpage Data'!$R$2:$R$899,'Realpage Data'!$A$2:$A$899,$C61,'Realpage Data'!$F$2:$F$899,"Effective RPSF") -> 1.699 | G61: =E61/$D61-1 -> -0.027002885 | H61: =F61/$D61-1 -> -0.054818698 | I61: =SUMIFS('RP - Unit Starts'!$AC$2:$AC$451,'RP - Unit Starts'!$A$2:$A$451,$C61,'RP - Unit Starts'!$F$2:$F$451,"Annual Unit Starts")/SUMIFS('RP - Unit Starts'!$AC$2:$AC$451,'RP - Unit Starts'!$A$2:$A$451,$C61,'RP - Unit Starts'!$F$2:$F$451,"Existing Units") -> 0.02449441 | J61: =SUMIFS('Realpage Data'!$V$2:$V$899,'Realpage Data'!$A$2:$A$899,$C61,'Realpage Data'!$F$2:$F$899,"Existing Units")/SUMIFS('Realpage Data'!$R$2:$R$899,'Realpage Data'!$A$2:$A$899,$C61,'Realpage Data'!$F$2:$F$899,"Existing Units")-1 -> 0.025148801 | K61: =INDEX('Fcst Walk'!$J$5:$J$69,MATCH($C61,'Fcst Walk'!$A$5:$A$69,0))/INDEX('Fcst Walk'!$F$5:$F$69,MATCH($C61,'Fcst Walk'!$A$5:$A$69,0))-1 -> 0.025 | L61: =INDEX('Fcst Walk'!$N$5:$N$69,MATCH($C61,'Fcst Walk'!$A$5:$A$69,0))/INDEX('Fcst Walk'!$J$5:$J$69,MATCH($C61,'Fcst Walk'!$A$5:$A$69,0))-1 -> 0.021 | M61: =INDEX('Fcst Walk'!$R$5:$R$69,MATCH($C61,'Fcst Walk'!$A$5:$A$69,0))/INDEX('Fcst Walk'!$N$5:$N$69,MATCH($C61,'Fcst Walk'!$A$5:$A$69,0))-1 -> 0.024 | N61: =INDEX('Fcst Walk'!$J$5:$J$69,MATCH($C61,'Fcst Walk'!$A$5:$A$69,0))/$D61-1 -> -0.031189165 | O61: =INDEX('Fcst Walk'!$N$5:$N$69,MATCH($C61,'Fcst Walk'!$A$5:$A$69,0))/$D61-1 -> -0.010844138 | P61: =INDEX('Fcst Walk'!$R$5:$R$69,MATCH($C61,'Fcst Walk'!$A$5:$A$69,0))/$D61-1 -> 0.012895603 | Q61: =INDEX('Fcst Walk'!$AM$5:$AM$69,MATCH($C61,'Fcst Walk'!$A$5:$A$69,0)) -> 2.8241908 | R61: =INDEX('Fcst Walk'!$AN$5:$AN$69,MATCH($C61,'Fcst Walk'!$A$5:$A$69,0)) | S61: =AVERAGE(INDEX('Realpage - His. Rent Change'!$I$2:$AV$577,MATCH($C61,'Realpage - His. Rent Change'!$A$2:$A$577,0),0)) -> 0.0452375 | T61: 0.0348 | U61: =IF(T61="",S61,AVERAGE(S61,T61)) -> 0.04001875 | V61: =IF(H61>=0,0,-H61/U61) -> 1.3698253
B62: =ROW()-4 -> 58 | C62: Cape Coral-Fort Myers, FL | D62: =SUMIFS('Realpage Data'!$R$2:$R$899,'Realpage Data'!$A$2:$A$899,$C62,'Realpage Data'!$F$2:$F$899,"Rent Roll (Rev/OSF)") -> 1.653858 | E62: =SUMIFS('Realpage Data'!$R$2:$R$899,'Realpage Data'!$A$2:$A$899,$C62,'Realpage Data'!$F$2:$F$899,"Asking RPSF") -> 1.682 | F62: =SUMIFS('Realpage Data'!$R$2:$R$899,'Realpage Data'!$A$2:$A$899,$C62,'Realpage Data'!$F$2:$F$899,"Effective RPSF") -> 1.582 | G62: =E62/$D62-1 -> 0.01701599 | H62: =F62/$D62-1 -> -0.043448694 | I62: =SUMIFS('RP - Unit Starts'!$AC$2:$AC$451,'RP - Unit Starts'!$A$2:$A$451,$C62,'RP - Unit Starts'!$F$2:$F$451,"Annual Unit Starts")/SUMIFS('RP - Unit Starts'!$AC$2:$AC$451,'RP - Unit Starts'!$A$2:$A$451,$C62,'RP - Unit Starts'!$F$2:$F$451,"Existing Units") -> 0.016965989 | J62: =SUMIFS('Realpage Data'!$V$2:$V$899,'Realpage Data'!$A$2:$A$899,$C62,'Realpage Data'!$F$2:$F$899,"Existing Units")/SUMIFS('Realpage Data'!$R$2:$R$899,'Realpage Data'!$A$2:$A$899,$C62,'Realpage Data'!$F$2:$F$899,"Existing Units")-1 -> 0.045536967 | K62: =INDEX('Fcst Walk'!$J$5:$J$69,MATCH($C62,'Fcst Walk'!$A$5:$A$69,0))/INDEX('Fcst Walk'!$F$5:$F$69,MATCH($C62,'Fcst Walk'!$A$5:$A$69,0))-1 -> 0.005 | L62: =INDEX('Fcst Walk'!$N$5:$N$69,MATCH($C62,'Fcst Walk'!$A$5:$A$69,0))/INDEX('Fcst Walk'!$J$5:$J$69,MATCH($C62,'Fcst Walk'!$A$5:$A$69,0))-1 -> 0.034 | M62: =INDEX('Fcst Walk'!$R$5:$R$69,MATCH($C62,'Fcst Walk'!$A$5:$A$69,0))/INDEX('Fcst Walk'!$N$5:$N$69,MATCH($C62,'Fcst Walk'!$A$5:$A$69,0))-1 -> 0.032 | N62: =INDEX('Fcst Walk'!$J$5:$J$69,MATCH($C62,'Fcst Walk'!$A$5:$A$69,0))/$D62-1 -> -0.038665937 | O62: =INDEX('Fcst Walk'!$N$5:$N$69,MATCH($C62,'Fcst Walk'!$A$5:$A$69,0))/$D62-1 -> -0.0059805792 | P62: =INDEX('Fcst Walk'!$R$5:$R$69,MATCH($C62,'Fcst Walk'!$A$5:$A$69,0))/$D62-1 -> 0.025828042 | Q62: =INDEX('Fcst Walk'!$AM$5:$AM$69,MATCH($C62,'Fcst Walk'!$A$5:$A$69,0)) -> 2.8775056 | R62: =INDEX('Fcst Walk'!$AN$5:$AN$69,MATCH($C62,'Fcst Walk'!$A$5:$A$69,0)) | S62: =AVERAGE(INDEX('Realpage - His. Rent Change'!$I$2:$AV$577,MATCH($C62,'Realpage - His. Rent Change'!$A$2:$A$577,0),0)) -> 0.059965 | U62: =IF(T62="",S62,AVERAGE(S62,T62)) -> 0.059965 | V62: =IF(H62>=0,0,-H62/U62) -> 0.72456756
B63: =ROW()-4 -> 59 | C63: Greenville/Spartanburg, SC | D63: =SUMIFS('Realpage Data'!$R$2:$R$899,'Realpage Data'!$A$2:$A$899,$C63,'Realpage Data'!$F$2:$F$899,"Rent Roll (Rev/OSF)") -> 1.4727785 | E63: =SUMIFS('Realpage Data'!$R$2:$R$899,'Realpage Data'!$A$2:$A$899,$C63,'Realpage Data'!$F$2:$F$899,"Asking RPSF") -> 1.401 | F63: =SUMIFS('Realpage Data'!$R$2:$R$899,'Realpage Data'!$A$2:$A$899,$C63,'Realpage Data'!$F$2:$F$899,"Effective RPSF") -> 1.379 | G63: =E63/$D63-1 -> -0.048736776 | H63: =F63/$D63-1 -> -0.063674528 | I63: =SUMIFS('RP - Unit Starts'!$AC$2:$AC$451,'RP - Unit Starts'!$A$2:$A$451,$C63,'RP - Unit Starts'!$F$2:$F$451,"Annual Unit Starts")/SUMIFS('RP - Unit Starts'!$AC$2:$AC$451,'RP - Unit Starts'!$A$2:$A$451,$C63,'RP - Unit Starts'!$F$2:$F$451,"Existing Units") -> 0.0018915354 | J63: =SUMIFS('Realpage Data'!$V$2:$V$899,'Realpage Data'!$A$2:$A$899,$C63,'Realpage Data'!$F$2:$F$899,"Existing Units")/SUMIFS('Realpage Data'!$R$2:$R$899,'Realpage Data'!$A$2:$A$899,$C63,'Realpage Data'!$F$2:$F$899,"Existing Units")-1 -> 0.010789218 | K63: =INDEX('Fcst Walk'!$J$5:$J$69,MATCH($C63,'Fcst Walk'!$A$5:$A$69,0))/INDEX('Fcst Walk'!$F$5:$F$69,MATCH($C63,'Fcst Walk'!$A$5:$A$69,0))-1 -> 0.018 | L63: =INDEX('Fcst Walk'!$N$5:$N$69,MATCH($C63,'Fcst Walk'!$A$5:$A$69,0))/INDEX('Fcst Walk'!$J$5:$J$69,MATCH($C63,'Fcst Walk'!$A$5:$A$69,0))-1 -> 0.031 | M63: =INDEX('Fcst Walk'!$R$5:$R$69,MATCH($C63,'Fcst Walk'!$A$5:$A$69,0))/INDEX('Fcst Walk'!$N$5:$N$69,MATCH($C63,'Fcst Walk'!$A$5:$A$69,0))-1 -> 0.031 | N63: =INDEX('Fcst Walk'!$J$5:$J$69,MATCH($C63,'Fcst Walk'!$A$5:$A$69,0))/$D63-1 -> -0.04682067 | O63: =INDEX('Fcst Walk'!$N$5:$N$69,MATCH($C63,'Fcst Walk'!$A$5:$A$69,0))/$D63-1 -> -0.01727211 | P63: =INDEX('Fcst Walk'!$R$5:$R$69,MATCH($C63,'Fcst Walk'!$A$5:$A$69,0))/$D63-1 -> 0.013192454 | Q63: =INDEX('Fcst Walk'!$AM$5:$AM$69,MATCH($C63,'Fcst Walk'!$A$5:$A$69,0)) -> 2.8847625 | R63: =INDEX('Fcst Walk'!$AN$5:$AN$69,MATCH($C63,'Fcst Walk'!$A$5:$A$69,0)) | S63: =AVERAGE(INDEX('Realpage - His. Rent Change'!$I$2:$AV$577,MATCH($C63,'Realpage - His. Rent Change'!$A$2:$A$577,0),0)) -> 0.05433 | U63: =IF(T63="",S63,AVERAGE(S63,T63)) -> 0.05433 | V63: =IF(H63>=0,0,-H63/U63) -> 1.1719957
B64: =ROW()-4 -> 60 | C64: Atlanta-Sandy Springs-Roswell, GA | D64: =SUMIFS('Realpage Data'!$R$2:$R$899,'Realpage Data'!$A$2:$A$899,$C64,'Realpage Data'!$F$2:$F$899,"Rent Roll (Rev/OSF)") -> 1.6284701 | E64: =SUMIFS('Realpage Data'!$R$2:$R$899,'Realpage Data'!$A$2:$A$899,$C64,'Realpage Data'!$F$2:$F$899,"Asking RPSF") -> 1.607 | F64: =SUMIFS('Realpage Data'!$R$2:$R$899,'Realpage Data'!$A$2:$A$899,$C64,'Realpage Data'!$F$2:$F$899,"Effective RPSF") -> 1.562 | G64: =E64/$D64-1 -> -0.013184242 | H64: =F64/$D64-1 -> -0.040817539 | I64: =SUMIFS('RP - Unit Starts'!$AC$2:$AC$451,'RP - Unit Starts'!$A$2:$A$451,$C64,'RP - Unit Starts'!$F$2:$F$451,"Annual Unit Starts")/SUMIFS('RP - Unit Starts'!$AC$2:$AC$451,'RP - Unit Starts'!$A$2:$A$451,$C64,'RP - Unit Starts'!$F$2:$F$451,"Existing Units") -> 0.014393886 | J64: =SUMIFS('Realpage Data'!$V$2:$V$899,'Realpage Data'!$A$2:$A$899,$C64,'Realpage Data'!$F$2:$F$899,"Existing Units")/SUMIFS('Realpage Data'!$R$2:$R$899,'Realpage Data'!$A$2:$A$899,$C64,'Realpage Data'!$F$2:$F$899,"Existing Units")-1 -> 0.018081549 | K64: =INDEX('Fcst Walk'!$J$5:$J$69,MATCH($C64,'Fcst Walk'!$A$5:$A$69,0))/INDEX('Fcst Walk'!$F$5:$F$69,MATCH($C64,'Fcst Walk'!$A$5:$A$69,0))-1 -> 0.01 | L64: =INDEX('Fcst Walk'!$N$5:$N$69,MATCH($C64,'Fcst Walk'!$A$5:$A$69,0))/INDEX('Fcst Walk'!$J$5:$J$69,MATCH($C64,'Fcst Walk'!$A$5:$A$69,0))-1 -> 0.017 | M64: =INDEX('Fcst Walk'!$R$5:$R$69,MATCH($C64,'Fcst Walk'!$A$5:$A$69,0))/INDEX('Fcst Walk'!$N$5:$N$69,MATCH($C64,'Fcst Walk'!$A$5:$A$69,0))-1 -> 0.017 | N64: =INDEX('Fcst Walk'!$J$5:$J$69,MATCH($C64,'Fcst Walk'!$A$5:$A$69,0))/$D64-1 -> -0.031225715 | O64: =INDEX('Fcst Walk'!$N$5:$N$69,MATCH($C64,'Fcst Walk'!$A$5:$A$69,0))/$D64-1 -> -0.014756552 | P64: =INDEX('Fcst Walk'!$R$5:$R$69,MATCH($C64,'Fcst Walk'!$A$5:$A$69,0))/$D64-1 -> 0.0019925866 | Q64: =INDEX('Fcst Walk'!$AM$5:$AM$69,MATCH($C64,'Fcst Walk'!$A$5:$A$69,0)) -> 2.9408322 | R64: =INDEX('Fcst Walk'!$AN$5:$AN$69,MATCH($C64,'Fcst Walk'!$A$5:$A$69,0)) | S64: =AVERAGE(INDEX('Realpage - His. Rent Change'!$I$2:$AV$577,MATCH($C64,'Realpage - His. Rent Change'!$A$2:$A$577,0),0)) -> 0.050315 | T64: 0.0394 | U64: =IF(T64="",S64,AVERAGE(S64,T64)) -> 0.0448575 | V64: =IF(H64>=0,0,-H64/U64) -> 0.9099379
B65: =ROW()-4 -> 61 | C65: Houston-Pasadena-The Woodlands, TX | D65: =SUMIFS('Realpage Data'!$R$2:$R$899,'Realpage Data'!$A$2:$A$899,$C65,'Realpage Data'!$F$2:$F$899,"Rent Roll (Rev/OSF)") -> 1.5651465 | E65: =SUMIFS('Realpage Data'!$R$2:$R$899,'Realpage Data'!$A$2:$A$899,$C65,'Realpage Data'!$F$2:$F$899,"Asking RPSF") -> 1.535 | F65: =SUMIFS('Realpage Data'!$R$2:$R$899,'Realpage Data'!$A$2:$A$899,$C65,'Realpage Data'!$F$2:$F$899,"Effective RPSF") -> 1.495 | G65: =E65/$D65-1 -> -0.019261124 | H65: =F65/$D65-1 -> -0.044817838 | I65: =SUMIFS('RP - Unit Starts'!$AC$2:$AC$451,'RP - Unit Starts'!$A$2:$A$451,$C65,'RP - Unit Starts'!$F$2:$F$451,"Annual Unit Starts")/SUMIFS('RP - Unit Starts'!$AC$2:$AC$451,'RP - Unit Starts'!$A$2:$A$451,$C65,'RP - Unit Starts'!$F$2:$F$451,"Existing Units") -> 0.016723492 | J65: =SUMIFS('Realpage Data'!$V$2:$V$899,'Realpage Data'!$A$2:$A$899,$C65,'Realpage Data'!$F$2:$F$899,"Existing Units")/SUMIFS('Realpage Data'!$R$2:$R$899,'Realpage Data'!$A$2:$A$899,$C65,'Realpage Data'!$F$2:$F$899,"Existing Units")-1 -> 0.015503499 | K65: =INDEX('Fcst Walk'!$J$5:$J$69,MATCH($C65,'Fcst Walk'!$A$5:$A$69,0))/INDEX('Fcst Walk'!$F$5:$F$69,MATCH($C65,'Fcst Walk'!$A$5:$A$69,0))-1 -> -0.005 | L65: =INDEX('Fcst Walk'!$N$5:$N$69,MATCH($C65,'Fcst Walk'!$A$5:$A$69,0))/INDEX('Fcst Walk'!$J$5:$J$69,MATCH($C65,'Fcst Walk'!$A$5:$A$69,0))-1 -> 0.02 | M65: =INDEX('Fcst Walk'!$R$5:$R$69,MATCH($C65,'Fcst Walk'!$A$5:$A$69,0))/INDEX('Fcst Walk'!$N$5:$N$69,MATCH($C65,'Fcst Walk'!$A$5:$A$69,0))-1 -> 0.021 | N65: =INDEX('Fcst Walk'!$J$5:$J$69,MATCH($C65,'Fcst Walk'!$A$5:$A$69,0))/$D65-1 -> -0.049593749 | O65: =INDEX('Fcst Walk'!$N$5:$N$69,MATCH($C65,'Fcst Walk'!$A$5:$A$69,0))/$D65-1 -> -0.030585623 | P65: =INDEX('Fcst Walk'!$R$5:$R$69,MATCH($C65,'Fcst Walk'!$A$5:$A$69,0))/$D65-1 -> -0.010227922 | Q65: =INDEX('Fcst Walk'!$AM$5:$AM$69,MATCH($C65,'Fcst Walk'!$A$5:$A$69,0)) -> 3.8093572 | R65: =INDEX('Fcst Walk'!$AN$5:$AN$69,MATCH($C65,'Fcst Walk'!$A$5:$A$69,0)) -> † | S65: =AVERAGE(INDEX('Realpage - His. Rent Change'!$I$2:$AV$577,MATCH($C65,'Realpage - His. Rent Change'!$A$2:$A$577,0),0)) -> 0.031655 | T65: 0.0186 | U65: =IF(T65="",S65,AVERAGE(S65,T65)) -> 0.0251275 | V65: =IF(H65>=0,0,-H65/U65) -> 1.7836171
B66: =ROW()-4 -> 62 | C66: New Orleans-Metairie/Slidell, LA | D66: =SUMIFS('Realpage Data'!$R$2:$R$899,'Realpage Data'!$A$2:$A$899,$C66,'Realpage Data'!$F$2:$F$899,"Rent Roll (Rev/OSF)") -> 1.670355 | E66: =SUMIFS('Realpage Data'!$R$2:$R$899,'Realpage Data'!$A$2:$A$899,$C66,'Realpage Data'!$F$2:$F$899,"Asking RPSF") -> 1.545 | F66: =SUMIFS('Realpage Data'!$R$2:$R$899,'Realpage Data'!$A$2:$A$899,$C66,'Realpage Data'!$F$2:$F$899,"Effective RPSF") -> 1.528 | G66: =E66/$D66-1 -> -0.075046933 | H66: =F66/$D66-1 -> -0.085224411 | I66: =SUMIFS('RP - Unit Starts'!$AC$2:$AC$451,'RP - Unit Starts'!$A$2:$A$451,$C66,'RP - Unit Starts'!$F$2:$F$451,"Annual Unit Starts")/SUMIFS('RP - Unit Starts'!$AC$2:$AC$451,'RP - Unit Starts'!$A$2:$A$451,$C66,'RP - Unit Starts'!$F$2:$F$451,"Existing Units") -> 0.0037215202 | J66: =SUMIFS('Realpage Data'!$V$2:$V$899,'Realpage Data'!$A$2:$A$899,$C66,'Realpage Data'!$F$2:$F$899,"Existing Units")/SUMIFS('Realpage Data'!$R$2:$R$899,'Realpage Data'!$A$2:$A$899,$C66,'Realpage Data'!$F$2:$F$899,"Existing Units")-1 -> 0.00071797817 | K66: =INDEX('Fcst Walk'!$J$5:$J$69,MATCH($C66,'Fcst Walk'!$A$5:$A$69,0))/INDEX('Fcst Walk'!$F$5:$F$69,MATCH($C66,'Fcst Walk'!$A$5:$A$69,0))-1 -> 0.003 | L66: =INDEX('Fcst Walk'!$N$5:$N$69,MATCH($C66,'Fcst Walk'!$A$5:$A$69,0))/INDEX('Fcst Walk'!$J$5:$J$69,MATCH($C66,'Fcst Walk'!$A$5:$A$69,0))-1 -> 0.03 | M66: =INDEX('Fcst Walk'!$R$5:$R$69,MATCH($C66,'Fcst Walk'!$A$5:$A$69,0))/INDEX('Fcst Walk'!$N$5:$N$69,MATCH($C66,'Fcst Walk'!$A$5:$A$69,0))-1 -> 0.028 | N66: =INDEX('Fcst Walk'!$J$5:$J$69,MATCH($C66,'Fcst Walk'!$A$5:$A$69,0))/$D66-1 -> -0.082480084 | O66: =INDEX('Fcst Walk'!$N$5:$N$69,MATCH($C66,'Fcst Walk'!$A$5:$A$69,0))/$D66-1 -> -0.054954486 | P66: =INDEX('Fcst Walk'!$R$5:$R$69,MATCH($C66,'Fcst Walk'!$A$5:$A$69,0))/$D66-1 -> -0.028493212 | Q66: =INDEX('Fcst Walk'!$AM$5:$AM$69,MATCH($C66,'Fcst Walk'!$A$5:$A$69,0)) -> 4.040016 | R66: =INDEX('Fcst Walk'!$AN$5:$AN$69,MATCH($C66,'Fcst Walk'!$A$5:$A$69,0)) -> † | S66: =AVERAGE(INDEX('Realpage - His. Rent Change'!$I$2:$AV$577,MATCH($C66,'Realpage - His. Rent Change'!$A$2:$A$577,0),0)) -> 0.0373125 | U66: =IF(T66="",S66,AVERAGE(S66,T66)) -> 0.0373125 | V66: =IF(H66>=0,0,-H66/U66) -> 2.2840713
B67: =ROW()-4 -> 63 | C67: Austin-Round Rock-San Marcos, TX | D67: =SUMIFS('Realpage Data'!$R$2:$R$899,'Realpage Data'!$A$2:$A$899,$C67,'Realpage Data'!$F$2:$F$899,"Rent Roll (Rev/OSF)") -> 1.6921677 | E67: =SUMIFS('Realpage Data'!$R$2:$R$899,'Realpage Data'!$A$2:$A$899,$C67,'Realpage Data'!$F$2:$F$899,"Asking RPSF") -> 1.691 | F67: =SUMIFS('Realpage Data'!$R$2:$R$899,'Realpage Data'!$A$2:$A$899,$C67,'Realpage Data'!$F$2:$F$899,"Effective RPSF") -> 1.595 | G67: =E67/$D67-1 -> -0.0006900397 | H67: =F67/$D67-1 -> -0.057422007 | I67: =SUMIFS('RP - Unit Starts'!$AC$2:$AC$451,'RP - Unit Starts'!$A$2:$A$451,$C67,'RP - Unit Starts'!$F$2:$F$451,"Annual Unit Starts")/SUMIFS('RP - Unit Starts'!$AC$2:$AC$451,'RP - Unit Starts'!$A$2:$A$451,$C67,'RP - Unit Starts'!$F$2:$F$451,"Existing Units") -> 0.015673893 | J67: =SUMIFS('Realpage Data'!$V$2:$V$899,'Realpage Data'!$A$2:$A$899,$C67,'Realpage Data'!$F$2:$F$899,"Existing Units")/SUMIFS('Realpage Data'!$R$2:$R$899,'Realpage Data'!$A$2:$A$899,$C67,'Realpage Data'!$F$2:$F$899,"Existing Units")-1 -> 0.026184454 | K67: =INDEX('Fcst Walk'!$J$5:$J$69,MATCH($C67,'Fcst Walk'!$A$5:$A$69,0))/INDEX('Fcst Walk'!$F$5:$F$69,MATCH($C67,'Fcst Walk'!$A$5:$A$69,0))-1 -> 0.009 | L67: =INDEX('Fcst Walk'!$N$5:$N$69,MATCH($C67,'Fcst Walk'!$A$5:$A$69,0))/INDEX('Fcst Walk'!$J$5:$J$69,MATCH($C67,'Fcst Walk'!$A$5:$A$69,0))-1 -> 0.023 | M67: =INDEX('Fcst Walk'!$R$5:$R$69,MATCH($C67,'Fcst Walk'!$A$5:$A$69,0))/INDEX('Fcst Walk'!$N$5:$N$69,MATCH($C67,'Fcst Walk'!$A$5:$A$69,0))-1 -> 0.024 | N67: =INDEX('Fcst Walk'!$J$5:$J$69,MATCH($C67,'Fcst Walk'!$A$5:$A$69,0))/$D67-1 -> -0.048938805 | O67: =INDEX('Fcst Walk'!$N$5:$N$69,MATCH($C67,'Fcst Walk'!$A$5:$A$69,0))/$D67-1 -> -0.027064397 | P67: =INDEX('Fcst Walk'!$R$5:$R$69,MATCH($C67,'Fcst Walk'!$A$5:$A$69,0))/$D67-1 -> -0.0037139428 | Q67: =INDEX('Fcst Walk'!$AM$5:$AM$69,MATCH($C67,'Fcst Walk'!$A$5:$A$69,0)) -> 4.2891585 | R67: =INDEX('Fcst Walk'!$AN$5:$AN$69,MATCH($C67,'Fcst Walk'!$A$5:$A$69,0)) -> † | S67: =AVERAGE(INDEX('Realpage - His. Rent Change'!$I$2:$AV$577,MATCH($C67,'Realpage - His. Rent Change'!$A$2:$A$577,0),0)) -> 0.028745 | T67: 0.0198 | U67: =IF(T67="",S67,AVERAGE(S67,T67)) -> 0.0242725 | V67: =IF(H67>=0,0,-H67/U67) -> 2.3657228
B68: =ROW()-4 -> 64 | C68: Denver-Aurora-Centennial, CO | D68: =SUMIFS('Realpage Data'!$R$2:$R$899,'Realpage Data'!$A$2:$A$899,$C68,'Realpage Data'!$F$2:$F$899,"Rent Roll (Rev/OSF)") -> 2.0970263 | E68: =SUMIFS('Realpage Data'!$R$2:$R$899,'Realpage Data'!$A$2:$A$899,$C68,'Realpage Data'!$F$2:$F$899,"Asking RPSF") -> 2.087 | F68: =SUMIFS('Realpage Data'!$R$2:$R$899,'Realpage Data'!$A$2:$A$899,$C68,'Realpage Data'!$F$2:$F$899,"Effective RPSF") -> 1.979 | G68: =E68/$D68-1 -> -0.0047812192 | H68: =F68/$D68-1 -> -0.056282718 | I68: =SUMIFS('RP - Unit Starts'!$AC$2:$AC$451,'RP - Unit Starts'!$A$2:$A$451,$C68,'RP - Unit Starts'!$F$2:$F$451,"Annual Unit Starts")/SUMIFS('RP - Unit Starts'!$AC$2:$AC$451,'RP - Unit Starts'!$A$2:$A$451,$C68,'RP - Unit Starts'!$F$2:$F$451,"Existing Units") -> 0.019471733 | J68: =SUMIFS('Realpage Data'!$V$2:$V$899,'Realpage Data'!$A$2:$A$899,$C68,'Realpage Data'!$F$2:$F$899,"Existing Units")/SUMIFS('Realpage Data'!$R$2:$R$899,'Realpage Data'!$A$2:$A$899,$C68,'Realpage Data'!$F$2:$F$899,"Existing Units")-1 -> 0.02161269 | K68: =INDEX('Fcst Walk'!$J$5:$J$69,MATCH($C68,'Fcst Walk'!$A$5:$A$69,0))/INDEX('Fcst Walk'!$F$5:$F$69,MATCH($C68,'Fcst Walk'!$A$5:$A$69,0))-1 -> 0.006 | L68: =INDEX('Fcst Walk'!$N$5:$N$69,MATCH($C68,'Fcst Walk'!$A$5:$A$69,0))/INDEX('Fcst Walk'!$J$5:$J$69,MATCH($C68,'Fcst Walk'!$A$5:$A$69,0))-1 -> 0.021 | M68: =INDEX('Fcst Walk'!$R$5:$R$69,MATCH($C68,'Fcst Walk'!$A$5:$A$69,0))/INDEX('Fcst Walk'!$N$5:$N$69,MATCH($C68,'Fcst Walk'!$A$5:$A$69,0))-1 -> 0.022 | N68: =INDEX('Fcst Walk'!$J$5:$J$69,MATCH($C68,'Fcst Walk'!$A$5:$A$69,0))/$D68-1 -> -0.050620414 | O68: =INDEX('Fcst Walk'!$N$5:$N$69,MATCH($C68,'Fcst Walk'!$A$5:$A$69,0))/$D68-1 -> -0.030683443 | P68: =INDEX('Fcst Walk'!$R$5:$R$69,MATCH($C68,'Fcst Walk'!$A$5:$A$69,0))/$D68-1 -> -0.0093584789 | Q68: =INDEX('Fcst Walk'!$AM$5:$AM$69,MATCH($C68,'Fcst Walk'!$A$5:$A$69,0)) -> 5.0385997 | R68: =INDEX('Fcst Walk'!$AN$5:$AN$69,MATCH($C68,'Fcst Walk'!$A$5:$A$69,0)) -> † | S68: =AVERAGE(INDEX('Realpage - His. Rent Change'!$I$2:$AV$577,MATCH($C68,'Realpage - His. Rent Change'!$A$2:$A$577,0),0)) -> 0.0349175 | T68: 0.0299 | U68: =IF(T68="",S68,AVERAGE(S68,T68)) -> 0.03240875 | V68: =IF(H68>=0,0,-H68/U68) -> 1.7366519
B69: =ROW()-4 -> 65 | C69: San Antonio-New Braunfels, TX | D69: =SUMIFS('Realpage Data'!$R$2:$R$899,'Realpage Data'!$A$2:$A$899,$C69,'Realpage Data'!$F$2:$F$899,"Rent Roll (Rev/OSF)") -> 1.4268025 | E69: =SUMIFS('Realpage Data'!$R$2:$R$899,'Realpage Data'!$A$2:$A$899,$C69,'Realpage Data'!$F$2:$F$899,"Asking RPSF") -> 1.387 | F69: =SUMIFS('Realpage Data'!$R$2:$R$899,'Realpage Data'!$A$2:$A$899,$C69,'Realpage Data'!$F$2:$F$899,"Effective RPSF") -> 1.325 | G69: =E69/$D69-1 -> -0.027896292 | H69: =F69/$D69-1 -> -0.071350098 | I69: =SUMIFS('RP - Unit Starts'!$AC$2:$AC$451,'RP - Unit Starts'!$A$2:$A$451,$C69,'RP - Unit Starts'!$F$2:$F$451,"Annual Unit Starts")/SUMIFS('RP - Unit Starts'!$AC$2:$AC$451,'RP - Unit Starts'!$A$2:$A$451,$C69,'RP - Unit Starts'!$F$2:$F$451,"Existing Units") -> 0.0025948699 | J69: =SUMIFS('Realpage Data'!$V$2:$V$899,'Realpage Data'!$A$2:$A$899,$C69,'Realpage Data'!$F$2:$F$899,"Existing Units")/SUMIFS('Realpage Data'!$R$2:$R$899,'Realpage Data'!$A$2:$A$899,$C69,'Realpage Data'!$F$2:$F$899,"Existing Units")-1 -> 0.0077846097 | K69: =INDEX('Fcst Walk'!$J$5:$J$69,MATCH($C69,'Fcst Walk'!$A$5:$A$69,0))/INDEX('Fcst Walk'!$F$5:$F$69,MATCH($C69,'Fcst Walk'!$A$5:$A$69,0))-1 -> -0.009 | L69: =INDEX('Fcst Walk'!$N$5:$N$69,MATCH($C69,'Fcst Walk'!$A$5:$A$69,0))/INDEX('Fcst Walk'!$J$5:$J$69,MATCH($C69,'Fcst Walk'!$A$5:$A$69,0))-1 -> 0.022 | M69: =INDEX('Fcst Walk'!$R$5:$R$69,MATCH($C69,'Fcst Walk'!$A$5:$A$69,0))/INDEX('Fcst Walk'!$N$5:$N$69,MATCH($C69,'Fcst Walk'!$A$5:$A$69,0))-1 -> 0.028 | N69: =INDEX('Fcst Walk'!$J$5:$J$69,MATCH($C69,'Fcst Walk'!$A$5:$A$69,0))/$D69-1 -> -0.079707948 | O69: =INDEX('Fcst Walk'!$N$5:$N$69,MATCH($C69,'Fcst Walk'!$A$5:$A$69,0))/$D69-1 -> -0.059461522 | P69: =INDEX('Fcst Walk'!$R$5:$R$69,MATCH($C69,'Fcst Walk'!$A$5:$A$69,0))/$D69-1 -> -0.033126445 | Q69: =INDEX('Fcst Walk'!$AM$5:$AM$69,MATCH($C69,'Fcst Walk'!$A$5:$A$69,0)) -> 5.068125 | R69: =INDEX('Fcst Walk'!$AN$5:$AN$69,MATCH($C69,'Fcst Walk'!$A$5:$A$69,0)) -> † | S69: =AVERAGE(INDEX('Realpage - His. Rent Change'!$I$2:$AV$577,MATCH($C69,'Realpage - His. Rent Change'!$A$2:$A$577,0),0)) -> 0.033875 | T69: 0.0212 | U69: =IF(T69="",S69,AVERAGE(S69,T69)) -> 0.0275375 | V69: =IF(H69>=0,0,-H69/U69) -> 2.5910158
C71: Sources & methodology
C72: RealPage DataDirect (datadirect_72.xlsx, Aug 2026 pull): actuals through 2026Q2; RealPage same-store YOY effective rent forecast 2026Q3–2029Q4; Existing Units forecast drives Fwd 12-Mo Inventory Growth.
C73: TTM Unit Starts (2025Q3–2026Q2) from datadirect_74 (Aug 2026 pull); 10-yr historical rent change carried from prior workbook (same Q2 2026 vintage). GSA = Green Street 10-yr avg — hardcoded inputs (blue), available for 23 of 50 markets.
C74: Years to Rent Roll Even (RP Forecast): Effective RPSF is walked forward quarterly — Path(t) = Path(t-4) × (1 + forecast YOY) — against a FLAT current rent roll PSF. Reported figure = time until the path recovers to the rent roll level and stays above it through the horizon (interpolated within the crossing quarter). See Fcst Walk tab.
C75: † = still below rent roll at 2029Q4 (3.5-yr forecast horizon); extended beyond the horizon at the terminal forecast growth rate.
C76: Old Method column = -Effective MtM ÷ 10-yr blended historical growth, shown for comparison. Note: the prior workbook’s RP 10-yr averages were mis-ranged (AVERAGEIF) and are corrected here (e.g. Charlotte: -0.2% → 5.3%).
C77: Directional tool per CB 8/17 spec — intentionally ignores renewal vs new-lease mix, retention, and rent roll drift. Q2 2026 levels reflect RealPage restatements and differ modestly from the prior pull.
C78: 15 expansion markets added Aug 2026 (CB request). TTM Unit Starts are ACTUALS for all 65 markets from RealPage DataDirect (datadirect_74.xlsx: quarterly Unit Starts 2021Q2-2026Q2 + Existing Units, all 150 markets; ties out exactly to the prior pull on the 50 overlap markets). Lake Charles, LA is not in the RealPage DataDirect market set.
C79: Dropped from this version to keep focus: PF LIRR proforma engine (Cap Rate to IRR Map) — available in the prior workbook.

Sheet Realpage Data
A1: Geography Name | B1: Geography Type | C1: Market Name | D1: Unique ID | E1: Metric Type | F1: Metric Name | G1: Category | H1: Niche | I1: Y2024Q1 | J1: Y2024Q2 | K1: Y2024Q3 | L1: Y2024Q4 | M1: Y2025Q1 | N1: Y2025Q2 | O1: Y2025Q3 | P1: Y2025Q4 | Q1: Y2026Q1 | R1: Y2026Q2 | S1: Y2026Q3 | T1: Y2026Q4 | U1: Y2027Q1 | V1: Y2027Q2 | W1: Y2027Q3 | X1: Y2027Q4 | Y1: Y2028Q1 | Z1: Y2028Q2 | AA1: Y2028Q3 | AB1: Y2028Q4 | AC1: Y2029Q1 | AD1: Y2029Q2 | AE1: Y2029Q3 | AF1: Y2029Q4
A2: Akron, OH | B2: Market | C2: Akron, OH | D2: 10420 | E2: Transaction Data - Operational | F2: Rent Roll (Rev/OSF) | G2: Totals | H2: Totals | I2: 1.2147683 | J2: 1.2256967 | K2: 1.2512071 | L2: 1.273789 | M2: 1.2839264 | N2: 1.303023 | O2: 1.3259442 | P2: 1.3194263 | Q2: 1.3246833 | R2: 1.3499301
A3: Akron, OH | B3: Market | C3: Akron, OH | D3: 10420 | E3: Performance | F3: Effective RPSF | G3: Totals | H3: Totals | I3: 1.286 | J3: 1.307 | K3: 1.341 | L3: 1.327 | M3: 1.347 | N3: 1.385 | O3: 1.417 | P3: 1.411 | Q3: 1.419 | R3: 1.44
A4: Akron, OH | B4: Market | C4: Akron, OH | D4: 10420 | E4: Performance | F4: Existing Units | G4: Totals | H4: Totals | I4: 45366 | J4: 45424 | K4: 45472 | L4: 45520 | M4: 45571 | N4: 45622 | O4: 45837 | P4: 46048 | Q4: 46134 | R4: 46163 | S4: 46163 | T4: 46163 | U4: 46163 | V4: 46163 | W4: 46394 | X4: 46406 | Y4: 46406 | Z4: 46406 | AA4: 46637 | AB4: 46648 | AC4: 46647 | AD4: 46646 | AE4: 46877 | AF4: 46887
A5: Akron, OH | B5: Market | C5: Akron, OH | D5: 10420 | E5: Performance | F5: Asking RPSF | G5: Totals | H5: Totals | I5: 1.29 | J5: 1.312 | K5: 1.346 | L5: 1.336 | M5: 1.354 | N5: 1.387 | O5: 1.42 | P5: 1.417 | Q5: 1.428 | R5: 1.449
A6: Akron, OH | B6: Market | C6: Akron, OH | D6: 10420 | E6: Same-Store Performance | F6: YOY Effective Rent Change | G6: Totals | H6: Totals | I6: 0.0423 | J6: 0.0274 | K6: 0.0351 | L6: 0.0359 | M6: 0.0373 | N6: 0.0411 | O6: 0.0352 | P6: 0.04 | Q6: 0.0328 | R6: 0.0301 | S6: 0.031 | T6: 0.031 | U6: 0.031 | V6: 0.033 | W6: 0.031 | X6: 0.031 | Y6: 0.03 | Z6: 0.03 | AA6: 0.029 | AB6: 0.029 | AC6: 0.029 | AD6: 0.029 | AE6: 0.029 | AF6: 0.029
A7: Akron, OH | B7: Market | C7: Akron, OH | D7: 10420 | E7: Supply & Demand | F7: Annual Property Starts | G7: Totals | H7: Totals | I7: 2 | J7: 2 | K7: 2 | L7: 2 | M7: 1 | N7: 0 | O7: 0 | P7: 0 | Q7: 0 | R7: 0
A8: Albany-Schenectady-Troy, NY | B8: Market | C8: Albany-Schenectady-Troy, NY | D8: 10580 | E8: Transaction Data - Operational | F8: Rent Roll (Rev/OSF) | G8: Totals | H8: Totals | I8: 1.721535 | J8: 1.7232234 | K8: 1.7548167 | L8: 1.7679916 | M8: 1.7671778 | N8: 1.7782893 | O8: 1.8128375 | P8: 1.8566497 | Q8: 1.8729926 | R8: 1.889791
A9: Albany-Schenectady-Troy, NY | B9: Market | C9: Albany-Schenectady-Troy, NY | D9: 10580 | E9: Performance | F9: Effective RPSF | G9: Totals | H9: Totals | I9: 1.693 | J9: 1.714 | K9: 1.726 | L9: 1.74 | M9: 1.751 | N9: 1.811 | O9: 1.85 | P9: 1.837 | Q9: 1.85 | R9: 1.88
A10: Albany-Schenectady-Troy, NY | B10: Market | C10: Albany-Schenectady-Troy, NY | D10: 10580 | E10: Performance | F10: Existing Units | G10: Totals | H10: Totals | I10: 66985 | J10: 67454 | K10: 67728 | L10: 67956 | M10: 68092 | N10: 68197 | O10: 68300 | P10: 68367 | Q10: 68421 | R10: 68494 | S10: 68566 | T10: 68672 | U10: 68749 | V10: 68893 | W10: 69083 | X10: 69228 | Y10: 69313 | Z10: 69457 | AA10: 69601 | AB10: 69743 | AC10: 69819 | AD10: 69943 | AE10: 70063 | AF10: 70169
A11: Albany-Schenectady-Troy, NY | B11: Market | C11: Albany-Schenectady-Troy, NY | D11: 10580 | E11: Performance | F11: Asking RPSF | G11: Totals | H11: Totals | I11: 1.697 | J11: 1.717 | K11: 1.732 | L11: 1.743 | M11: 1.753 | N11: 1.816 | O11: 1.853 | P11: 1.841 | Q11: 1.855 | R11: 1.884
A12: Albany-Schenectady-Troy, NY | B12: Market | C12: Albany-Schenectady-Troy, NY | D12: 10580 | E12: Same-Store Performance | F12: YOY Effective Rent Change | G12: Totals | H12: Totals | I12: 0.0472 | J12: 0.0299 | K12: 0.0179 | L12: 0.0222 | M12: 0.0284 | N12: 0.0367 | O12: 0.0378 | P12: 0.0294 | Q12: 0.0299 | R12: 0.0264 | S12: 0.026 | T12: 0.022 | U12: 0.017 | V12: 0.016 | W12: 0.018 | X12: 0.026 | Y12: 0.028 | Z12: 0.025 | AA12: 0.026 | AB12: 0.029 | AC12: 0.029 | AD12: 0.025 | AE12: 0.024 | AF12: 0.03
A13: Albany-Schenectady-Troy, NY | B13: Market | C13: Albany-Schenectady-Troy, NY | D13: 10580 | E13: Supply & Demand | F13: Annual Property Starts | G13: Totals | H13: Totals | I13: 7 | J13: 8 | K13: 12 | L13: 10 | M13: 8 | N13: 7 | O13: 3 | P13: 6 | Q13: 5 | R13: 4
A14: Albuquerque, NM | B14: Market | C14: Albuquerque, NM | D14: 10740 | E14: Transaction Data - Operational | F14: Rent Roll (Rev/OSF) | G14: Totals | H14: Totals | I14: 1.5248877 | J14: 1.5395235 | K14: 1.552652 | L14: 1.5855803 | M14: 1.5880006 | N14: 1.6017976 | O14: 1.6109823 | P14: 1.6116879 | Q14: 1.6112929 | R14: 1.627998
A15: Albuquerque, NM | B15: Market | C15: Albuquerque, NM | D15: 10740 | E15: Performance | F15: Effective RPSF | G15: Totals | H15: Totals | I15: 1.563 | J15: 1.578 | K15: 1.597 | L15: 1.59 | M15: 1.588 | N15: 1.598 | O15: 1.612 | P15: 1.583 | Q15: 1.584 | R15: 1.612
A16: Albuquerque, NM | B16: Market | C16: Albuquerque, NM | D16: 10740 | E16: Performance | F16: Existing Units | G16: Totals | H16: Totals | I16: 56831 | J16: 57160 | K16: 57618 | L16: 58005 | M16: 58214 | N16: 58266 | O16: 58433 | P16: 58748 | Q16: 58897 | R16: 59079 | S16: 59378 | T16: 59378 | U16: 59405 | V16: 59415 | W16: 59792 | X16: 59929 | Y16: 59770 | Z16: 59765 | AA16: 60176 | AB16: 60324 | AC16: 60167 | AD16: 60155 | AE16: 60564 | AF16: 60716
A17: Albuquerque, NM | B17: Market | C17: Albuquerque, NM | D17: 10740 | E17: Performance | F17: Asking RPSF | G17: Totals | H17: Totals | I17: 1.571 | J17: 1.591 | K17: 1.611 | L17: 1.599 | M17: 1.596 | N17: 1.609 | O17: 1.622 | P17: 1.599 | Q17: 1.6 | R17: 1.628
A18: Albuquerque, NM | B18: Market | C18: Albuquerque, NM | D18: 10740 | E18: Same-Store Performance | F18: YOY Effective Rent Change | G18: Totals | H18: Totals | I18: 0.0142 | J18: 0.0056 | K18: 0.0062 | L18: 0.018 | M18: 0.015 | N18: 0.0078 | O18: -0.0094 | P18: -0.0256 | Q18: -0.0229 | R18: -0.0067 | S18: -0.004 | T18: 0.001 | U18: 0.008 | V18: 0.018 | W18: 0.031 | X18: 0.033 | Y18: 0.034 | Z18: 0.036 | AA18: 0.038 | AB18: 0.039 | AC18: 0.038 | AD18: 0.037 | AE18: 0.035 | AF18: 0.034
A19: Albuquerque, NM | B19: Market | C19: Albuquerque, NM | D19: 10740 | E19: Supply & Demand | F19: Annual Property Starts | G19: Totals | H19: Totals | I19: 5 | J19: 3 | K19: 4 | L19: 2 | M19: 1 | N19: 1 | O19: 1 | P19: 1 | Q19: 2 | R19: 3
A20: Allentown-Bethlehem-Easton, PA-NJ | B20: Market | C20: Allentown-Bethlehem-Easton, PA-NJ | D20: 10900 | E20: Transaction Data - Operational | F20: Rent Roll (Rev/OSF) | G20: Totals | H20: Totals | I20: 1.6806331 | J20: 1.6946529 | K20: 1.716649 | L20: 1.7281398 | M20: 1.7429784 | N20: 1.737571 | O20: 1.7678881 | P20: 1.8041899 | Q20: 1.8159847 | R20: 1.8676643
A21: Allentown-Bethlehem-Easton, PA-NJ | B21: Market | C21: Allentown-Bethlehem-Easton, PA-NJ | D21: 10900 | E21: Performance | F21: Effective RPSF | G21: Totals | H21: Totals | I21: 1.79 | J21: 1.804 | K21: 1.846 | L21: 1.86 | M21: 1.869 | N21: 1.91 | O21: 1.929 | P21: 1.923 | Q21: 1.923 | R21: 1.96
A22: Allentown-Bethlehem-Easton, PA-NJ | B22: Market | C22: Allentown-Bethlehem-Easton, PA-NJ | D22: 10900 | E22: Performance | F22: Existing Units | G22: Totals | H22: Totals | I22: 44600 | J22: 44726 | K22: 44822 | L22: 45196 | M22: 45404 | N22: 45671 | O22: 45826 | P22: 46047 | Q22: 46107 | R22: 46309 | S22: 46604 | T22: 47243 | U22: 47462 | V22: 47602 | W22: 47806 | X22: 47850 | Y22: 47877 | Z22: 48016 | AA22: 48215 | AB22: 48241 | AC22: 48245 | AD22: 48364 | AE22: 48538 | AF22: 48548
A23: Allentown-Bethlehem-Easton, PA-NJ | B23: Market | C23: Allentown-Bethlehem-Easton, PA-NJ | D23: 10900 | E23: Performance | F23: Asking RPSF | G23: Totals | H23: Totals | I23: 1.797 | J23: 1.81 | K23: 1.85 | L23: 1.863 | M23: 1.873 | N23: 1.916 | O23: 1.934 | P23: 1.933 | Q23: 1.935 | R23: 1.974
A24: Allentown-Bethlehem-Easton, PA-NJ | B24: Market | C24: Allentown-Bethlehem-Easton, PA-NJ | D24: 10900 | E24: Same-Store Performance | F24: YOY Effective Rent Change | G24: Totals | H24: Totals | I24: 0.0299 | J24: 0.0199 | K24: 0.0303 | L24: 0.0323 | M24: 0.0435 | N24: 0.0569 | O24: 0.0362 | P24: 0.0214 | Q24: 0.0147 | R24: 0.0148 | S24: 0.019 | T24: 0.026 | U24: 0.027 | V24: 0.026 | W24: 0.024 | X24: 0.025 | Y24: 0.028 | Z24: 0.029 | AA24: 0.031 | AB24: 0.032 | AC24: 0.032 | AD24: 0.031 | AE24: 0.032 | AF24: 0.032
A25: Allentown-Bethlehem-Easton, PA-NJ | B25: Market | C25: Allentown-Bethlehem-Easton, PA-NJ | D25: 10900 | E25: Supply & Demand | F25: Annual Property Starts | G25: Totals | H25: Totals | I25: 8 | J25: 6 | K25: 6 | L25: 4 | M25: 2 | N25: 5 | O25: 5 | P25: 5 | Q25: 5 | R25: 2
A26: Anaheim-Santa Ana-Irvine, CA | B26: Market | C26: Anaheim-Santa Ana-Irvine, CA | D26: 11244 | E26: Transaction Data - Operational | F26: Rent Roll (Rev/OSF) | G26: Totals | H26: Totals | I26: 2.9577199 | J26: 2.9814415 | K26: 3.0358027 | L26: 3.0770533 | M26: 3.1047578 | N26: 3.1649269 | O26: 3.1806598 | P26: 3.2240905 | Q26: 3.2618546 | R26: 3.2890408
A27: Anaheim-Santa Ana-Irvine, CA | B27: Market | C27: Anaheim-Santa Ana-Irvine, CA | D27: 11244 | E27: Performance | F27: Effective RPSF | G27: Totals | H27: Totals | I27: 3.115 | J27: 3.117 | K27: 3.173 | L27: 3.164 | M27: 3.164 | N27: 3.213 | O27: 3.259 | P27: 3.231 | Q27: 3.231 | R27: 3.264
A28: Anaheim-Santa Ana-Irvine, CA | B28: Market | C28: Anaheim-Santa Ana-Irvine, CA | D28: 11244 | E28: Performance | F28: Existing Units | G28: Totals | H28: Totals | I28: 269177 | J28: 269472 | K28: 270319 | L28: 270962 | M28: 271449 | N28: 272221 | O28: 272688 | P28: 273224 | Q28: 274073 | R28: 274800 | S28: 275500 | T28: 277814 | U28: 278365 | V28: 279047 | W28: 279606 | X28: 280271 | Y28: 280907 | Z28: 281545 | AA28: 282261 | AB28: 282937 | AC28: 283202 | AD28: 283820 | AE28: 284750 | AF28: 285060
A29: Anaheim-Santa Ana-Irvine, CA | B29: Market | C29: Anaheim-Santa Ana-Irvine, CA | D29: 11244 | E29: Performance | F29: Asking RPSF | G29: Totals | H29: Totals | I29: 3.125 | J29: 3.129 | K29: 3.187 | L29: 3.177 | M29: 3.174 | N29: 3.22 | O29: 3.266 | P29: 3.242 | Q29: 3.24 | R29: 3.274
A30: Anaheim-Santa Ana-Irvine, CA | B30: Market | C30: Anaheim-Santa Ana-Irvine, CA | D30: 11244 | E30: Same-Store Performance | F30: YOY Effective Rent Change | G30: Totals | H30: Totals | I30: 0.0255 | J30: 0.0201 | K30: 0.0143 | L30: 0.0069 | M30: 0.0134 | N30: 0.0213 | O30: 0.0136 | P30: 0.0082 | Q30: 0.0098 | R30: 0.0126 | S30: 0.014 | T30: 0.02 | U30: 0.023 | V30: 0.023 | W30: 0.025 | X30: 0.028 | Y30: 0.029 | Z30: 0.027 | AA30: 0.027 | AB30: 0.029 | AC30: 0.029 | AD30: 0.027 | AE30: 0.026 | AF30: 0.028
A31: Anaheim-Santa Ana-Irvine, CA | B31: Market | C31: Anaheim-Santa Ana-Irvine, CA | D31: 11244 | E31: Supply & Demand | F31: Annual Property Starts | G31: Totals | H31: Totals | I31: 5 | J31: 5 | K31: 5 | L31: 6 | M31: 6 | N31: 5 | O31: 4 | P31: 7 | Q31: 9 | R31: 9
A32: Ann Arbor, MI | B32: Market | C32: Ann Arbor, MI | D32: 11460 | E32: Transaction Data - Operational | F32: Rent Roll (Rev/OSF) | G32: Totals | H32: Totals | I32: 1.636363 | J32: 1.6120573 | K32: 1.6333019 | L32: 1.6432909 | M32: 1.6216436 | N32: 1.6144145 | O32: 1.6377233 | P32: 1.6695835 | Q32: 1.6625014 | R32: 1.6642905
A33: Ann Arbor, MI | B33: Market | C33: Ann Arbor, MI | D33: 11460 | E33: Performance | F33: Effective RPSF | G33: Totals | H33: Totals | I33: 1.765 | J33: 1.804 | K33: 1.83 | L33: 1.814 | M33: 1.806 | N33: 1.866 | O33: 1.812 | P33: 1.693 | Q33: 1.752 | R33: 1.806
A34: Ann Arbor, MI | B34: Market | C34: Ann Arbor, MI | D34: 11460 | E34: Performance | F34: Existing Units | G34: Totals | H34: Totals | I34: 38647 | J34: 38791 | K34: 39225 | L34: 39542 | M34: 38845 | N34: 38919 | O34: 39056 | P34: 39125 | Q34: 39125 | R34: 38892 | S34: 39279 | T34: 39332 | U34: 39339 | V34: 39360 | W34: 39383 | X34: 39383 | Y34: 39383 | Z34: 39450 | AA34: 39644 | AB34: 39729 | AC34: 39759 | AD34: 39827 | AE34: 39970 | AF34: 40031
A35: Ann Arbor, MI | B35: Market | C35: Ann Arbor, MI | D35: 11460 | E35: Performance | F35: Asking RPSF | G35: Totals | H35: Totals | I35: 1.776 | J35: 1.818 | K35: 1.84 | L35: 1.823 | M35: 1.826 | N35: 1.891 | O35: 1.836 | P35: 1.726 | Q35: 1.792 | R35: 1.84
A36: Ann Arbor, MI | B36: Market | C36: Ann Arbor, MI | D36: 11460 | E36: Same-Store Performance | F36: YOY Effective Rent Change | G36: Totals | H36: Totals | I36: 0.021 | J36: 0.0245 | K36: 0.0195 | L36: 0.0355 | M36: 0.0194 | N36: 0.0243 | O36: -0.0238 | P36: -0.0594 | Q36: -0.0206 | R36: -0.0224 | S36: -0.016 | T36: -0.007 | U36: 0.005 | V36: 0.018 | W36: 0.022 | X36: 0.022 | Y36: 0.019 | Z36: 0.019 | AA36: 0.022 | AB36: 0.023 | AC36: 0.02 | AD36: 0.021 | AE36: 0.023 | AF36: 0.023
A37: Ann Arbor, MI | B37: Market | C37: Ann Arbor, MI | D37: 11460 | E37: Supply & Demand | F37: Annual Property Starts | G37: Totals | H37: Totals | I37: 5 | J37: 2 | K37: 1 | L37: 1 | M37: 2 | N37: 2 | O37: 1 | P37: 1 | Q37: 1 | R37: 1
A38: Asheville/Waynesville, NC | B38: Market | C38: Asheville/Waynesville, NC | D38: 211700 | E38: Transaction Data - Operational | F38: Rent Roll (Rev/OSF) | G38: Totals | H38: Totals | I38: 1.6303974 | J38: 1.6339579 | K38: 1.6262226 | L38: 1.6265261 | M38: 1.6283748 | N38: 1.6200707 | O38: 1.6121796 | P38: 1.5966216 | Q38: 1.5841803 | R38: 1.566481
A39: Asheville/Waynesville, NC | B39: Market | C39: Asheville/Waynesville, NC | D39: 211700 | E39: Performance | F39: Effective RPSF | G39: Totals | H39: Totals | I39: 1.648 | J39: 1.669 | K39: 1.67 | L39: 1.654 | M39: 1.602 | N39: 1.586 | O39: 1.551 | P39: 1.549 | Q39: 1.537 | R39: 1.513
A40: Asheville/Waynesville, NC | B40: Market | C40: Asheville/Waynesville, NC | D40: 211700 | E40: Performance | F40: Existing Units | G40: Totals | H40: Totals | I40: 25832 | J40: 26220 | K40: 26575 | L40: 26731 | M40: 26996 | N40: 27692 | O40: 28180 | P40: 28886 | Q40: 29674 | R40: 30377 | S40: 30637 | T40: 30978 | U40: 31177 | V40: 31856 | W40: 32778 | X40: 33172 | Y40: 33415 | Z40: 33592 | AA40: 33742 | AB40: 33991 | AC40: 34064 | AD40: 34130 | AE40: 34268 | AF40: 34508
A41: Asheville/Waynesville, NC | B41: Market | C41: Asheville/Waynesville, NC | D41: 211700 | E41: Performance | F41: Asking RPSF | G41: Totals | H41: Totals | I41: 1.66 | J41: 1.679 | K41: 1.684 | L41: 1.67 | M41: 1.631 | N41: 1.614 | O41: 1.584 | P41: 1.583 | Q41: 1.58 | R41: 1.564
A42: Asheville/Waynesville, NC | B42: Market | C42: Asheville/Waynesville, NC | D42: 211700 | E42: Same-Store Performance | F42: YOY Effective Rent Change | G42: Totals | H42: Totals | I42: -0.0186 | J42: -0.0045 | K42: -0.0047 | L42: -0.004 | M42: -0.028 | N42: -0.0511 | O42: -0.0801 | P42: -0.0728 | Q42: -0.0537 | R42: -0.0553 | S42: -0.048 | T42: -0.039 | U42: -0.019 | V42: 0.008 | W42: 0.039 | X42: 0.04 | Y42: 0.037 | Z42: 0.033 | AA42: 0.034 | AB42: 0.037 | AC42: 0.036 | AD42: 0.036 | AE42: 0.036 | AF42: 0.035
A43: Asheville/Waynesville, NC | B43: Market | C43: Asheville/Waynesville, NC | D43: 211700 | E43: Supply & Demand | F43: Annual Property Starts | G43: Totals | H43: Totals | I43: 9 | J43: 10 | K43: 12 | L43: 9 | M43: 6 | N43: 7 | O43: 8 | P43: 10 | Q43: 13 | R43: 11
A44: Atlanta-Sandy Springs-Roswell, GA | B44: Market | C44: Atlanta-Sandy Springs-Roswell, GA | D44: 12060 | E44: Transaction Data - Operational | F44: Rent Roll (Rev/OSF) | G44: Totals | H44: Totals | I44: 1.6588153 | J44: 1.6548683 | K44: 1.6461472 | L44: 1.6248239 | M44: 1.6179004 | N44: 1.6199404 | O44: 1.6204697 | P44: 1.6262962 | Q44: 1.6285172 | R44: 1.6284701
A45: Atlanta-Sandy Springs-Roswell, GA | B45: Market | C45: Atlanta-Sandy Springs-Roswell, GA | D45: 12060 | E45: Performance | F45: Effective RPSF | G45: Totals | H45: Totals | I45: 1.593 | J45: 1.597 | K45: 1.584 | L45: 1.547 | M45: 1.551 | N45: 1.567 | O45: 1.573 | P45: 1.549 | Q45: 1.552 | R45: 1.562
A46: Atlanta-Sandy Springs-Roswell, GA | B46: Market | C46: Atlanta-Sandy Springs-Roswell, GA | D46: 12060 | E46: Performance | F46: Existing Units | G46: Totals | H46: Totals | I46: 560365 | J46: 566113 | K46: 573379 | L46: 579055 | M46: 583692 | N46: 588232 | O46: 591864 | P46: 595053 | Q46: 597135 | R46: 599838 | S46: 601863 | T46: 604556 | U46: 607519 | V46: 610684 | W46: 613476 | X46: 614978 | Y46: 616481 | Z46: 619075 | AA46: 620622 | AB46: 621880 | AC46: 623306 | AD46: 625912 | AE46: 627393 | AF46: 628508
A47: Atlanta-Sandy Springs-Roswell, GA | B47: Market | C47: Atlanta-Sandy Springs-Roswell, GA | D47: 12060 | E47: Performance | F47: Asking RPSF | G47: Totals | H47: Totals | I47: 1.613 | J47: 1.621 | K47: 1.614 | L47: 1.575 | M47: 1.58 | N47: 1.598 | O47: 1.606 | P47: 1.585 | Q47: 1.592 | R47: 1.607
A48: Atlanta-Sandy Springs-Roswell, GA | B48: Market | C48: Atlanta-Sandy Springs-Roswell, GA | D48: 12060 | E48: Same-Store Performance | F48: YOY Effective Rent Change | G48: Totals | H48: Totals | I48: -0.0443 | J48: -0.0466 | K48: -0.0448 | L48: -0.0409 | M48: -0.0326 | N48: -0.0268 | O48: -0.0169 | P48: -0.0107 | Q48: -0.0119 | R48: -0.0127 | S48: -0.009 | T48: -0.002 | U48: 0.005 | V48: 0.01 | W48: 0.015 | X48: 0.019 | Y48: 0.019 | Z48: 0.017 | AA48: 0.022 | AB48: 0.022 | AC48: 0.018 | AD48: 0.017 | AE48: 0.019 | AF48: 0.024
A49: Atlanta-Sandy Springs-Roswell, GA | B49: Market | C49: Atlanta-Sandy Springs-Roswell, GA | D49: 12060 | E49: Supply & Demand | F49: Annual Property Starts | G49: Totals | H49: Totals | I49: 46 | J49: 46 | K49: 43 | L49: 41 | M49: 39 | N49: 35 | O49: 38 | P49: 40 | Q49: 39 | R49: 34
A50: Atlantic City-Hammonton, NJ | B50: Market | C50: Atlantic City-Hammonton, NJ | D50: 12100 | E50: Transaction Data - Operational | F50: Rent Roll (Rev/OSF) | G50: Totals | H50: Totals | I50: 1.553639 | J50: 1.5690853 | K50: 1.6213791 | L50: 1.6423203 | M50: 1.6531613 | N50: 1.6703651 | O50: 1.6923661 | P50: 1.7121431 | Q50: 1.7403978 | R50: 1.7650959
A51: Atlantic City-Hammonton, NJ | B51: Market | C51: Atlantic City-Hammonton, NJ | D51: 12100 | E51: Performance | F51: Effective RPSF | G51: Totals | H51: Totals | I51: 1.799 | J51: 1.832 | K51: 1.869 | L51: 1.839 | M51: 1.859 | N51: 1.916 | O51: 1.9 | P51: 1.838 | Q51: 1.844 | R51: 1.962
A52: Atlantic City-Hammonton, NJ | B52: Market | C52: Atlantic City-Hammonton, NJ | D52: 12100 | E52: Performance | F52: Existing Units | G52: Totals | H52: Totals | I52: 32177 | J52: 32301 | K52: 32337 | L52: 32345 | M52: 32359 | N52: 32367 | O52: 32384 | P52: 32400 | Q52: 32400 | R52: 32433 | S52: 32594 | T52: 32620 | U52: 32627 | V52: 32635 | W52: 32773 | X52: 32753 | Y52: 32691 | Z52: 32681 | AA52: 32800 | AB52: 32760 | AC52: 32691 | AD52: 32681 | AE52: 32800 | AF52: 32760
A53: Atlantic City-Hammonton, NJ | B53: Market | C53: Atlantic City-Hammonton, NJ | D53: 12100 | E53: Performance | F53: Asking RPSF | G53: Totals | H53: Totals | I53: 1.805 | J53: 1.837 | K53: 1.869 | L53: 1.843 | M53: 1.868 | N53: 1.919 | O53: 1.901 | P53: 1.865 | Q53: 1.878 | R53: 1.974
A54: Atlantic City-Hammonton, NJ | B54: Market | C54: Atlantic City-Hammonton, NJ | D54: 12100 | E54: Same-Store Performance | F54: YOY Effective Rent Change | G54: Totals | H54: Totals | I54: 0.0367 | J54: 0.0291 | K54: 0.0503 | L54: 0.0364 | M54: 0.0331 | N54: 0.0437 | O54: 0.0117 | P54: -0.0066 | Q54: -0.0112 | R54: 0.025 | S54: 0.034 | T54: 0.048 | U54: 0.054 | V54: 0.048 | W54: 0.051 | X54: 0.046 | Y54: 0.044 | Z54: 0.036 | AA54: 0.038 | AB54: 0.037 | AC54: 0.036 | AD54: 0.031 | AE54: 0.037 | AF54: 0.038
A55: Atlantic City-Hammonton, NJ | B55: Market | C55: Atlantic City-Hammonton, NJ | D55: 12100 | E55: Supply & Demand | F55: Annual Property Starts | G55: Totals | H55: Totals | I55: 0 | J55: 0 | K55: 0 | L55: 0 | M55: 0 | N55: 0 | O55: 0 | P55: 0 | Q55: 0 | R55: 0
A56: Augusta-Richmond County, GA-SC | B56: Market | C56: Augusta-Richmond County, GA-SC | D56: 12260 | E56: Transaction Data - Operational | F56: Rent Roll (Rev/OSF) | G56: Totals | H56: Totals | I56: 1.3035648 | J56: 1.2943145 | K56: 1.2930078 | L56: 1.3138281 | M56: 1.324265 | N56: 1.3555287 | O56: 1.3755137 | P56: 1.3422678 | Q56: 1.3504947 | R56: 1.3338614
A57: Augusta-Richmond County, GA-SC | B57: Market | C57: Augusta-Richmond County, GA-SC | D57: 12260 | E57: Performance | F57: Effective RPSF | G57: Totals | H57: Totals | I57: 1.224 | J57: 1.237 | K57: 1.236 | L57: 1.243 | M57: 1.26 | N57: 1.275 | O57: 1.278 | P57: 1.259 | Q57: 1.283 | R57: 1.306
A58: Augusta-Richmond County, GA-SC | B58: Market | C58: Augusta-Richmond County, GA-SC | D58: 12260 | E58: Performance | F58: Existing Units | G58: Totals | H58: Totals | I58: 33303 | J58: 33524 | K58: 33766 | L58: 34048 | M58: 34233 | N58: 34309 | O58: 34387 | P58: 34747 | Q58: 34938 | R58: 35340 | S58: 35625 | T58: 35714 | U58: 35765 | V58: 35801 | W58: 36079 | X58: 36200 | Y58: 36290 | Z58: 36355 | AA58: 36644 | AB58: 36750 | AC58: 36809 | AD58: 36841 | AE58: 37100 | AF58: 37182
A59: Augusta-Richmond County, GA-SC | B59: Market | C59: Augusta-Richmond County, GA-SC | D59: 12260 | E59: Performance | F59: Asking RPSF | G59: Totals | H59: Totals | I59: 1.24 | J59: 1.256 | K59: 1.254 | L59: 1.258 | M59: 1.271 | N59: 1.284 | O59: 1.293 | P59: 1.28 | Q59: 1.305 | R59: 1.323
A60: Augusta-Richmond County, GA-SC | B60: Market | C60: Augusta-Richmond County, GA-SC | D60: 12260 | E60: Same-Store Performance | F60: YOY Effective Rent Change | G60: Totals | H60: Totals | I60: -0.0137 | J60: -0.006 | K60: -0.0092 | L60: 0.0063 | M60: 0.036 | N60: 0.0376 | O60: 0.0284 | P60: 0.0049 | Q60: 0.0016 | R60: 0.003 | S60: 0.007 | T60: 0.014 | U60: 0.021 | V60: 0.031 | W60: 0.036 | X60: 0.037 | Y60: 0.035 | Z60: 0.034 | AA60: 0.036 | AB60: 0.035 | AC60: 0.032 | AD60: 0.032 | AE60: 0.033 | AF60: 0.034
A61: Augusta-Richmond County, GA-SC | B61: Market | C61: Augusta-Richmond County, GA-SC | D61: 12260 | E61: Supply & Demand | F61: Annual Property Starts | G61: Totals | H61: Totals | I61: 2 | J61: 2 | K61: 1 | L61: 2 | M61: 3 | N61: 3 | O61: 2 | P61: 2 | Q61: 1 | R61: 1
A62: Austin-Round Rock-San Marcos, TX | B62: Market | C62: Austin-Round Rock-San Marcos, TX | D62: 12420 | E62: Transaction Data - Operational | F62: Rent Roll (Rev/OSF) | G62: Totals | H62: Totals | I62: 1.8734019 | J62: 1.8620184 | K62: 1.8368736 | L62: 1.8037782 | M62: 1.7884238 | N62: 1.7818565 | O62: 1.7610387 | P62: 1.7280348 | Q62: 1.7121723 | R62: 1.6921677
A63: Austin-Round Rock-San Marcos, TX | B63: Market | C63: Austin-Round Rock-San Marcos, TX | D63: 12420 | E63: Performance | F63: Effective RPSF | G63: Totals | H63: Totals | I63: 1.79 | J63: 1.776 | K63: 1.736 | L63: 1.681 | M63: 1.663 | N63: 1.647 | O63: 1.626 | P63: 1.575 | Q63: 1.572 | R63: 1.595
A64: Austin-Round Rock-San Marcos, TX | B64: Market | C64: Austin-Round Rock-San Marcos, TX | D64: 12420 | E64: Performance | F64: Existing Units | G64: Totals | H64: Totals | I64: 307166 | J64: 315122 | K64: 324575 | L64: 332196 | M64: 337774 | N64: 341358 | O64: 344832 | P64: 348323 | Q64: 350661 | R64: 353454 | S64: 356189 | T64: 359130 | U64: 361160 | V64: 362709 | W64: 364927 | X64: 366835 | Y64: 368820 | Z64: 370536 | AA64: 372789 | AB64: 374674 | AC64: 376590 | AD64: 378216 | AE64: 380368 | AF64: 382168
A65: Austin-Round Rock-San Marcos, TX | B65: Market | C65: Austin-Round Rock-San Marcos, TX | D65: 12420 | E65: Performance | F65: Asking RPSF | G65: Totals | H65: Totals | I65: 1.817 | J65: 1.81 | K65: 1.782 | L65: 1.72 | M65: 1.71 | N65: 1.703 | O65: 1.691 | P65: 1.646 | Q65: 1.657 | R65: 1.691
A66: Austin-Round Rock-San Marcos, TX | B66: Market | C66: Austin-Round Rock-San Marcos, TX | D66: 12420 | E66: Same-Store Performance | F66: YOY Effective Rent Change | G66: Totals | H66: Totals | I66: -0.0683 | J66: -0.0745 | K66: -0.0817 | L66: -0.0737 | M66: -0.0696 | N66: -0.0736 | O66: -0.0744 | P66: -0.0777 | Q66: -0.0738 | R66: -0.0513 | S66: -0.044 | T66: -0.031 | U66: -0.016 | V66: 0.009 | W66: 0.025 | X66: 0.026 | Y66: 0.024 | Z66: 0.023 | AA66: 0.025 | AB66: 0.025 | AC66: 0.023 | AD66: 0.024 | AE66: 0.028 | AF66: 0.03
A67: Austin-Round Rock-San Marcos, TX | B67: Market | C67: Austin-Round Rock-San Marcos, TX | D67: 12420 | E67: Supply & Demand | F67: Annual Property Starts | G67: Totals | H67: Totals | I67: 44 | J67: 41 | K67: 35 | L67: 33 | M67: 31 | N67: 28 | O67: 28 | P67: 25 | Q67: 20 | R67: 19
A68: Bakersfield-Delano, CA | B68: Market | C68: Bakersfield-Delano, CA | D68: 12540 | E68: Transaction Data - Operational | F68: Rent Roll (Rev/OSF) | G68: Totals | H68: Totals | I68: 1.1958454 | J68: 1.2061487 | K68: 1.2233776 | L68: 1.2527597 | M68: 1.3308099 | N68: 1.3422249 | O68: 1.1863968 | P68: 1.2199365 | Q68: 1.0334964 | R68: 1.0392707
A69: Bakersfield-Delano, CA | B69: Market | C69: Bakersfield-Delano, CA | D69: 12540 | E69: Performance | F69: Effective RPSF | G69: Totals | H69: Totals | I69: 1.696 | J69: 1.699 | K69: 1.709 | L69: 1.735 | M69: 1.728 | N69: 1.766 | O69: 1.787 | P69: 1.785 | Q69: 1.801 | R69: 1.815
A70: Bakersfield-Delano, CA | B70: Market | C70: Bakersfield-Delano, CA | D70: 12540 | E70: Performance | F70: Existing Units | G70: Totals | H70: Totals | I70: 27237 | J70: 27237 | K70: 27237 | L70: 27237 | M70: 27323 | N70: 27495 | O70: 27609 | P70: 27609 | Q70: 27609 | R70: 27609 | S70: 27609 | T70: 27711 | U70: 27930 | V70: 28017 | W70: 28107 | X70: 28137 | Y70: 28137 | Z70: 28201 | AA70: 28271 | AB70: 28291 | AC70: 28285 | AD70: 28347 | AE70: 28415 | AF70: 28432
A71: Bakersfield-Delano, CA | B71: Market | C71: Bakersfield-Delano, CA | D71: 12540 | E71: Performance | F71: Asking RPSF | G71: Totals | H71: Totals | I71: 1.701 | J71: 1.701 | K71: 1.709 | L71: 1.735 | M71: 1.73 | N71: 1.767 | O71: 1.788 | P71: 1.788 | Q71: 1.802 | R71: 1.815
A72: Bakersfield-Delano, CA | B72: Market | C72: Bakersfield-Delano, CA | D72: 12540 | E72: Same-Store Performance | F72: YOY Effective Rent Change | G72: Totals | H72: Totals | I72: 0.0167 | J72: 0.0098 | K72: 0.0048 | L72: 0.0174 | M72: 0.0189 | N72: 0.0328 | O72: 0.0291 | P72: 0.0105 | Q72: 0.0185 | R72: 0.01 | S72: 0.011 | T72: 0.015 | U72: 0.018 | V72: 0.023 | W72: 0.031 | X72: 0.032 | Y72: 0.033 | Z72: 0.033 | AA72: 0.033 | AB72: 0.033 | AC72: 0.031 | AD72: 0.03 | AE72: 0.03 | AF72: 0.03
A73: Bakersfield-Delano, CA | B73: Market | C73: Bakersfield-Delano, CA | D73: 12540 | E73: Supply & Demand | F73: Annual Property Starts | G73: Totals | H73: Totals | I73: 2 | J73: 2 | K73: 1 | L73: 1 | M73: 0 | N73: 2 | O73: 2 | P73: 2 | Q73: 2 | R73: 0
A74: Baltimore-Columbia-Towson, MD | B74: Market | C74: Baltimore-Columbia-Towson, MD | D74: 12580 | E74: Transaction Data - Operational | F74: Rent Roll (Rev/OSF) | G74: Totals | H74: Totals | I74: 1.9809609 | J74: 1.9852586 | K74: 1.9951707 | L74: 2.0038503 | M74: 2.0038416 | N74: 2.0191748 | O74: 2.0496179 | P74: 2.0499258 | Q74: 2.0325153 | R74: 2.0260802
A75: Baltimore-Columbia-Towson, MD | B75: Market | C75: Baltimore-Columbia-Towson, MD | D75: 12580 | E75: Performance | F75: Effective RPSF | G75: Totals | H75: Totals | I75: 1.828 | J75: 1.856 | K75: 1.878 | L75: 1.867 | M75: 1.886 | N75: 1.911 | O75: 1.912 | P75: 1.889 | Q75: 1.901 | R75: 1.935
A76: Baltimore-Columbia-Towson, MD | B76: Market | C76: Baltimore-Columbia-Towson, MD | D76: 12580 | E76: Performance | F76: Existing Units | G76: Totals | H76: Totals | I76: 236488 | J76: 237022 | K76: 237631 | L76: 238785 | M76: 239635 | N76: 239828 | O76: 240038 | P76: 240165 | Q76: 240425 | R76: 240604 | S76: 241309 | T76: 241719 | U76: 242044 | V76: 242351 | W76: 242982 | X76: 243292 | Y76: 243622 | Z76: 243974 | AA76: 244623 | AB76: 244940 | AC76: 245259 | AD76: 245572 | AE76: 246151 | AF76: 246384
A77: Baltimore-Columbia-Towson, MD | B77: Market | C77: Baltimore-Columbia-Towson, MD | D77: 12580 | E77: Performance | F77: Asking RPSF | G77: Totals | H77: Totals | I77: 1.843 | J77: 1.87 | K77: 1.893 | L77: 1.883 | M77: 1.898 | N77: 1.926 | O77: 1.93 | P77: 1.913 | Q77: 1.926 | R77: 1.955
A78: Baltimore-Columbia-Towson, MD | B78: Market | C78: Baltimore-Columbia-Towson, MD | D78: 12580 | E78: Same-Store Performance | F78: YOY Effective Rent Change | G78: Totals | H78: Totals | I78: 0.0062 | J78: 0.0112 | K78: 0.0169 | L78: 0.019 | M78: 0.0263 | N78: 0.0156 | O78: 0.0069 | P78: 0.0006 | Q78: -0.0037 | R78: 0.0045 | S78: 0.007 | T78: 0.01 | U78: 0.014 | V78: 0.021 | W78: 0.025 | X78: 0.025 | Y78: 0.025 | Z78: 0.026 | AA78: 0.027 | AB78: 0.028 | AC78: 0.029 | AD78: 0.029 | AE78: 0.031 | AF78: 0.032
A79: Baltimore-Columbia-Towson, MD | B79: Market | C79: Baltimore-Columbia-Towson, MD | D79: 12580 | E79: Supply & Demand | F79: Annual Property Starts | G79: Totals | H79: Totals | I79: 9 | J79: 2 | K79: 3 | L79: 4 | M79: 7 | N79: 9 | O79: 10 | P79: 9 | Q79: 6 | R79: 5
A80: Baton Rouge, LA | B80: Market | C80: Baton Rouge, LA | D80: 12940 | E80: Transaction Data - Operational | F80: Rent Roll (Rev/OSF) | G80: Totals | H80: Totals | I80: 1.2333279 | J80: 1.2461437 | K80: 1.2439294 | L80: 1.2380069 | M80: 1.2370096 | N80: 1.2402328 | O80: 1.2457815 | P80: 1.2608008 | Q80: 1.2614263 | R80: 1.2681901
A81: Baton Rouge, LA | B81: Market | C81: Baton Rouge, LA | D81: 12940 | E81: Performance | F81: Effective RPSF | G81: Totals | H81: Totals | I81: 1.246 | J81: 1.263 | K81: 1.264 | L81: 1.258 | M81: 1.256 | N81: 1.289 | O81: 1.29 | P81: 1.259 | Q81: 1.275 | R81: 1.3
A82: Baton Rouge, LA | B82: Market | C82: Baton Rouge, LA | D82: 12940 | E82: Performance | F82: Existing Units | G82: Totals | H82: Totals | I82: 51504 | J82: 51642 | K82: 51846 | L82: 52009 | M82: 52075 | N82: 52125 | O82: 52025 | P82: 52025 | Q82: 52025 | R82: 52025 | S82: 52025 | T82: 52025 | U82: 52103 | V82: 52337 | W82: 52337 | X82: 52471 | Y82: 52564 | Z82: 52816 | AA82: 52852 | AB82: 53009 | AC82: 53124 | AD82: 53386 | AE82: 53426 | AF82: 53582
A83: Baton Rouge, LA | B83: Market | C83: Baton Rouge, LA | D83: 12940 | E83: Performance | F83: Asking RPSF | G83: Totals | H83: Totals | I83: 1.261 | J83: 1.282 | K83: 1.282 | L83: 1.271 | M83: 1.268 | N83: 1.301 | O83: 1.299 | P83: 1.277 | Q83: 1.297 | R83: 1.316
A84: Baton Rouge, LA | B84: Market | C84: Baton Rouge, LA | D84: 12940 | E84: Same-Store Performance | F84: YOY Effective Rent Change | G84: Totals | H84: Totals | I84: -0.0101 | J84: -0.0219 | K84: -0.0144 | L84: -0.0149 | M84: -0.0033 | N84: 0.0076 | O84: -0.0066 | P84: -0.0159 | Q84: -0.001 | R84: 0.0051 | S84: 0.01 | T84: 0.017 | U84: 0.025 | V84: 0.03 | W84: 0.031 | X84: 0.028 | Y84: 0.025 | Z84: 0.023 | AA84: 0.022 | AB84: 0.021 | AC84: 0.017 | AD84: 0.016 | AE84: 0.017 | AF84: 0.018
A85: Baton Rouge, LA | B85: Market | C85: Baton Rouge, LA | D85: 12940 | E85: Supply & Demand | F85: Annual Property Starts | G85: Totals | H85: Totals | I85: 3 | J85: 1 | K85: 1 | L85: 0 | M85: 0 | N85: 0 | O85: 1 | P85: 1 | Q85: 1 | R85: 1
A86: Birmingham, AL | B86: Market | C86: Birmingham, AL | D86: 13820 | E86: Transaction Data - Operational | F86: Rent Roll (Rev/OSF) | G86: Totals | H86: Totals | I86: 1.2316698 | J86: 1.2334323 | K86: 1.2428728 | L86: 1.2573898 | M86: 1.2488612 | N86: 1.2402819 | O86: 1.2589108 | P86: 1.2558032 | Q86: 1.2608027 | R86: 1.2671121
A87: Birmingham, AL | B87: Market | C87: Birmingham, AL | D87: 13820 | E87: Performance | F87: Effective RPSF | G87: Totals | H87: Totals | I87: 1.251 | J87: 1.267 | K87: 1.269 | L87: 1.254 | M87: 1.261 | N87: 1.261 | O87: 1.266 | P87: 1.249 | Q87: 1.259 | R87: 1.273
A88: Birmingham, AL | B88: Market | C88: Birmingham, AL | D88: 13820 | E88: Performance | F88: Existing Units | G88: Totals | H88: Totals | I88: 79797 | J88: 80087 | K88: 80464 | L88: 80747 | M88: 80892 | N88: 81086 | O88: 81503 | P88: 82044 | Q88: 82358 | R88: 82502 | S88: 82550 | T88: 82550 | U88: 82889 | V88: 82940 | W88: 83230 | X88: 83237 | Y88: 83538 | Z88: 83594 | AA88: 83905 | AB88: 83939 | AC88: 84264 | AD88: 84335 | AE88: 84655 | AF88: 84685
A89: Birmingham, AL | B89: Market | C89: Birmingham, AL | D89: 13820 | E89: Performance | F89: Asking RPSF | G89: Totals | H89: Totals | I89: 1.267 | J89: 1.283 | K89: 1.29 | L89: 1.271 | M89: 1.279 | N89: 1.283 | O89: 1.287 | P89: 1.27 | Q89: 1.284 | R89: 1.303
A90: Birmingham, AL | B90: Market | C90: Birmingham, AL | D90: 13820 | E90: Same-Store Performance | F90: YOY Effective Rent Change | G90: Totals | H90: Totals | I90: -0.0058 | J90: -0.0081 | K90: -0.0167 | L90: -0.0033 | M90: 0.0058 | N90: -0.002 | O90: -0.0045 | P90: -0.0187 | Q90: -0.0095 | R90: -0.0057 | S90: -0.004 | T90: -0.001 | U90: 0.005 | V90: 0.012 | W90: 0.021 | X90: 0.033 | Y90: 0.032 | Z90: 0.029 | AA90: 0.027 | AB90: 0.025 | AC90: 0.023 | AD90: 0.022 | AE90: 0.021 | AF90: 0.021
A91: Birmingham, AL | B91: Market | C91: Birmingham, AL | D91: 13820 | E91: Supply & Demand | F91: Annual Property Starts | G91: Totals | H91: Totals | I91: 4 | J91: 5 | K91: 5 | L91: 4 | M91: 1 | N91: 1 | O91: 1 | P91: 1 | Q91: 2 | R91: 1
A92: Boise City, ID | B92: Market | C92: Boise City, ID | D92: 14260 | E92: Transaction Data - Operational | F92: Rent Roll (Rev/OSF) | G92: Totals | H92: Totals | I92: 1.7246944 | J92: 1.710061 | K92: 1.7184447 | L92: 1.7260753 | M92: 1.699189 | N92: 1.7009255 | O92: 1.7189513 | P92: 1.7226842 | Q92: 1.7429135 | R92: 1.7432193
A93: Boise City, ID | B93: Market | C93: Boise City, ID | D93: 14260 | E93: Performance | F93: Effective RPSF | G93: Totals | H93: Totals | I93: 1.657 | J93: 1.714 | K93: 1.72 | L93: 1.673 | M93: 1.677 | N93: 1.73 | O93: 1.751 | P93: 1.71 | Q93: 1.743 | R93: 1.824
A94: Boise City, ID | B94: Market | C94: Boise City, ID | D94: 14260 | E94: Performance | F94: Existing Units | G94: Totals | H94: Totals | I94: 35626 | J94: 36396 | K94: 37210 | L94: 38051 | M94: 38726 | N94: 39353 | O94: 39551 | P94: 39780 | Q94: 40002 | R94: 40146 | S94: 40371 | T94: 40532 | U94: 40722 | V94: 40722 | W94: 41934 | X94: 42698 | Y94: 43020 | Z94: 42987 | AA94: 43977 | AB94: 44502 | AC94: 44752 | AD94: 44670 | AE94: 45607 | AF94: 46117
A95: Boise City, ID | B95: Market | C95: Boise City, ID | D95: 14260 | E95: Performance | F95: Asking RPSF | G95: Totals | H95: Totals | I95: 1.685 | J95: 1.736 | K95: 1.738 | L95: 1.699 | M95: 1.698 | N95: 1.749 | O95: 1.77 | P95: 1.734 | Q95: 1.765 | R95: 1.838
A96: Boise City, ID | B96: Market | C96: Boise City, ID | D96: 14260 | E96: Same-Store Performance | F96: YOY Effective Rent Change | G96: Totals | H96: Totals | I96: -0.0468 | J96: -0.018 | K96: 0.0001 | L96: 0.0068 | M96: 0.0194 | N96: 0.0112 | O96: 0.0014 | P96: 0.0101 | Q96: 0.0202 | R96: 0.0444 | S96: 0.045 | T96: 0.045 | U96: 0.046 | V96: 0.055 | W96: 0.059 | X96: 0.053 | Y96: 0.046 | Z96: 0.044 | AA96: 0.049 | AB96: 0.048 | AC96: 0.049 | AD96: 0.044 | AE96: 0.049 | AF96: 0.049
A97: Boise City, ID | B97: Market | C97: Boise City, ID | D97: 14260 | E97: Supply & Demand | F97: Annual Property Starts | G97: Totals | H97: Totals | I97: 6 | J97: 3 | K97: 3 | L97: 1 | M97: 2 | N97: 2 | O97: 5 | P97: 4 | Q97: 3 | R97: 3
A98: Boston-Cambridge-Newton, MA-NH | B98: Market | C98: Boston-Cambridge-Newton, MA-NH | D98: 14460 | E98: Transaction Data - Operational | F98: Rent Roll (Rev/OSF) | G98: Totals | H98: Totals | I98: 3.1280938 | J98: 3.1522729 | K98: 3.1948902 | L98: 3.2034454 | M98: 3.2093265 | N98: 3.2499551 | O98: 3.2879572 | P98: 3.3334985 | Q98: 3.3232672 | R98: 3.3208161
A99: Boston-Cambridge-Newton, MA-NH | B99: Market | C99: Boston-Cambridge-Newton, MA-NH | D99: 14460 | E99: Performance | F99: Effective RPSF | G99: Totals | H99: Totals | I99: 3.259 | J99: 3.304 | K99: 3.355 | L99: 3.322 | M99: 3.342 | N99: 3.427 | O99: 3.431 | P99: 3.353 | Q99: 3.36 | R99: 3.438
A100: Boston-Cambridge-Newton, MA-NH | B100: Market | C100: Boston-Cambridge-Newton, MA-NH | D100: 14460 | E100: Performance | F100: Existing Units | G100: Totals | H100: Totals | I100: 426506 | J100: 427826 | K100: 429526 | L100: 431442 | M100: 432547 | N100: 434513 | O100: 437069 | P100: 438876 | Q100: 440466 | R100: 441937 | S100: 443120 | T100: 443465 | U100: 444265 | V100: 446535 | W100: 448124 | X100: 449162 | Y100: 449825 | Z100: 451400 | AA100: 452539 | AB100: 453498 | AC100: 453967 | AD100: 455518 | AE100: 456606 | AF100: 457522
...

Sheet Realpage - His. Rent Change
A1: Geography Name | B1: Geography Type | C1: Market Name | D1: Unique ID | E1: Metric Type | F1: Metric Name | G1: Category | H1: Niche | I1: Y2016Q1 | J1: Y2016Q2 | K1: Y2016Q3 | L1: Y2016Q4 | M1: Y2017Q1 | N1: Y2017Q2 | O1: Y2017Q3 | P1: Y2017Q4 | Q1: Y2018Q1 | R1: Y2018Q2 | S1: Y2018Q3 | T1: Y2018Q4 | U1: Y2019Q1 | V1: Y2019Q2 | W1: Y2019Q3 | X1: Y2019Q4 | Y1: Y2020Q1 | Z1: Y2020Q2 | AA1: Y2020Q3 | AB1: Y2020Q4 | AC1: Y2021Q1 | AD1: Y2021Q2 | AE1: Y2021Q3 | AF1: Y2021Q4 | AG1: Y2022Q1 | AH1: Y2022Q2 | AI1: Y2022Q3 | AJ1: Y2022Q4 | AK1: Y2023Q1 | AL1: Y2023Q2 | AM1: Y2023Q3 | AN1: Y2023Q4 | AO1: Y2024Q1 | AP1: Y2024Q2 | AQ1: Y2024Q3 | AR1: Y2024Q4 | AS1: Y2025Q1 | AT1: Y2025Q2 | AU1: Y2025Q3 | AV1: Y2025Q4
A2: Abilene, TX | B2: Market | C2: Abilene, TX | D2: 10180 | E2: Performance | F2: YOY Effective Rent Change | G2: Totals | H2: Totals | I2: 0.0073 | J2: 0.0061 | K2: 0.0801 | L2: 0.065 | M2: 0.0877 | N2: 0.1047 | O2: 0.0377 | P2: 0.0457 | Q2: 0.0409 | R2: 0.0396 | S2: 0.0375 | T2: 0.0413 | U2: 0.0503 | V2: 0.0538 | W2: 0.0411 | X2: 0.041 | Y2: 0.0269 | Z2: 0.0027 | AA2: 0.0044 | AB2: 0.0211 | AC2: 0.0169 | AD2: 0.0328 | AE2: 0.0626 | AF2: 0.0688 | AG2: 0.0811 | AH2: 0.0935 | AI2: 0.0662 | AJ2: 0.0638 | AK2: 0.0677 | AL2: 0.0625 | AM2: 0.0519 | AN2: 0.0537 | AO2: 0.0376 | AP2: 0.0429 | AQ2: 0.0383 | AR2: 0.0474 | AS2: 0.0657 | AT2: 0.0827 | AU2: 0.1297 | AV2: 0.1869
A3: Akron, OH | B3: Market | C3: Akron, OH | D3: 10420 | E3: Performance | F3: YOY Effective Rent Change | G3: Totals | H3: Totals | I3: 0.0271 | J3: 0.0232 | K3: 0.0279 | L3: 0.0192 | M3: 0.0148 | N3: 0.0068 | O3: 0.0172 | P3: 0.0205 | Q3: 0.0156 | R3: 0.0318 | S3: 0.0277 | T3: 0.03 | U3: 0.0339 | V3: 0.0142 | W3: 0.0215 | X3: 0.0253 | Y3: 0.0392 | Z3: 0.0452 | AA3: 0.0338 | AB3: 0.0438 | AC3: 0.0331 | AD3: 0.0632 | AE3: 0.1079 | AF3: 0.0892 | AG3: 0.1053 | AH3: 0.1152 | AI3: 0.103 | AJ3: 0.1115 | AK3: 0.1004 | AL3: 0.0724 | AM3: 0.0494 | AN3: 0.0466 | AO3: 0.0488 | AP3: 0.0492 | AQ3: 0.0583 | AR3: 0.0519 | AS3: 0.0571 | AT3: 0.0741 | AU3: 0.0806 | AV3: 0.0841
A4: Alamogordo, NM | B4: Market | C4: Alamogordo, NM | D4: 10460 | E4: Performance | F4: YOY Effective Rent Change | G4: Totals | H4: Totals | N4: 0.028 | W4: 0.2314 | X4: 0.2133 | Y4: 0.1963 | Z4: 0.1757 | AA4: -0.0082 | AB4: -0.0011 | AC4: 0.0197 | AD4: 0.0394 | AE4: 0.0546 | AF4: 0.1411 | AG4: 0.1412 | AH4: 0.1447 | AI4: 0.1358 | AJ4: 0.0572 | AK4: 0.0701 | AL4: 0.0236
A5: Albany, GA | B5: Market | C5: Albany, GA | D5: 10500 | E5: Performance | F5: YOY Effective Rent Change | G5: Totals | H5: Totals | I5: 0.0796 | J5: 0.1222 | K5: 0.0445 | L5: 0.0764 | M5: 0.0726 | N5: 0.0353 | O5: 0.0709 | P5: 0.0519 | Q5: 0.0814 | R5: 0.0856 | S5: 0.048 | T5: 0.0284 | U5: 0.0089 | V5: 0.0131 | W5: 0.0336 | X5: 0.0543 | Y5: 0.0823 | Z5: 0.0797 | AA5: 0.0778 | AB5: 0.0821 | AC5: 0.0502 | AD5: 0.0576 | AE5: 0.0538 | AF5: 0.123 | AG5: 0.1603 | AH5: 0.2311 | AI5: 0.2432 | AJ5: 0.1327 | AK5: 0.099 | AL5: 0.02 | AM5: 0.0574 | AN5: 0.081 | AO5: 0.0809 | AP5: 0.0827 | AQ5: 0.0256 | AR5: -0.0096 | AS5: -0.0443 | AT5: 0.0024 | AU5: -0.1087 | AV5: -0.0573
A6: Albany, OR | B6: Market | C6: Albany, OR | D6: 10540 | E6: Performance | F6: YOY Effective Rent Change | G6: Totals | H6: Totals | I6: 0.0362 | J6: 0.0211 | K6: 0.054 | L6: 0.104 | M6: 0.089 | N6: 0.1398 | O6: 0.1514 | P6: 0.1381 | Q6: 0.1202 | R6: 0.071 | S6: 0.0322 | T6: 0.0443 | U6: 0.0521 | V6: 0.0582 | W6: 0.0722 | X6: 0.0068 | Y6: -0.0158 | Z6: -0.0289 | AA6: -0.018 | AB6: 0.0278 | AC6: 0.0567 | AD6: 0.08 | AE6: 0.0798 | AF6: 0.1422 | AG6: 0.1671 | AH6: 0.1676 | AI6: 0.1663 | AJ6: 0.1145 | AK6: 0.0892 | AL6: 0.0672 | AM6: 0.0106 | AN6: 0.0054 | AO6: -0.0026 | AP6: 0.0033 | AQ6: 0.0677 | AR6: 0.0508 | AS6: 0.0483 | AT6: -0.0335 | AU6: -0.1011 | AV6: -0.1371
A7: Albany-Schenectady-Troy, NY | B7: Market | C7: Albany-Schenectady-Troy, NY | D7: 10580 | E7: Performance | F7: YOY Effective Rent Change | G7: Totals | H7: Totals | I7: 0.041 | J7: 0.0335 | K7: 0.0355 | L7: 0.0383 | M7: 0.0336 | N7: 0.0435 | O7: 0.0297 | P7: 0.0262 | Q7: 0.0327 | R7: 0.0231 | S7: 0.0338 | T7: 0.0395 | U7: 0.0294 | V7: 0.0341 | W7: 0.0202 | X7: 0.0109 | Y7: 0.0215 | Z7: 0.0142 | AA7: 0.0184 | AB7: 0.0313 | AC7: 0.0318 | AD7: 0.0406 | AE7: 0.0563 | AF7: 0.0603 | AG7: 0.0741 | AH7: 0.0978 | AI7: 0.1297 | AJ7: 0.109 | AK7: 0.091 | AL7: 0.0939 | AM7: 0.0636 | AN7: 0.0618 | AO7: 0.0637 | AP7: 0.0339 | AQ7: 0.0164 | AR7: 0.0299 | AS7: 0.0323 | AT7: 0.0548 | AU7: 0.0733 | AV7: 0.062
A8: Albert Lea, MN | B8: Market | C8: Albert Lea, MN | D8: 10660 | E8: Performance | F8: YOY Effective Rent Change | G8: Totals | H8: Totals
A9: Albuquerque, NM | B9: Market | C9: Albuquerque, NM | D9: 10740 | E9: Performance | F9: YOY Effective Rent Change | G9: Totals | H9: Totals | I9: 0.0231 | J9: 0.0254 | K9: 0.0244 | L9: 0.0334 | M9: 0.0315 | N9: 0.0393 | O9: 0.0395 | P9: 0.0242 | Q9: 0.0312 | R9: 0.0248 | S9: 0.038 | T9: 0.0505 | U9: 0.0584 | V9: 0.061 | W9: 0.0757 | X9: 0.0676 | Y9: 0.0536 | Z9: 0.0457 | AA9: 0.0491 | AB9: 0.0794 | AC9: 0.0903 | AD9: 0.1436 | AE9: 0.2059 | AF9: 0.2064 | AG9: 0.1955 | AH9: 0.1698 | AI9: 0.1318 | AJ9: 0.0999 | AK9: 0.0882 | AL9: 0.0658 | AM9: 0.0207 | AN9: 0.0149 | AO9: 0.0246 | AP9: 0.0124 | AQ9: 0.0099 | AR9: 0.015 | AS9: 0.0132 | AT9: 0.0201 | AU9: 0.0246 | AV9: 0.009
A10: Alexandria, LA | B10: Market | C10: Alexandria, LA | D10: 10780 | E10: Performance | F10: YOY Effective Rent Change | G10: Totals | H10: Totals | I10: 0.0636 | J10: -0.0479 | K10: -0.0691 | L10: 0.0486 | M10: 0.0021 | N10: 0.0271 | O10: 0.0424 | P10: -0.0372 | Q10: 0.0448 | R10: 0.0343 | S10: -0.0105 | T10: 0.0082 | U10: -0.0043 | V10: 0.0031 | W10: 0.0448 | X10: 0.0336 | Y10: 0.0639 | Z10: 0.0401 | AA10: 0.0133 | AB10: 0.0477 | AC10: 0.0225 | AD10: 0.024 | AE10: 0.0646 | AF10: 0.0488 | AG10: 0.0586 | AH10: 0.1108 | AI10: 0.0747 | AJ10: 0.078 | AK10: 0.0328 | AL10: -0.0143 | AM10: 0.0067 | AN10: 0.0036 | AO10: 0.0185 | AP10: 0.0215 | AQ10: 0.0229 | AR10: 0.0317 | AS10: 0.051 | AT10: 0.1444 | AU10: 0.1573 | AV10: 0.0973
A11: Alexandria, MN | B11: Market | C11: Alexandria, MN | D11: 10820 | E11: Performance | F11: YOY Effective Rent Change | G11: Totals | H11: Totals | AF11: -0.0029 | AG11: -0.0123 | AH11: -0.0156 | AI11: 0.0074 | AS11: 0.1218 | AT11: 0.1341 | AU11: 0.1112 | AV11: 0.0686
A12: Allentown-Bethlehem-Easton, PA-NJ | B12: Market | C12: Allentown-Bethlehem-Easton, PA-NJ | D12: 10900 | E12: Performance | F12: YOY Effective Rent Change | G12: Totals | H12: Totals | I12: 0.0559 | J12: 0.0439 | K12: 0.0286 | L12: 0.0193 | M12: 0.016 | N12: 0.0292 | O12: 0.0398 | P12: 0.0483 | Q12: 0.0501 | R12: 0.0364 | S12: 0.0605 | T12: 0.0604 | U12: 0.0603 | V12: 0.054 | W12: 0.0245 | X12: 0.0258 | Y12: 0.0293 | Z12: 0.0149 | AA12: 0.0349 | AB12: 0.0512 | AC12: 0.0535 | AD12: 0.0744 | AE12: 0.1123 | AF12: 0.146 | AG12: 0.1526 | AH12: 0.1587 | AI12: 0.1282 | AJ12: 0.0875 | AK12: 0.0607 | AL12: 0.0479 | AM12: 0.0352 | AN12: 0.0358 | AO12: 0.0325 | AP12: 0.0242 | AQ12: 0.0311 | AR12: 0.0331 | AS12: 0.0437 | AT12: 0.0641 | AU12: 0.0456 | AV12: 0.0355
A13: Alma, MI | B13: Market | C13: Alma, MI | D13: 10940 | E13: Performance | F13: YOY Effective Rent Change | G13: Totals | H13: Totals
A14: Altoona, PA | B14: Market | C14: Altoona, PA | D14: 11020 | E14: Performance | F14: YOY Effective Rent Change | G14: Totals | H14: Totals
A15: Altus, OK | B15: Market | C15: Altus, OK | D15: 11060 | E15: Performance | F15: YOY Effective Rent Change | G15: Totals | H15: Totals
A16: Amarillo, TX | B16: Market | C16: Amarillo, TX | D16: 11100 | E16: Performance | F16: YOY Effective Rent Change | G16: Totals | H16: Totals | I16: 0.0301 | J16: 0.0177 | K16: 0.0232 | L16: 0.0031 | M16: 0.0103 | N16: 0.0264 | O16: 0.0071 | P16: -0.0004 | Q16: -0.0003 | R16: 0.0049 | S16: 0.0175 | T16: 0.031 | U16: -0.0002 | V16: 0.0022 | W16: -0.0042 | X16: 0.0104 | Y16: 0.0316 | Z16: 0.028 | AA16: 0.03 | AB16: 0.0295 | AC16: 0.0407 | AD16: 0.0712 | AE16: 0.0943 | AF16: 0.1073 | AG16: 0.1291 | AH16: 0.131 | AI16: 0.1454 | AJ16: 0.1226 | AK16: 0.098 | AL16: 0.0552 | AM16: 0.0173 | AN16: 0.0128 | AO16: 0.0062 | AP16: 0.0136 | AQ16: 0.0163 | AR16: 0.0016 | AS16: 0.0131 | AT16: 0.0126 | AU16: 0.0368 | AV16: 0.0682
A17: Ames, IA | B17: Market | C17: Ames, IA | D17: 11180 | E17: Performance | F17: YOY Effective Rent Change | G17: Totals | H17: Totals | I17: -0.0121 | J17: -0.0177 | K17: 0.0294 | L17: 0.0218 | M17: 0.112 | N17: 0.0916 | O17: 0.0731 | P17: 0.0945 | Q17: -0.0226 | R17: 0.0047 | S17: -0.0894 | T17: -0.0957 | U17: -0.0768 | V17: -0.0847 | W17: -0.0414 | X17: -0.0702 | Y17: -0.0796 | Z17: -0.0482 | AA17: 0.029 | AB17: 0.0478 | AC17: 0.1147 | AD17: 0.0611 | AE17: -0.0159 | AF17: 0.0038 | AG17: -0.0513 | AH17: 0.0866 | AI17: 0.1819 | AJ17: 0.2012 | AK17: 0.2223 | AL17: 0.0935 | AM17: 0.0573 | AN17: 0.022 | AO17: -0.0059 | AP17: -0.0154 | AQ17: 0.0091 | AR17: 0.0409 | AS17: 0.0562 | AT17: 0.0806 | AU17: 0.0724 | AV17: 0.02
A18: Anaheim-Santa Ana-Irvine, CA | B18: Market | C18: Anaheim-Santa Ana-Irvine, CA | D18: 11244 | E18: Performance | F18: YOY Effective Rent Change | G18: Totals | H18: Totals | I18: 0.0572 | J18: 0.0597 | K18: 0.0544 | L18: 0.0527 | M18: 0.0397 | N18: 0.0391 | O18: 0.0378 | P18: 0.0308 | Q18: 0.0367 | R18: 0.0273 | S18: 0.0319 | T18: 0.0319 | U18: 0.0256 | V18: 0.0376 | W18: 0.0347 | X18: 0.0325 | Y18: 0.0377 | Z18: -0.0041 | AA18: -0.0157 | AB18: -0.0026 | AC18: 0.0114 | AD18: 0.0634 | AE18: 0.1349 | AF18: 0.174 | AG18: 0.1894 | AH18: 0.1918 | AI18: 0.1474 | AJ18: 0.0865 | AK18: 0.0492 | AL18: 0.025 | AM18: 0.021 | AN18: 0.0317 | AO18: 0.0297 | AP18: 0.0234 | AQ18: 0.0155 | AR18: 0.0083 | AS18: 0.0154 | AT18: 0.03 | AU18: 0.0296 | AV18: 0.0236
A19: Anchorage, AK | B19: Market | C19: Anchorage, AK | D19: 11260 | E19: Performance | F19: YOY Effective Rent Change | G19: Totals | H19: Totals | P19: -0.0018 | Q19: 0.0154 | R19: 0.0453 | S19: 0.0181 | T19: 0.0057 | U19: -0.0044 | V19: -0.0229 | W19: 0.0012 | X19: -0.01 | Y19: 0.0383 | Z19: 0.0415 | AA19: 0.073 | AB19: 0.1047 | AC19: 0.069 | AD19: 0.0972 | AE19: 0.0921 | AF19: 0.0956 | AG19: 0.1329 | AH19: 0.1306 | AI19: 0.1359 | AJ19: 0.1367 | AK19: 0.1073 | AL19: 0.1141 | AM19: 0.1599 | AN19: 0.0944 | AO19: 0.0709 | AP19: 0.0613 | AQ19: -0.006 | AR19: 0.0241 | AS19: 0.0395 | AT19: 0.042 | AU19: 0.0271 | AV19: 0.0231
A20: Andrews, TX | B20: Market | C20: Andrews, TX | D20: 11380 | E20: Performance | F20: YOY Effective Rent Change | G20: Totals | H20: Totals
A21: Angola, IN | B21: Market | C21: Angola, IN | D21: 11420 | E21: Performance | F21: YOY Effective Rent Change | G21: Totals | H21: Totals
A22: Ann Arbor, MI | B22: Market | C22: Ann Arbor, MI | D22: 11460 | E22: Performance | F22: YOY Effective Rent Change | G22: Totals | H22: Totals | I22: 0.0497 | J22: 0.0573 | K22: 0.0333 | L22: 0.0427 | M22: 0.034 | N22: 0.0233 | O22: 0.0625 | P22: 0.032 | Q22: 0.0292 | R22: 0.0427 | S22: 0.0363 | T22: 0.0504 | U22: 0.0552 | V22: 0.0418 | W22: 0.0442 | X22: 0.0458 | Y22: 0.0393 | Z22: 0.0361 | AA22: 0.0078 | AB22: 0.0103 | AC22: 0.004 | AD22: 0.0422 | AE22: 0.1073 | AF22: 0.1452 | AG22: 0.1601 | AH22: 0.1636 | AI22: 0.1339 | AJ22: 0.0884 | AK22: 0.0726 | AL22: 0.0402 | AM22: 0.0223 | AN22: 0.0233 | AO22: 0.0375 | AP22: 0.0421 | AQ22: 0.0395 | AR22: 0.0382 | AS22: 0.021 | AT22: 0.0545 | AU22: 0.0158 | AV22: -0.0388
A23: Anniston-Oxford, AL | B23: Market | C23: Anniston-Oxford, AL | D23: 11500 | E23: Performance | F23: YOY Effective Rent Change | G23: Totals | H23: Totals | K23: -0.0674 | L23: -0.0482 | M23: -0.0577 | N23: -0.0644 | O23: 0.0327 | P23: 0.0379 | Q23: 0.0186 | R23: 0.031 | S23: 0.0486 | T23: 0.0146 | U23: 0.061 | V23: 0.0574 | W23: 0.0569 | X23: 0.0822 | Y23: 0.0626 | Z23: 0.0415 | AA23: 0.0379 | AB23: 0.0363 | AC23: 0.0343 | AD23: 0.0339 | AE23: 0.0572 | AF23: 0.0812 | AG23: 0.101 | AH23: 0.1241 | AI23: 0.1157 | AJ23: 0.1451 | AK23: 0.1654 | AL23: 0.1461 | AM23: 0.1073 | AN23: 0.029 | AO23: -0.0243 | AP23: -0.0401 | AQ23: -0.0097 | AR23: 0.0156 | AS23: 0.0298 | AT23: 0.1139
A24: Appleton, WI | B24: Market | C24: Appleton, WI | D24: 11540 | E24: Performance | F24: YOY Effective Rent Change | G24: Totals | H24: Totals | I24: 0.1246 | J24: 0.1363 | K24: 0.1147 | L24: 0.0739 | M24: 0.0682 | N24: 0.0702 | O24: 0.0612 | P24: 0.0003 | Q24: 0.0089 | R24: 0.012 | S24: 0.0235 | T24: 0.0275 | U24: 0.0336 | V24: 0.0403 | W24: 0.0419 | X24: 0.045 | Y24: 0.056 | Z24: 0.0816 | AA24: 0.0885 | AB24: 0.0592 | AC24: 0.0431 | AD24: 0.028 | AE24: 0.0572 | AF24: 0.1311 | AG24: 0.1421 | AH24: 0.1813 | AI24: 0.2013 | AJ24: 0.1146 | AK24: 0.1194 | AL24: 0.0749 | AM24: 0.1271 | AN24: 0.1572 | AO24: 0.1521 | AP24: 0.1696 | AQ24: 0.0546 | AR24: 0.1071 | AS24: 0.1017 | AT24: 0.1018 | AU24: 0.1366 | AV24: 0.0762
A25: Ardmore, OK | B25: Market | C25: Ardmore, OK | D25: 11620 | E25: Performance | F25: YOY Effective Rent Change | G25: Totals | H25: Totals
A26: Arkansas City-Winfield, KS | B26: Market | C26: Arkansas City-Winfield, KS | D26: 11680 | E26: Performance | F26: YOY Effective Rent Change | G26: Totals | H26: Totals
A27: Asheville/Waynesville, NC | B27: Market | C27: Asheville/Waynesville, NC | D27: 211700 | E27: Performance | F27: YOY Effective Rent Change | G27: Totals | H27: Totals | I27: 0.0659 | J27: 0.0307 | K27: 0.0408 | L27: 0.059 | M27: 0.0411 | N27: 0.0346 | O27: 0.0269 | P27: 0.0246 | Q27: 0.045 | R27: 0.0482 | S27: 0.0582 | T27: 0.0509 | U27: 0.0554 | V27: 0.0512 | W27: 0.0244 | X27: 0.0142 | Y27: 0.0115 | Z27: -0.0141 | AA27: -0.0017 | AB27: 0.0393 | AC27: 0.0463 | AD27: 0.1059 | AE27: 0.1835 | AF27: 0.221 | AG27: 0.2073 | AH27: 0.197 | AI27: 0.1548 | AJ27: 0.0939 | AK27: 0.1012 | AL27: 0.06 | AM27: 0.015 | AN27: 0.0017 | AO27: -0.0143 | AP27: 0.0037 | AQ27: 0.0064 | AR27: 0.0039 | AS27: -0.0242 | AT27: -0.0444 | AU27: -0.0685 | AV27: -0.0623
A28: Ashland, OH | B28: Market | C28: Ashland, OH | D28: 11740 | E28: Performance | F28: YOY Effective Rent Change | G28: Totals | H28: Totals | M28: 0.2309 | N28: 0.2057 | O28: 0.1721 | P28: 0.1918 | Q28: 0.0324 | R28: 0.07 | S28: 0.0478 | T28: 0.0619 | U28: 0.0473 | V28: 0.015 | W28: 0.0398 | X28: 0.0207 | Y28: 0.0324 | Z28: 0.0342 | AA28: 0.0354 | AB28: 0.0758 | AC28: 0.0607 | AD28: 0.0568 | AE28: 0.0477 | AF28: 0.0187 | AG28: 0.0962 | AH28: 0.0758 | AI28: 0.3532 | AJ28: 0.4112 | AK28: 0.3854 | AL28: 0.4224 | AM28: 0.1845 | AN28: 0.1304 | AO28: 0.0657 | AP28: 0.075 | AQ28: 0.0386 | AR28: 0.0512 | AS28: 0.0559 | AT28: 0.0267 | AU28: 0.0402 | AV28: 0.0153
A29: Astoria, OR | B29: Market | C29: Astoria, OR | D29: 11820 | E29: Performance | F29: YOY Effective Rent Change | G29: Totals | H29: Totals
A30: Athens-Clarke County, GA | B30: Market | C30: Athens-Clarke County, GA | D30: 12020 | E30: Performance | F30: YOY Effective Rent Change | G30: Totals | H30: Totals | I30: 0.0548 | J30: 0.0435 | K30: 0.0835 | L30: 0.1128 | M30: 0.1063 | N30: 0.1336 | O30: 0.123 | P30: 0.1083 | Q30: 0.0696 | R30: 0.0417 | S30: 0.034 | T30: 0.0399 | U30: 0.0707 | V30: 0.0566 | W30: 0.0524 | X30: 0.059 | Y30: 0.0671 | Z30: 0.0519 | AA30: 0.0552 | AB30: 0.0545 | AC30: 0.061 | AD30: 0.1096 | AE30: 0.176 | AF30: 0.1578 | AG30: 0.1279 | AH30: 0.1277 | AI30: 0.0911 | AJ30: 0.0512 | AK30: 0.0539 | AL30: 0.091 | AM30: 0.061 | AN30: 0.0884 | AO30: 0.0868 | AP30: 0.026 | AQ30: -0.0204 | AR30: -0.0456 | AS30: -0.0381 | AT30: -0.0365 | AU30: -0.0379 | AV30: -0.0375
A31: Athens, OH | B31: Market | C31: Athens, OH | D31: 11900 | E31: Performance | F31: YOY Effective Rent Change | G31: Totals | H31: Totals | I31: 0.0091 | J31: -0.0156 | K31: -0.0521 | L31: -0.1365 | M31: -0.0674 | N31: -0.0332 | O31: -0.0073 | P31: 0.1152 | Q31: 0.032 | R31: 0.0327 | S31: 0.0367 | T31: 0.018 | U31: 0.0429 | V31: 0.0244 | W31: 0.0326 | X31: 0.0584 | Y31: 0.0235 | Z31: -0.0052 | AA31: -0.0282 | AB31: -0.0199 | AC31: 0.0047 | AD31: 0.0131 | AE31: 0.0915 | AF31: 0.0642 | AG31: 0.053 | AO31: 0.1351 | AP31: 0.1861 | AQ31: 0.1262 | AR31: 0.1873 | AS31: 0.0435
A32: Athens, TN | B32: Market | C32: Athens, TN | D32: 11940 | E32: Performance | F32: YOY Effective Rent Change | G32: Totals | H32: Totals | AN32: 0.3829 | AO32: 0.256 | AP32: -0.0885 | AQ32: 0.0661 | AR32: 0.0319 | AS32: -0.0104
A33: Athens, TX | B33: Market | C33: Athens, TX | D33: 11980 | E33: Performance | F33: YOY Effective Rent Change | G33: Totals | H33: Totals | AI33: 0.1193 | AJ33: 0.0975 | AK33: 0.1356 | AL33: 0.0977 | AM33: 0.0716 | AN33: 0.0724 | AO33: 0.0661 | AP33: 0.079 | AQ33: 0.0748 | AR33: 0.0499 | AS33: -0.0118 | AT33: -0.0157 | AU33: -0.0233 | AV33: -0.0076
A34: Atlanta-Sandy Springs-Roswell, GA | B34: Market | C34: Atlanta-Sandy Springs-Roswell, GA | D34: 12060 | E34: Performance | F34: YOY Effective Rent Change | G34: Totals | H34: Totals | I34: 0.0721 | J34: 0.0666 | K34: 0.0645 | L34: 0.0627 | M34: 0.0615 | N34: 0.0615 | O34: 0.0524 | P34: 0.0506 | Q34: 0.0609 | R34: 0.0537 | S34: 0.0628 | T34: 0.0698 | U34: 0.069 | V34: 0.0678 | W34: 0.0595 | X34: 0.0488 | Y34: 0.0348 | Z34: 0.0005 | AA34: 0.0039 | AB34: 0.0247 | AC34: 0.046 | AD34: 0.1202 | AE34: 0.1904 | AF34: 0.2267 | AG34: 0.2246 | AH34: 0.1916 | AI34: 0.1232 | AJ34: 0.0575 | AK34: 0.0318 | AL34: 0.0084 | AM34: -0.0272 | AN34: -0.039 | AO34: -0.0389 | AP34: -0.0417 | AQ34: -0.0377 | AR34: -0.0336 | AS34: -0.0252 | AT34: -0.0158 | AU34: -0.0019 | AV34: 0.0051
A35: Atlantic City-Hammonton, NJ | B35: Market | C35: Atlantic City-Hammonton, NJ | D35: 12100 | E35: Performance | F35: YOY Effective Rent Change | G35: Totals | H35: Totals | I35: 0.0688 | J35: -0.0418 | K35: 0.0801 | L35: 0.1279 | M35: 0.0661 | N35: 0.075 | O35: 0.0352 | P35: -0.0115 | Q35: 0.0125 | R35: 0.0784 | S35: 0.0955 | T35: 0.0699 | U35: 0.0611 | V35: 0.0285 | W35: 0.042 | X35: 0.0612 | Y35: 0.0523 | Z35: 0.0212 | AA35: 0.0073 | AB35: 0.0307 | AC35: 0.0789 | AD35: 0.1007 | AE35: 0.151 | AF35: 0.14 | AG35: 0.1123 | AH35: 0.1446 | AI35: 0.1642 | AJ35: 0.1641 | AK35: 0.1618 | AL35: 0.1584 | AM35: 0.0791 | AN35: 0.0791 | AO35: 0.0769 | AP35: 0.032 | AQ35: 0.0533 | AR35: 0.0364 | AS35: 0.0331 | AT35: 0.0498 | AU35: 0.0196 | AV35: 0.0023
